Workbook

Sheet 说明与图例
A1: 阳光电源园区智慧物流 · 分部门调研问题清单
A2: 使用说明
A3: 1. 每个部门单独一个工作表（见下方标签），可分别打印或发给对应部门访谈填写。
A4: 2. 黄色列为填写栏：受访人 / 联系人、回答 / 现状记录、状态、跟进 / 备注。
A5: 3. 「优先级」和「状态」为下拉选择；优先级已按建议预填，可按贵司实际调整。
A6: 4. 「进度看板」工作表会根据各表「状态」列自动统计各部门完成率，无需手工汇总。
A7: 优先级定义
A8: 高 | B8: 决定项目范围、造价或能否落地的关键问题，应最先问清。
A9: 中 | B9: 影响方案设计与功能细节的重要问题。
A10: 低 | B10: 锦上添花或后续阶段再细化的问题。
A12: 填写示例（此行仅为格式示范，正式填写见各部门工作表）
A13: 优先级 | B13: 调研问题 | C13: 目的 / 影响 | D13: 受访人 / 联系人 | E13: 回答 / 现状记录 | F13: 状态 | G13: 跟进 / 备注
A14: 高 | B14: 现在如何调度、排队、分配月台？用什么工具？ | C14: 现状基线与痛点 | D14: 张经理（物流部） | E14: 目前靠门卫电话通知 + 微信群，高峰全靠人工协调 | F14: 进行中 | G14: 需索取近一个月车流台账
A16: ★ 无论对接哪个部门，都应优先问清的关键先决问题
A17: · IOC 平台是哪家生态、数据接入规范是什么？
A18: · ERP 是否为 SAP？是否已上 WMS / MES？
A19: · 三园高峰车流曲线与货物类型（是否含危化）？
A20: · 现有硬件（摄像头 / 道闸 / 地磅）与网络（5G / WiFi / 专网）存量？
A21: · 信息安全与部署要求（等保 / 私有化 / 内外网隔离）？
A22: · 预算区间、分期节奏与期望上线时间？

Sheet 进度看板
A1: 调研进度看板（自动统计）
A2: 各部门「状态」列填为「已完成」后，完成率自动更新。
A3: 部门 | B3: 问题总数 | C3: 已完成 | D3: 完成率 | E3: 高优先级数 | F3: 待办（未完成）
A4: 决策层 / 项目发起人 | B4: =COUNTA(决策层!C4:C200) -> 8 | C4: =COUNTIF(决策层!G4:G200,"已完成") -> 0 | D4: =IFERROR(C4/B4,0) -> 0 | E4: =COUNTIF(决策层!B4:B200,"高") -> 5 | F4: =B4-C4 -> 8
A5: 物流部 / 供应链管理部 | B5: =COUNTA(物流供应链部!C4:C200) -> 8 | C5: =COUNTIF(物流供应链部!G4:G200,"已完成") -> 0 | D5: =IFERROR(C5/B5,0) -> 0 | E5: =COUNTIF(物流供应链部!B4:B200,"高") -> 4 | F5: =B5-C5 -> 8
A6: 生产计划 | B6: =COUNTA(生产计划PMC!C4:C200) -> 5 | C6: =COUNTIF(生产计划PMC!G4:G200,"已完成") -> 0 | D6: =IFERROR(C6/B6,0) -> 0 | E6: =COUNTIF(生产计划PMC!B4:B200,"高") -> 2 | F6: =B6-C6 -> 5
A7: 仓储 / 收发货管理部 | B7: =COUNTA(仓储收发货!C4:C200) -> 6 | C7: =COUNTIF(仓储收发货!G4:G200,"已完成") -> 0 | D7: =IFERROR(C7/B7,0) -> 0 | E7: =COUNTIF(仓储收发货!B4:B200,"高") -> 3 | F7: =B7-C7 -> 6
A8: IT / 数字化 / 信息化部 | B8: =COUNTA(IT数字化!C4:C200) -> 9 | C8: =COUNTIF(IT数字化!G4:G200,"已完成") -> 0 | D8: =IFERROR(C8/B8,0) -> 0 | E8: =COUNTIF(IT数字化!B4:B200,"高") -> 5 | F8: =B8-C8 -> 9
A9: 智慧园区 / IOC 运营团队 | B9: =COUNTA(智慧园区IOC!C4:C200) -> 5 | C9: =COUNTIF(智慧园区IOC!G4:G200,"已完成") -> 0 | D9: =IFERROR(C9/B9,0) -> 0 | E9: =COUNTIF(智慧园区IOC!B4:B200,"高") -> 2 | F9: =B9-C9 -> 5
A10: 安全 / EHS / 保卫部 | B10: =COUNTA(安全EHS保卫!C4:C200) -> 5 | C10: =COUNTIF(安全EHS保卫!G4:G200,"已完成") -> 0 | D10: =IFERROR(C10/B10,0) -> 0 | E10: =COUNTIF(安全EHS保卫!B4:B200,"高") -> 2 | F10: =B10-C10 -> 5
A11: 园区 / 行政后勤 / 物业 | B11: =COUNTA(园区行政物业!C4:C200) -> 5 | C11: =COUNTIF(园区行政物业!G4:G200,"已完成") -> 0 | D11: =IFERROR(C11/B11,0) -> 0 | E11: =COUNTIF(园区行政物业!B4:B200,"高") -> 2 | F11: =B11-C11 -> 5
A12: 采购 / 财务 | B12: =COUNTA(采购财务!C4:C200) -> 5 | C12: =COUNTIF(采购财务!G4:G200,"已完成") -> 0 | D12: =IFERROR(C12/B12,0) -> 0 | E12: =COUNTIF(采购财务!B4:B200,"高") -> 1 | F12: =B12-C12 -> 5
A13: 一线现场 + 承运商 | B13: =COUNTA(现场与承运商!C4:C200) -> 5 | C13: =COUNTIF(现场与承运商!G4:G200,"已完成") -> 0 | D13: =IFERROR(C13/B13,0) -> 0 | E13: =COUNTIF(现场与承运商!B4:B200,"高") -> 2 | F13: =B13-C13 -> 5
A14: 合计 | B14: =SUM(B4:B13) -> 61 | C14: =SUM(C4:C13) -> 0 | D14: =IFERROR(C14/B14,0) -> 0 | E14: =SUM(E4:E13) -> 28 | F14: =SUM(F4:F13) -> 61

Sheet 决策层
A1: 决策层 / 项目发起人（Sponsor）
A2: 黄色列为填写栏；优先级 / 状态为下拉选择。填写后「进度看板」自动统计完成率。
A3: 序号 | B3: 优先级 | C3: 调研问题 | D3: 目的 / 影响 | E3: 受访人 / 联系人 | F3: 回答 / 现状记录 | G3: 状态 | H3: 跟进 / 备注
A4: 1 | B4: 高 | C4: 本项目最想解决的前三个痛点是什么？ | D4: 明确核心目标与范围 | G4: 未开始
A5: 2 | B5: 高 | C5: 成功的量化标准是什么（如缩短在园时长 X%、可视度达到什么程度）？ | D5: 定义验收指标 | G5: 未开始
A6: 3 | B6: 高 | C6: 范围边界：仅园区内，还是含出厂在途？三园同步还是先试点？ | D6: 直接决定方案范围与造价 | G6: 未开始
A7: 4 | B7: 高 | C7: 预算区间与分期投资节奏？ | D7: 决定方案档次与选型 | G7: 未开始
A8: 5 | B8: 高 | C8: 期望上线时间与关键里程碑？ | D8: 项目排期 | G8: 未开始
A9: 6 | B9: 中 | C9: 业务 Owner 与决策 / 验收机制、项目组织如何设置？ | D9: 明确责任与推进机制 | G9: 未开始
A10: 7 | B10: 中 | C10: 对国产 vs 原生（SAP）路线、私有化 vs 云是否有倾向？ | D10: 选型方向 | G10: 未开始
A11: 8 | B11: 低 | C11: 是否有对标企业或期望参考的案例？ | D11: 参考借鉴 | G11: 未开始

Sheet 物流供应链部
A1: 物流部 / 供应链管理部（核心业务方）
A2: 黄色列为填写栏；优先级 / 状态为下拉选择。填写后「进度看板」自动统计完成率。
A3: 序号 | B3: 优先级 | C3: 调研问题 | D3: 目的 / 影响 | E3: 受访人 / 联系人 | F3: 回答 / 现状记录 | G3: 状态 | H3: 跟进 / 备注
A4: 1 | B4: 高 | C4: 每天 / 每园的车流时间分布与峰谷曲线，高峰几点、并发多少？ | D4: 预约削峰与产能设计的关键输入 | G4: 未开始
A5: 2 | B5: 高 | C5: 货车类型（重卡 / 厢车 / 新能源）与货物类别，是否含危化 / 超限？ | D5: 影响定位分级与安全管控 | G5: 未开始
A6: 3 | B6: 高 | C6: 现在如何调度、排队、分配月台？用什么工具（电话 / 微信 / 纸单 / Excel）？ | D6: 现状基线与痛点 | G6: 未开始
A7: 4 | B7: 高 | C7: 最需要监控的时效环节与 KPI 口径（在园时长从哪算到哪）？ | D7: 时效引擎与 KPI 定义 | G7: 未开始
A8: 5 | B8: 中 | C8: 承运商数量、能否要求司机用小程序预约、履约与考核现状？ | D8: 预约落地可行性 | G8: 未开始
A9: 6 | B9: 中 | C9: 现有排队等待、拥堵的典型场景与发生频次？ | D9: 量化痛点 | G9: 未开始
A10: 7 | B10: 中 | C10: 是否有跨园调拨？三园货量与流向差异？ | D10: 多园协同设计 | G10: 未开始
A11: 8 | B11: 低 | C11: 现有报表 / 台账样式，希望保留哪些口径？ | D11: 平滑迁移 | G11: 未开始

Sheet 生产计划PMC
A1: 生产计划（PMC）/ 制造部
A2: 黄色列为填写栏；优先级 / 状态为下拉选择。填写后「进度看板」自动统计完成率。
A3: 序号 | B3: 优先级 | C3: 调研问题 | D3: 目的 / 影响 | E3: 受访人 / 联系人 | F3: 回答 / 现状记录 | G3: 状态 | H3: 跟进 / 备注
A4: 1 | B4: 高 | C4: 到货与生产节拍如何联动？是否有齐套 / JIT / 线边库补料要求？ | D4: 预约与生产协同 | G4: 未开始
A5: 2 | B5: 高 | C5: 是否有 MES / APS？能否提供到货计划用于反向排预约？ | D5: 集成与智能预约数据源 | G5: 未开始
A6: 3 | B6: 中 | C6: 装卸优先级规则（哪些物料需插单 / 绿色通道）？ | D6: 叫号与调度策略 | G6: 未开始
A7: 4 | B7: 中 | C7: 生产异常（缺料 / 停线）时对物流的应急要求？ | D7: 应急调度 | G7: 未开始
A8: 5 | B8: 低 | C8: 计划变更频率与提前期？ | D8: 预约配额动态调整 | G8: 未开始

Sheet 仓储收发货
A1: 仓储 / 收发货管理部
A2: 黄色列为填写栏；优先级 / 状态为下拉选择。填写后「进度看板」自动统计完成率。
A3: 序号 | B3: 优先级 | C3: 调研问题 | D3: 目的 / 影响 | E3: 受访人 / 联系人 | F3: 回答 / 现状记录 | G3: 状态 | H3: 跟进 / 备注
A4: 1 | B4: 高 | C4: 每园月台数量、位置，可否指定车型 / 货类，当前利用率？ | D4: 月台调度核心数据 | G4: 未开始
A5: 2 | B5: 高 | C5: 装卸流程与平均时长、瓶颈在哪？ | D5: 时效与瓶颈分析 | G5: 未开始
A6: 3 | B6: 高 | C6: 是否已上 WMS？装卸任务是否需与库存 / 收货单联动、接口方式？ | D6: 集成范围 | G6: 未开始
A7: 4 | B7: 中 | C7: 叉车 / 装卸班组如何调度、人力班次如何安排？ | D7: 资源协同 | G7: 未开始
A8: 5 | B8: 中 | C8: 收发货单据流程与凭证要求（签收 / 拍照 / 过磅单）？ | D8: 流程数字化 | G8: 未开始
A9: 6 | B9: 低 | C9: 退货 / 逆向、异常收货如何处理？ | D9: 边界场景 | G9: 未开始

Sheet IT数字化
A1: IT / 数字化 / 信息化部（集成关键方）
A2: 黄色列为填写栏；优先级 / 状态为下拉选择。填写后「进度看板」自动统计完成率。
A3: 序号 | B3: 优先级 | C3: 调研问题 | D3: 目的 / 影响 | E3: 受访人 / 联系人 | F3: 回答 / 现状记录 | G3: 状态 | H3: 跟进 / 备注
A4: 1 | B4: 高 | C4: ERP 是否为 SAP、版本？WMS / MES 是什么系统？ | D4: 决定集成路线 | G4: 未开始
A5: 2 | B5: 高 | C5: 各系统可提供的接口类型（API / 中间件 / 数据库 / 文件）？ | D5: 集成方式 | G5: 未开始
A6: 3 | B6: 高 | C6: IOC 平台是哪家（华为 / 阿里 / 新华三等）、数据接入协议与规范（MQTT / Kafka / API 主题格式）？ | D6: IOC 对接关键 | G6: 未开始
A7: 4 | B7: 高 | C7: 部署要求：私有化 / 云、等保合规、内外网隔离策略？ | D7: 部署与合规 | G7: 未开始
A8: 5 | B8: 高 | C8: 园区网络现状：5G / 工业 WiFi / 物联网专网覆盖，室外与厂房内信号如何？ | D8: 感知层与网络设计 | G8: 未开始
A9: 6 | B9: 中 | C9: 主数据（车辆 / 承运商 / 月台编码）由谁维护、如何同步？ | D9: 数据一致性 | G9: 未开始
A10: 7 | B10: 中 | C10: 账号 / 权限 / 单点登录、接口安全与运维要求？ | D10: 安全与运维 | G10: 未开始
A11: 8 | B11: 中 | C11: 现有数据中台 / 集成平台（ESB / iPaaS）可复用吗？ | D11: 降低集成成本 | G11: 未开始
A12: 9 | B12: 低 | C12: 数据留存周期、备份与灾备要求？ | D12: 非功能需求 | G12: 未开始

Sheet 智慧园区IOC
A1: 智慧园区 / IOC 运营团队
A2: 黄色列为填写栏；优先级 / 状态为下拉选择。填写后「进度看板」自动统计完成率。
A3: 序号 | B3: 优先级 | C3: 调研问题 | D3: 目的 / 影响 | E3: 受访人 / 联系人 | F3: 回答 / 现状记录 | G3: 状态 | H3: 跟进 / 备注
A4: 1 | B4: 高 | C4: IOC 大屏现有哪些主题？希望物流以什么形态呈现（一张图 / 看板 / 告警）？ | D4: 可视化设计 | G4: 未开始
A5: 2 | B5: 高 | C5: 接入是推数据还是页面嵌入？刷新频率与数据留存要求？ | D5: 对接方式 | G5: 未开始
A6: 3 | B6: 中 | C6: 是否已有其他子系统（安防 / 能耗 / 停车）可复用感知与联动？ | D6: 复用与联动 | G6: 未开始
A7: 4 | B7: 中 | C7: 大屏 / 指挥中心的使用场景与角色（值班 / 领导巡检）？ | D7: 呈现优先级 | G7: 未开始
A8: 5 | B8: 低 | C8: 是否需要移动端 / APP 查看？ | D8: 交付形态 | G8: 未开始

Sheet 安全EHS保卫
A1: 安全 / EHS / 保卫部
A2: 黄色列为填写栏；优先级 / 状态为下拉选择。填写后「进度看板」自动统计完成率。
A3: 序号 | B3: 优先级 | C3: 调研问题 | D3: 目的 / 影响 | E3: 受访人 / 联系人 | F3: 回答 / 现状记录 | G3: 状态 | H3: 跟进 / 备注
A4: 1 | B4: 高 | C4: 大门准入与身份核验现有规则？是否已有道闸 / 门禁 / 车牌识别设备？ | D4: 准入方案与硬件复用 | G4: 未开始
A5: 2 | B5: 高 | C5: 危化区 / 装卸区的安全管控与电子围栏 / 防撞 / 人员定位要求？ | D5: 定位分级与安全 | G5: 未开始
A6: 3 | B6: 中 | C6: 是否需与消防 / 应急联动（报警触发疏散 / 车位释放）？ | D6: 联动机制 | G6: 未开始
A7: 4 | B7: 中 | C7: 外来车辆 / 人员的登记与权限管控流程？ | D7: 准入流程 | G7: 未开始
A8: 5 | B8: 低 | C8: 安全事故历史与重点防控区域？ | D8: 风险识别 | G8: 未开始

Sheet 园区行政物业
A1: 园区 / 行政后勤 / 物业
A2: 黄色列为填写栏；优先级 / 状态为下拉选择。填写后「进度看板」自动统计完成率。
A3: 序号 | B3: 优先级 | C3: 调研问题 | D3: 目的 / 影响 | E3: 受访人 / 联系人 | F3: 回答 / 现状记录 | G3: 状态 | H3: 跟进 / 备注
A4: 1 | B4: 高 | C4: 园区道路、蓄车场 / 等候区、停车与地磅的现状与容量？ | D4: 蓄车与叫号设计 | G4: 未开始
A5: 2 | B5: 高 | C5: 现有摄像头点位、道闸、地磅的品牌型号（判断能否复用）？ | D5: 硬件复用评估 | G5: 未开始
A6: 3 | B6: 中 | C6: 施工布线可行性、供电、机房 / 弱电间条件？ | D6: 实施可行性 | G6: 未开始
A7: 4 | B7: 中 | C7: 物业配合与作业窗口、安装施工的时间限制？ | D7: 实施排期 | G7: 未开始
A8: 5 | B8: 低 | C8: 园区平面图 / CAD、点位图能否提供？ | D8: 设计输入 | G8: 未开始

Sheet 采购财务
A1: 采购 / 财务
A2: 黄色列为填写栏；优先级 / 状态为下拉选择。填写后「进度看板」自动统计完成率。
A3: 序号 | B3: 优先级 | C3: 调研问题 | D3: 目的 / 影响 | E3: 受访人 / 联系人 | F3: 回答 / 现状记录 | G3: 状态 | H3: 跟进 / 备注
A4: 1 | B4: 高 | C4: 采购模式（整体集成商 vs 分包）、招投标流程与合规要求？ | D4: 采购路径 | G4: 未开始
A5: 2 | B5: 中 | C5: 预算科目、分期投资节奏？ | D5: 资金安排 | G5: 未开始
A6: 3 | B6: 中 | C6: 投资回报衡量口径（ROI / 降本指标）？ | D6: 立项支撑 | G6: 未开始
A7: 4 | B7: 中 | C7: 若涉及外部 TMS：运费结算规则与承运商合同现状？ | D7: 结算范围 | G7: 未开始
A8: 5 | B8: 低 | C8: 供应商准入 / 合格供应商库要求？ | D8: 采购合规 | G8: 未开始

Sheet 现场与承运商
A1: 一线现场 + 承运商（最真实的一线视角）
A2: 黄色列为填写栏；优先级 / 状态为下拉选择。填写后「进度看板」自动统计完成率。
A3: 序号 | B3: 优先级 | C3: 调研问题 | D3: 目的 / 影响 | E3: 受访人 / 联系人 | F3: 回答 / 现状记录 | G3: 状态 | H3: 跟进 / 备注
A4: 1 | B4: 高 | C4: 现场调度 / 门卫 / 装卸班组：实际操作卡在哪、最耗时环节、最想要什么？ | D4: 真实痛点 | G4: 未开始
A5: 2 | B5: 高 | C5: 司机 / 承运商能否接受线上预约？晚点 / 爽约如何处理？ | D5: 预约落地 | G5: 未开始
A6: 3 | B6: 中 | C6: 司机对绿色通道、紧急插单的诉求？ | D6: 策略设计 | G6: 未开始
A7: 4 | B7: 中 | C7: 现场信息传递方式（对讲 / 微信 / 喊话）与交接痛点？ | D7: 现状 | G7: 未开始
A8: 5 | B8: 低 | C8: 一线人员的信息化接受度与培训需求？ | D8: 变革管理 | G8: 未开始
