Workbook

Sheet 总价汇总表
A1: 密级：公开
A2: 阳光电源智慧园区一期建设清单报价清单-汇总表
A3: 序号 | B3: 系统名称 | C3: 税率 | D3: 不含税总价 | E3: 含税总价 | F3: 备注
A4: 1 | B4: 硬件部分 | C4: 0.13 | D4: ='硬件-报价汇总表'!D7 -> 7857359 | E4: =D4*(1+C4) -> 8878815.7
A5: 2 | B5: 软件部分 | C5: 0.13 | D5: ='软件-报价汇总表'!G7 -> 3952000 | E5: =D5*(1+C5) -> 4465760
A6: 3 | B6: 总计（元） | D6: =SUM(D4:D5) -> 11809359
D7: 按此未税金额投标

Sheet 硬件-报价汇总表
A1: 密级：公开
A2: 阳光电源智慧园区一期建设清单（硬件）报价清单
A3: 序号 | B3: 系统名称 | C3: 税率 | D3: 不含税总价 | E3: 备注
A4: 1 | B4: 智慧消防及物联系统 | C4: 0.13 | D4: =SUM('硬件-报价明细'!Q4:Q33) -> 2604713
A5: 2 | B5: 智慧安防系统 | C5: 0.13 | D5: =SUM('硬件-报价明细'!Q36:Q110) -> 5229283
A6: 3 | B6: 等保测评 | C6: 0.13 | D6: =SUM('硬件-报价明细'!Q112) -> 23363
A7: 4 | B7: 不含税总计（元） | D7: =SUM(D4:D6) -> 7857359
A8: 报价须知： 1、报价前请仔细阅读《硬件-报价说明》。 2、付款方式：电汇，合同签订后预付合同对应金额的20%，初验完成后支付合同对应金额的50%（且累积支付不超实际产值70%），终验决算完成支付至决算对应金额的90%，剩余10%作为质保金，自竣工验收通过满1年后如无质量问题、无发生甲方代扣代付维修费用，甲方无息支付质保金。

Sheet 硬件-报价说明
A1: 密级：公开
A2: 阳光电源智慧园区一期建设清单（硬件） 投标报价说明
A3: 说明 | B3: 本报价说明作为投标文件的重要组成部分，与招标文件、技术规格书及合同具有同等效力。投标人须仔细阅读并充分理解所有条款，报价提交后视为已完全响应。
A4: 一、报价范围与计价模式
A5: 总价包含范围 | B5: 1、投标总价含设备、材料等运输、卸货、搬用、保存、安装、集成调试，通断测试，福禄克测试，质保期内保证项目稳定运行的所需全部费用。
B6: 2、投标总价含设备、线缆、柜、箱体等的机打标签、整理等工作，达到《阳光电源弱电施工工艺参考图册》、《阳光电源厂区及办公区弱电标识标签规则》要求。
B7: 3、投标总价含施工、技术支持、操作人员培训等，含3年原厂质保运维服务等，故障1小时响应，故障处理6小时内完成。
B8: 4、投标总价含材料费、施工费、调试费、措施费、安全文明施工费、税金、总包管理服务费、施工用水电费用、辅材、实现平台功能前端设备调整（角度、位置等）等项目交付前一切费用，辅材包括但不限于六类非屏蔽水晶头、音频接插头、各种螺丝、吊卡、丝杆、铁皮卡、自攻螺丝、膨胀管、绝缘子、接线端子、弓背、管道支持柱、拉爆三件套、膨胀螺栓、机柜螺丝、垫片、绝缘胶布、透明胶布、扎带、标签纸、魔术贴、网线固线器、标签机、钩钉、刚性卡箍、螺丝杆帽、PVC线槽、自喷漆、明装86盒、明装86盒盖板、弯管器、墙面开孔及开槽及修复、地面开挖及绿化恢复、其他施工工具等辅材。
A9: “实体净量+量价分离”计价规则 | B9: 本项目所有强弱电管、线、桥架类材料实行“实体净量+量价分离”计价模式，清单工程量仅依据设计图纸标注的水平/垂直投影净长度计算，施工中必然发生的桥架（含管道）内敷设弯曲、桥架上翻下翻、机柜与终端处的预留长度，以及各类管、线、桥架类材料的合理损耗等，其工程量与费用均视为投标人施工技术的一部分，须在编制综合单价时一并考虑（相关费用在材料单价中体现），结算时不再单独计量。
A10: 综合单价包干 | B10: 综合单价为包干价，包括但不限于完成工程量清单子目特征描述、工作内容描述等全部内容所需的人工费、材料费（甲供材除外）、机械费、管理费、利润、税金等全部费用，特征描述中不完善，但按常规属于完成该对应子目所必须有的工作内容，视为已包含在综合单价中。
A11: 二、技术要求与执行标准
A12: 工艺与标签规范 | B12: 施工须符合《阳光电源弱电施工工艺参考图册》、《阳光电源厂区及办公区弱电标识标签规则》，含设备、线缆、柜体等机打标签及整理。
A13: 施工界面与现场踏勘 | B13: 投标人应踏勘现场，充分了解施工移交界面及标准（如地面、墙面找平层厚度可能产生的变化），相关费用包含在报价中。
A14: 深化设计与规范要求 | B14: 本工程工程量清单项目仅列出主要包含范围，投标单位应结合设计图及标准作法进行理解，投标单位需按规范及设计要求深化施工工艺及对应施工工艺作法，本部分费用已含在本合同总价中。
A15: 三、投标报价与格式要求
A16: 报价格式 | B16: 报价时按照甲方提供表格格式要求进行报价；乙方提供excel表格报价电子档文件（可编辑版本即可），并提供word版本盖章报价扫描件（包含表头：序号、项目名称、工程量、单位、投标品牌、投标型号、参数（响应/正偏离/负偏离）、正/负偏离参数项、材料未税单价、施工未税单价、未税小计、备注）。
A17: 单价一致性 | B17: 清单中所列相同项目，投标单位报价须保持一致，若投标报价不一致，则以报价较低的单价计算并调整总价。
A18: 链接正确性 | B18: 投标清单中的链接由投标人自行负责核实。
A19: 金额精度 | B19: 工程量清单内所有工程量及金额均需保留两位小数，并以显示精度为准。
A20: 四、风险与变更条款
A21: 未尽事宜 | B21: 其他未尽事宜详见招标技术规格书及其他招标材料。
A22: 设计冲突处理 | B22: 清单中的所有主材要求详见图纸说明、技术规范书要求及清单描述，如相关描述有冲突时，按高标准执行。
A23: 材料及品牌更换 | B23: 材料如招标人提出替换时，费用只计算材料价差和税金，不再计取其他费用。
A24: 施工风险 | B24: 1、投标人已综合考虑施工中可能发生的各类风险（如材料损耗、预留长度、现场条件变化等），相关费用已包含在报价中。
B25: 2、合同期内人工、材料、机械和临时设施及施工水电费的费用、费率等价格要素的波动，合同执行期内一律不予调整。
B26: 3、施工费含白天施工、夜间施工、节假日施工等。

Sheet 硬件-报价明细
A1: 密级：公开 | H1: 乙方必填项 | I1: 乙方必填项 | J1: 乙方必填项 | K1: 乙方必填项 | L1: 乙方必填项 | M1: 乙方必填项 | O1: 乙方必填项 | Q1: 乙方必填项
A2: 序号 | B2: 设备名称 | C2: 技术参数要求 | D2: 推荐品牌 | E2: 数量 | F2: 单位 | G2: 备注 | H2: 投标品牌 | I2: 投标型号 | J2: 投标参数 | K2: 参数（响应/正偏离/负偏离） | L2: 正/负偏离 参数项 | M2: 施工未税单价 | N2: 施工小计未税 | O2: 材料未税单价 | P2: 材料小计未税 | Q2: 未税小计 | R2: 备注
B3: 一、智慧消防及物联系统
A4: 1 | B4: 用户信息传输装置 | C4: 壁挂式，用于消防远程监控，通过RS232端口实时监测所连接火灾报警控制器的报警信息，并通过有线网络传递到监控平台。满足GB26875-2011标准。 | D4: 主机信号采集数量：青鸟自动报警主机*20，青岛鼎信自动报警主机*1，利达自动报警主机*1，各品牌需对应使用适配的用户信息传输硬件 | E4: 22 | F4: 台 | H4: 青鸟 | I4: JBF-TD803 | J4: 下行：RS232串口（三芯电缆，长度<15米） 上行：TCP/IP网络（标准网线，长度<50米）; 最多可记录 100,000 条历史事件; 主电：AC 187~242V, 50Hz 备电：DC 12V / 4Ah（支持主备电自动切换）; 2组 DC12V 200mA 有源输出（驱动继电器） 1组 DC12V 200mA 电源（内部模块供电） 1组 DC5V 1A 电源（内部模块供电）; 壁挂式安装，上进线; 尺寸310mm(长) × 110mm(宽) × 420mm(高) 满足GB26875-2011标准。 | K4: 响应 | L4: / | M4: 489 | N4: =E4*M4 -> 10758 | O4: 4035 | P4: =E4*O4 -> 88770 | Q4: =E4*(M4+O4) -> 99528
E5: 1 | F5: 台 | H5: 鼎信 | I5: TS-CS-8101 | J5: 主电电源：额定工作电压 AC220V/50Hz，宽电压范围 AC176V～AC420V 可接入； 备电电源：12V/2.3Ah 蓄电池； 容量：配接一台控制器； 液晶规格：320×480 彩色液晶屏； 使用环境：温度：0℃~+40℃； 相对湿度≤95%，不凝露； 外形尺寸：270.0mm× 190.0mm× 62.5mm(长× 宽× 高)； 安装孔距：水平间距 226.0mm，垂直间距 93.0mm； 重量：约 2.1kg； 外壳防护等级：IP30； | K5: 响应 | L5: / | M5: 489 | N5: =E5*M5 -> 489 | O5: 7434 | P5: =E5*O5 -> 7434 | Q5: =E5*(M5+O5) -> 7923
E6: 1 | F6: 台 | H6: 利达 | I6: LD6920 | J6: DC 24V；< 200mA； CAN总线、RS232串口、开关量输入；支持 GPRS/2G、TCP/IP、电话线（可选配） | K6: 响应 | L6: / | M6: 489 | N6: =E6*M6 -> 489 | O6: 5310 | P6: =E6*O6 -> 5310 | Q6: =E6*(M6+O6) -> 5799
A7: 2 | B7: 全局网络控制器 | C7: 1.名称：全局网络控制器 2.参数要求：单核 A8@1GHz，1GB DDR3 / 4GB microSD，2× 百兆，2×RS-485，可扩展4 个 I/O/ 现场总线模块。协议：BACnet IP/MS/TP + Modbus TCP/RTU + LonWorks + KNX + SNMP + oBIX，编程：Niagara 图形化编程，功能极强，适合复杂联锁 / 算法。满足现场现场功能所需的点位授权费 | D7: 霍尼韦尔、江森、西门子 | E7: 9 | F7: 台 | H7: 霍尼韦尔 | I7: WEB-8050-U | J7: 1GHz处理器，1024MB内存，4096MB闪存，支持50个Device且数据点不大于2,500点，2条总线 | K7: 响应 | L7: / | M7: 326 | N7: =E7*M7 -> 2934 | O7: 33864 | P7: =E7*O7 -> 304776 | Q7: =E7*(M7+O7) -> 307710
A8: 3 | B8: 可编程网络控制器 | C8: 通讯接口：100M以太网，双网口 协议：BACnetIP/Modbus-TCP 扩展接口通讯：控制器内部协议 DI输入接口：数量最大24路，干接点接入 DO控制接口：8路，继电器负载能力2A/30VDC UI输入接口：最大16路，支持电阻型温度NTC20K，电压型湿度0~10V，电压型CO2,0~10V，电压型CO 0~10V,电流型水压4~20mA，电流型流量计4~20mA，执行器0~10V和2~10V反馈 AO输出接口：8路，支持4~20mA和0~10V输出 RS485接口数量：2个，其中一个支持多合一传感器接入，另外一路备用 支持PLC功能，支持PLC逻辑编程 尺寸：225x115x 57mm 外壳原料： UL 94 ABS 电源：DC24V/3A 重量：500g | D8: 霍尼韦尔、江森、西门子 | E8: 129 | F8: 台 | H8: 霍尼韦尔 | I8: PUC5533-PB2 | J8: BACnet现场控制器DDC 5UI,5DI,3AO,3DO | K8: 响应 | L8: / | M8: 233 | N8: =E8*M8 -> 30057 | O8: 1405 | P8: =E8*O8 -> 181245 | Q8: =E8*(M8+O8) -> 211302 | S8: 招标要求带网络协议装换控制模块，PUC5533-PB2为总线型控制模块不满足招标参数，
A9: 4 | B9: 可编程控制盘 | C9: 1、包含：空开、导轨及接线端子 2、国产优质箱体，根据实际安装设备测量后成套定制 | D9: 国产一线品牌，空开品牌为良信、正泰、公牛 | E9: 129 | F9: 台 | H9: 正泰 | I9: 定制成套 | J9: 含空开、导轨及接线端子，国产优质箱体，根据实际安装设备测量后成套定制 | K9: 响应 | L9: / | M9: 233 | N9: =E9*M9 -> 30057 | O9: 781 | P9: =E9*O9 -> 100749 | Q9: =E9*(M9+O9) -> 130806
A10: 5 | B10: 电源模块 | C10: 输入：85–264VAC（全球宽压），50/60Hz 输出：24VDC 可调（约 24–26V） 电流：1.3A / 2.5A / 4A（常用 4A 配 DDC） 保护：过压、短路、过载、过热（自恢复） EMC：EN61000-6-2、EN61000-4 系列，工业级 安装：35mm DIN 导轨 外壳：UL94 V-0 阻燃塑料 工作温度：-20℃ ~ +60℃ | D10: 霍尼韦尔、江森、西门子 | E10: 129 | F10: 台 | H10: 施耐德 | I10: ABL2REM12100D | J10: ‌输入‌：90~264VAC全球宽压，适配50/60Hz工业电网 ‌输出‌：24VDC，额定电流5A，总功率120W，输出电压支持24~28V微调 ‌转换效率‌：最高可达87.5%，满载运行温升可控 ‌防护机制‌：集成过压、短路、过载、过热四重自恢复保护，故障消除后自动恢复运行 ‌安装方式‌：适配标准35mm DIN导轨，卡扣式安装无需额外固定 ‌外壳与环境‌：UL94 V-0阻燃塑料外壳，工作温度范围-20℃~+65℃ ‌合规认证‌：通过UL508工业控制设备认证，满足EN61000-6-2工业级EMC抗扰标准 | K10: 响应 | L10: / | M10: 17 | N10: =E10*M10 -> 2193 | O10: 276 | P10: =E10*O10 -> 35604 | Q10: =E10*(M10+O10) -> 37797
A11: 6 | B11: 液位开关 | C11: 电缆长度：3M；电缆类型：PVC（聚氯乙烯）；包装形式：纸箱批量简易包装； | D11: 霍尼韦尔、江森、西门子 | E11: 13 | F11: 台 | H11: 霍尼韦尔 | I11: HSL-LS05 | J11: 浮球液位开关,延长线缆长度5m | K11: 响应 | L11: / | M11: 140 | N11: =E11*M11 -> 1820 | O11: 159 | P11: =E11*O11 -> 2067 | Q11: =E11*(M11+O11) -> 3887
A12: 7 | B12: 压力变送器 | C12: 输出信号：4-20MA；量程范围：0-25 bar；过程连接：1/4 NPT；电气连接：1M； | D12: 霍尼韦尔、江森、西门子 | E12: 362 | F12: 台 | H12: 霍尼韦尔 | I12: HSP-W | J12: 量程0-16Bar，精度：±1%FS ；信号0-10VDC，电源14-30VDC； IP65；3线制；G1/4 male | K12: 响应 | L12: / | M12: 140 | N12: =E12*M12 -> 50680 | O12: 412 | P12: =E12*O12 -> 149144 | Q12: =E12*(M12+O12) -> 199824
A13: 8 | B13: 流量传感器 | C13: 电源:10 to 35 VDC；电源消耗:最大40mA；输出:脉冲:NPN开集方波输出，最大60V@50mA;频率:3.2至200Hz。脉冲宽度:2.5毫秒+25%，4-20mA:4mA是0fts，20 mA是25 fts。过程连接:标准配置为1-1/2”NPT外螺纹，可选2“NPT外螺纹。管径满足现场环境 | D13: 霍尼韦尔、江森、西门子 | E13: 75 | F13: 台 | H13: 霍尼韦尔 | I13: PFT-IDN-B111-S | J13: 供电与功耗：10-35 VDC，最大 40mA。 - 脉冲输出：NPN 开集方波，最大 60V@50mA，频率 3.2-200Hz，脉宽 2.5ms±25%。 • 模拟输出：4mA 对应 0 ft/s，20mA 对应 25 ft/s。 - 过程连接：标准 1½" NPT 外螺纹。 • 材质与量程：黄铜本体，流速范围 1.2-25 ft/s（0.37-7.62 m/s） | K13: 响应 | L13: / | M13: 408 | N13: =E13*M13 -> 30600 | O13: 4779 | P13: =E13*O13 -> 358425 | Q13: =E13*(M13+O13) -> 389025
A14: 9 | B14: 氧浓度监测传感器 | C14: 工作温度 -20~50℃ 工作湿度 5~95% RH 无冷凝 压力范围 90~110KPa 稳定性 ≤5% 信号值 / 年 响应时间 ≤10S 预热时间 ≥5 分钟 零点漂移（-20~40℃） ±0.3%Vol 重复性 ≤1% 使用寿命 ≥24 个月 量程 0~25% VOL 精度 ±2%FS 分辨率 0.1%VOL | D14: 霍尼韦尔、江森、西门子 | E14: 26 | F14: 台 | H14: 霍尼韦尔 | I14: G3Ex121 | J14: 电源：DC24V±25% 输出：0~10V，4~20mA(三线)，RS485/Modbus 负载：≥2kΩ(0~10V)，≤500Ω(4~20mA) 开关输出：1×SPST，3A/30VDC 显示：LED 数码管显示，电源/故障/报警LED 指示灯 应用环境：-20~55°C，10~95%RH(非冷凝)，压力86~106kPa 外壳材料：铸铝外壳，不锈钢探头和不锈钢网烧结过滤器 | K14: 响应 | L14: / | M14: 140 | N14: =E14*M14 -> 3640 | O14: 1912 | P14: =E14*O14 -> 49712 | Q14: =E14*(M14+O14) -> 53352
A15: 10 | B15: 温湿度传感器 | C15: 精度：±2%RH；湿度输出：0-10V；温度输出：NTC20K，±0.2°C @25°C；温度量程：0~50℃；继电器输出：无；LCD显示无； | D15: 霍尼韦尔、江森、西门子 | E15: 2 | F15: 台 | H15: 霍尼韦尔 | I15: HSH-RV3B | J15: 壁挂式温湿度传感器，NTC20K温度输出，3%湿度精度，0~10V | K15: 响应 | L15: / | M15: 140 | N15: =E15*M15 -> 280 | O15: 425 | P15: =E15*O15 -> 850 | Q15: =E15*(M15+O15) -> 1130
A16: 11 | B16: 管道风速监测传感器 | C16: 量程：0–20 m/s（0–4000 ft/min），精度：±0.2 m/s（≤10 m/s）；±2% FS（>10 m/s），输出信号：0–10VDC（线性对应量程），供电：24VDC ±10%（BA 标准供电） 材质 / 防护：ABS 外壳，探杆 304 不锈钢；IP65 温度：-10℃~+50℃（耐高温款可达 80℃） 安装：法兰开孔插入式，带密封圈，漏风小 | D16: 霍尼韦尔、江森、西门子 | E16: 89 | F16: 台 | H16: 霍尼韦尔 | I16: AVT25101 | J16: 风速变送器，风管型风速变送器，输出：0-10VDC&4-20mA | K16: 响应 | L16: / | M16: 140 | N16: =E16*M16 -> 12460 | O16: 913 | P16: =E16*O16 -> 81257 | Q16: =E16*(M16+O16) -> 93717
A17: 12 | B17: 继电器 | C17: 适配电磁阀信号选配 | D17: 霍尼韦尔、江森、西门子 | E17: 100 | F17: 个 | H17: 西门子 | I17: ER2EL - D24 | J17: 8脚 5A 2开2闭 DC24V | K17: 响应 | L17: / | M17: 17 | N17: =E17*M17 -> 1700 | O17: 16 | P17: =E17*O17 -> 1600 | Q17: =E17*(M17+O17) -> 3300
A18: 13 | B18: 交流电流变送器 | C18: 输出4-20mA三相模块RS485信号 | D18: 霍尼韦尔、江森、西门子 | E18: 168 | F18: 个 | H18: 霍尼韦尔 | I18: CSNK500M | J18: 输出4-20mA，三相模块，RS485信号 | K18: 响应 | L18: / | M18: 140 | N18: =E18*M18 -> 23520 | O18: 457 | P18: =E18*O18 -> 76776 | Q18: =E18*(M18+O18) -> 100296
A19: 14 | B19: 光纤熔接盒（含光纤熔纤） | C19: SC4芯单模满配含熔接尾纤、法兰、SC光跳线 | D19: 一舟、普天天纪、罗格朗 | E19: 129 | F19: 个 | H19: 一舟 | I19: S953-4X+S905-3*4+S812*4 | J19: SC4芯单模满配含熔接尾纤、法兰、SC光跳线 | K19: 响应 | L19: / | M19: 52 | N19: =E19*M19 -> 6708 | O19: 71 | P19: =E19*O19 -> 9159 | Q19: =E19*(M19+O19) -> 15867
A20: 15 | B20: 光纤收发器 | C20: 1个10/100M/1000M网口，1个1000Mbps光口（SC），工作波长：1550nm（发送）、1310nm（接收），20km。 | D20: TP-LINK、山泽、烽火 | E20: 129 | F20: 对 | H20: TP-LINK | I20: TL-FC311A-20+TL-FC311B-20 | J20: 1个10/100M/1000M网口，1个1000Mbps光口（SC），工作波长：1550nm（发送）、1310nm（接收），20km。 | K20: 响应 | L20: / | M20: 17 | N20: =E20*M20 -> 2193 | O20: 240 | P20: =E20*O20 -> 30960 | Q20: =E20*(M20+O20) -> 33153
A21: 16 | B21: 光纤收发器架 | C21: 14槽光纤收发器机架；标准机柜安装； | D21: TP-LINK、山泽、烽火 | E21: 34 | F21: 个 | H21: TP-LINK | I21: TL-FC1400 | J21: 14槽光纤收发器机架；标准机柜安装； | K21: 响应 | L21: / | M21: 17 | N21: =E21*M21 -> 578 | O21: 504 | P21: =E21*O21 -> 17136 | Q21: =E21*(M21+O21) -> 17714
A22: 17 | B22: 室外4芯单模光缆 | C22: 1.标准：YD/T769，ISO/IEC11801，ANSI/TIA -568-C.3 2.全截面阻水结构，松套管填充纤膏，松套管和钢带之间填充缆膏，确保良好的阻水防潮性能 3.光纤规格：B1.3（OS2） 4.衰减＠20℃（dB/Km）：＠1310nm≤0.36，＠1550nm≤0.22 5.光纤芯数：4芯 6.护套：夹带钢丝的钢-聚乙烯粘结护套，MDPE，黑色 7.允许拉伸力：长期：600N，短期：1500N 8.允许压扁力：长期：300N/100mm，短期：1000N/100mm 9.最小弯曲半径：动态：20D，静态：10D | D22: 一舟、普天天纪、罗格朗 | E22: 130000 | F22: m | H22: 一舟 | I22: D173-4 | J22: 1.标准：YD/T769，ISO/IEC11801，ANSI/TIA -568-C.3 2.全截面阻水结构，松套管填充纤膏，松套管和钢带之间填充缆膏，确保良好的阻水防潮性能 3.光纤规格：B1.3（OS2） 4.衰减＠20℃（dB/Km）：＠1310nm≤0.36，＠1550nm≤0.22 5.光纤芯数：4芯 6.护套：夹带钢丝的钢-聚乙烯粘结护套，MDPE，黑色 7.允许拉伸力：长期：600N，短期：1500N 8.允许压扁力：长期：300N/100mm，短期：1000N/100mm 9.最小弯曲半径：动态：20D，静态：10D | K22: 响应 | L22: / | M22: 1 | N22: =E22*M22 -> 130000 | O22: 2 | P22: =E22*O22 -> 260000 | Q22: =E22*(M22+O22) -> 390000 | S22: 施工费偏低无法实现
A23: 18 | B23: 24口光纤配线架（含尾纤、LC双工耦合器、熔接） | C23: 1.标准：YD/T778，ISO/IEC 11801，ANSI/TIA -568-C.3 2.安装方式：19″机架式安装 3.4个光缆进线口，带固定PG头，盒内配置光缆护套固定装置，光缆加强件固定装置 4.通用型设计，可兼容：LC双工、SC单工、FC、ST适配器，一个4口支架仅需一颗螺丝，便于安装和拆卸 5.进出光纤方便灵活，有充裕的光纤盘存空间，光纤和尾纤弯曲半径不小于30mm 6.端口数量： 24口，空余端口可安装空白功能件，高度：1U 7.表面处理：静电喷塑 8.材料：优质冷扎钢板 9.表面颜色：黑色 10.含LC双工耦合器 | D23: 一舟、普天天纪、罗格朗 | E23: 24 | F23: 个 | H23: 一舟 | I23: S952-12X+S905-7-1*12+S813*24 | J23: 1.标准：YD/T778，ISO/IEC 11801，ANSI/TIA -568-C.3 2.安装方式：19″机架式安装 3.4个光缆进线口，带固定PG头，盒内配置光缆护套固定装置，光缆加强件固定装置 4.通用型设计，可兼容：LC双工、SC单工、FC、ST适配器，一个4口支架仅需一颗螺丝，便于安装和拆卸 5.进出光纤方便灵活，有充裕的光纤盘存空间，光纤和尾纤弯曲半径不小于30mm 6.端口数量： 24口，空余端口可安装空白功能件，高度：1U 7.表面处理：静电喷塑 8.材料：优质冷扎钢板 9.表面颜色：黑色 10.含LC双工耦合器 | K23: 响应 | L23: / | M23: 17 | N23: =E23*M23 -> 408 | O23: 308 | P23: =E23*O23 -> 7392 | Q23: =E23*(M23+O23) -> 7800
A24: 19 | B24: 光纤跳线 | C24: 单模双芯SC-LC优质2米光纤跳线； | D24: 一舟、普天天纪、罗格朗 | E24: =E20 -> 129 | F24: 个 | H24: 一舟 | I24: S928 | J24: 单模双芯SC-LC优质2米光纤跳线； | K24: 响应 | L24: / | M24: 6 | N24: =E24*M24 -> 774 | O24: 24 | P24: =E24*O24 -> 3096 | Q24: =E24*(M24+O24) -> 3870
A25: 20 | B25: 六类非屏蔽跳线（2m） | C25: 1.标准：不低于TIA/EIA568-C.2、ISO/IEC11801、IEC60332-1、GB 50311； 2.导体规格：多股绞合，软圆铜线，4×2×23AWG； 3.护套材料：PVC，护套外径：6.3±0.3mm； 4.插头规格：RJ45，8P8C； 5.插拔次数：≥1000次； 6.最高传输频率：不小于250MHz； 7.线缆外护套上间隔印有商标、电缆编号、电缆类别、线规、防火等级、标准； 8.支持以太网供电应用（POE/POE+）； 9.描述：用于办公桌桌面跳线，长度2米 10.为了保证性能的匹配性和稳定性，综合布线光纤系统、铜缆系统应采用同一品牌。 | D25: 一舟、普天天纪、罗格朗 | E25: =E20*2 -> 258 | F25: 个 | H25: 一舟 | I25: SF200-GY | J25: 1.标准：不低于TIA/EIA568-C.2、ISO/IEC11801、IEC60332-1、GB 50311； 2.导体规格：2.导体规格：多股绞合铜线，4×2×24AWG； 3.护套材料：PVC，护套外径：6.3±0.3mm； 4.插头规格：RJ45，8P8C； 5.插拔次数：≥1000次； 6.最高传输频率：不小于250MHz； 7.线缆外护套上间隔印有商标、电缆编号、电缆类别、线规、防火等级、标准； 8.支持以太网供电应用（POE/POE+）； 9.描述：用于办公桌桌面跳线，长度2米 10.为了保证性能的匹配性和稳定性，综合布线光纤系统、铜缆系统应采用同一品牌。 | K25: 响应 | L25: / | M25: 6 | N25: =E25*M25 -> 1548 | O25: 13 | P25: =E25*O25 -> 3354 | Q25: =E25*(M25+O25) -> 4902
A26: 21 | B26: 24口接入交换机-单电源 | C26: ★在不插板卡情况下，单设备交换容量≥336Gbps，包转发率≥120Mpps，提供≥24个千兆电接口、≥4个千兆SFP光接口 1、支持堆叠技术或者虚拟化技术 2、支持 4K 802.1Q VLAN,支持Voice VLAN及Voice VLAN中可以同时识别多厂家的OUI地址，支持端口VLAN、MAC VLAN 3、支持标准IP ACL（基于IP地址的硬件ACL）支持扩展IP ACL（基于IP地址、TCP/UDP端口号的硬件ACL） 4、支持QOS 5、支持一对一、多对一、一对多的镜像 6、支持DHCP Server、DHCP Client、DHCP Snooping、DHCP Relay、DHCP Option82 7、支持广播风暴抑制 8、支持设备登陆管理的AAA安全认证、radius认证、支持802.1x、支持ssh2.0 9、支持STP/RSTP/MSTP协议 10、支持链路聚合（支持静态、动态链路聚合、千兆口聚合） 11、有标准的或私有的邻居发现协议 12、支持VLAN虚接口 13、支持 IPv4 /ipv6静态路由 14、支持OSPFv2、OSPFv3 15、支持SNMPv1/v2/v3，WEB网管，支持命令行接口配置，Telnet，SSH，Console口配置，支持系统日志，分级告警，调试信息输出，NTP/SNTP ★16、提供真实有效的工信部入网证复印件； ★17、原厂质保≥3年 ★18、考虑设备兼容性、项目实施、交付及售后服务，采用与核心交换机同一品牌。 | D26: 华三、锐捷（非睿易） | E26: 12 | F26: 台 | H26: 锐捷 | I26: RG-S2910-24GT4SFP-L | J26: 24个10/100/1000Base-T自适应以太网接口，4个1GE SFP接口； 交换容量:598Gbps/5.98Tbps;包转发率:126Mpps; 支持4K 802.1Q VLAN，支持Port based VLAN，支持MAC based VLAN，支持Voice VLAN，支持GVRP； 支持STP、RSTP、MSTP； 支持DHCP Server ，支持DHCP Client ，支持DHCP Snooping，支持DHCP Relay； 支持VSU虚拟化技术，支持本地堆叠和远程堆叠，支持通过标准业务口实现虚拟化； 支持IPv4/IPv6静态路由、可扩展支持RIP、RIPng、OSPF、OSPFv3协议; 支持端口流量识别，支持端口流量限速，支持802.1p/DSCP/TOS流量分类，支持SP、WRR、DRR、SP+WFQ、 SP+WRR、SP+DRR、RED/WRED队列调度； 支持过滤非法的MAC地址，支持广播风暴抑制，支持BPDU Guard，支持CPP、NFPP，支持端口保护； 支持SNMP、CLI(Telnet/Console)、RMON、SSH、Syslog/Debug、NTP/SNTP、FTP、TFTP、Web、WIS公有云平台管理; | K26: 响应 | L26: / | M26: 58 | N26: =E26*M26 -> 696 | O26: 1487 | P26: =E26*O26 -> 17844 | Q26: =E26*(M26+O26) -> 18540
A27: 22 | B27: 千兆单模光模块 | C27: LC接口，单模千兆光纤（和交换机同品牌） | D27: 华三、锐捷（非睿易） | E27: 24 | F27: 个 | H27: 锐捷 | I27: MINI-GBIC-LX-SM1310 | J27: 1000BASE-LX mini GBIC转换模块（1310nm），10km | K27: 响应 | L27: / | M27: 2 | N27: =E27*M27 -> 48 | O27: 112 | P27: =E27*O27 -> 2688 | Q27: =E27*(M27+O27) -> 2736
A28: 23 | B28: 信号线 | C28: 国标，RVV2*1.0 | D28: 一舟、普天天纪、罗格朗 | E28: 3800 | F28: m | H28: 一舟 | I28: G1807_60227 IEC 53(RVV) 2x1.0 | J28: 国标，RVV2*1.0 | K28: 响应 | L28: / | M28: 2 | N28: =E28*M28 -> 7600 | O28: 3 | P28: =E28*O28 -> 11400 | Q28: =E28*(M28+O28) -> 19000
A29: 24 | B29: 信号线 | C29: 国标，RVVP2*1.0 | D29: 一舟、普天天纪、罗格朗 | E29: 7200 | F29: m | H29: 一舟 | I29: G4407_RVVP2x1.0 | J29: 国标，RVVP2*1.0 | K29: 响应 | L29: / | M29: 2 | N29: =E29*M29 -> 14400 | O29: 6 | P29: =E29*O29 -> 43200 | Q29: =E29*(M29+O29) -> 57600
A30: 25 | B30: 信号线 | C30: 国标，RVVP4*1.0 | D30: 一舟、普天天纪、罗格朗 | E30: 5000 | F30: m | H30: 一舟 | I30: G4607_RVVP4*1.0 | J30: 国标，RVVP4*1.0 | K30: 响应 | L30: / | M30: 2 | N30: =E30*M30 -> 10000 | O30: 9 | P30: =E30*O30 -> 45000 | Q30: =E30*(M30+O30) -> 55000
A31: 26 | B31: 信号线 | C31: 国标，RVVP6*1.0 | D31: 一舟、普天天纪、罗格朗 | E31: 154 | F31: m | H31: 一舟 | I31: G4807_RVVP6x1.0 | J31: 国标，RVVP6*1.0 | K31: 响应 | L31: / | M31: 2 | N31: =E31*M31 -> 308 | O31: 13 | P31: =E31*O31 -> 2002 | Q31: =E31*(M31+O31) -> 2310
A32: 27 | B32: JDG20管 | C32: JDG管，壁厚不小于1.0MM,φ20；含主材、接头、固定扣件（含钢结构扣件）等辅材 | D32: 国产 | E32: 25000 | F32: m | H32: 国产 | I32: JDG20*1.0 | J32: JDG管，壁厚不小于1.0MM,φ20；含主材、接头、固定扣件（含钢结构扣件） | K32: 响应 | L32: / | M32: 10 | N32: =E32*M32 -> 250000 | O32: 3 | P32: =E32*O32 -> 75000 | Q32: =E32*(M32+O32) -> 325000
A33: 28 | B33: 辅材 | C33: 设备安装配套辅材，水晶头，扎带等 | D33: 国产 | E33: 1 | F33: 项 | H33: 国产 | I33: / | J33: / | K33: 响应 | L33: / | M33: 5825 | N33: =E33*M33 -> 5825 | O33: 0 | P33: =E33*O33 -> 0 | Q33: =E33*(M33+O33) -> 5825
B34: 二、智慧安防系统 | N34: =E34*M34 -> 0 | P34: =E34*O34 -> 0
B35: 2.1、视频监控系统 | N35: =E35*M35 -> 0 | P35: =E35*O35 -> 0
A36: 1 | B36: 抗振防抖场景专用摄像机 | C36: 1.设备采用金属机身，主要接口：1个M12航空头网络接口、1个CVBS接口、1个音频输入接口，1个音频输出接口、1个RS485接口、1个报警输入接口、1个报警输出接口、1个SD卡卡槽（内置） 2.内置1/1.8英寸，400万像素CMOS传感器；最大亮度鉴别等级试验≥11级；最大帧率60fps；延时试验小于200ms；照度适应范围不小于140dB 3.外壳防护等级IP66/IP68 4.机身部分碰撞防护等级IK10 5.摄像机应能在额定电源电压DC9V-DC36V范围内正常工作，支持POE供电 6.设备支持红外和暖光补光灯，可通过IE浏览器或客户端切换补光灯类型 7.最低照度试验：彩色：0.0005 lx，黑白：0.0001 lx 8.支持开启、关闭畸变矫正功能 9.防抖功能检查：在水平X轴方向随机抖动频率范围5Hz-62Hz，加速度有效值：5.6m/s²，最大振幅3.39mm；相机配置：2560X1440，最大焦距，座装安装，镜头方向朝下；在图像中指定4个像素点，最大偏移应不超过±1%。 10.防抖功能检查：在水平Y轴方向随机抖动频率范围5Hz-62Hz，加速度有效值：5.6m/s²，最大振幅3.39mm；相机配置：2560X1440，最大焦距，座装安装，镜头方向朝下；在图像中指定4个像素点，最大偏移应不超过±1%。 11.防抖功能检查：在垂直Z轴方向随机抖动频率范围5Hz-26Hz，加速度有效值：5.6m/s²，最大振幅3.39mm；相机配置：2560X1440，最大焦距，座装安装，镜头方向朝下；在图像中指定4个像素点，最大偏移应不超过±1.5%。 12.在彩色模式下，当照度降低至一定值时，设备可自动开启白光灯补光，设备在白天、夜晚均可输出彩色视频图像 13.可通过扫描预览界面上生产的二维码获取设备资料。 14.当移动侦测、进入区域、离开区域、越界区域或区域入侵报警类型设置为人和/或车时，仅当检测区域中出现对应的人和/或车时，才触发报警；当报警产生时，可触发联动白光灯闪烁，白光灯闪烁的时间和频率可设置 15.设备具有APP管理功能，支持在线导入APP、删除APP、加载运行APP、配置APP操作，APP管理操作无需重启设备，操作期间预览画面无中断。 16.设备支持用户自定义最多16个AI算法库，可设置当前生效的算法库和显示当前算法库的运行状态，并支持修改、删除算法库及自定义算法库名称。 17.设备具有良好的环境适应性，工作温度范围可达-40℃～60℃。 | D36: 海康 | E36: 6 | F36: 台 | H36: 海康威视 | I36: DS-2XC7245/KZ | J36: 1.设备采用金属机身，主要接口：1个M12航空头网络接口、1个CVBS接口、1个音频输入接口，1个音频输出接口、1个RS485接口、1个报警输入接口、1个报警输出接口、1个SD卡卡槽（内置）。 2.内置1/1.8英寸，400万像素CMOS传感器。 3.最大亮度鉴别等级试验≥11级。 4.最大帧率60fps。 5.延时试验小于200ms。 6.照度适应范围不小于140dB。 7.外壳防护等级IP66/IP68。 8.机身部分碰撞防护等级IK10。 9.摄像机应能在额定电源电压DC9V-DC36V范围内正常工作，支持POE供电。 10.设备支持红外和暖光补光灯，可通过IE浏览器或客户端切换补光灯类型。 11.最低照度试验：彩色：0.0005 lx，黑白：0.0001 lx。 12.支持开启、关闭畸变矫正功能。 13.防抖功能检查：在水平X轴方向随机抖动频率范围5Hz-62Hz，加速度有效值：5.6m/s²，最大振幅3.39mm；相机配置：2560X1440，最大焦距，座装安装，镜头方向朝下；在图像中指定4个像素点，最大偏移应不超过±1%。 14.防抖功能检查：在水平Y轴方向随机抖动频率范围5Hz-62Hz，加速度有效值：5.6m/s²，最大振幅3.39mm；相机配置：2560X1440，最大焦距，座装安装，镜头方向朝下；在图像中指定4个像素点，最大偏移应不超过±1%。 15.防抖功能检查：在垂直Z轴方向随机抖动频率范围5Hz-26Hz，加速度有效值：5.6m/s²，最大振幅3.39mm；相机配置：2560X1440，最大焦距，座装安装，镜头方向朝下；在图像中指定4个像素点，最大偏移应不超过±1.5%。 16.在彩色模式下，当照度降低至一定值时，设备可自动开启白光灯补光，设备在白天、夜晚均可输出彩色视频图像 17.可通过扫描预览界面上生产的二维码获取设备资料。 18.当移动侦测、进入区域、离开区域、越界区域或区域入侵报警类型设置为人和/或车时，仅当检测区域中出现对应的人和/或车时，才触发报警；当报警产生时，可触发联动白光灯闪烁，白光灯闪烁的时间和频率可设置 19.设备具有APP管理功能，支持在线导入APP、删除APP、加载运行APP、配置APP操作，APP管理操作无需重启设备，操作期间预览画面无中断。 20.设备支持用户自定义最多16个AI算法库，可设置当前生效的算法库和显示当前算法库的运行状态，并支持修改、删除算法库及自定义算法库名称。 21.设备具有良好的环境适应性，工作温度范围可达-40℃～60℃。 | K36: 响应 | L36: / | M36: 210 | N36: =E36*M36 -> 1260 | O36: 3027 | P36: =E36*O36 -> 18162 | Q36: =E36*(M36+O36) -> 19422
A37: 2 | B37: 400万变焦筒型网络摄像机 | C37: 1.支持输出图像分辨率不低于2560x1440 2.最低照度彩色：0.005 lx，最大亮度鉴别等级不小于11级 3.补光距离：红外不低于50 m，白光不低于30 m 4.支持电动变焦 5.具备区域入侵、越界、进入区域、离开区域、人员聚集、快速移动、徘徊、物品移除、物品遗留、停车智能分析功能，当以上智能分析行为达到设定的阈值时，可通过客户端软件或IE浏览器给出报警提示 6.同一场景相同图像质量下设备在H.264或H265编码方式时，开启智能编码功能和不开启智能编码相比，码率节约80% 7.靶面尺寸为1/2.7英寸，内置1个麦克风，具有1个RJ45 网络接口，1路音频输入、1路音频输出、1路报警输入、1路报警输出、1 个复位按钮、1个 SD 卡槽、1个 DC12V 电压输出接口 8.支持H.264、H.265视频编码格式，且具有High Profile编码能力 9.支持电源电源在DC12V±25%范围内变化时正常工作，支持POE 10.IP67防护等级 | D37: 海康 | E37: 68 | F37: 台 | H37: 海康威视 | I37: DS-2CD2645V3-FD | J37: 1.支持输出图像分辨率不低于2560x1440 2.支持电动变焦；焦距&视场角：2.7~13.5 mm，水平视场角：100.2°~33.3°，垂直视场角：53.3°~18.7°，对角视场角：119.0°~38.1° 3.最低照度彩色：0.005 lx，最大亮度鉴别等级不小于11级 4.补光距离：红外不低于50 m，白光不低于30 m 5.具备区域入侵、越界、进入区域、离开区域、人员聚集、快速移动、徘徊、物品移除、物品遗留、停车智能分析功能，当以上智能分析行为达到设定的阈值时，可通过客户端软件或IE浏览器给出报警提示 6.同一场景相同图像质量下设备在H.264或H265编码方式时，开启智能编码功能和不开启智能编码相比，码率节约80% 7.靶面尺寸为1/2.7英寸，内置1个麦克风，具有1个RJ45 网络接口，1路音频输入、1路音频输出、1路报警输入、1路报警输出、1 个复位按钮、1个 SD 卡槽、1个 DC12V 电压输出接口 8.支持H.264、H.265视频编码格式，且具有High Profile编码能力 9.支持电源电源在DC12V±25%范围内变化时正常工作，支持POE 10.IP67防护等级 | K37: 响应 | L37: / | M37: 140 | N37: =E37*M37 -> 9520 | O37: 526 | P37: =E37*O37 -> 35768 | Q37: =E37*(M37+O37) -> 45288
A38: 3 | B38: 热成像摄像机 | C38: ★热成像：分辨率：256×192；焦距：焦距可选：3/7/10mm； 可见光：分辨率：2688*1520，400万；焦距：焦距可选：4mm/8mm/12.4mm； 支持1路音频输入，1路音频输出； 支持2路报警输入，2路报警输出； 外壳防护等级：IP67； 电源电压在DC12V±20%范围内变化时，能正常工作； 可通过IE浏览器在热成像画面中设置点、线段、区域测温规则； 点测温、线测温、区域测温中存在高于或者低于报警或预报警温度时，可在客户端显示不同的报警颜色进行报警提示，联动报警输出，联动录像及联动抓拍； 支持声音联动报警功能。可对智能行为、温度超过阈值、出现高温点等行为进行检测并报警，报警声音可设置，同时支持自定义； ★噪声等效温差为8mk，最小可分辨温差为200mk（（公京检第2401130038号第100条） 热成像视频图像具有白热、黑热、融合1、融合2、彩虹1、铁红2、深褐色等42种显示模式 含安装支架 | D38: 海康 | E38: 199 | F38: 台 | H38: 海康威视 | I38: HM-TD2628-XX/T1A | J38: 1.热成像分辨率：256 × 192；热成像焦距可选值：3mm/7mm/10 mm 2.可见光分辨率：2688 × 1520；可见光焦距可选值：4mm/8mm/12.4 mm 3.报警输入：支持2路DC 0~5 V报警输入；报警输出：支持2路常开型继电器输出，报警类型可设置 4.音频输入：1路3.5 mm Mic in/Line in interface. Line input: 2-2.4 V[p-p]；音频输出：1路3.5mm Impedance: 600Ω 5.电源输入：12 VDC ± 25%，PoE (802.3at, class 4) 6.防护等级：IP67 7.可通过IE浏览器在热成像画面中设置点、线段、区域测温规则 8.点测温、线测温、区域测温中存在高于或者低于报警或预报警温度时，可在客户端显示不同的报警颜色进行报警提示，联动报警输出，联动录像及联动抓拍 9.支持声音联动报警功能。可对智能行为、温度超过阈值、出现高温点等行为进行检测并报警，报警声音可设置，同时支持自定义 10.噪声等效温差(NETD)检验：热成像视频图像噪声等效温差(NETD)≤8mK 11.最小可分辨温差(MRTD)检验：热成像视频图像最小可分辨温差(MRTD)≤200mk 12.热成像视频图像具有白热、黑热、融合1、融合2、彩虹1、铁红2、深褐色等42种显示模式 13.画面分割功能检验：可通过IE浏览器开启或关闭画面分割功能，开启后会将画面平分为12宫格，每个宫格均可输出最高温、最低温及平均温数值 含支架安装 | K38: 响应 | L38: / | M38: 140 | N38: =E38*M38 -> 27860 | O38: 2097 | P38: =E38*O38 -> 417303 | Q38: =E38*(M38+O38) -> 445163
A39: 4 | B39: 高空球型鹰眼 | C39: 1.全景通道最高分辨率不小于6072 x 2640，细节通道最高分辨率不小于3840x2160。 2.全景通道内置4个镜头、靶面尺寸不小于1/1.8英寸的CMOS传感器，细节通道内置1个镜头，靶面尺寸不小于1/1.2英寸的CMOS传感器。 3.设备在全景拼接模式下，垂直视场角不小于110°，水平视场角不小于180°。可将4个全景视频图像进行拼接，实现不小于180°拼接画面显示，并抓拍拼接后的图片。 4.细节通道内置镜头支持不小于45倍光学变倍，镜头最大焦距不小于320mm。 5.设备具有光学防抖功能，将镜头倍率设置为最大，快门设置为1/25s，在振动台振幅不大于0.3°，振动频率不大于10Hz情况下，设备视场角应无明显变化，视频图像在振动过程中应保持稳定清晰 6.设备内置2个雨刷器，雨刷器1可清洁全景通道镜头表面玻璃，雨刷器2可清洁细节通道镜头表面玻璃。 7.设备细节通道水平手控最大速度不小于500°/s，垂直手控最大速度不小于350°/s。 8.设备具备双安装接口，一个为快速旋转安装接口，一个为多孔稳定安装接口。 9.支持不小于300个预置位，支持预置位冻结功能。 10.内置不少于3个GPU芯片。 11.支持智能行为分析功能，智能分析行为类型为区域入侵、越界入侵、进入区域、离开区域等，支持行为分析触发后联动聚焦、联动目标跟踪、报警上传等多种报警触发方式。 12.设备在全景视频图像中点击或框选移动目标至设备开始转动的时间小于0.3s，全景图像检测到且框选出移动目标至设备开始转动时间小于0.3s。 13.设备全景通道支持人员密度检测功能，可开启、关闭人员密度检测功能，最多可设置8个多边形（3～10条边）人员密度检测区域。每个区域的名称、人员数量报警阈值等级（低、中、高等级）可自定义。 14.设备全景通道车辆拥堵检测功能，开启车辆拥堵检测功能后，当设置区域内的车辆滞留时间超过设定值时，可通过IE浏览器给出报警提示。 15.设备可切换智能模式，当更换当前智能模式时设备不需重启，新智能模式即可生效。 16.设备全景通道具有默认拼接、手动拼接、自动拼接3种拼接模式；自动拼接模式下设备可自动获取特征并进行拼接。 17.设备具有AI-ISP图像质量提升功能，在低照度环境下，可自动调节预览场景视频画面中人脸、人体、车辆等目标及预览场景视频画面的区域曝光、亮度、色彩饱和度、对比度、锐度等。 18.设备具有不少于1个RJ45网络接口、1个光纤接口、7路报警输入、2路报警输出、1路音频输入、1路音频输出。内置的北斗定位模块，具有定位功能，可自动获取设备所在位置经纬度信息。 19.防护等级不低于IP67。 | D39: 海康 | E39: 3 | F39: 台 | H39: 海康威视 | I39: DS-2DP1618XS-LD | J39: 1.全景通道最高分辨率不小于6072 x 2640，细节通道最高分辨率不小于3840x2160。 2.全景通道内置4个镜头、靶面尺寸不小于1/1.8英寸的CMOS传感器，细节通道内置1个镜头，靶面尺寸不小于1/1.2英寸的CMOS传感器。 3.设备在全景拼接模式下，垂直视场角不小于110°，水平视场角不小于180°。可将4个全景视频图像进行拼接，实现不小于180°拼接画面显示，并抓拍拼接后的图片。 4.细节通道内置镜头支持不小于45倍光学变倍，镜头最大焦距不小于320mm。 5.设备具有光学防抖功能，将镜头倍率设置为最大，快门设置为1/25s，在振动台振幅不大于0.3°，振动频率不大于10Hz情况下，设备视场角应无明显变化，视频图像在振动过程中应保持稳定清晰。 6.设备内置2个雨刷器，雨刷器1可清洁全景通道镜头表面玻璃，雨刷器2可清洁细节通道镜头表面玻璃。 7.设备细节通道水平手控最大速度不小于500°/s，垂直手控最大速度不小于350°/s。 8.设备具备双安装接口，一个为快速旋转安装接口，一个为多孔稳定安装接口。 9.支持不小于300个预置位，支持预置位冻结功能。 10.内置不少于3个GPU芯片。 11.支持智能行为分析功能，智能分析行为类型为区域入侵、越界入侵、进入区域、离开区域等，支持行为分析触发后联动聚焦、联动目标跟踪、报警上传等多种报警触发方式。 12.设备在全景视频图像中点击或框选移动目标至设备开始转动的时间小于0.3s，全景图像检测到且框选出移动目标至设备开始转动时间小于0.3s。 13.设备全景通道支持人员密度检测功能，可开启、关闭人员密度检测功能，最多可设置8个多边形（3～10条边）人员密度检测区域。每个区域的名称、人员数量报警阈值等级（低、中、高等级）可自定义。 14.设备全景通道车辆拥堵检测功能，开启车辆拥堵检测功能后，当设置区域内的车辆滞留时间超过设定值时，可通过IE浏览器给出报警提示。 15.设备可切换智能模式，当更换当前智能模式时设备不需重启，新智能模式即可生效。 16.设备水平安装在8m高度时，可通过全景通道监控设备正下方8m且水平距离0.5m处的行人目标。 17.设备全景通道具有默认拼接、手动拼接、自动拼接3种拼接模式；自动拼接模式下设备可自动获取特征并进行拼接。 18.设备具有AI-ISP图像质量提升功能，在低照度环境下，可自动调节预览场景视频画面中人脸、人体、车辆等目标及预览场景视频画面的区域曝光、亮度、色彩饱和度、对比度、锐度等。 19.设备支持画中画功能，可通过IE浏览器在细节图像中叠加全景视频图像进行预览。 20.设备可在立体防控系统平台上添加、修改、删除和标注AR标签，包括警务站视频标签、建筑物视频标签、卡口视频标签和普通视频标签，最多可添加500个标签。可通过客户端软件在视频画面上添加定点标签、区域标签、矢量标签和方向标签，并可对标签进行联动操作。 21.当设备调焦或转动时，立体防控系统平台上的AR视频标签应与所标记物体保持相对静止。 22.当通过标签名称对标签进行搜索并选中指定标签时，设备应转动至指定标签方向并聚焦，当点击指定标签时，可查看标签信息并对相关联的设备视频图像进行预览和放大等操作。 23.设备具有偏色矫正功能，可通过手动或自动的方式对采集到的视频进行偏色矫正。 24.设备可对全景通道、细节通道监控画面中的移动标签进行跟踪且跟踪时间、跟踪倍率可设，在跟踪过程中，移动标签始终位于画面中心位置。在细节通道上添加或删除指定标签时，全景通道的相同位置应自动添加或删除该标签。 25.开启补光灯，可识别距设备不小于500m处的人体轮廓。 26.设备具有不少于1个RJ45网络接口、1个光纤接口、7路报警输入、2路报警输出、1路音频输入、1路音频输出。内置的北斗定位模块，具有定位功能，可自动获取设备所在位置经纬度信息。 27.防护等级不低于IP67。 | K39: 响应 | L39: / | M39: 233 | N39: =E39*M39 -> 699 | O39: 28673 | P39: =E39*O39 -> 86019 | Q39: =E39*(M39+O39) -> 86718
A40: 5 | B40: 人脸识别布控球 | C40: 1.单北斗5G双摄便携球套装 2.支持双摄：40倍光学变倍机芯，最大分辨率2560*1440，图像清晰、细腻，低照度，彩色0.0001Lux；全景镜头8M，分辨率2160×3840 3.支持自动彩转黑功能，实现昼夜监控 4.支持人脸比对，可存储30W张人脸名单（含一张1TB TF卡） 5.支持车辆检测及抓拍 6.支持抽烟、佩戴安全帽、玩手机、未穿工作服检测 7.支持3D-DNR 8.支持双TF卡存储 9.支持5G模块（天线内置），可额外扩展1个4G模块 10.配置可拆卸电池，单电池可支持8-9小时连续工作 11.支持双MIC、双扬声器，可选配支持LINE IN\LINE OUT 12.支持自定义语音导入，可关联智能分析报警 13.自带2.4寸LCD显示屏，可支持视频预览，云台控制等，可显示当前电池电量、定位状态、3G/4G/5G状态、录像状态、存储容量、蓝牙状态、平台连接状态、Wi-Fi状态、智能算法模式等 14.底部配置高吸力磁铁，安装便捷 | D40: 海康 | E40: 5 | F40: 台 | H40: 海康威视 | I40: iDS-MCD402-MF/40X+TF-P1/1T/TAY | J40: 1.单北斗5G双摄便携球套装 2.支持双摄：40倍光学变倍机芯，最大分辨率2560*1440，图像清晰、细腻，低照度，彩色0.0001Lux；全景镜头8M，分辨率2160×3840； 3.支持自动彩转黑功能，实现昼夜监控 4.支持人脸比对，可存储30W张人脸名单（已配置1张1TB TF卡） 5.支持车辆检测及抓拍 6.支持抽烟、佩戴安全帽、玩手机、未穿工作服检测 7.支持3D-DNR 8.支持双TF卡存储 9.支持5G模块（天线内置），可额外扩展1个4G模块 10.配置可拆卸电池，单电池可支持8-9小时连续工作 11.支持双MIC、双扬声器，可选配支持LINE IN\LINE OUT 12.支持自定义语音导入，可关联智能分析报警 13.自带2.4寸LCD显示屏，可支持视频预览，云台控制等，可显示当前电池电量、定位状态、3G/4G/5G状态、录像状态、存储容量、蓝牙状态、平台连接状态、Wi-Fi状态、智能算法模式等 14.底部配置高吸力磁铁，安装便捷 | K40: 响应 | L40: / | M40: 233 | N40: =E40*M40 -> 1165 | O40: 18053 | P40: =E40*O40 -> 90265 | Q40: =E40*(M40+O40) -> 91430
A41: 6 | B41: 智能融合应用主机 | C41: 1.整机最大支持512路普通视频流(2MP)接入或768路文搜相机(2MP/4MP)接入，实现大模型以文搜图算法、人脸算法、结构化算法并行分析 2.整机共搭载8张GPU计算卡，其中4张抓拍卡，用于视频全目标抓拍；4张计算卡，共6个虚拟引擎，可自定义配置以文搜图算法、人脸算法、结构化算法 3.设备支持1亿条目标抓拍图片、结构化属性、模型存储（人脸+结构化） 4.集成GCN聚类算法，实现二级人员聚类方案，提供更优的人员目标聚类效果 5.大模型以文搜图算法；支持1亿条图片数据秒级文本搜图 6.大模型文本预警：支持文本描述目标关键特征，快速开启布防任务；支持1000条文本语义预警布防；最大支持50路视频流文本预警 7.大模型文本微调：支持对搜索结果进行快速标定和文本微调训练，提升文本搜图和预警效果；单次最大支持50张图片进行微调 8.人脸应用：支持目标抓拍、比对报警，以图搜图、属性检索，高频报警，1V1比对，人员档案 9.支持300万人脸静态库，300万人脸名单库比对报警，128个名单库，1亿条抓拍数据秒级检索 10.结构化应用：支持人体/车辆/非机动车抓拍、建模，以图搜图、属性检索 11.CPU：2颗64位多核处理器 12.GPU：8张GPU计算卡 13.系统内存：160GB DDR4内存 14.系统盘：2×240GB SSD 15.数据盘：1×1.92T SSD（M.2 NVMe），1× 4TB SATA盘，8× 8TB SATA盘 16.网络接口：2×千兆电口 + 2×万兆光口 17.其它接口：2×VGA接口，4×USB接口 18.整机电源：1200W ，1+1冗余电源 | D41: 海康 | E41: 1 | F41: 台 | H41: 海康威视 | I41: DS-IX2512-U/SF | J41: 【智能应用】 整机最大支持512路普通视频流(2MP)接入或768路文搜相机(2MP/4MP)接入，实现智能目标抓拍、大模型以文搜图算法、人脸算法、结构化算法并行分析。 整机共搭载8张GPU计算卡，其中4张抓拍卡，用于视频全目标抓拍；4张计算卡，共6个虚拟引擎，可自定义配置以文搜图算法、人脸算法、结构化算法； 设备支持1亿条目标抓拍图片、结构化属性、模型存储（人脸+结构化） 集成GCN聚类算法，实现二级人员聚类方案，提供更优的人员目标聚类效果 支持以下3大类算法： 1、大模型以文搜图算法 实时视频流/历史视频流：最大支持512路分析（512路2MP/256路4MP/128路8MP 视频流） 图片流：建模性能90张/秒（目标小图或 2MP/4MP大图+坐标）或65张/秒（8MP大图+坐标） 大模型图文建模：支持对目标进行大模型建模，通过建模引擎将目标图片转化成语义数据模型 大模型文本搜图：输入搜索目标的文本描述，可快速搜索对应的视图内容，支持搜人、车、非机动车、物品； 支持1亿条图片数据秒级文本搜图 大模型文本预警：支持文本描述目标关键特征，快速开启布防任务；支持1000条文本语义预警布防；最大支持50路视频流文本预警 大模型文本微调：支持对搜索结果进行快速标定和文本微调训练，提升文本搜图和预警效果；单次最大支持50张图片进行微调 单个虚拟引擎：90张/秒（目标小图或 2MP/4MP大图+坐标）或65张/秒（8MP大图+坐标），预分配1个虚拟引擎 2、人脸算法 人脸应用：支持目标抓拍、比对报警，以图搜图、属性检索，高频报警，1V1比对，人员档案 实时视频流/历史视频流：最大支持512路分析（512路2MP/256路4MP/128路8MP 视频流） 图片流：支持384张/秒（建模+比对+聚类） 离线录像导入，支持1TB空间，最大支持128倍速分析（128倍速2MP/64倍速4MP/32倍速8MP 视频文件） 支持300万人脸静态库，300万人脸名单库比对报警，128个名单库，1亿条抓拍数据秒级检索 单个虚拟引擎：128张/秒（建模+比对+聚类），预分配3个虚拟引擎 3、结构化算法 结构化应用：支持人体/车辆/非机动车抓拍、建模，以图搜图、属性检索 实时视频流/历史视频流：最大支持512路分析（512路2MP/256路4MP/128路8MP 视频流） 图片流：支持260张/秒 单个虚拟引擎：最大130张/秒，预分配2个虚拟引擎 离线录像导入，支持1TB空间，最大支持128倍速分析（128倍速2MP/64倍速4MP/32倍速8MP 视频文件） 【硬件规格】 CPU：2颗64位多核处理器 GPU：8张GPU计算卡 系统内存：160GB DDR4内存 系统盘：2×240GB SSD 数据盘：1×1.92TB SSD（M.2 NVMe），1× 4TB SATA盘，8× 8TB SATA盘 网络接口：2×千兆电口 + 2×万兆光口 其它接口：2×VGA接口，4×USB接口 整机电源：1200W ，1+1冗余电源 机箱尺寸：87.5 mm(高) × 446.6 mm（宽） × 835 mm（深） | K41: 响应 | L41: / | M41: 117 | N41: =E41*M41 -> 117 | O41: 605310 | P41: =E41*O41 -> 605310 | Q41: =E41*(M41+O41) -> 605427
A42: 7 | B42: AI服务器 | C42: 主处理器：配置2颗KP920处理器，核数≥24核，主频≥2.5GHz； 操作系统：openEuler-22.03-LTS-aarch64 智能卡数量：配置8张Atlas 300V 智能卡；最大可支持8个智能卡 场景以本表格《附录五硬件场景需求表》为准 要求算法识别准确率、设备监测准确率不低于95% | D42: 海康 | E42: 4 | F42: 台 | H42: 海康威视 | I42: DS-IF2008/AI | J42: 处理器：配置2颗KP920 7260处理器，核数≥64核，主频≥2.6GHz；支持2颗鲲鹏920处理器（每颗处理器32/48/64核，主频2.6GHz） 内存：配置 384G DDR4；最大支持32根内存插槽，其中32核机型16个DDR4内存插槽，48/64核机型32个DDR4内存插槽 存储方案：配置1块480G SSD；最多配置16个3.5英寸SAS/SATA硬盘 独显&GPU扩展：配置8张Atlas 300V Pro加速卡；最大可支持8个半高半长单宽AI加速卡 存储控制器：标配SAS_HBA 卡，支持RAID 0/1/10；可选支持 RAID 0, 1, 5, 6, 10, 50, 60，可选支持超级电容掉电保护 网络控制器：配置2个千兆电口、2个万兆光口；支持2个板载网络插卡，每个插卡支持4*G电口或者2*10GE/25GE光口；或支持2个OCP3.0网卡 PCI&PCI E扩展槽：最大可支持11个标准PCIe槽位；或2个PCIe4.0 x16+5个PCIe 4.0 x8；或9个PCIe 4.0 x8标准插槽 散热系统：支持4个热拔插风扇模组，支持N+1冗余 电源方案：配置2000W(1+1)冗余电源；2个热插拔900W或2000W交流电源模块；支持1+1冗余 其它端口：前面板提供2个USB3.0 、1个VGA、1个Type-C接口； 后面板提供2个USB3.0端口、1个DB15 VGA端口、1个3.5mm串口、1个RJ45系统管理端口 机箱尺寸：447 mm*814 mm*86.1 mm（宽*深*高） 操作系统兼容：HIKOS、openEuler、SUSE、Ubuntu、CentOS、中标麒麟、银河麒麟、普华、统信、中科红旗、麒麟信安、拓林思等操作系统等操作系统 管理功能：BMC支持IPMI、SOL、KVM over IP以及虚拟媒体，提供1个10/100/1000Mbps的RJ45管理网口 | K42: 响应 | L42: / | M42: 140 | N42: =E42*M42 -> 560 | O42: 329204 | P42: =E42*O42 -> 1316816 | Q42: =E42*(M42+O42) -> 1317376
A43: 8 | B43: 存储服务器 | C43: 1.服务器配置： 1颗64位多核处理器，8GB内存，内存支持扩展到≥256GB，内置SSD固态硬盘（可以扩展到4个SSD作为缓存盘），配置8个风扇，风扇支持热插拔并可冗余温控调速；支持热插拔1+1AC220V电源或1+1直流冗余电源供电 2. 设备具备1个定位灯、1个电源灯、1个设备报警灯、1个就绪灯、1个网络状态灯、1个系统盘状态灯、1个硬盘状态灯，机箱具备防尘滤网，采用双立柱防震设计。设备左右侧面各2个抬手，具备前面板抽拉标签卡 3. 4个2.5Gb网口，支持2个前置 USB2.0接口、2个后置USB3.0接口，支持1个前置VGA接口、1个后置HDMI接口，支持1个RS-232串口，支持4个PCI-E3.0 4. 可接入2T/3T/4T/6T/8T/10T/12T/14T/16T/18T/20T/25T/26T/30T SATA/SAS硬盘；支持NL-SAS 硬盘、HDD硬盘、SSD硬盘、氦气硬盘、空气硬盘；支持 CMR或SMR硬盘；支持硬盘交错/分时启动 5.支持SATA和SAS混插，支持不同品牌（希捷、西数、东芝、海康威视）的硬盘混插；支持不同大小的硬盘混合使用，可显示硬盘的总容量（各个硬盘容量之和） 6. 应能接入并存储总码流不超过4096Mbps的2048路2Mbps码流或1024路4Mbps码流的视(音)频图像;同时转发总码流不超过4096Mbps的2048路2MbpS码流或1024路4Mbps码流的视(音)频图像;同时下载总码流不超过4096Mbps的2Mbps码流的视(音)频图像;同时回放总码流不超过1400 Mbps的视(音)频图像。当RAID处于降级或重构状态时，存储业务正常。在转发模式下，可进行4096路2Mbps视频码流转发，在总带宽不变的情况下，接入、转发、回放间的性能值可自由调整 7. 支持 ONVIF、PSIA、TCP/IP、UDP、SIP、SIP2.0、RTSP、RTP、RTCP、iSCSI、CIFS(SMB)、NFS、FTP、HTTP、AFP、RSYNC、SNMP、IPV4、IPV6、HLS、S3、OSS等协议，支持IP组播 8.抓拍图片、弹出报警画面、发送语音提示、上传中心、蜂鸣报警以及日志 9.可扩展支持将前端一路视频流同时存入两台存储；支持双机间编码器和录像同步，故障时可进行互相接管 10.可对视音频、图片、结构化数据、对象等文件进行混合存储，并可通过http和https方式下载 11.支持查看硬盘体检报告、硬盘深度体检和磁盘档案；支持下载单个硬盘或批量硬盘的报告，支持按时间显示硬盘的坏扇区、温度、振动变化趋势的曲线图；支持硬盘体检报告打印输出；支持查看硬盘体检的历史记录、硬盘健康状态，包括健康、亚健康、故障等； 12.更换系统盘并配置好信息后，再次开机无需人工介入，可自动恢复业务，历史数据不应丢失。 13.配置48块8T硬盘 | D43: 海康 | E43: 3 | F43: 台 | H43: 海康威视 | I43: DS-A71148R/GR | J43: 1.设备配置：≥1颗64位多核处理器，≥8GB内存，内存支持扩展到≥256GB，内置SSD固态硬盘（可以扩展到4个SSD作为缓存盘），配置≥8个风扇，风扇支持热插拔并可冗余温控调速；支持热插拔1+1AC220V电源或1+1直流冗余电源供电 2.设备标配：≥4个2.5Gb网口，支持2个前置 USB2.0接口、2个后置USB3.0接口，支持1个前置VGA接口、1个后置HDMI接口，支持1个RS-232串口，支持4个PCI-E扩展槽 3.具有48个硬盘热插拔插槽；支持硬盘热插拔设备在读写数据时，热插拔设备内的任意块硬盘，设备正常运行不宕机，硬盘不损坏，数据不丢失，业务不中断（本次已配置48块8TB硬盘） 4.设备具备1个定位灯、1个电源灯、1个设备报警灯、1个就绪灯、1个网络状态灯、1个系统盘状态灯、1个硬盘状态灯，机箱具备防尘滤网，采用双立柱防震设计。设备左右侧面各2个抬手，具备前面板抽拉标签卡 5. 可接入2T/3T/4T/6T/8T/10T/12T/14T/16T/18T/20T/25T/26T/30T SATA/SAS硬盘；支持NL-SAS 硬盘、HDD硬盘、SSD硬盘、氦气硬盘、空气硬盘；支持 CMR或SMR硬盘；支持硬盘交错/分时启动 6.支持视音频、图片、智能数据流进行混合直存，无须存储服务器和图片服务器的参与，平台服务器宕机时，存储业务正常；支持国际GB/T 28181和Onvif视频流直存模式 7.支持 ONVIF、PSIA、TCP/IP、UDP、SIP、SIP2.0、RTSP、RTP、RTCP、iSCSI、CIFS(SMB)、NFS、FTP、HTTP、AFP、RSYNC、SNMP、IPV4、IPV6、HLS、S3、OSS等协议，支持IP组播 8.支持网络RAID纠删码技术，多台存储设备组建网络RAID，设置为负载均衡；单台或多台存储设备组建网络RAID，允许每组RAID中任意1-18个磁盘发生故障，数据不丢失，存储服务不中断；允许每组RAID中任意20块硬盘发生故障，业务不中断 9.设备支持版本回退功能，在当前版本出现故障或操作失误后，可进行回退到历史版本，回退后录像正常回放，且历史录像完整 10.设备支持MAID2.0磁盘节能功能，当磁盘不工作时，可根据设置的时间自动启动磁盘降速或磁盘休眠指令，降低磁盘驱动能耗 11.设备支持硬盘的多级工作模式，包括性能模式、空闲模式（A\B\C，A：硬盘短时空闲，可以正常响应IO；B：较多空闲，磁头不再移动，硬盘满转；C:硬盘完全空闲，磁头不再移动，硬盘降速）、休眠模式（硬盘不再旋转，新下发IO需要唤醒） 12.BMC支持复杂密码，设备首次使用默认密码登录BMC时，提示修改密码，并且需要强制修改完密码后重新登陆，否则无法进入BMC web | K43: 响应 | L43: / | M43: 140 | N43: =E43*M43 -> 420 | O43: 228542 | P43: =E43*O43 -> 685626 | Q43: =E43*(M43+O43) -> 686046
A44: 9 | B44: 原有安防监控平台扩容 | C44: 本次项目新增的前端摄像机需接入原有监控管理平台进行统一管理，并实现如下功能： 一、视频预览 1、支持视频实时预览能力，实现预览窗口布局切换、预览画面自适应及全屏切换； 2、支持云台控制、实时抓图、紧急录像、即时回放、主子码流切换、声音开启\关闭、辅屏预览（1个辅屏）、对讲、广播、报警输出控制的能力； 3、支持智能规则展示的能力（如：针对热成像设备温度信息实时展示）； 4、支持资源视图管理能力，以视图形式管理监控点、视频预览轮巡等自定义资源组，其中视图类型包含公有视图和私有视图； 5、支持全景视频监控预览能力，支持球型鹰眼、全景摄像机的全景模式； 二、录像回放 1、支持录像计划管理能力，支持实时录像计划、录像回传计划； 2、支持录像回放能力，支持多画面同步回放和异步回放切换、超高倍速回放、分段回放、录像下载、录像剪辑、录像标签、录像锁定、录像抓图； 三、图片监控 1、支持视频预览与图片实时监控模式切换能力，实现图片监控模式； 2、支持图片查询回放能力，实现按监控点、时间段展示抓拍图片； 3、支持图片自动播放能力，支持图片自动播放速度可设置； 4、支持图片下载能力； 四、视频上墙 1、支持电视墙场景管理能力，实现场景窗口配置、场景切换计划配置以及轮巡计划的管理； 2、支持上墙控制能力，实现场景一键上墙、场景切换、电视墙切换、监控点上下墙、轮巡控制操作； 五、视频事件 1、支持视频事件布撤防能力，可按计划模版进行布防，事件类型包括移动侦测、视频丢失、视频遮挡、报警输入、报警输出； 六、事件录像管理 支持事件录像存储配置、事件录像检索和下载管理。 | D44: 海康 | E44: 281 | F44: 路 | H44: 海康威视 | I44: 视频监控软件 | J44: 视频监控应用提供视频管理服务，支持编码设备通过海康设备网络SDK协议、海康Ehome协议、海康ISUP5.0协议、GB28181协议、ONVIF协议、大华设备网络SDK协议、萤石协议接入平台，实现视频预览、录像回放、视频上墙、视频事件监控服务能力，并且在网络带宽不足、有流量限制的网络环境下可以通过以图片替代视频的模式提供监控服务。 【功能介绍】 一、视频预览 1、支持视频实时预览能力，实现预览窗口布局切换、预览画面自适应及全屏切换； 2、支持云台控制、实时抓图、紧急录像、即时回放、主子码流切换、声音开启\关闭、辅屏预览（1个辅屏）、对讲、广播、报警输出控制的能力； 3、支持智能规则展示的能力（如：针对热成像设备温度信息实时展示）； 4、支持资源视图管理能力，以视图形式管理监控点、视频预览轮巡等自定义资源组，其中视图类型包含公有视图和私有视图； 5、支持全景视频监控预览能力，支持球型鹰眼、全景摄像机的全景模式； 二、录像回放 1、支持录像计划管理能力，支持实时录像计划、录像回传计划； 2、支持录像回放能力，支持多画面同步回放和异步回放切换、超高倍速回放、分段回放、录像下载、录像剪辑、录像标签、录像锁定、录像抓图； 三、图片监控 1、支持视频预览与图片实时监控模式切换能力，实现图片监控模式； 2、支持图片查询回放能力，实现按监控点、时间段展示抓拍图片； 3、支持图片自动播放能力，支持图片自动播放速度可设置； 4、支持图片下载能力； 四、视频上墙 1、支持电视墙场景管理能力，实现场景窗口配置、场景切换计划配置以及轮巡计划的管理； 2、支持上墙控制能力，实现场景一键上墙、场景切换、电视墙切换、监控点上下墙、轮巡控制操作； 五、视频事件 1、支持视频事件布撤防能力，可按计划模版进行布防，事件类型包括移动侦测、视频丢失、视频遮挡、报警输入、报警输出； 六、事件录像管理 支持事件录像存储配置、事件录像检索和下载管理。 【规格参数】 1、支持监控点数量10W个（超过5000需要分布式部署）； 2、支持并发取流带宽2000M，例如以2M/路计算最大并发路数为1000路 （以千兆服务器为例，每台服务器并发取流带宽为600M，超过600M需要分布式部署）； 3、解码能力：在i7、GTX1070的PC上，解码H264、720P的视频36路； 4、支持电视墙最大场景数128个； 5、单个电视墙最大支持数量25*25个； 6、单个窗口最大分割数量16个。 | K44: 响应 | L44: / | M44: 0 | N44: =E44*M44 -> 0 | O44: 19 | P44: =E44*O44 -> 5339 | Q44: =E44*(M44+O44) -> 5339
A45: 10 | B45: 8口POE接入交换机（带光口） | C45: 千兆以太网交换机，PoE交换机； 端口描述：不低于10个10/100/1000M电口，不低于2个SFP口，1个console口； 背板带宽：不低于336Gbps/3.36Tbps； 包转发率：不低于27Mpps/102Mpps； 支持Console，Telnet，WEB，SNMP； PoE：1-8口支持（整机PoE供电不低于125W，最大同时支持8个PoE端口） PoE+：1-8口支持（整机PoE供电不低于125W，最大同时支持4个PoE+端口） | D45: 华三、锐捷（非睿易） | E45: 15 | F45: 台 | H45: 锐捷 | I45: RG-S2906-10GT2MS-P-L | J45: 10个10/100/1000M自适应电口，2个1G/2.5G SFP光口，固化单交流电源，无风扇，1-8端口支持PoE/PoE+远程供电，125W POE供电 交换容量：432Gbps/4.32Tbps 包转发率：30/108Mpps 支持过滤地址，支持静态地址； 支持4K 802.1Q VLAN，支持Port based VLAN，支持Voice VLAN； 过滤非法的MAC地址，支持硬件CPP、NFPP； IPv4/IPv6静态路由 支持MAC扩展ACL，支持ACL80，支持全局ACL，支持ACL重定向； 支持IEEE 802.3az标准的EEE（Energy Efficient Ethernet，节能以太网）技术； SNMP、CLI(Telnet/Console)、Syslog/Debug、NTP、TFTP、Web、WIS公有云平台管理 | K45: 响应 | L45: / | M45: 58 | N45: =E45*M45 -> 870 | O45: 1805 | P45: =E45*O45 -> 27075 | Q45: =E45*(M45+O45) -> 27945
A46: 11 | B46: 24口POE接入交换机-单电源 | C46: 1.在不插板卡情况下，单设备交换容量≥336Gbps，包转发率≥126Mpps，提供≥24个千兆电接口、≥4个万兆SFP+光接口。 2.支持支持802.3at/POE+供电标准。 1、支持堆叠技术或者虚拟化技术 2、支持 4K 802.1Q VLAN,支持Voice VLAN及Voice VLAN中可以同时识别多厂家的OUI地址，支持端口VLAN、MAC VLAN 3、支持标准IP ACL（基于IP地址的硬件ACL）支持扩展IP ACL（基于IP地址、TCP/UDP端口号的硬件ACL） 4、支持QOS 5、支持一对一、多对一、一对多的镜像 6、支持DHCP Server、DHCP Client、DHCP Snooping、DHCP Relay、DHCP Option82 7、支持广播风暴抑制 8、支持设备登陆管理的AAA安全认证、radius认证、支持802.1x、支持ssh2.0 9、支持STP/RSTP/MSTP协议 10、支持链路聚合（支持静态、动态链路聚合、千兆口聚合、万兆口聚合） 11、有标准的或私有的邻居发现协议 12、支持VLAN虚接口 13、支持 IPv4 /ipv6静态路由 14、支持OSPFv2、OSPFv3 15、支持SNMPv1/v2/v3，WEB网管，支持命令行接口配置，Telnet，SSH，Console口配置，支持系统日志，分级告警，调试信息输出，NTP/SNTP ★15、提供真实有效的工信部入网证复印件； ★16、原厂质保≥3年 | D46: 华三、锐捷（非睿易） | E46: 17 | F46: 台 | H46: 锐捷 | I46: RG-S2910-24GT4XS-P-L | J46: 24个10/100/1000Base-T自适应以太网接口（POE+），4个1GE/10GE SFP+接口； 交换容量:672Gbps/6.72Tbps;包转发率:126Mpps;单端口最大供电30W，整机最大供电370W； 支持4K 802.1Q VLAN，支持Port based VLAN，支持MAC based VLAN，支持Voice VLAN，支持GVRP； 支持STP、RSTP、MSTP； 支持DHCP Server ，支持DHCP Client ，支持DHCP Snooping，支持DHCP Relay； 支持VSU虚拟化技术，支持本地堆叠和远程堆叠，支持通过标准业务口实现虚拟化； 支持IPv4/IPv6静态路由、可扩展支持RIP、RIPng、OSPF、OSPFv3协议; 支持端口流量识别，支持端口流量限速，支持802.1p/DSCP/TOS流量分类，支持SP、WRR、DRR、SP+WFQ、 SP+WRR、SP+DRR、RED/WRED队列调度； 支持过滤非法的MAC地址，支持广播风暴抑制，支持BPDU Guard，支持CPP、NFPP，支持端口保护； 支持SNMP、CLI(Telnet/Console)、RMON、SSH、Syslog/Debug、NTP/SNTP、FTP、TFTP、Web、WIS公有云平台管理; | K46: 响应 | L46: / | M46: 2 | N46: =E46*M46 -> 34 | O46: 3558 | P46: =E46*O46 -> 60486 | Q46: =E46*(M46+O46) -> 60520
A47: 12 | B47: 千兆单模光模块 | C47: LC接口，单模千兆光纤（和交换机同品牌） | D47: 华三、锐捷（非睿易） | E47: 30 | F47: 个 | H47: 锐捷 | I47: MINI-GBIC-LX-SM1310 | J47: 1000BASE-LX mini GBIC转换模块（1310nm），10km | K47: 响应 | L47: / | M47: 2 | N47: =E47*M47 -> 60 | O47: 112 | P47: =E47*O47 -> 3360 | Q47: =E47*(M47+O47) -> 3420
... A49: 14 | B49: 六类非屏蔽双绞线 | C49: 1.标准：不低于TIA/EIA568-C.2、ISO/IEC11801、IEC60332-1、GB 50311； 2.最高传输频率不低于250MHz； 3.导体规格：单根导体直径不小于0.57±0.02； 4.屏蔽方式：U/UTP，线对采用“十”字骨架隔离； 5.护套材料：LSZH，护套外径：6.3±0.3mm； 6.支持以太网供电（Power over Ethernet）应用（POE/POE+）； 7.综合布线光纤系统、铜缆系统应采用同一品牌。 | D49: 一舟、普天天纪、罗格朗 | E49: 20000 | F49: 个 | H49: 一舟 | I49: D165-D | J49: 1.标准：不低于TIA/EIA568-C.2、ISO/IEC11801、IEC60332-1、GB 50311； 2.最高传输频率不低于250MHz； 3.导体规格：单根导体直径不小于0.57±0.02； 4.屏蔽方式：U/UTP，线对采用“十”字骨架隔离； 5.护套材料：LSZH，护套外径：6.3±0.3mm； 6.支持以太网供电（Power over Ethernet）应用（POE/POE+）； 7.综合布线光纤系统、铜缆系统应采用同一品牌。 | K49: 响应 | L49: / | M49: 1 | N49: =E49*M49 -> 20000 | O49: 3 | P49: =E49*O49 -> 60000 | Q49: =E49*(M49+O49) -> 80000
A50: 15 | B50: 电源线 | C50: 国标，RVV3*2.5 | D50: 一舟、普天天纪、罗格朗 | E50: =E51*70*1.1 -> 2464 | F50: m | H50: 一舟 | I50: G1910_60227 IEC 53(RVV) 3x2.5 | J50: 国标，RVV3*2.5 | K50: 响应 | L50: / | M50: 2 | N50: =E50*M50 -> 4928 | O50: 11 | P50: =E50*O50 -> 27104 | Q50: =E50*(M50+O50) -> 32032
A51: 16 | B51: 背包箱 | C51: 1.尺寸：不低于400mmX300mmX500mm 2.配置空开、插线板，设备的安装附件和安装螺钉；满足现场使用需求。 3.结构：整体结构采用拼焊结构，牢固、钢性好、牢固可靠，表面采用热镀锌处理。 4.防护等级不低于IP55，保护内部设备不受外界恶劣环境的干扰； 5.箱体采用1.2mm的标号201不锈钢板，整体喷塑。 颜色和立杆保持一致。 | D51: 国产 | E51: =E45+E46 -> 32 | F51: 个 | H51: 国产 | I51: 400mmX300mmX500mm | J51: 尺寸：400mmX300mmX500mm 防护等级不低于IP55 箱体采用1.2mm的标号201不锈钢板 | K51: 响应 | L51: / | M51: 117 | N51: =E51*M51 -> 3744 | O51: 271 | P51: =E51*O51 -> 8672 | Q51: =E51*(M51+O51) -> 12416
A52: 17 | B52: 3.5米监控立杆 | C52: 1.3.5米监控立杆，含地笼及混凝土基础； 2.颜色和背包箱保持一致。 | D52: 国产 | E52: 100 | F52: 个 | H52: 国产 | I52: 3.5米 | J52: 3.5米监控立杆，含地笼及混凝土基础； | K52: 响应 | L52: / | M52: 466 | N52: =E52*M52 -> 46600 | O52: 404 | P52: =E52*O52 -> 40400 | Q52: =E52*(M52+O52) -> 87000
A53: 18 | B53: 光纤熔接盒（含光纤熔纤） | C53: SC4芯单模满配含熔接尾纤、法兰、SC光跳线。 | D53: 一舟、普天天纪、罗格朗 | E53: =E45+E46 -> 32 | F53: 个 | H53: 一舟 | I53: S953-4X+S905-3*4+S812*4 | J53: SC4芯单模满配含熔接尾纤、法兰、SC光跳线 | K53: 响应 | L53: / | M53: 52 | N53: =E53*M53 -> 1664 | O53: 71 | P53: =E53*O53 -> 2272 | Q53: =E53*(M53+O53) -> 3936
A54: 19 | B54: 室外4芯单模光缆 | C54: 1.标准：YD/T769，ISO/IEC11801，ANSI/TIA -568-C.3 2.全截面阻水结构，松套管填充纤膏，松套管和钢带之间填充缆膏，确保良好的阻水防潮性能 3.光纤规格：B1.3（OS2） 4.衰减＠20℃（dB/Km）：＠1310nm≤0.36，＠1550nm≤0.22 5.光纤芯数：4芯 6.护套：夹带钢丝的钢-聚乙烯粘结护套，MDPE，黑色 7.允许拉伸力：长期：600N，短期：1500N 8.允许压扁力：长期：300N/100mm，短期：1000N/100mm 9.最小弯曲半径：动态：20D，静态：10D | D54: 一舟、普天天纪、罗格朗 | E54: 10560 | F54: m | H54: 一舟 | I54: D173-4 | J54: 1.标准：YD/T769，ISO/IEC11801，ANSI/TIA -568-C.3 2.全截面阻水结构，松套管填充纤膏，松套管和钢带之间填充缆膏，确保良好的阻水防潮性能 3.光纤规格：B1.3（OS2） 4.衰减＠20℃（dB/Km）：＠1310nm≤0.36，＠1550nm≤0.22 5.光纤芯数：4芯 6.护套：夹带钢丝的钢-聚乙烯粘结护套，MDPE，黑色 7.允许拉伸力：长期：600N，短期：1500N 8.允许压扁力：长期：300N/100mm，短期：1000N/100mm 9.最小弯曲半径：动态：20D，静态：10D | K54: 响应 | L54: / | M54: 1 | N54: =E54*M54 -> 10560 | O54: 2 | P54: =E54*O54 -> 21120 | Q54: =E54*(M54+O54) -> 31680 | S54: 施工费偏低无法实现
A55: 20 | B55: 24口光纤配线架（含尾纤、LC双工耦合器、熔接） | C55: 1.标准：YD/T778，ISO/IEC 11801，ANSI/TIA -568-C.3 2.安装方式：19″机架式安装 3.4个光缆进线口，带固定PG头，盒内配置光缆护套固定装置，光缆加强件固定装置 4.通用型设计，可兼容：LC双工、SC单工、FC、ST适配器，一个4口支架仅需一颗螺丝，便于安装和拆卸 5.进出光纤方便灵活，有充裕的光纤盘存空间，光纤和尾纤弯曲半径不小于30mm 6.端口数量： 24口，空余端口可安装空白功能件，高度：1U 7.表面处理：静电喷塑 8.材料：优质冷扎钢板 9.表面颜色：黑色 10.含LC双工耦合器 | D55: 一舟、普天天纪、罗格朗 | E55: 3 | F55: 个 | H55: 一舟 | I55: S952-12X+S905-7-1*12+S813*24 | J55: 1.标准：YD/T778，ISO/IEC 11801，ANSI/TIA -568-C.3 2.安装方式：19″机架式安装 3.4个光缆进线口，带固定PG头，盒内配置光缆护套固定装置，光缆加强件固定装置 4.通用型设计，可兼容：LC双工、SC单工、FC、ST适配器，一个4口支架仅需一颗螺丝，便于安装和拆卸 5.进出光纤方便灵活，有充裕的光纤盘存空间，光纤和尾纤弯曲半径不小于30mm 6.端口数量： 24口，空余端口可安装空白功能件，高度：1U 7.表面处理：静电喷塑 8.材料：优质冷扎钢板 9.表面颜色：黑色 10.含LC双工耦合器 | K55: 响应 | L55: / | M55: 17 | N55: =E55*M55 -> 51 | O55: 308 | P55: =E55*O55 -> 924 | Q55: =E55*(M55+O55) -> 975
A56: 21 | B56: 光纤跳线 | C56: 单模双芯LC-LC优质3米光纤跳线； | D56: 一舟、普天天纪、罗格朗 | E56: =E53 -> 32 | F56: 个 | H56: 一舟 | I56: S936 | J56: 单模双芯LC-LC优质3米光纤跳线； | K56: 响应 | L56: / | M56: 6 | N56: =E56*M56 -> 192 | O56: 24 | P56: =E56*O56 -> 768 | Q56: =E56*(M56+O56) -> 960
A57: 22 | B57: JDG20管 | C57: JDG管，壁厚不小于1.0MM,φ20；含主材、接头、固定扣件（含钢结构扣件）等辅材 | D57: 国产 | E57: 15000 | F57: m | H57: 国产 | I57: JDG20*1.0 | J57: JDG管，壁厚不小于1.0MM,φ20；含主材、接头、固定扣件（含钢结构扣件） | K57: 响应 | L57: / | M57: 10 | N57: =E57*M57 -> 150000 | O57: 3 | P57: =E57*O57 -> 45000 | Q57: =E57*(M57+O57) -> 195000
A58: 23 | B58: 辅材 | C58: 设备安装配套辅材，水晶头，扎带等 | E58: 1 | F58: 项 | K58: 响应 | L58: / | M58: 5825 | N58: =E58*M58 -> 5825 | O58: 0 | P58: =E58*O58 -> 0 | Q58: =E58*(M58+O58) -> 5825
B59: 2.2、无人机软硬件套装 | N59: =E59*M59 -> 0 | P59: =E59*O59 -> 0
A60: 1 | B60: 无人机 | C60: 最大飞行时间（无风环境）：＞50分钟 环境适应性：防护等级≥ IP55，最大抗风速度≥12 米/秒 环境感知：全向双目视觉系统，辅以机身底部三维红外传感器 广角：1/1.3 英寸 CMOS，有效像素 4800 万 中长焦：1/1.3 英寸 CMOS，有效像素 4800 万 长焦：1/1.5 英寸 CMOS，有效像素 4800 万 热成像相机：1280 × 1024@30fps 激光测距：正入射量程 1800 米（1 Hz）@20% 反射率目标 线缆级自动避障 | D60: 大疆、道通、复亚智能、云圣智能 | E60: 1 | F60: 台 | H60: 大疆 | I60: 1.DJI Matrice 4TD（中国版） 2.DJI AL1 探照灯 3.DJI AS1 喊话器 4.DJI Matrice 4 避障雷达 | J60: 最大飞行时间（无风环境）：54分钟 环境适应性：防护等级： IP55，最大抗风速度：12 米/秒 环境感知：全向双目视觉系统，辅以机身底部三维红外传感器 广角：1/1.3 英寸 CMOS，有效像素 4800 万 中长焦：1/1.3 英寸 CMOS，有效像素 4800 万 长焦：1/1.5 英寸 CMOS，有效像素 4800 万 热成像相机：1280 × 1024@30fps 激光测距：正入射量程 1800 米（1 Hz）@20% 反射率目标 线缆级自动避障 | K60: 响应 | L60: / | M60: 0 | N60: =E60*M60 -> 0 | O60: 57978 | P60: =E60*O60 -> 57978 | Q60: =E60*(M60+O60) -> 57978
A61: 2 | B61: 无人机巢及中继 | C61: 环境适应性：工作温度为 -30℃ 至 50℃ ，防护等级为 IP56 最大作业半径≥5 公里 充电时间＜30 分钟 舱内可直播相机分辨率：1920 × 1080 机巢图传系统 依据现场情况自行评估是否需要增加中继设备 | D61: 大疆、道通、复亚智能、云圣智能 | E61: 1 | F61: 套 | H61: 大疆 | I61: 1.大疆机场3 2.DJI 增强图传模块 3.大疆O4地面站 4.DJI Care 行业无忧旗舰版（DJI O4 地面站）中国版 5.设备安装与部署 | J61: 环境适应性：工作温度为 -30℃ 至 50℃ ，防护等级为 IP56 最大作业半径：10 公里 充电时间:27分钟 舱内可直播相机分辨率：1920 × 1080 机巢图传系统 依据现场情况自行评估需要增加中继设备 | K61: 响应 | L61: / | M61: 0 | N61: =E61*M61 -> 0 | O61: 114793 | P61: =E61*O61 -> 114793 | Q61: =E61*(M61+O61) -> 114793
A62: 3 | B62: 无人机平台 | C62: 私有化平台，支持算法和大模型，支持二次开发，可视化界面操作 支持本地建模，支持一键起飞，多航线设定（巡检航线和指令航线） 支持自定义模糊查找、导出照片 接入智慧安防系统 巡查管理支持无人机航线绘制和飞行任务管理，同时提供飞行实时监控： 1、航线绘制： 提供自定义航线，支持手动在地图上绘制航电，生成航线 2、飞行任务管理： 提供基础巡查任务管理，对指定航线进行巡检，支持单次、重复、定时、连续等飞行策略 3、飞行监控：支持全局视角、无人机视角多视角展示： 1）支持以2.5D地图可视化呈现无人机、机库、手持地面站、飞手等地理位置及相关信息，对禁飞区、电子围栏等区域分布进行图上统计展示。 2）支持展示地面站数量、无人机数量、任务数量、飞行里程、飞行架次、飞行时长等。 3）支持对当前执飞无人机进行实时动态监测，展示无人机当前位置、高度、速度等信息，可以查看当前无人机挂载视频实时画面。 4）支持无人机远程控制，包含一键起飞、一键返航等操作，可以针对无人机挂载设备进行广播喊话、拍照、云台控制等操作。 5）支持展示任务信息、航线信息、预警信息、地面站信息等。 6）支持按飞机、按飞手、按任务查询对应飞行任务的图片档案信息。 7）支持飞机、按飞手、按任务查询对应飞行任务的视频档案信息。 | D62: 大疆、道通、复亚智能、云圣智能 | E62: 1 | F62: 套 | H62: 大疆 | I62: 1.大疆司空 2 一体机套装（中国标准版） 2.烟雾识别 3.明火识别 4.消防通道占用识别 5.违规堆放识别 | J62: 私有化平台，支持算法和大模型，支持二次开发，可视化界面操作 支持本地建模，支持一键起飞，多航线设定（巡检航线和指令航线） 支持自定义模糊查找、导出照片 接入智慧安防系统 巡查管理支持无人机航线绘制和飞行任务管理，同时提供飞行实时监控： 1、航线绘制： 提供自定义航线，支持手动在地图上绘制航电，生成航线 2、飞行任务管理： 提供基础巡查任务管理，对指定航线进行巡检，支持单次、重复、定时、连续等飞行策略 3、飞行监控：支持全局视角、无人机视角多视角展示： 1）支持以2.5D地图可视化呈现无人机、机库、手持地面站、飞手等地理位置及相关信息，对禁飞区、电子围栏等区域分布进行图上统计展示。 2）支持展示地面站数量、无人机数量、任务数量、飞行里程、飞行架次、飞行时长等。 3）支持对当前执飞无人机进行实时动态监测，展示无人机当前位置、高度、速度等信息，可以查看当前无人机挂载视频实时画面。 4）支持无人机远程控制，包含一键起飞、一键返航等操作，可以针对无人机挂载设备进行广播喊话、拍照、云台控制等操作。 5）支持展示任务信息、航线信息、预警信息、地面站信息等。 6）支持按飞机、按飞手、按任务查询对应飞行任务的图片档案信息。 7）支持飞机、按飞手、按任务查询对应飞行任务的视频档案信息。 | K62: 响应 | L62: / | M62: 0 | N62: =E62*M62 -> 0 | O62: 102890 | P62: =E62*O62 -> 102890 | Q62: =E62*(M62+O62) -> 102890
B63: 2.3、巡更管理 | M63: 0 | N63: =E63*M63 -> 0 | O63: 0 | P63: =E63*O63 -> 0
A64: 1 | B64: 手持设备 | C64: 1.ARM八核2.0GHz处理器，4GB RAM，64GB ROM 2.图像采集：前置摄像头500万像素；后置摄像头1300万像素 3.支持二维码、NFC读卡、室外GPS定位+电子地图巡更方案 4.内置高灵敏度卫星定位模块，支持北斗，GPS，Glonass定位 5.防水、防尘、防摔（IP68）,支持1.5米防摔，适合全天候野外作业 6.支持NFC协议；支持ISO15693、ISO14443A/B 7.支持远程巡更任务接收，巡更任务管理 8.支持巡更人员登录注册，进行权限管理 9.支持巡更任务查询，巡更任务提醒等协助巡更的功能 10.有网络环境下支持巡更记录实时上传，无网络环境下支持巡更记录断点续传 | D64: 蓝卡、广拓、海康 | E64: 15 | F64: 台 | H64: 海康威视 | I64: DS-MDT102/MF | J64: 巡更手持机(C) ARM八核2.0GHz处理器，4GB RAM，64GB ROM 图像采集：前置摄像头500万像素；后置摄像头1300万像素 支持二维码、NFC读卡、室外GPS定位+电子地图巡更方案 内置高灵敏度卫星定位模块，支持北斗，GPS，Glonass定位 防水、防尘、防摔（IP68）,支持1.5米防摔，适合全天候野外作业 支持NFC协议；支持ISO15693、ISO14443A/B 支持远程巡更任务接收，巡更任务管理 支持巡更人员登录注册，进行权限管理 支持巡更任务查询，巡更任务提醒等协助巡更的功能 有网络环境下支持巡更记录实时上传，无网络环境下支持巡更记录断点续传 | K64: 响应 | L64: / | M64: 0 | N64: =E64*M64 -> 0 | O64: 2283 | P64: =E64*O64 -> 34245 | Q64: =E64*(M64+O64) -> 34245
A65: 2 | B65: 巡更牌 | C65: 1.NFC巡更打卡，使用单兵设备可直接进行巡更打卡 2.二维码扫描，通过系统权限验证的用户，可通过扫描二维码查看巡更记录 3.抬头预留空窗，可根据需求自主印刷 4.工作温度：-40℃～85℃ 5.工作湿度：5%～95% 无冷凝 | D65: 蓝卡、广拓、海康 | E65: 50 | F65: 台 | H65: 海康威视 | I65: DS-TRC100-8/X | J65: 巡更牌 NFC巡更打卡，使用单兵设备可直接进行巡更打卡 二维码扫描，通过系统权限验证的用户，可通过扫描二维码查看巡更记录； 抬头预留空窗，可根据需求自主印刷 工作温度：-40℃～85℃ 工作湿度：5%～95% 无冷凝 | K65: 响应 | L65: / | M65: 29 | N65: =E65*M65 -> 1450 | O65: 58 | P65: =E65*O65 -> 2900 | Q65: =E65*(M65+O65) -> 4350
A66: 3 | B66: 卡片录入仪 | C66: 1.支持发卡类型：ID卡、IC卡、身份证物料卡号（序列号）、普通CPU卡、国密CPU卡 2.USB2.0接口 3.具有2个Sim卡尺寸的PSAM卡座 4.工作电压：DC 5V 5.工作电流：0.2A | D66: 蓝卡、广拓、海康 | E66: 1 | F66: 台 | H66: 海康威视 | I66: DS-K1F100K | J66: 支持发卡类型：ID卡、IC卡、身份证物料卡号（序列号）、普通CPU卡、国密CPU卡； USB2.0接口； 具有2个Sim卡尺寸的PSAM卡座； 工作电压：DC 5V； 工作电流：0.2A； 尺寸：117*67.5*14.3mm | K66: 响应 | L66: / | M66: 0 | N66: =E66*M66 -> 0 | O66: 563 | P66: =E66*O66 -> 563 | Q66: =E66*(M66+O66) -> 563
A67: 4 | B67: 巡更管理软件 | C67: 一、巡更点 1、支持将门禁设备、近距离射频识别NFC、二维码等多种方式设置为巡更点打卡凭证； 2、支持根据实际管理需求自定义扩展巡更点类型； 二、巡更计划 1、支持有序巡更与无序巡更两种现场巡更模式。 2、支持对巡更计划进行全流程管理，可配置计划名称、有效期、任务执行周期（支持每天/每周/每月/每年或指定日期）、巡更点及执行人。执行人支持按具体人员、角色或组织进行灵活分配。 3、支持查看巡更计划列表，显示信息包括计划名称、巡更区域、巡更点数量、计划有效期等；同时支持按计划名称、状态、计划有效期、创建时间、巡更区域等多条件对计划进行检索。 三、巡更任务 1、支持系统根据巡更计划自动执行巡更任务的生成。 2、支持管理人员手动触发基于巡更计划的巡更任务生成。 3、支持通过待办任务方式提醒巡更人员按时执行巡更任务。 4、支持查看巡更任务列表，显示信息包括巡更任务编号、所属巡更计划、所属区域、任务类型、巡更点数量、发现问题数、任务开始时间等；同时支持按任务状态、任务类型、任务开始时间等多条件对任务进行检索。 3、支持离线巡更模式，可通过专用巡更棒或现场移动APP执行打卡操作。 四、巡更记录 1、支持查看巡更任务记录，显示信息包括巡更任务编号、所属区域、巡更计划模板、任务时间、巡更对象数等，并支持按条件检索及数据导出。 2、支持查看单次巡更任务的详细报告，并可支持打印。 | D67: 蓝卡、广拓、海康 | E67: 1 | F67: 套 | H67: 海康威视 | I67: 巡更管理软件 | J67: 一、巡更点 1、支持将门禁设备、近距离射频识别NFC、二维码等多种方式设置为巡更点打卡凭证； 2、支持根据实际管理需求自定义扩展巡更点类型； 二、巡更计划 1、支持有序巡更与无序巡更两种现场巡更模式。 2、支持对巡更计划进行全流程管理，可配置计划名称、有效期、任务执行周期（支持每天/每周/每月/每年或指定日期）、巡更点及执行人。执行人支持按具体人员、角色或组织进行灵活分配。 3、支持查看巡更计划列表，显示信息包括计划名称、巡更区域、巡更点数量、计划有效期等；同时支持按计划名称、状态、计划有效期、创建时间、巡更区域等多条件对计划进行检索。 三、巡更任务 1、支持系统根据巡更计划自动执行巡更任务的生成。 2、支持管理人员手动触发基于巡更计划的巡更任务生成。 3、支持通过待办任务方式提醒巡更人员按时执行巡更任务。 4、支持查看巡更任务列表，显示信息包括巡更任务编号、所属巡更计划、所属区域、任务类型、巡更点数量、发现问题数、任务开始时间等；同时支持按任务状态、任务类型、任务开始时间等多条件对任务进行检索。 3、支持离线巡更模式，可通过专用巡更棒或现场移动APP执行打卡操作。 四、巡更记录 1、支持查看巡更任务记录，显示信息包括巡更任务编号、所属区域、巡更计划模板、任务时间、巡更对象数等，并支持按条件检索及数据导出。 2、支持查看单次巡更任务的详细报告，并可支持打印。 | K67: 响应 | L67: / | M67: 0 | N67: =E67*M67 -> 0 | O67: 1805 | P67: =E67*O67 -> 1805 | Q67: =E67*(M67+O67) -> 1805
B68: 2.4、周界防护-定位型振动光纤系统 | N68: =E68*M68 -> 0 | P68: =E68*O68 -> 0
A69: 1 | B69: 传感光缆 | C69: 1.光纤类型: 4芯单模光纤 2.纤芯类型: G.652D 9/125μm 非色散位移单模光纤 3.光缆外径: 8.6mm(±5%) 4.抗压系数: 短期：1000N/10cm 5.长期：300N/10cm 6.拉伸强度: 短期：1500N 7.长期：600N 8.最小弯曲半径: 光缆外径的10倍（静态） 9.光缆外径的20倍（动态） 10.光缆传输衰减: 1310nm≤0.36dB/km；1550nm≤0.22dB/km 11.工作温度: -40~70℃ 12.工作湿度: 0~95%R.H 13.防护等级: IP68 | D69: 福科斯、广拓、海康 | E69: 22000 | F69: m | H69: 海康威视 | I69: DS-PO2-iDFM/S4/G | J69: 【基本参数】 光纤类型: 4芯单模光纤 纤芯类型: G.652D 光缆外径: 8.6mm(±5%) 抗压系数: 短期：1000N/10cm 长期：300N/10cm 拉伸强度: 短期：1500N 长期：600N 最小弯曲半径: 光缆外径的10倍（静态） 光缆外径的20倍（动态） 光缆传输衰减: 1310nm≤0.36dB/km 1550nm≤0.22dB/km 【一般规范】 工作温度: -40~70℃ 工作湿度: 0~95%R.H 防护等级: IP68 | K69: 响应 | L69: / | M69: 5 | N69: =E69*M69 -> 110000 | O69: 2 | P69: =E69*O69 -> 44000 | Q69: =E69*(M69+O69) -> 154000
A70: 2 | B70: 定位型振动光纤处理器 | C70: 1.当在布防区域模拟触发入侵报警时，在1s的时间内输出入侵报警信号。 2.当出现断纤时，在1s的时间内通过系统输出断纤报警信号，且可通过显示/指示单元显示距光纤始端最近的断纤位置，该信号的输出形式应在说明书中明示且应区别于其他报警信号。 3.分布式定位型振动光纤系统的外壳设有防拆保护装置,当外壳被打开到足以触及其中的任何控制部件或机械固定的调节器时,防拆保护装置动作,并输出防拆报警信号,该信号的输出形式应区别于其他报瞥信号。 4.通道开关按键16个，支持通过通道开关按键启用/关闭通道功能 5.系统支持报警分级功能，共分为3个级别，由3至1报警紧迫或重要程度逐级增加。系统支持各等级独立设置阈值参数。 6.系统支持与摄像机联动，并支持通过摄像机对图片、视频进行分析复核 7.定位精度（检测结果）：探测距离≤5km，定位精度±2.0m；探测距离＞5km且≤20km，定位精度±5.0m；探测距离＞20km且≤40km，定位精度±5.0m；探测距离＞40km且≤80km，定位精度±5.0m 8.在固定的振动激励条件下（振幅及频率不变），系统探测到的振动幅度最大偏差在±10%以内。 9.在固定声源激励敏感部件的条件下，系统支持音频信号还原及播放。 10.抗风干扰符合III级风速干扰条件下，不产生误报警和漏报警：Ill级：7～8级风速、Ih、17.1m/s～20.7m/s 11.抗雨干扰符合满足III级暴雨干扰条件下，不产生误报警和漏报警：Ill级：暴雨、每24h降水强度100mm、lh 12.主机应支持至少8路输入(开关量),至少8路输出(开关量)接口扩展。 13.系统应具有远程参数配置与程序更新功能;应具有集中维护管理功能,应可在远端进行系统设备的日常维护管理。 14.单通道瀑布图数据应每分钟实时上报；瀑布图原始数据采样分辨率应能达到0.4m，时间分辨率应不大于0.1；系统应支持瀑布图数据输出和瀑布图数据管理 | D70: 福科斯、广拓、海康 | E70: 1 | F70: 台 | H70: 海康威视 | I70: DS-QFA3016DW | J70: 1.当在布防区域模拟触发入侵报警时，在1s的时间内输出入侵报警信号。 2.当出现断纤时，在1s的时间内通过系统输出断纤报警信号，且可通过显示/指示单元显示距光纤始端最近的断纤位置，该信号的输出形式应在说明书中明示且应区别于其他报警信号。 3.分布式定位型振动光纤系统的外壳设有防拆保护装置,当外壳被打开到足以触及其中的任何控制部件或机械固定的调节器时,防拆保护装置动作,并输出防拆报警信号,该信号的输出形式应区别于其他报瞥信号。 4.通道开关按键16个，支持通过通道开关按键启用/关闭通道功能 5.系统支持报警分级功能，共分为3个级别，由3至1报警紧迫或重要程度逐级增加。系统支持各等级独立设置阈值参数。 6.系统支持与摄像机联动，并支持通过摄像机对图片、视频进行分析复核 7.定位精度（检测结果）：探测距离≤5km，定位精度±2.0m；探测距离＞5km且≤20km，定位精度±5.0m；探测距离＞20km且≤40km，定位精度±5.0m；探测距离＞40km且≤80km，定位精度±5.0m 8.在固定的振动激励条件下（振幅及频率不变），系统探测到的振动幅度最大偏差在±10%以内。 9.在固定声源激励敏感部件的条件下，系统支持音频信号还原及播放。 10.抗风干扰符合III级风速干扰条件下，不产生误报警和漏报警：Ill级：7～8级风速、Ih、17.1m/s～20.7m/s。 11.抗雨干扰符合满足III级暴雨干扰条件下，不产生误报警和漏报警：Ill级：暴雨、每24h降水强度100mm、lh。 12.当使用0.1Hz~5kHz范围内的固定频率模拟振动时，客户端应能解调出对应振动频率。 13.高温检测：室内设备符合II级试验条件：55°C±2°C、2h；室外设备符合II级试验条件：70°C±2°C、2h； 14.低温检测：室内设备符合II级试验条件：-10°C±3°C、2h；室外设备符合II级试验条件：-40°C±3°C、2h； 15.恒定湿热试验：室内、室外设备均符合试验条件：（40±2）°C、相对湿度（93±2）%，持续时间48h； 16.激光安全认证等级一级（GB/T 7247.1-2024 《激光产品的安全 第 1 部分:设备分类和要求》） 17.系统采用DAS技术 18.多点同时报警：当探测器被触发时,应能在信号处理器或显示/指示单元上指示出入侵发生的位置。当定位型探测器同一个光纤振动传感器的多个位置同时被触发时,不应漏掉指示任意一个位置。 19.当信号处理器的电源断开时，探测器应能产生报警状态。 20.主机应支持至少8路输入(开关量),至少8路输出(开关量)接口扩展。 21.系统应具有远程参数配置与程序更新功能;应具有集中维护管理功能,应可在远端进行系统设备的日常维护管理。 22.主机风扇故障时,系统应能产生报警。当风扇失效后,系统应能正常工作1小时以上。 23.主机应支持热插拔硬盘驱动器、热插拔风扇。 24.客户端应支持告警事件音频播放功能,应支持以瀑布图形式在时间/空间/强度三个指标进行呈现。 25.单通道瀑布图数据应每分钟实时上报。 26.瀑布图原始数据采样分辨率应能达到0.4m，时间分辨率应不大于0.1S | K70: 响应 | L70: / | M70: 117 | N70: =E70*M70 -> 117 | O70: 302655 | P70: =E70*O70 -> 302655 | Q70: =E70*(M70+O70) -> 302772
A71: 3 | B71: 抗紫外线扎带 | C71: 1.安装方式: 将扎线带尾巴穿过头部，即可束紧。 2.尺寸规格: 5*300mm 3.最大承受拉力: 200N±15N 4.包装数量: 250根/包 5.耐温: -40℃ ~ +80℃ 6.材料: 尼龙PA66抗紫外线（UV）原料 | D71: 福科斯、广拓、海康 | E71: 323 | F71: 包 | H71: 海康威视 | I71: DS-PO2-CTS/UV5300 | J71: 【常规参数】 安装方式: 将扎线带尾巴穿过头部，即可束紧。 【基本参数】 尺寸规格: 5*300mm 最大承受拉力: 200N±15N 包装数量: 250根/包 耐温: -40℃ ~ +80℃ 材料: 尼龙PA66抗紫外线（UV）原料 | K71: 响应 | L71: / | M71: 29 | N71: =E71*M71 -> 9367 | O71: 41 | P71: =E71*O71 -> 13243 | Q71: =E71*(M71+O71) -> 22610
A72: 4 | B72: 光纤接续盒 | C72: 1.光纤接续盒 2.材质：ABS工程塑料 3.规格：进出缆数，二进二出 | D72: 福科斯、广拓、海康 | E72: 9 | F72: 只 | H72: 海康威视 | I72: DS-PO2-UG/ABS | J72: 光纤接续盒 材质：ABS工程塑料 规格：进出缆数，二进二出 尺寸(宽x高x深)：460mm*170mm*110mm 外壳材质：ABS工程塑料 | K72: 响应 | L72: / | M72: 29 | N72: =E72*M72 -> 261 | O72: 154 | P72: =E72*O72 -> 1386 | Q72: =E72*(M72+O72) -> 1647
A73: 5 | B73: 塑料格栅 | C73: 1.塑料格栅是用于埋地方式部署振动光纤时，用于埋地时承载探测光缆的承载物 2.尺寸(宽x高x深): 网格：3.2cm*3.5cm；边宽3.3mm；边厚：1.3mm | D73: 福科斯、广拓、海康 | E73: 8800 | F73: m2 | H73: 海康威视 | I73: DS-PO-PG | J73: 塑料格栅 塑料格栅是用于埋地方式部署振动光纤时，用于埋地时承载探测光缆的承载物 尺寸(宽x高x深)：网格：3.2cm*3.5cm；边宽3.3mm；边厚：1.3mm | K73: 响应 | L73: / | M73: 6 | N73: =E73*M73 -> 52800 | O73: 8 | P73: =E73*O73 -> 70400 | Q73: =E73*(M73+O73) -> 123200
A74: 6 | B74: 周界防范大模型超脑 | C74: 1.存储接口：1个SATA接口，内置1TB硬盘 2.视频接口：1×HDMI，1×VGA 3.网络接口：2×RJ45 10/100/1000Mbps自适应以太网口 4.报警接口：4路报警输入，1路报警输出 5.串行接口：1路RS-232接口、1路RS-485接口 6.USB接口：1×USB 2.0，1×USB 3.0 7.整机搭载2颗高性能AI引擎，支持周界防范引擎模式 8.周界防范应用：支持对平台下发图片进行二次分析，检测图片中的人体，车辆目标，并将分析结果回传平台；图片流性能：4张/s；单颗AI引擎分析能力：2张/s | D74: 福科斯、广拓、海康 | E74: 1 | F74: 台 | H74: 海康威视 | I74: iDS-6716NX/S-ZD | J74: 1盘位1.5U嵌入式边缘计算主机，采用存算一体架构，内置高性能AI处理器 【硬件规格】 存储接口：1个SATA接口，内置1TB硬盘 视频接口：1×HDMI，1×VGA 网络接口：2×RJ45 10/100/1000Mbps自适应以太网口 报警接口：4路报警输入，1路报警输出 串行接口：1路RS-232接口、1路RS-485接口 USB接口：1×USB 2.0，1×USB 3.0 【智能应用】 整机搭载2颗高性能AI引擎，支持周界防范引擎模式 一、周界防范应用： 支持对平台下发图片进行二次分析，检测图片中的人体，车辆目标，并将分析结果回传平台； 图片流性能：4张/s 单颗AI引擎分析能力：2张/s | K74: 响应 | L74: / | M74: 350 | N74: =E74*M74 -> 350 | O74: 9664 | P74: =E74*O74 -> 9664 | Q74: =E74*(M74+O74) -> 10014
A75: 7 | B75: 振动光纤接入管理软件 | C75: 一、设备管理 1、支持以海康ISAPI协议接入，实现振动光纤单元采集的事件接收； 2、支持根据单元号、振动光纤主机名称查询振动光纤单元报警信息； 3、支持在地图上展示振动光纤实际部署位置、有效长度； 4、支持以列表方式展示振动设备信息，包含设备名称、IP等信息； 5、支持对振动光纤主机设备添加、删除、修改； 6、支持对振动光纤主机设备进行手动校时； 7、支持筛选出从未被平台连接成功的振动光纤主机设备。 二、光纤标定 1、支持通过振动曲线方式查询振动单元号，并支持与监控点位进行绑定； 2、支持通过导入导出的方式对单元号、监控点、经纬度进行绑定； 三、光纤上图 1、支持振动光纤主机上图，地图上可以查看主机的部署位置； 2、支持光纤上图，地图上可以查看光纤的铺设情况； 3、支持在地图上控制振动光纤的显示与隐藏； 4、支持查看振动光纤的主机数量、光纤长度（在线长度、离线长度）； 5、支持在地图上查看在线光纤分布及离线光纤分布情况； 6、支持在地图上查看光纤每个单元号与视频设备关联关系； 7、振动光纤报警时，支持在地图上高亮报警的光纤位置及关联球机高亮显示。 | D75: 福科斯、广拓、海康 | E75: 1 | F75: 套 | H75: 海康威视 | I75: 振动光纤接入管理软件 | J75: 【功能描述】 一、设备管理 1、支持以海康ISAPI协议接入，实现振动光纤单元采集的事件接收； 2、支持根据单元号、振动光纤主机名称查询振动光纤单元报警信息； 3、支持在地图上展示振动光纤实际部署位置、有效长度； 4、支持以列表方式展示振动设备信息，包含设备名称、IP等信息； 5、支持对振动光纤主机设备添加、删除、修改； 6、支持对振动光纤主机设备进行手动校时； 7、支持筛选出从未被平台连接成功的振动光纤主机设备。 二、光纤标定 1、支持通过振动曲线方式查询振动单元号，并支持与监控点位进行绑定； 2、支持通过导入导出的方式对单元号、监控点、经纬度进行绑定； 三、光纤上图 1、支持振动光纤主机上图，地图上可以查看主机的部署位置； 2、支持光纤上图，地图上可以查看光纤的铺设情况； 3、支持在地图上控制振动光纤的显示与隐藏； 4、支持查看振动光纤的主机数量、光纤长度（在线长度、离线长度）； 5、支持在地图上查看在线光纤分布及离线光纤分布情况； 6、支持在地图上查看光纤每个单元号与视频设备关联关系； 7、振动光纤报警时，支持在地图上高亮报警的光纤位置及关联球机高亮显示。 【性能参数】 1、支持振动光纤主机管理数量100个； 2、设备上报数据最大并发处理数量200条/秒 | K75: 响应 | L75: / | M75: 0 | N75: =E75*M75 -> 0 | O75: 9027 | P75: =E75*O75 -> 9027 | Q75: =E75*(M75+O75) -> 9027
A76: 8 | B76: 周界监测预警软件 | C76: 一、光纤报警定位及处置 1、提供报警实时信息的展示及处置能力，； 2、支持实时报警信息展示，以及历史报警信息的查询和回看； 3、支持报警发生时报警信息弹窗，显示当前的报警信息以及报警联动信息，包括：视频、录像、抓图、报警位置。 二 、雷达轨迹 1、提供布防区域目标物的轨迹跟踪显示以及视频跟踪能力； 2、支持对布防区域内报警目标物体的轨迹跟踪和实时视频接力跟踪（仅雷达设备支持轨迹跟踪）； 3、支持目标物跟踪时，显示目标物的位置、速度、方向信息； 4、支持布防区域内单目标和多目标跟踪； 三、重点视频点位管理 1、提供地图上重点点位视频的布局配置、实时视频播放及广播能力； 2、支持显示重点点位实时视频，可以任意拖放具体位置。 四、预警策略编排 1、支持振动光纤联动、雷达联动、区域入侵等不同事件组合产生新组合预警。 2、支持组合预警发生的时间间隔配置。 3、支持事件的发生先后顺序进行配置。 4、支持配置组合策略生效的资源、时间。 五、图上数据展示 1、支持数据统计展示，可以自由拖放布局，包括：图上资源统计数据、报警统计数据、资源在线状态统计。 六、图上资源控制 1、支持地图上资源显示控制，包括：虚拟防区、监控点、岗亭、雷达、报警器、自定义资源等。 七、报警研判复核管理 1、从空间维度对报警进行处理，以虚拟防区为单位，对关联的物联设备的报警事件进行合并； 2、从时间维度对报警进行处理，提供周计划配置、有效期配置、临时失效时间配置等功能； 3、从报警的业务属性维度进行处理，例如温度报警的温度属性、雷达轨迹时间的速度属性。 八、预警事件管理 1、提供历史报警检索、报警统计报表。 | D76: 福科斯、广拓、海康 | E76: 1 | F76: 套 | H76: 海康威视 | I76: 周界监测预警软件 | J76: 【功能描述】 一、光纤报警定位及处置 1、提供报警实时信息的展示及处置能力，； 2、支持实时报警信息展示，以及历史报警信息的查询和回看； 3、支持报警发生时报警信息弹窗，显示当前的报警信息以及报警联动信息，包括：视频、录像、抓图、报警位置。 二 、雷达轨迹 1、提供布防区域目标物的轨迹跟踪显示以及视频跟踪能力； 2、支持对布防区域内报警目标物体的轨迹跟踪和实时视频接力跟踪（仅雷达设备支持轨迹跟踪）； 3、支持目标物跟踪时，显示目标物的位置、速度、方向信息； 4、支持布防区域内单目标和多目标跟踪； 三、重点视频点位管理 1、提供地图上重点点位视频的布局配置、实时视频播放及广播能力； 2、支持显示重点点位实时视频，可以任意拖放具体位置。 四、预警策略编排 1、支持振动光纤联动、雷达联动、区域入侵等不同事件组合产生新组合预警。 2、支持组合预警发生的时间间隔配置。 3、支持事件的发生先后顺序进行配置。 4、支持配置组合策略生效的资源、时间。 五、图上数据展示 1、支持数据统计展示，可以自由拖放布局，包括：图上资源统计数据、报警统计数据、资源在线状态统计。 六、图上资源控制 1、支持地图上资源显示控制，包括：虚拟防区、监控点、岗亭、雷达、报警器、自定义资源等。 七、报警研判复核管理 1、从空间维度对报警进行处理，以虚拟防区为单位，对关联的物联设备的报警事件进行合并； 2、从时间维度对报警进行处理，提供周计划配置、有效期配置、临时失效时间配置等功能； 3、从报警的业务属性维度进行处理，例如温度报警的温度属性、雷达轨迹时间的速度属性。 八、预警事件管理 1、提供历史报警检索、报警统计报表。 | K76: 响应 | L76: / | M76: 0 | N76: =E76*M76 -> 0 | O76: 9558 | P76: =E76*O76 -> 9558 | Q76: =E76*(M76+O76) -> 9558
A77: 7 | B77: 土方开完及回填 | C77: 现场开挖回填 | E77: 3500 | F77: m | H77: / | I77: / | J77: / | K77: 响应 | L77: / | M77: 0 | N77: =E77*M77 -> 0 | O77: 36 | P77: =E77*O77 -> 126000 | Q77: =E77*(M77+O77) -> 126000
A78: 8 | B78: 绿化破坏恢复 | C78: 绿化破坏恢复 | E78: 2000 | F78: 平方米 | H78: / | I78: / | J78: / | K78: 响应 | L78: / | M78: 0 | N78: =E78*M78 -> 0 | O78: 29 | P78: =E78*O78 -> 58000 | Q78: =E78*(M78+O78) -> 58000
B79: 2.5、红外对射报警 | N79: =E79*M79 -> 0 | P79: =E79*O79 -> 0
A80: 1 | B80: 四光束红外对射 | C80: 1.探测方式：主动红外 2.警戒距离：100米 3.光源类型：红外数字脉冲 4.光源波长：940nm 5.光束频率：750Hz 6.光轴角度：水平180°(±90°)；垂直 20°(±10°) 7.感应速度：50-700ms 8.防拆输出：NC 触点容量 DC30V0.5A max 9.光束数量：4光束 10.报警输出接口：NC/NO 触点容量 DC30V0.5A max 11.防护等级：IP55 12.工作温度及湿度：-25℃~+55℃；≤95%（无凝结） 13.产品重量：2265g（毛重） 14.产品尺寸：370mm*96mm*95mm 15.外壳材质：PC(外罩)+ABS(本体) 16.工作电压：DC12-24V / AC12-18V 17.工作电流：投光器+受光器≤130mA 18.最大功率：≤5W 19.含配套支架 | D80: 福科斯、广拓、海康 | E80: 11 | F80: 对 | H80: 海康威视 | I80: DS-PB401-4100-R | J80: 探测方式：主动红外 警戒距离：100米 光源类型：红外数字脉冲 光源波长：940nm 光束频率：750Hz 光轴角度：水平180°(±90°)；垂直 20°(±10°) 感应速度：50-700ms 防拆输出：NC 触点容量 DC30V0.5A max 光束数量：4光束 报警输出接口：NC/NO 触点容量 DC30V0.5A max 防护等级：IP55 工作温度及湿度：-25℃~+55℃；≤95%（无凝结） 产品重量：2265g（毛重） 产品尺寸：370mm*96mm*95mm 外壳材质：PC(外罩)+ABS(本体) 工作电压：DC12-24V / AC12-18V 工作电流：投光器+受光器≤130mA 最大功率：≤5W 含安装支架 | K80: 响应 | L80: / | M80: 350 | N80: =E80*M80 -> 3850 | O80: 658 | P80: =E80*O80 -> 7238 | Q80: =E80*(M80+O80) -> 11088
A81: 2 | B81: 工控箱 | C81: 配套工控箱 | D81: 福科斯、广拓、海康 | E81: 6 | F81: 台 | H81: 海康威视 | I81: DS-PB-WPB01P | J81: 红外对射工控箱（镀锌喷塑） 周界报警对射类产品户外弱电施工工控箱，工业级防护。 内置工业级漏电保护模块，施工、检修安全保障。 内置工业级浪涌防护模块，有效降低感应雷、浪涌电流对内接弱电设备的损害，保障其稳定运行。 内置工业级开关电源模块，为红外对射发射、接收端以及其他配套外设提供直流供电。 | K81: 响应 | L81: / | M81: 233 | N81: =E81*M81 -> 1398 | O81: 520 | P81: =E81*O81 -> 3120 | Q81: =E81*(M81+O81) -> 4518
A82: 3 | B82: 总线报警主机 | C82: 1.具有规定权限的用户应能对控制指示设备进行全部和/或部分设防操作。设防成功后，控制指示设备应有相应的指示。设防失败时，控制指示设备应能立即给出指示和/或报警信号和/或信息。 2.当控制指示设备的多个探测回路依次或同时被触发时，不应产生漏报警。 3.告警装置安装在机内时，报警声压应不小于80dB(A)，告警装置安装在机外时，报警声压应不小于100dB(A)。 4.控制指示设备在开机后，应能进行自检，并给出自检结果指示。 5.控制指示设备应具有主电源和备用电源，应能在主电源和备用电源之间转换，电源转换时，工作应正常，不应出现漏报警及误报警:当主电源断电时，应能自动转换至备用电源供电;当主电源恢复时，可自动转换至主电源供电，并对备用电源自动充电:在给备用电源充电的同时，工作应正常。 6.主机支持 MAC、IP 绑定或限制访问 7.主机防拆报警不额外占用主机防区 8.主机上报支持至少4个中心组 | D82: 福科斯、广拓、海康 | E82: 1 | F82: 台 | H82: 海康威视 | I82: DS-19A08-01BN/F | J82: 操作系统：Linux 日志存储：40000条 系统校时：手动校时、NTP校时 子系统：8个 公共子系统：支持 板载防区：8路 扩展防区：最大可扩展248路（其中无线防区上限为64个） 板载警号输出：1路 板载继电器输出：4路 扩展输出：最大可扩展252路 具有规定权限的用户应能对控制指示设备进行全部和/或部分设防操作。设防成功后，控制指示设备应有相应的指示。设防失败时，控制指示设备应能立即给出指示和/或报警信号和/或信息。 当控制指示设备的多个探测回路依次或同时被触发时，不应产生漏报警。 告警装置安装在机内时，报警声压应不小于80dB(A)，告警装置安装在机外时，报警声压应不小于100dB(A)。 控制指示设备在开机后，应能进行自检，并给出自检结果指示。 控制指示设备应具有主电源和备用电源，应能在主电源和备用电源之间转换，电源转换时，工作应正常，不应出现漏报警及误报警:当主电源断电时，应能自动转换至备用电源供电;当主电源恢复时，可自动转换至主电源供电，并对备用电源自动充电:在给备用电源充电的同时，工作应正常。 主机支持 MAC、IP 绑定或限制访问 主机防拆报警不额外占用主机防区 主机上报支持至少4个中心组 | K82: 响应 | L82: / | M82: 350 | N82: =E82*M82 -> 350 | O82: 1699 | P82: =E82*O82 -> 1699 | Q82: =E82*(M82+O82) -> 2049
A83: 4 | B83: 控制键盘 | C83: 1.有线LCD键盘（支持遥控器&刷卡） 2.操作指令接收：支持对报警系统进行布防、撤防、消警、旁路、旁路恢复、紧急求助等操作 3.操作方式管理：支持密码、遥控器、刷卡方式对报警系统进行操作指令交互 4.报警状态指示：支持对报警系统防区报警状态进行实时指示，包括指示灯变化，提示音变化，文字内容变化等 5.系统状态展示：支持对报警系统运行状态进行展示，包括主电源状态、蓄电池状态、防拆状态、子系统布撤防状态，防区状态、扩展模块状态等 6.胁迫码功能：支持通过胁迫密码进行布撤防管理，并将警情进行中心上报 7.防区名称自定义：支持防区名称自定义配置，在键盘屏幕中展示对应文字内容 8.配置管理：支持通过键盘对报警主机进行参数配置，包括密码修改、防区类型配置、上报中心参数配置等 | D83: 福科斯、广拓、海康 | E83: 1 | F83: 台 | H83: 海康威视 | I83: DS-PK-LRT | J83: 有线LCD键盘（支持遥控器&刷卡） 操作指令接收：支持对报警系统进行布防、撤防、消警、旁路、旁路恢复、紧急求助等操作 操作方式管理：支持密码、遥控器、刷卡方式对报警系统进行操作指令交互 报警状态指示：支持对报警系统防区报警状态进行实时指示，包括指示灯变化，提示音变化，文字内容变化等 系统状态展示：支持对报警系统运行状态进行展示，包括主电源状态、蓄电池状态、防拆状态、子系统布撤防状态，防区状态、扩展模块状态等 胁迫码功能：支持通过胁迫密码进行布撤防管理，并将警情进行中心上报 防区名称自定义：支持防区名称自定义配置，在键盘屏幕中展示对应文字内容 配置管理：支持通过键盘对报警主机进行参数配置，包括密码修改、防区类型配置、上报中心参数配置等 操作系统：Linux 显示屏：LCD（尺寸80X25mm） 指示灯：5个 按键数量：20个 蜂鸣器：支持 遥控器：支持 卡片：支持 无线频率：RF433Mhz 双向无线通讯：支持 跳频技术：支持 无线加密：AES128 总线类型：RS485 总线距离：800米 总线线型：RVV4*1.0mm² 主电源：DC 12 V RS-485接口：1路 使用场景：室内 安装方式：壁挂 供电方式：DC 12 V 额定功率：1.2W 最大功率：1.8W 颜色：白色 外壳材质：塑料 产品重量：≤0.28 kg 产品尺寸：164 mm（宽）× 124 mm（深）× 31 mm（高） 工作温度及湿度：-10°C~55°C，湿度小于90%（无凝结） 存储温度及湿度：-20°C~60C，湿度小于90%（无凝结） | K83: 响应 | L83: / | M83: 117 | N83: =E83*M83 -> 117 | O83: 228 | P83: =E83*O83 -> 228 | Q83: =E83*(M83+O83) -> 345
A84: 5 | B84: 报警主机蓄电池 | C84: 1.电池类型：阀控密封式铅酸蓄电池 2.电池规格：DC12V7AH 3.停止供电电压：10.5V 4.电池放电温度及湿度：-20°C~50°C，湿度小于95%（无凝结） 5.电池充电温度及湿度：-20°C~50°C，湿度小于95%（无凝结） 6.安装方式：立式 7.颜色：黑色 8.外壳材质：ABS阻燃（V-1） 9.产品重量：2.0±3%Kg 10.产品尺寸：151mm*65mm*100mm 11.工作温度及湿度：-20°C~50°C，湿度小于95%（无凝结） | D84: 福科斯、广拓、海康 | E84: 1 | F84: 台 | H84: 海康威视 | I84: DS-PZ101VB | J84: 报警主机蓄电池 高效充放电：采用高能量密度和功率密度，具备优秀的瞬间大电流能力、充电接受能力和循环放电性能 安全环保：采用铅钙多元合金格栅和可靠的阀控密封技术，耐腐蚀性强 电池类型：阀控密封式铅酸蓄电池 电池规格：DC12V7AH 停止供电电压：10.5V 电池放电温度及湿度：-20°C~50°C，湿度小于95%（无凝结） 电池充电温度及湿度：-20°C~50°C，湿度小于95%（无凝结） 安装方式：立式 颜色：黑色 外壳材质：ABS阻燃（V-1） 产品重量：2.0±3%Kg 产品尺寸：151mm*65mm*100mm 工作温度及湿度：-20°C~50°C，湿度小于95%（无凝结） | K84: 响应 | L84: / | M84: 117 | N84: =E84*M84 -> 117 | O84: 81 | P84: =E84*O84 -> 81 | Q84: =E84*(M84+O84) -> 198
A85: 6 | B85: 警灯警号 | C85: 1.设备类型：声光警号（声光报警器） 2.警灯颜色：红色 3.报警音量：105dB 4.硬件接口：红/黑线 5.使用环境：室内/外（IP54室外防水） 6.外壳材质：PC+ABS 7.安装方式：壁挂 8.工作电源：DC12V/220mA（宽压8-16V DC） 9.工作温度：-20 °C 至 60 °C 10.工作湿度：10% 至 90% 11.产品尺寸：140*134*33mm | D85: 福科斯、广拓、海康 | E85: 1 | F85: 个 | H85: 海康威视 | I85: DS-PS1-R | J85: 【技术参数】 1、设备类型：声光警号（声光报警器） 2、警灯颜色：红色 3、报警音量：105dB 4、硬件接口：红/黑线 5、使用环境：室内/外（IP54室外防水） 6、外壳材质：PC+ABS 7、安装方式：壁挂 8、工作电源：DC12V/220mA（宽压8-16V DC） 9、工作温度：-20 °C 至 60 °C 10、工作湿度：10% 至 90% 11、产品尺寸：140*134*33mm 【产品功能】 1、声光报警：提供警灯闪烁和报警音频输出，用于提示警情处置 2、模式切换：支持关闭报警音频输出，仅提供警灯闪烁模式输出 3、内置水平仪：可通过内置水平仪调节安装角度，方便调试安装 | K85: 响应 | L85: / | M85: 117 | N85: =E85*M85 -> 117 | O85: 48 | P85: =E85*O85 -> 48 | Q85: =E85*(M85+O85) -> 165
A86: 7 | B86: 总线2防区扩展模块 | C86: 1.设备类型：总线2防区扩展模块 2.防区数量：2个 3.通讯接口：M-BUS 4.通讯线材：RVV2*1.5 5.通讯协议：M-BUS协议 6.外壳材质：塑料 7.使用环境：室内 8.工作电源：DC36V/20mA Max（主机总线供电） 9.工作温度：-10 °C 至 55 °C 10.工作湿度：10% 至 90% 11.产品尺寸：49.4*32*14.3mm | D86: 福科斯、广拓、海康 | E86: 11 | F86: 台 | H86: 海康威视 | I86: DS-19M02 | J86: 【技术参数】 1、设备类型：总线2防区扩展模块 2、防区数量：2个 3、通讯接口：M-BUS 4、通讯线材：RVV2*1.5 5、通讯协议：M-BUS协议 6、外壳材质：塑料 7、使用环境：室内 8、工作电源：DC36V/20mA Max（主机总线供电） 9、工作温度：-10 °C 至 55 °C 10、工作湿度：10% 至 90% 11、产品尺寸：49.4*32*14.3mm 【产品功能】 1、防区扩展：通过RVV线方式接入报警主机，扩展2路有线防区 2、总线无极性：总线接口不区分极性，方便施工安装 3、地址设置：通过拨码方式设置模块地址，拨码地址不能重复 | K86: 响应 | L86: / | M86: 70 | N86: =E86*M86 -> 770 | O86: 90 | P86: =E86*O86 -> 990 | Q86: =E86*(M86+O86) -> 1760
A87: 8 | B87: 入侵报警软件 | C87: 1、支持报警子系统管理能力，包含布防、撤防、消警控制操作； 2、支持防区管理能力，包含旁路、旁路恢复操作； 3、支持实时入侵报警能力； 4、支持历史入侵报警事件查询及导出能力； | D87: 福科斯、广拓、海康 | E87: 1 | F87: 台 | H87: 海康威视 | I87: 入侵报警软件 | J87: 入侵报警应用基于前端防区探测器进行园区范围内的入侵行为或意外事件的迅速感知和处理，实现针对园区内部的高效安全防范。 【功能介绍】 1、支持报警子系统管理能力，包含布防、撤防、消警控制操作； 2、支持防区管理能力，包含旁路、旁路恢复操作； 3、支持实时入侵报警能力； 4、支持历史入侵报警事件查询及导出能力； 【规格参数】 1、支持管理最大防区数量10000个； 2、支持报警记录最大存储数量1000W条。 | K87: 响应 | L87: / | M87: 0 | N87: =E87*M87 -> 0 | O87: 1062 | P87: =E87*O87 -> 1062 | Q87: =E87*(M87+O87) -> 1062
A88: 9 | B88: 信号线 | C88: 国标，RVV2*1.5 | D88: 一舟、普天天纪、罗格朗 | E88: 2400 | F88: m | H88: 一舟 | I88: G1808_60227 IEC 53(RVV) 2x1.5 | J88: 国标，RVV2*1.5 | K88: 响应 | L88: / | M88: 2 | N88: =E88*M88 -> 4800 | O88: 4 | P88: =E88*O88 -> 9600 | Q88: =E88*(M88+O88) -> 14400
A89: 10 | B89: 信号线 | C89: 国标，RVV4*0.75 | D89: 一舟、普天天纪、罗格朗 | E89: 200 | F89: m | H89: 一舟 | I89: G2003_60227 IEC 53(RVV) 4x0.75 | J89: 国标，RVV4*0.75 | K89: 响应 | L89: / | M89: 2 | N89: =E89*M89 -> 400 | O89: 5 | P89: =E89*O89 -> 1000 | Q89: =E89*(M89+O89) -> 1400
A90: 11 | B90: JDG20管 | C90: JDG管，壁厚不小于1.0MM,φ20；含主材、接头、固定扣件（含钢结构扣件）等辅材 | D90: 国产 | E90: 1000 | F90: m | H90: 国产 | I90: JDG20*1.0 | J90: JDG管，壁厚不小于1.0MM,φ20；含主材、接头、固定扣件（含钢结构扣件） | K90: 响应 | L90: / | M90: 10 | N90: =E90*M90 -> 10000 | O90: 3 | P90: =E90*O90 -> 3000 | Q90: =E90*(M90+O90) -> 13000
B91: 2.6、其它硬件 | N91: =E91*M91 -> 0 | P91: =E91*O91 -> 0
A92: 1 | B92: 全局网络控制器 | C92: 1.名称：全局网络控制器 2.参数：单核 A8@1GHz，1GB DDR3 / 4GB microSD，2× 百兆，2×RS-485，可扩展4 个 I/O/ 现场总线模块。协议：BACnet IP/MS/TP + Modbus TCP/RTU + LonWorks + KNX + SNMP + oBIX，编程：Niagara 图形化编程，功能极强，适合复杂联锁 / 算法。满足现场现场功能所需的点位授权费 | D92: 霍尼韦尔、江森、西门子 | E92: 1 | F92: 台 | H92: 霍尼韦尔 | I92: WEB-8050-U | J92: 1GHz处理器，1024MB内存，4096MB闪存，支持50个Device且数据点不大于2,500点，2条总线 | K92: 响应 | L92: / | M92: 326 | N92: =E92*M92 -> 326 | O92: 4035 | P92: =E92*O92 -> 4035 | Q92: =E92*(M92+O92) -> 4361
A93: 2 | B93: 可编程网络控制器 | C93: 通讯接口：100M以太网，双网口 协议：BACnetIP/Modbus-TCP 扩展接口通讯：控制器内部协议 DI输入接口：数量最大24路，干接点接入 DO控制接口：8路，继电器负载能力2A/30VDC UI输入接口：最大16路，支持电阻型温度NTC20K，电压型湿度0~10V，电压型CO2,0~10V，电压型CO 0~10V,电流型水压4~20mA，电流型流量计4~20mA，执行器0~10V和2~10V反馈 AO输出接口：8路，支持4~20mA和0~10V输出 RS485接口数量：2个，其中一个支持多合一传感器接入，另外一路备用 支持PLC功能，支持PLC逻辑编程 尺寸：225x115x 57mm 外壳原料： UL 94 ABS 电源：DC24V/3A 重量：500g | D93: 霍尼韦尔、江森、西门子 | E93: 9 | F93: 台 | H93: 霍尼韦尔 | I93: PUC5533-PB2 | J93: BACnet现场控制器DDC 5UI,5DI,3AO,3DO | K93: 响应 | L93: / | M93: 233 | N93: =E93*M93 -> 2097 | O93: 3360 | P93: =E93*O93 -> 30240 | Q93: =E93*(M93+O93) -> 32337 | S93: 招标要求带网络协议装换控制模块，PUC5533-PB2为总线型控制模块不满足招标参数， 和智慧消防第三项，完全一样的东西价格相差巨大，
A94: 3 | B94: 可编程控制盘 | C94: 1、包含、空开、导轨及接线端子 2、国产优质箱体，根据实际安装设备测量后成套定制 | D94: 霍尼韦尔、江森、西门子 | E94: 9 | F94: 台 | H94: 国产一线品牌 | I94: 1200*800*200 | J94: 1、包含、空开良信16A*3、正泰220V转24V变压器*1、电源模块明纬250V转24VDC*1、继电器正泰*15、接线端子*260、导轨*3M、线材*120M、线槽*6m | K94: 响应 | L94: / | M94: 233 | N94: =E94*M94 -> 2097 | O94: 781 | P94: =E94*O94 -> 7029 | Q94: =E94*(M94+O94) -> 9126
A95: 4 | B95: 电源模块 | C95: 输入：85–264VAC（全球宽压），50/60Hz 输出：24VDC 可调（约 24–26V） 电流：1.3A / 2.5A / 4A（常用 4A 配 DDC） 保护：过压、短路、过载、过热（自恢复） EMC：EN61000-6-2、EN61000-4 系列，工业级 安装：35mm DIN 导轨 外壳：UL94 V-0 阻燃塑料 工作温度：-20℃ ~ +60℃ | D95: 霍尼韦尔、江森、西门子 | E95: 9 | F95: 台 | H95: 霍尼韦尔 | I95: 8U-PWSP04 | J95: 输入：85-264 VAC，50/60Hz 输出：24 VDC 电流：4A 保护：过流保护、过压保护、短路保护 EMC：符合CE、UL、RoHS标准 安装：35mm DIN导轨安装 外壳：工业级阻燃外壳 工作温度：-20℃ ~ +60℃ | K95: 响应 | L95: / | M95: 17 | N95: =E95*M95 -> 153 | O95: 276 | P95: =E95*O95 -> 2484 | Q95: =E95*(M95+O95) -> 2637
A96: 5 | B96: 水浸变送器 | C96: 漏水探测器;固定电极式;可设置 5 级灵敏度;继电器：1×SPST(3A-30VDC 或 250VAC) 工作环境：-10~50°C，5~95%RH，非凝露 | D96: 霍尼韦尔、江森、西门子 | E96: 39 | F96: 台 | H96: 霍尼韦尔 | I96: WLD200 | J96: 漏水探测器;固定电极式;可设置 5 级灵敏度;继电器：1×SPST(3A-30VDC 或 250VAC) 工作环境：-10~50°C，5~95%RH，非凝露 | K96: 响应 | L96: / | M96: 175 | N96: =E96*M96 -> 6825 | O96: 614 | P96: =E96*O96 -> 23946 | Q96: =E96*(M96+O96) -> 30771
A97: 6 | B97: 噪声监测传感器 | C97: 量程：30~120dBA（A 计权）。 精度：±0.5dB，分辨率 0.1dB。 频率：20Hz~12.5kHz。 供电：10~30VDC（建议 24V）。 防护：IP65，室外可用 输出信号为 0-10V。 | D97: 国产一线品牌 | E97: 14 | F97: 台 | H97: 国产 | I97: RS485 | J97: 量程：30~120dBA（A 计权）。 精度：±0.5dB，分辨率 0.1dB。 频率：20Hz~12.5kHz。 供电：10~30VDC（建议 24V）。 防护：IP65，室外可用 输出信号为 0-10V。 | K97: 响应 | L97: / | M97: 140 | N97: =E97*M97 -> 1960 | O97: 165 | P97: =E97*O97 -> 2310 | Q97: =E97*(M97+O97) -> 4270
A98: 7 | B98: 光纤熔接盒（含光纤熔纤） | C98: SC4芯单模满配含熔接尾纤、法兰、SC光跳线 | D98: 一舟、普天天纪、罗格朗 | E98: =E92+E93 -> 10 | F98: 个 | H98: 一舟 | I98: S953-4X+S905-3*4+S812*4 | J98: SC4芯单模满配含熔接尾纤、法兰、SC光跳线 | K98: 响应 | L98: / | M98: 52 | N98: =E98*M98 -> 520 | O98: 71 | P98: =E98*O98 -> 710 | Q98: =E98*(M98+O98) -> 1230
A99: 8 | B99: 光纤收发器 | C99: 1个10/100M/1000M网口，1个1000Mbps光口（SC），工作波长：1550nm（发送）、1310nm（接收），20km。 | D99: TP-LINK、山泽、烽火 | E99: =E92+E93 -> 10 | F99: 对 | H99: TP-LINK | I99: TL-FC311A-20+TL-FC311B-20 | J99: 1个10/100M/1000M网口，1个1000Mbps光口（SC），工作波长：1550nm（发送）、1310nm（接收），20km。 | K99: 响应 | L99: / | M99: 17 | N99: =E99*M99 -> 170 | O99: 240 | P99: =E99*O99 -> 2400 | Q99: =E99*(M99+O99) -> 2570
A100: 9 | B100: 光纤收发器架 | C100: 14槽光纤收发器机架；标准机柜安装； | D100: TP-LINK、山泽、烽火 | E100: 1 | F100: 个 | H100: TP-LINK | I100: TL-FC1400 | J100: 14槽光纤收发器机架；标准机柜安装； | K100: 响应 | L100: / | M100: 17 | N100: =E100*M100 -> 17 | O100: 504 | P100: =E100*O100 -> 504 | Q100: =E100*(M100+O100) -> 521
A101: 10 | B101: 室外4芯单模光缆 | C101: 1.标准：YD/T769，ISO/IEC11801，ANSI/TIA -568-C.3 2.全截面阻水结构，松套管填充纤膏，松套管和钢带之间填充缆膏，确保良好的阻水防潮性能 3.光纤规格：B1.3（OS2） 4.衰减＠20℃（dB/Km）：＠1310nm≤0.36，＠1550nm≤0.22 5.光纤芯数：4芯 6.护套：夹带钢丝的钢-聚乙烯粘结护套，MDPE，黑色 7.允许拉伸力：长期：600N，短期：1500N 8.允许压扁力：长期：300N/100mm，短期：1000N/100mm 9.最小弯曲半径：动态：20D，静态：10D | D101: 一舟、普天天纪、罗格朗 | E101: =E99*300 -> 3000 | F101: m | H101: 一舟 | I101: D173-4 | J101: 1.标准：YD/T769，ISO/IEC11801，ANSI/TIA -568-C.3 2.全截面阻水结构，松套管填充纤膏，松套管和钢带之间填充缆膏，确保良好的阻水防潮性能 3.光纤规格：B1.3（OS2） 4.衰减＠20℃（dB/Km）：＠1310nm≤0.36，＠1550nm≤0.22 5.光纤芯数：4芯 6.护套：夹带钢丝的钢-聚乙烯粘结护套，MDPE，黑色 7.允许拉伸力：长期：600N，短期：1500N 8.允许压扁力：长期：300N/100mm，短期：1000N/100mm 9.最小弯曲半径：动态：20D，静态：10D | K101: 响应 | L101: / | M101: 1 | N101: =E101*M101 -> 3000 | O101: 2 | P101: =E101*O101 -> 6000 | Q101: =E101*(M101+O101) -> 9000 | S101: 施工费偏低无法实现
...

Sheet 软件-报价汇总表
A1: 密级：公开
A2: 阳光电源智慧园区一期建设清单（软件）报价清单
A3: 序号 | B3: 项目内容 | C3: 数量 | D3: 单位 | E3: 税率 | F3: 未税单价 | G3: 未税小计 | H3: 含税小计
A4: 1 | B4: 产品费用 | C4: 1 | D4: 项 | E4: 0.13 | F4: ='软件-产品费用报价明细'!G11 -> 2270000 | G4: =C4*F4 -> 2270000 | H4: =G4*(1+E4) -> 2565100
A5: 2 | B5: 实施费用 | C5: 1 | D5: 项 | E5: 0.13 | F5: ='软件-实施费用报价明细'!N36 -> 1455000 | G5: =C5*F5 -> 1455000 | H5: =G5*(1+E5) -> 1644150
A6: 3 | B6: 运维费（第四到第五年） | C6: 2 | D6: 年 | E6: 0.13 | F6: =G4*5% -> 113500 | G6: =C6*F6 -> 227000 | H6: =G6*(1+E6) -> 256510
A7: 4 | B7: 合计 | G7: =SUM(G4:G6) -> 3952000 | H7: =SUM(H4:H6) -> 4465760
A8: 报价须知： 1、三年免费维护（即一期整体验收后36个月），第四年开始维护费用比率为产品费用的【5】 %；即第四年开始每年收取【113500】元；维保协议根据需要另行签订，维保价格不高于本次报价。 2、报价已包含完成本项目的一切费用； 3、报价有效期：90天； 4、付款方式：电汇，合同签订后预付合同对应金额20%，蓝图完成经客户确认后支付合同对应金额20%，上线完成经客户确认后支付合同对应金额30%，上线6个月保驾护航完成经客户确认后支付合同对应金额20%，自上线验收合格1年后支付10%。 5、本项目一期的所有功能需求及产品，均由报价人提供； 6、实施费用为人天单价，后续增加期数（如有）实施费用以不高于本次人天价格执行； 7、人天费用不得已“赠送、总价折扣、缩减人天量形式”进行优惠； 8、单价需符合市场规律，价格不得以免费赠送形式报价； 9、本次项目具体清单，请按自己格式拟定，并且与本表一起盖章作为投标价格标；

Sheet 软件-产品费用报价明细
A1: 序号 | B1: 软件/模块名称 | C1: 版本号 | D1: 数量 | E1: 单位 | F1: 未税单价 | G1: 未税合计 | H1: 是否买断 | I1: 备注
A2: =ROW()-1 -> 1 | B2: 智慧物流 | C2: V1.0 | D2: 1 | E2: 套 | F2: 450000 | G2: =D2*F2 -> 450000 | H2: 否 | I2: 如是否买断为“否”，则报价需包含运维阶段（第一至五年）的所有订阅费用
A3: =ROW()-1 -> 2 | B3: 智慧消防 | C3: V1.0 | D3: 1 | E3: 套 | F3: 300000 | G3: =D3*F3 -> 300000 | H3: 否
A4: =ROW()-1 -> 3 | B4: 智慧安防 | C4: V1.0 | D4: 1 | E4: 套 | F4: 250000 | G4: =D4*F4 -> 250000 | H4: 否
A5: =ROW()-1 -> 4 | B5: 宿舍管理 | C5: V1.0 | D5: 1 | E5: 套 | F5: 150000 | G5: =D5*F5 -> 150000 | H5: 否
A6: =ROW()-1 -> 5 | B6: 外协人员管理 | C6: V1.0 | D6: 1 | E6: 套 | F6: 300000 | G6: =D6*F6 -> 300000 | H6: 否
A7: =ROW()-1 -> 6 | B7: 报表管理模块 | C7: V1.0 | D7: 1 | E7: 套 | F7: 250000 | G7: =D7*F7 -> 250000 | H7: 否
A8: =ROW()-1 -> 7 | B8: 系统管理模块 | C8: V1.0 | D8: 1 | E8: 套 | F8: 20000 | G8: =D8*F8 -> 20000 | H8: 否
A9: =ROW()-1 -> 8 | B9: 移动及多屏应用 | C9: V1.0 | D9: 1 | E9: 套 | F9: 50000 | G9: =D9*F9 -> 50000 | H9: 否
A10: =ROW()-1 -> 9 | B10: 智慧园区平台 | C10: V1.0 | D10: 1 | E10: 套 | F10: 500000 | G10: =D10*F10 -> 500000 | H10: 否
A11: 未税合计 | G11: =SUM(G2:G10) -> 2270000

Sheet 软件-实施费用报价明细
A1: 密级：秘密
A2: 【阳光电源智慧园区一期建设项目】人天资源投入价格清单
A3: 项目人员姓名 | B3: 项目角色 | C3: 实施方式 | D3: 人天数量（人/天） | M3: 人天费用（未税）
D4: 项目启动 | E4: 需求分析 | F4: 方案设计 | G4: 系统开发 | H4: 系统测试 | I4: 上线准备 | J4: 上线推广 | K4: 上线后现场运维【6】个月 | L4: 人天汇总 | M4: 实施单价 （人/天/元） | N4: 实施费用 小计(元)
B5: 自然周 | C5: 现场/远程 | D5: Week1—Week2 | E5: Week3—Week6 | F5: Week6—Week12 | G5: Week8—Week32 | H5: Week17—Week36 | I5: Week20—Week37 | J5: Week23—Week40 | K5: Week41—Week64
B6: 项目经理 | C6: 现场 | D6: 8 | E6: 10 | F6: 12 | G6: 20 | H6: 8 | I6: 5 | J6: 15 | K6: 0 | L6: =SUM(D6:K6) -> 78 | M6: 2000 | N6: =M6*L6 -> 156000
C7: 远程 | D7: 0 | E7: 0 | F7: 0 | G7: 0 | H7: 0 | I7: 0 | J7: 0 | K7: 0 | L7: =SUM(D7:K7) -> 0 | M7: 2000 | N7: =M7*L7 -> 0
B8: 业务分析师 | C8: 现场 | D8: 3 | E8: 5 | F8: 0 | G8: 0 | H8: 0 | I8: 0 | J8: 0 | K8: 0 | L8: =SUM(D8:K8) -> 8 | M8: 2000 | N8: =M8*L8 -> 16000
C9: 远程 | D9: 0 | E9: 5 | F9: 15 | G9: 5 | H9: 0 | I9: 0 | J9: 0 | K9: 0 | L9: =SUM(D9:K9) -> 25 | M9: 2000 | N9: =M9*L9 -> 50000
B10: 方案架构师 | C10: 现场 | D10: 3 | E10: 0 | F10: 0 | G10: 0 | H10: 0 | I10: 0 | J10: 0 | K10: 0 | L10: =SUM(D10:K10) -> 3 | M10: 2000 | N10: =M10*L10 -> 6000
C11: 远程 | D11: 0 | E11: 10 | F11: 15 | G11: 0 | H11: 0 | I11: 0 | J11: 0 | K11: 0 | L11: =SUM(D11:K11) -> 25 | M11: 2000 | N11: =M11*L11 -> 50000
B12: 产品经理 | C12: 现场 | D12: 0 | E12: 5 | F12: 0 | G12: 0 | H12: 0 | I12: 0 | J12: 0 | K12: 0 | L12: =SUM(D12:K12) -> 5 | M12: 2000 | N12: =M12*L12 -> 10000
C13: 远程 | D13: 3 | E13: 5 | F13: 15 | G13: 10 | H13: 0 | I13: 0 | J13: 0 | K13: 0 | L13: =SUM(D13:K13) -> 33 | M13: 2000 | N13: =M13*L13 -> 66000
B14: UI工程师 | C14: 现场 | D14: 0 | E14: 0 | F14: 0 | G14: 0 | H14: 0 | I14: 0 | J14: 0 | K14: 0 | L14: =SUM(D14:K14) -> 0 | M14: 1500 | N14: =M14*L14 -> 0
C15: 远程 | D15: 0 | E15: 3 | F15: 10 | G15: 2 | H15: 0 | I15: 0 | J15: 0 | K15: 0 | L15: =SUM(D15:K15) -> 15 | M15: 1500 | N15: =M15*L15 -> 22500
B16: 开发工程师1 | C16: 现场 | D16: 0 | E16: 0 | F16: 0 | G16: 0 | H16: 0 | I16: 0 | J16: 0 | K16: 0 | L16: =SUM(D16:K16) -> 0 | M16: 2000 | N16: =M16*L16 -> 0
C17: 远程 | D17: 0 | E17: 0 | F17: 0 | G17: 60 | H17: 10 | I17: 2 | J17: 0 | K17: 0 | L17: =SUM(D17:K17) -> 72 | M17: 2000 | N17: =M17*L17 -> 144000
B18: 开发工程师2 | C18: 现场 | D18: 0 | E18: 0 | F18: 0 | G18: 0 | H18: 0 | I18: 0 | J18: 0 | K18: 0 | L18: =SUM(D18:K18) -> 0 | M18: 2000 | N18: =M18*L18 -> 0
C19: 远程 | D19: 0 | E19: 0 | F19: 0 | G19: 60 | H19: 10 | I19: 2 | J19: 0 | K19: 0 | L19: =SUM(D19:K19) -> 72 | M19: 2000 | N19: =M19*L19 -> 144000
B20: 开发工程师3 | C20: 现场 | D20: 0 | E20: 0 | F20: 0 | G20: 0 | H20: 0 | I20: 0 | J20: 0 | K20: 0 | L20: =SUM(D20:K20) -> 0 | M20: 2000 | N20: =M20*L20 -> 0
C21: 远程 | D21: 0 | E21: 0 | F21: 0 | G21: 60 | H21: 10 | I21: 2 | J21: 0 | K21: 0 | L21: =SUM(D21:K21) -> 72 | M21: 2000 | N21: =M21*L21 -> 144000
B22: 开发工程师4 | C22: 现场 | D22: 0 | E22: 0 | F22: 0 | G22: 0 | H22: 0 | I22: 0 | J22: 0 | K22: 0 | L22: =SUM(D22:K22) -> 0 | M22: 2000 | N22: =M22*L22 -> 0
C23: 远程 | D23: 0 | E23: 0 | F23: 0 | G23: 60 | H23: 10 | I23: 2 | J23: 0 | K23: 0 | L23: =SUM(D23:K23) -> 72 | M23: 2000 | N23: =M23*L23 -> 144000
B24: 测试工程师1 | C24: 现场 | D24: 0 | E24: 0 | F24: 0 | G24: 0 | H24: 0 | I24: 0 | J24: 0 | K24: 0 | L24: =SUM(D24:K24) -> 0 | M24: 1200 | N24: =M24*L24 -> 0
C25: 远程 | D25: 0 | E25: 0 | F25: 0 | G25: 0 | H25: 30 | I25: 0 | J25: 0 | K25: 0 | L25: =SUM(D25:K25) -> 30 | M25: 1200 | N25: =M25*L25 -> 36000
B26: 测试工程师2 | C26: 现场 | D26: 0 | E26: 0 | F26: 0 | G26: 0 | H26: 0 | I26: 0 | J26: 0 | K26: 0 | L26: =SUM(D26:K26) -> 0 | M26: 1200 | N26: =M26*L26 -> 0
C27: 远程 | D27: 0 | E27: 0 | F27: 0 | G27: 0 | H27: 30 | I27: 0 | J27: 0 | K27: 0 | L27: =SUM(D27:K27) -> 30 | M27: 1200 | N27: =M27*L27 -> 36000
B28: 实施顾问 | C28: 现场 | D28: 0 | E28: 0 | F28: 0 | G28: 0 | H28: 0 | I28: 40 | J28: 30 | K28: 0 | L28: =SUM(D28:K28) -> 70 | M28: 1500 | N28: =M28*L28 -> 105000
C29: 远程 | D29: 0 | E29: 0 | F29: 0 | G29: 0 | H29: 0 | I29: 0 | J29: 0 | K29: 0 | L29: =SUM(D29:K29) -> 0 | M29: 1500 | N29: =M29*L29 -> 0
B30: 实施工程师 | C30: 现场 | D30: 0 | E30: 0 | F30: 0 | G30: 0 | H30: 0 | I30: 0 | J30: 0 | K30: 0 | L30: =SUM(D30:K30) -> 0 | M30: 1500 | N30: =M30*L30 -> 0
C31: 远程 | D31: 0 | E31: 0 | F31: 0 | G31: 0 | H31: 0 | I31: 40 | J31: 30 | K31: 0 | L31: =SUM(D31:K31) -> 70 | M31: 1500 | N31: =M31*L31 -> 105000
B32: 运维工程师 | C32: 现场 | D32: 0 | E32: 0 | F32: 0 | G32: 0 | H32: 0 | I32: 0 | J32: 0 | K32: 132 | L32: =SUM(D32:K32) -> 132 | M32: 1500 | N32: =M32*L32 -> 198000
C33: 远程 | D33: 0 | E33: 0 | F33: 0 | G33: 0 | H33: 0 | I33: 0 | J33: 0 | K33: 0 | L33: =SUM(D33:K33) -> 0 | M33: 1500 | N33: =M33*L33 -> 0
B34: 项目专员 | C34: 现场 | D34: 0 | E34: 0 | F34: 0 | G34: 0 | H34: 0 | I34: 0 | J34: 0 | K34: 0 | L34: =SUM(D34:K34) -> 0 | M34: 1500 | N34: =M34*L34 -> 0
C35: 远程 | D35: 0 | E35: 0 | F35: 0 | G35: 0 | H35: 0 | I35: 10 | J35: 5 | K35: 0 | L35: =SUM(D35:K35) -> 15 | M35: 1500 | N35: =M35*L35 -> 22500
K36: 人天量总计 | L36: =SUM(L6:L35) -> 827 | M36: 费用总计 | N36: =SUM(N6:N35) -> 1455000
A37: 甲方备注： | C37: 请合理安排项目计划，人力投入需要具体到每个人员的每周投入
C38: 本项目报价清单中单价固定，招标范围内总价包干。项目交付中若有需求量变更按投标单价据实结算；
C39: 项目费用需要在表中具体到每个人员的实施费用，费用包含差旅食宿等一切费用，后期不再接受报价外费用。
A40: 乙方备注： | C40: 实施费用增值税专票税率：【13】 %
A44: 备注：以上是实施费用报价模板，须按照模板报价。

Sheet 附录五硬件场景需求表
A1: 项目范围 | B1: 系统 | C1: 序号 | D1: 设施设备 | E1: 数量 | F1: 涉及硬件类型
A2: 智慧消防系统 | B2: 消防水系统 | C2: 1 | D2: 消防水池 | E2: 水池数量 | F2: 水位仪传感器7个（包括电动力1个）
C3: 2 | D3: 消防水箱 | E3: 水箱数量 | F3: 水位仪传感器6个（包括电动力1个）、出水管流量传感器12个（包括电动力2个）
C4: 3 | D4: 消防泵/喷淋泵 | E4: 泵数量 | F4: 电气监控28个（包括电动力4个）
C5: 4 | D5: 稳压泵 | E5: 泵数量 | F5: 电气监控、启停状态/次数监测28个（包括电动力4个）
C6: 5 | D6: 隔膜气压罐 | E6: 罐体数量 | F6: 14个（包括电动力2个）
C7: 6 | D7: 配电柜 | E7: 柜体数量 | F7: 电气监控9个（包括电动力2个）
C8: 7 | D8: 控制柜 | E8: 柜体数量 | F8: 电气监控、远程手自动变更28个（包括电动力4个）
C9: 8 | D9: 消防测试栓 | E9: 屋面测试栓数量 | F9: 压力传感器 30
C10: 9 | D10: 末端测试 | E10: 末端数量 | F10: 压力传感器 200
C11: 10 | D11: 消防泵房 | E11: 泵房数量 | F11: 9个（包括电动力2个消防泵房/稳压泵房）
C12: 11 | D12: 进水阀 | E12: 水池、水箱水量 | F12: 流量计、压力传感器13个（包括电动力2个）
C13: 12 | D13: 关键管路（进出水主管） | E13: 进出水管数量 | F13: 阀门启闭状态检测、压力传感器、流量监测（50个阀门启闭状态、压力传感器、流量监测）
C14: 13 | D14: 湿式报警阀\预作用阀 | E14: 报警阀数量 | F14: 上下腔压力监测、判断，水力警铃传感69个报警阀、69个水力警铃
... C16: 15 | D16: 消防水炮主机 | E16: 水炮数量 | F16: 电磁阀启动信号 2
B17: 全淹没气灭 | C17: 16 | D17: 环境检测 | E17: 全淹没房间数量 | F17: 氧浓度监测接入消防平台 33个
C18: 17 | D18: 电磁阀、泄压口 | E18: 瓶体数量 | F18: 压力传感器/电磁阀启动监测（100个）
B19: 排烟系统 | C19: 18 | D19: 排烟风机 | E19: 风机数量 | F19: 排烟风速计量（含风向）110
C20: 19 | D20: 电动挡烟垂壁 | E20: / | F20: 释放状态
B21: 防火卷帘 | F21: 释放状态
B22: 排水系统 | C22: 20 | D22: 雨水截止阀 | F22: 自动灭火后联动对应雨水截止阀关闭
C23: 21 | D23: 关键机房、泵房排水泵 | E23: 水泵数量 | F23: 启闭监测 24个（6个消防泵房）
C24: 22 | D24: 关键机房、泵房 | F24: 防水浸监测（10个）
B25: 可燃气体 | C25: 23 | D25: 可燃气体报警主机 | E25: 主机数量 | F25: 可燃气体报警主机接入消防平台 8个
C26: 24 | D26: 可燃气体管路 | E26: 燃气管道数量 | F26: 燃气、压缩空气等管道加装可联动电磁阀 （2个）
B27: 电气火灾监控 | F27: 在线电压、剩余电流检测、电缆温度检测 数量太多400+
B28: 视频监控系统 | C28: 25 | D28: 自动报警系统 | F28: 自动报警系统联动范围摄像头、算法判断 数量太多1000+
C29: 26 | D29: 安全出口堵塞 | F29: 摄像头算法判断安全出口、疏散通道 150+
C30: 27 | D30: 屋面光伏摄像头 | F30: 烟雾、火焰摄像头 （60+）
D31: 电动自行车充电区 | F31: 40+
D32: 电动叉车充电区 | F32: 8
D33: AGV充电区 | F33: 15
D34: 电动汽车充电区 | F34: 60+
D35: 厨房灶台 | F35: 15+
B36: 关键岗位通讯设备 | C36: 28 | D36: 手持设备 | F36: 关键岗位用于设备点检、救援联动、保修维修等功能(12-15台）
A37: 智慧安防系统 | B37: 周界防护 | C37: 29 | D37: 震动光纤 | F37: 光纤、接收器等（4000米周长）
C38: 30 | D38: 周界监控 | F38: 基于算法和震动光纤提示报警（40台摄像机）
C39: 31 | D39: 红外对射报警 | F39: 对车辆道闸下口、窄小区域提示报警（11）
B40: 全面监控 | C40: 32 | D40: 屋面 | F40: 鹰眼相机 提供园区概状视频监控3-4台
C41: 33 | D41: 车道相机 | F41: 对违停、逆行等行为进行算法判断20台
C42: 34 | D42: 无人机 | F42: 按固定轨道轮训，视频上传算法1台
B43: 巡更系统 | C43: 35 | D43: 巡更点 | F43: 使用NFC等设备进行巡更管理40+
A45: 场景类型* | B45: 场所* | C45: 位置* | D45: 需求场景* | F45: 已有摄像头数量* | G45: 优先级*
A46: EHS | B46: M6 | C46: 一楼东侧和南侧老化测试区 | D46: 监测绝缘鞋火焰和烟雾，噪音监测； | F46: 24 | G46: 高
A47: EHS | B47: M6 | C47: 一楼东侧和南侧后的老化设备间 | D47: 监测绝缘鞋火焰和烟雾； | F47: 16 | G47: 高
A48: EHS | B48: M6 | C48: 一楼行车下方工作区域 | D48: 监测工人佩戴安全帽，防砸鞋；人员是否处于吊装物下方 | F48: 0 | G48: 中
A49: EHS | B49: M6 | C49: 一楼板链线旁检修口 | D49: 维修口打开会有信号数据，信号接入摄像头去判断人员是否佩戴安全帽； | F49: 1 | G49: 中
A50: EHS | B50: M6 | C50: 一楼生命线 | D50: 检测人员登高时人员是否配戴安全帽与安全带 | F50: 2 | G50: 中
A51: EHS | B51: M8 | C51: 一楼南边模组房机械臂区域 | D51: 需要进行人员安全帽监测； | F51: 1 | G51: 中
A52: EHS | B52: M8 | C52: 一楼南边的悬臂吊 | D52: 作业时监测下方人员的是否穿戴安全帽和防砸鞋；人员是否处于吊装物下方。 | F52: 1 | G52: 中
A53: EHS | B53: M8 | C53: 一楼南边悬臂吊旁边的调试区 | D53: 需要穿绝缘鞋，火焰烟雾监测； | F53: 0 | G53: 高
A54: EHS | B54: M9 | C54: 一楼南侧区域的老化测试区 | D54: 需要进行绝缘鞋和烟雾火焰监测，噪音监测； | F54: 1 | G54: 高
A55: EHS | B55: M9 | C55: 一楼南侧区域的老化设备间 | D55: 需要进行绝缘鞋、火焰和烟雾检测； | F55: 0 | G55: 高
A56: EHS | B56: M15 | C56: 车间内主次干道 | D56: 识别物料占道、超线摆放、地面垃圾5S问题 | F56: / | G56: 中
A57: EHS | B57: M15 | C57: 一楼电芯上线区 | D57: 监测安全帽、火焰和烟雾（考虑摄像头与火焰烟感联动）；监测噪声区域人员暴露时长。 | F57: 4 | G57: 高
A58: EHS | B58: M15 | C58: 一楼电芯堆叠区 | D58: 监测安全帽、火焰和烟雾（考虑摄像头与火焰烟感联动）；监测噪声区域人员暴露时长。 | F58: 3 | G58: 高
A59: EHS | B59: M15 | C59: 一楼西侧的悬臂吊工作区 | D59: 监测下方施工是否配戴安全帽和防砸鞋，火焰及烟雾监测（考虑摄像头与烟感联动）；人员是否处于吊装物下方 | F59: 0 | G59: 中
A60: EHS | B60: 化学品库 | C60: 园区东侧和西侧化学品库 | D60: 监测液体倾倒、泄漏，抽烟，手机监测，温度湿度监测报警；，火焰及烟雾监测（考虑摄像头与烟感联动）； | F60: 2 | G60: 高
A61: EHS | B61: 叉车充电区 | C61: M19西侧叉车充电区 | D61: 监测火焰及烟雾（考虑摄像头与烟感联动） | F61: 0 | G61: 中
A62: EHS | B62: 龙门吊 | C62: M9右侧堆场上方龙门吊 | D62: 监测龙门吊下方工作区，工人是否佩戴安全帽，人员是否处于吊装物下方 | F62: 0 | G62: 中
A63: EHS | B63: M8 | C63: M8南侧污水处理站 | D63: 监测污水站顶部进出口，识别有无开启动作，人员是否佩戴安全帽 | F63: 0 | G63: 中
A64: EHS | B64: M10 | C64: 一楼仓储区 | D64: 围栏内监测安全帽，火焰及烟雾监测（考虑摄像头与烟感联动）； | F64: 34 | G64: 中
A65: EHS | B65: M10 | C65: 一楼仓储区 | D65: 围栏外使用电动托盘车需要穿反光背心、防砸鞋。 | F65: 26 | G65: 中
A66: EHS | B66: M5 | C66: 二楼X射线监测室 | D66: 监测人员操作时是否穿戴铅衣 | F66: 1 | G66: 中
A67: EHS | B67: M5 | C67: 二楼工装清洗室 | D67: 监测防尘口罩，需加装摄像头与烟感联动 | F67: 1 | G67: 中
A68: EHS | B68: M5 | C68: 二楼波峰焊操作台 | D68: 操作时监测人员需佩戴防护口罩 | F68: 3 | G68: 中
... A71: EHS | B71: 园区 | C71: 园区道路 | D71: 叉车、托盘车驾驶人员是否穿反光马甲、操作托盘车是否穿防砸鞋；车辆驾驶是否超速（叉车15，托盘车8） | F71: 311 | G71: 高
A73: 场景类型* | B73: 场所* | C73: 位置* | D73: 需求场景* | F73: 已有摄像头数量* | G73: 优先级*
A74: 道路交通 | B74: 园区道路 | C74: 全部 | D74: 违停、堆物、人员聚集、 | F74: 311 | G74: 低
A75: 周界防护 | B75: 园区围墙 | C75: 全部 | D75: 翻越 | F75: 92 | G75: 中
A76: 屋面光伏 | B76: 屋面光伏安装场所 | C76: 全部 | D76: 烟雾、火焰 | F76: 0 | G76: 高
A77: 安全出口 | B77: 所有厂房 | C77: 全部 | D77: 安全出口堵塞 | F77: 150 | G77: 低
A78: 消防水池水箱 | B78: 水泵房 | C78: 7处 | D78: 液位仪传感器 | F78: 7 | G78: 高
B79: 稳压泵房 | C79: 6处 | D79: 液位传感器 | F79: 6 | G79: 高
A80: 水泵电气监控 | B80: 水泵房 | C80: 7处 | D80: 水泵电气监控 | F80: 28 | G80: 高
B81: 稳压泵房 | C81: 6处 | D81: 电气监控、启停状态/次数监测 | F81: 28 | G81: 高
A82: 配电柜 | B82: 水泵房 | C82: 7处 | D82: 电气监控 | F82: 9 | G82: 高
A83: 控制柜 | B83: 水泵房 | C83: 7处 | D83: 电气监控、远程手自动变更 | F83: 28 | G83: 高
A84: 消防测试栓 | B84: 屋面 | C84: 30处 | D84: 压力监控 | F84: 30 | G84: 高
A85: 末端测试 | B85: 厂房、宿舍各防火分区 | C85: 200处 | D85: 压力监控 | F85: 200 | G85: 高
A86: 补水阀 | B86: 水泵房、稳压泵房 | C86: 13处 | D86: 流量监控、压力监控 | F86: 13 | G86: 高
