Workbook

Sheet 总价汇总表
A1: 密级：公开
A2: XX智慧园区一期建设清单报价清单-汇总表
A3: 序号 | B3: 系统名称 | C3: 税率 | D3: 不含税总价 | E3: 含税总价 | F3: 备注
A4: 1 | B4: 硬件部分 | C4: 0.13 | D4: ='硬件-报价汇总表'!D7 -> 8509539.1 | E4: =D4*(1+C4) -> 9615779.1
A5: 2 | B5: 软件部分 | C5: 0.13 | D5: 2550183 | E5: =D5*(1+C5) -> 2881706.8
A6: 3 | B6: 总计（元） | D6: =SUM(D4:D5) -> 11059722 | E6: =SUM(E4:E5) -> 12497486
D7: 按此未税金额投标
C9: 施工合计未税 | D9: 材料合计未税
C10: ='硬件-报价明细'!N115 -> 1686598 | D10: ='硬件-报价明细'!P115 -> 6822941.1 | E10: =SUM(C10:D10) -> 8509539.1
C12: =C10*1.13 -> 1905855.7 | D12: =D10*1.13 -> 7709923.4 | E12: =SUM(C12:D12) -> 9615779.1
C14: 111 | D14: 667
D16: =1180-C14-D14 -> 402

Sheet 硬件-报价汇总表
A1: 密级：公开
A2: XX智慧园区一期建设清单（硬件）报价清单
A3: 序号 | B3: 系统名称 | C3: 税率 | D3: 不含税总价 | E3: 备注
A4: 1 | B4: 智慧消防及物联系统 | C4: 0.13 | D4: =SUM('硬件-报价明细'!Q7:Q33) -> 3180591.7
A5: 2 | B5: 智慧安防系统 | C5: 0.13 | D5: =SUM('硬件-报价明细'!Q36:Q110) -> 5271075.4
A6: 3 | B6: 等保测评 | C6: 0.13 | D6: ='硬件-报价明细'!Q112 -> 57872
A7: 4 | B7: 不含税总计（元） | D7: =SUM(D4:D6) -> 8509539.1
A8: 报价须知： 1、报价前请仔细阅读《硬件-报价说明》。 2、付款方式：电汇，初验完成后支付合同对应金额的70%（且累积支付不超实际产值70%），终验决算完成支付至决算对应金额的90%，剩余10%作为质保金，自竣工验收通过满1年后如无质量问题、无发生甲方代扣代付维修费用，甲方无息支付质保金。详见SOW内约定。

Sheet 硬件-报价说明
A1: 密级：公开
A2: XX智慧园区一期建设清单（硬件） 投标报价说明
A3: 说明 | B3: 本报价说明作为投标文件的重要组成部分，与招标文件、技术规格书及合同具有同等效力。投标人须仔细阅读并充分理解所有条款，报价提交后视为已完全响应。
A4: 一、报价范围与计价模式
A5: 总价包含范围 | B5: 1、投标总价含设备、材料等运输、卸货、搬用、保存、安装、集成调试，通断测试，福禄克测试，质保期内保证项目稳定运行的所需全部费用。
B6: 2、投标总价含设备、线缆、柜、箱体等的机打标签、整理等工作，达到《XX弱电施工工艺参考图册》、《XX厂区及办公区弱电标识标签规则》要求。
B7: 3、投标总价含施工、技术支持、操作人员培训等，含3年原厂质保运维服务等，故障1小时响应，故障处理6小时内完成。
B8: 4、投标总价含材料费、施工费、调试费、措施费、安全文明施工费、税金、总包管理服务费、施工用水电费用、辅材、实现平台功能前端设备调整（角度、位置等）等项目交付前一切费用，辅材包括但不限于六类非屏蔽水晶头、音频接插头、各种螺丝、吊卡、丝杆、铁皮卡、自攻螺丝、膨胀管、绝缘子、接线端子、弓背、管道支持柱、拉爆三件套、膨胀螺栓、机柜螺丝、垫片、绝缘胶布、透明胶布、扎带、标签纸、魔术贴、网线固线器、标签机、钩钉、刚性卡箍、螺丝杆帽、PVC线槽、自喷漆、明装86盒、明装86盒盖板、弯管器、墙面开孔及开槽及修复、地面开挖及绿化恢复、其他施工工具等辅材。
A9: “实体净量+量价分离”计价规则 | B9: 本项目所有强弱电管、线、桥架类材料实行“实体净量+量价分离”计价模式，清单工程量仅依据设计图纸标注的水平/垂直投影净长度计算，施工中必然发生的桥架（含管道）内敷设弯曲、桥架上翻下翻、机柜与终端处的预留长度，以及各类管、线、桥架类材料的合理损耗等，其工程量与费用均视为投标人施工技术的一部分，须在编制综合单价时一并考虑（相关费用在材料单价中体现），结算时不再单独计量。
A10: 综合单价包干 | B10: 综合单价为包干价，包括但不限于完成工程量清单子目特征描述、工作内容描述等全部内容所需的人工费、材料费（甲供材除外）、机械费、管理费、利润、税金等全部费用，特征描述中不完善，但按常规属于完成该对应子目所必须有的工作内容，视为已包含在综合单价中。
A11: 二、技术要求与执行标准
A12: 工艺与标签规范 | B12: 施工须符合《XX弱电施工工艺参考图册》、《XX厂区及办公区弱电标识标签规则》，含设备、线缆、柜体等机打标签及整理。
A13: 施工界面与现场踏勘 | B13: 投标人应踏勘现场，充分了解施工移交界面及标准（如地面、墙面找平层厚度可能产生的变化），相关费用包含在报价中。
A14: 深化设计与规范要求 | B14: 本工程工程量清单项目仅列出主要包含范围，投标单位应结合设计图及标准作法进行理解，投标单位需按规范及设计要求深化施工工艺及对应施工工艺作法，本部分费用已含在本合同总价中。
A15: 三、投标报价与格式要求
A16: 报价格式 | B16: 报价时按照甲方提供表格格式要求进行报价；乙方提供excel表格报价电子档文件（可编辑版本即可），并提供word版本盖章报价扫描件（包含表头：序号、项目名称、工程量、单位、投标品牌、投标型号、参数（响应/正偏离/负偏离）、正/负偏离参数项、材料未税单价、施工未税单价、未税小计、备注）。
A17: 单价一致性 | B17: 清单中所列相同项目，投标单位报价须保持一致，若投标报价不一致，则以报价较低的单价计算并调整总价。
A18: 链接正确性 | B18: 投标清单中的链接由投标人自行负责核实。
A19: 金额精度 | B19: 工程量清单内所有工程量及金额均需保留两位小数，并以显示精度为准。
A20: 四、风险与变更条款
A21: 未尽事宜 | B21: 其他未尽事宜详见招标技术规格书及其他招标材料。
A22: 设计冲突处理 | B22: 清单中的所有主材要求详见图纸说明、技术规范书要求及清单描述，如相关描述有冲突时，按高标准执行。
A23: 材料及品牌更换 | B23: 材料如招标人提出替换时，费用只计算材料价差和税金，不再计取其他费用。
A24: 施工风险 | B24: 1、投标人已综合考虑施工中可能发生的各类风险（如材料损耗、预留长度、现场条件变化等），相关费用已包含在报价中。
B25: 2、合同期内人工、材料、机械和临时设施及施工水电费的费用、费率等价格要素的波动，合同执行期内一律不予调整。
B26: 3、施工费含白天施工、夜间施工、节假日施工等。

Sheet 硬件-报价明细
A1: 密级：公开 | H1: 乙方必填项 | I1: 乙方必填项 | J1: 乙方必填项 | K1: 乙方必填项 | L1: 乙方必填项 | M1: 乙方必填项 | O1: 乙方必填项 | Q1: 乙方必填项
A2: 序号 | B2: 设备名称 | C2: 技术参数要求 | D2: 推荐品牌 | E2: 数量 | F2: 单位 | G2: 备注 | H2: 投标品牌 | I2: 投标型号 | J2: 投标参数 | K2: 参数（响应/正偏离/负偏离） | L2: 正/负偏离 参数项 | M2: 施工未税单价 | N2: 施工合价未税 | O2: 材料未税单价 | P2: 材料合价未税 | Q2: 未税小计 | R2: 备注
B3: 一、智慧消防及物联系统
A4: 1 | B4: 用户信息传输装置 | C4: 壁挂式，用于消防远程监控，通过RS232端口实时监测所连接火灾报警控制器的报警信息，并通过有线网络传递到监控平台。满足GB26875-2011标准。 | D4: 主机信号采集数量：青鸟自动报警主机*20，青岛鼎信自动报警主机*1，利达自动报警主机*1，各品牌需对应使用适配的用户信息传输硬件 | E4: 24 | F4: 台 | H4: 青鸟 | I4: JBF5891 | J4: 用于实现火灾报警控制器与云端进行有线通讯（网线）的联网设备，DC24V供电，外型尺寸 136*89*36(mm)。 | K4: 响应 | M4: 131.84 | N4: =E4*M4 -> 3164.16 | O4: 2622.5 | P4: =E4*O4 -> 62940 | Q4: =ROUND((M4+O4)*E4,2) -> 66104.16
E5: 1 | F5: 台 | H5: 鼎信 | I5: TS-CS-8101 | J5: 主电电源：额定工作电压 AC220V/50Hz，宽电压范围 AC176V～AC420V 可接入； 备电电源：12V/2.3Ah 蓄电池； 容量：配接一台控制器； 液晶规格：320×480 彩色液晶屏； 使用环境：温度：0℃~+40℃； 相对湿度≤95%，不凝露； 外形尺寸：270.0mm× 190.0mm× 62.5mm(长× 宽× 高)； 安装孔距：水平间距 226.0mm，垂直间距 93.0mm； 重量：约 2.1kg； 外壳防护等级：IP30； | K5: 响应 | M5: 131.84 | N5: =E5*M5 -> 131.84 | O5: 7255 | P5: =E5*O5 -> 7255 | Q5: =ROUND((M5+O5)*E5,2) -> 7386.84 | S5: 增加项
E6: 1 | F6: 台 | H6: 利达 | I6: LD6920 | J6: DC 24V；< 200mA； CAN总线、RS232串口、开关量输入；支持 GPRS/2G、TCP/IP、电话线（可选配） | K6: 响应 | M6: 131.84 | N6: =E6*M6 -> 131.84 | O6: 5243 | P6: =E6*O6 -> 5243 | Q6: =ROUND((M6+O6)*E6,2) -> 5374.84 | S6: 增加项
A7: 2 | B7: 全局网络控制器 | C7: 1.名称：全局网络控制器 2.参数要求：单核 A8@1GHz，1GB DDR3 / 4GB microSD，2× 百兆，2×RS-485，可扩展4 个 I/O/ 现场总线模块。协议：BACnet IP/MS/TP + Modbus TCP/RTU + LonWorks + KNX + SNMP + oBIX，编程：Niagara 图形化编程，功能极强，适合复杂联锁 / 算法。满足现场现场功能所需的点位授权费 | D7: 霍尼韦尔、江森、西门子 | E7: 9 | F7: 台 | H7: 霍尼韦尔 | I7: ECC200-PE | J7: 边缘网络控制器，3条RS485总线；支持编程数据管理等功能 | K7: 响应 | M7: 32.96 | N7: =E7*M7 -> 296.64 | O7: 7240.88 | P7: =E7*O7 -> 65167.92 | Q7: =ROUND((M7+O7)*E7,2) -> 65464.56
A8: 3 | B8: 可编程网络控制器 | C8: 通讯接口：100M以太网，双网口 协议：BACnetIP/Modbus-TCP 扩展接口通讯：控制器内部协议 DI输入接口：数量最大24路，干接点接入 DO控制接口：8路，继电器负载能力2A/30VDC UI输入接口：最大16路，支持电阻型温度NTC20K，电压型湿度0~10V，电压型CO2,0~10V，电压型CO 0~10V,电流型水压4~20mA，电流型流量计4~20mA，执行器0~10V和2~10V反馈 AO输出接口：8路，支持4~20mA和0~10V输出 RS485接口数量：2个，其中一个支持多合一传感器接入，另外一路备用 支持PLC功能，支持PLC逻辑编程 尺寸：225x115x 57mm 外壳原料： UL 94 ABS 电源：DC24V/3A 重量：500g | D8: 霍尼韦尔、江森、西门子 | E8: 129 | F8: 台 | H8: 霍尼韦尔 | I8: WEBs系列控制器 | J8: 通讯接口：100M以太网，双网口 协议：BACnetIP/Modbus-TCP 扩展接口通讯：控制器内部协议 DI输入接口：数量最大24路，干接点接入 DO控制接口：8路，继电器负载能力2A/30VDC UI输入接口：最大16路，支持电阻型温度NTC20K，电压型湿度0~10V，电压型CO2,0~10V，电压型CO 0~10V,电流型水压4~20mA，电流型流量计4~20mA，执行器0~10V和2~10V反馈 AO输出接口：8路，支持4~20mA和0~10V输出 RS485接口数量：2个，其中一个支持多合一传感器接入，另外一路备用 | K8: 响应 | M8: 32.96 | N8: =E8*M8 -> 4251.84 | O8: 5424.7 | P8: =E8*O8 -> 699786.3 | Q8: =ROUND((M8+O8)*E8,2) -> 704038.14 | S8: 没有点表，满配接入点56个可以打7折
A9: 4 | B9: 可编程控制盘 | C9: 1、包含：空开、导轨及接线端子 2、国产优质箱体，根据实际安装设备测量后成套定制 | D9: 国产一线品牌，空开品牌为良信、正泰、公牛 | E9: 129 | F9: 台 | H9: 定制 | I9: DDC-Panel-XL | J9: 1、包含：空开、导轨及接线端子 2、国产优质箱体，根据实际安装设备测量后成套定制 | K9: 响应 | M9: 164.8 | N9: =E9*M9 -> 21259.2 | O9: 1485.31 | P9: =E9*O9 -> 191604.99 | Q9: =ROUND((M9+O9)*E9,2) -> 212864.19
A10: 5 | B10: 电源模块 | C10: 输入：85–264VAC（全球宽压），50/60Hz 输出：24VDC 可调（约 24–26V） 电流：1.3A / 2.5A / 4A（常用 4A 配 DDC） 保护：过压、短路、过载、过热（自恢复） EMC：EN61000-6-2、EN61000-4 系列，工业级 安装：35mm DIN 导轨 外壳：UL94 V-0 阻燃塑料 工作温度：-20℃ ~ +60℃ | D10: 霍尼韦尔、江森、西门子 | E10: 129 | F10: 台 | H10: 霍尼韦尔 | I10: 24VDC | J10: 输入：85–264VAC（全球宽压），50/60Hz 输出：24VDC 可调（约 24–26V） 电流：1.3A / 2.5A / 4A（常用 4A 配 DDC） 保护：过压、短路、过载、过热（自恢复） EMC：EN61000-6-2、EN61000-4 系列，工业级 安装：35mm DIN 导轨 外壳：UL94 V-0 阻燃塑料 工作温度：-20℃ ~ +60℃ | K10: 响应 | M10: 21.63 | N10: =E10*M10 -> 2790.27 | O10: 102.8 | P10: =E10*O10 -> 13261.2 | Q10: =ROUND((M10+O10)*E10,2) -> 16051.47 | S10: 修改品牌
A11: 6 | B11: 液位开关 | C11: 电缆长度：3M；电缆类型：PVC（聚氯乙烯）；包装形式：纸箱批量简易包装； | D11: 霍尼韦尔、江森、西门子 | E11: 13 | F11: 台 | H11: 霍尼韦尔 | I11: HSL-LS05 | J11: 电缆长度：5M；电缆类型：PVC（聚氯乙烯）；包装形式：纸箱批量简易包装； | K11: 响应 | M11: 154.5 | N11: =E11*M11 -> 2008.5 | O11: 169.89 | P11: =E11*O11 -> 2208.57 | Q11: =ROUND((M11+O11)*E11,2) -> 4217.07 | S11: 修改品牌
A12: 7 | B12: 压力变送器 | C12: 输出信号：4-20MA；量程范围：0-25 bar；过程连接：1/4 NPT；电气连接：1M； | D12: 霍尼韦尔、江森、西门子 | E12: 362 | F12: 台 | H12: 霍尼韦尔 | I12: HSP-W225MB | J12: 输出信号：4-20MA；量程范围：0-25 bar；过程连接：1/4 NPT；电气连接：1M； | K12: 响应 | M12: 131.84 | N12: =E12*M12 -> 47726.08 | O12: 494.79 | P12: =E12*O12 -> 179113.98 | Q12: =ROUND((M12+O12)*E12,2) -> 226840.06 | S12: 修改品牌
A13: 8 | B13: 流量传感器 | C13: 电源:10 to 35 VDC；电源消耗:最大40mA；输出:脉冲:NPN开集方波输出，最大60V@50mA;频率:3.2至200Hz。脉冲宽度:2.5毫秒+25%，4-20mA:4mA是0fts，20 mA是25 fts。过程连接:标准配置为1-1/2”NPT外螺纹，可选2“NPT外螺纹。管径满足现场环境 | D13: 霍尼韦尔、江森、西门子 | E13: 75 | F13: 台 | H13: 霍尼韦尔 | I13: HMF-EM16F100N4MY | J13: 口径100，通讯协议和接口：Modbus RTU， RS485，输出信号：4-20mA脉冲输，供电：24VDC100VAC 至 240VAC | K13: 响应 | M13: 350.2 | N13: =E13*M13 -> 26265 | O13: 7055.22 | P13: =E13*O13 -> 529141.5 | Q13: =ROUND((M13+O13)*E13,2) -> 555406.5 | S13: 修改品牌
A14: 9 | B14: 氧浓度监测传感器 | C14: 工作温度 -20~50℃ 工作湿度 5~95% RH 无冷凝 压力范围 90~110KPa 稳定性 ≤5% 信号值 / 年 响应时间 ≤10S 预热时间 ≥5 分钟 零点漂移（-20~40℃） ±0.3%Vol 重复性 ≤1% 使用寿命 ≥24 个月 量程 0~25% VOL 精度 ±2%FS 分辨率 0.1%VOL | D14: 霍尼韦尔、江森、西门子 | E14: 26 | F14: 台 | H14: 霍尼韦尔 | I14: O2-W2 | J14: 工作温度 -20~50℃ 工作湿度 5~95% RH 无冷凝 压力范围 90~110KPa 稳定性 ≤5% 信号值 / 年 响应时间 ≤10S 预热时间 ≥5 分钟 零点漂移（-20~40℃） ±0.3%Vol 重复性 ≤1% 使用寿命 ≥24 个月 量程 0~25% VOL 精度 ±2%FS 分辨率 0.1%VOL | K14: 响应 | M14: 131.84 | N14: =E14*M14 -> 3427.84 | O14: 107 | P14: =E14*O14 -> 2782 | Q14: =ROUND((M14+O14)*E14,2) -> 6209.84 | S14: 修改品牌
A15: 10 | B15: 温湿度传感器 | C15: 精度：±2%RH；湿度输出：0-10V；温度输出：NTC20K，±0.2°C @25°C；温度量程：0~50℃；继电器输出：无；LCD显示无； | D15: 霍尼韦尔、江森、西门子 | E15: 2 | F15: 台 | H15: 霍尼韦尔 | I15: HSH-RV2B | J15: 精度：±2%RH；湿度输出：0-10V；温度输出：NTC20K，±0.3°C @25°C；温度量程：-10 ℃ ~ 60 ℃℃； | K15: 响应 | M15: 131.84 | N15: =E15*M15 -> 263.68 | O15: 481.8 | P15: =E15*O15 -> 963.6 | Q15: =ROUND((M15+O15)*E15,2) -> 1227.28
A16: 11 | B16: 管道风速监测传感器 | C16: 量程：0–20 m/s（0–4000 ft/min），精度：±0.2 m/s（≤10 m/s）；±2% FS（>10 m/s），输出信号：0–10VDC（线性对应量程），供电：24VDC ±10%（BA 标准供电） 材质 / 防护：ABS 外壳，探杆 304 不锈钢；IP65 温度：-10℃~+50℃（耐高温款可达 80℃） 安装：法兰开孔插入式，带密封圈，漏风小 | D16: 霍尼韦尔、江森、西门子 | E16: 89 | F16: 台 | H16: 霍尼韦尔 | I16: HSV-ADH30U | J16: 风速传感器，一体式，最大量程30m/s,0-10V/4-20mA输出，不带显示 | K16: 响应 | M16: 154.5 | N16: =E16*M16 -> 13750.5 | O16: 1074.06 | P16: =E16*O16 -> 95591.34 | Q16: =ROUND((M16+O16)*E16,2) -> 109341.84 | S16: 修改品牌
A17: 12 | B17: 继电器 | C17: 适配电磁阀信号选配 | D17: 霍尼韦尔、江森、西门子 | E17: 100 | F17: 个 | H17: 霍尼韦尔 | I17: SZR-LY4-N1 DC24V | K17: 响应 | M17: 21.63 | N17: =E17*M17 -> 2163 | O17: 198.26 | P17: =E17*O17 -> 19826 | Q17: =ROUND((M17+O17)*E17,2) -> 21989 | S17: 修改品牌
A18: 13 | B18: 交流电流变送器 | C18: 输出4-20mA三相模块RS485信号 | D18: 霍尼韦尔、江森、西门子 | E18: 168 | F18: 个 | H18: 霍尼韦尔 | I18: AC0-5A4-20mA10V | J18: 输出4-20mA三相模块RS485信号 | K18: 响应 | M18: 144.2 | N18: =E18*M18 -> 24225.6 | O18: 165.74 | P18: =E18*O18 -> 27844.32 | Q18: =ROUND((M18+O18)*E18,2) -> 52069.92 | S18: 修改品牌
A19: 14 | B19: 光纤熔接盒（含光纤熔纤） | C19: SC4芯单模满配含熔接尾纤、法兰、SC光跳线 | D19: 一舟、普天天纪、罗格朗 | E19: 129 | F19: 个 | H19: 一舟 | I19: S953-4X+ 4*S905-3+ 4*S812+ 2*S922 | J19: 含4个SC单工耦合器，4条SC单芯单模尾纤，2条SC-SC双芯单模跳纤 | K19: 响应 | M19: 98.88 | N19: =E19*M19 -> 12755.52 | O19: 111.19 | P19: =E19*O19 -> 14343.51 | Q19: =ROUND((M19+O19)*E19,2) -> 27099.03
A20: 15 | B20: 光纤收发器 | C20: 1个10/100M/1000M网口，1个1000Mbps光口（SC），工作波长：1550nm（发送）、1310nm（接收），20km。 | D20: TP-LINK、山泽、烽火 | E20: 129 | F20: 对 | H20: 普联 | I20: TL-FC311A-3 | J20: 普联（TP-LINK）TL-FC311A-3千兆单模单纤光纤收发器 光电转换器SC单芯3km（单只装） | K20: 响应 | M20: 32.96 | N20: =E20*M20 -> 4251.84 | O20: 182.53 | P20: =E20*O20 -> 23546.37 | Q20: =ROUND((M20+O20)*E20,2) -> 27798.21
A21: 16 | B21: 光纤收发器架 | C21: 14槽光纤收发器机架；标准机柜安装； | D21: TP-LINK、山泽、烽火 | E21: 34 | F21: 个 | H21: 普联 | I21: TL-FC1400 | J21: 普联（TP-LINK） TL-FC1400单模多模光纤收发器14槽机架单纤双纤光电转换器整理箱机柜2U机箱 | K21: 响应 | M21: 87.55 | N21: =E21*M21 -> 2976.7 | O21: 543.38 | P21: =E21*O21 -> 18474.92 | Q21: =ROUND((M21+O21)*E21,2) -> 21451.62
A22: 17 | B22: 室外4芯单模光缆 | C22: 1.标准：YD/T769，ISO/IEC11801，ANSI/TIA -568-C.3 2.全截面阻水结构，松套管填充纤膏，松套管和钢带之间填充缆膏，确保良好的阻水防潮性能 3.光纤规格：B1.3（OS2） 4.衰减＠20℃（dB/Km）：＠1310nm≤0.36，＠1550nm≤0.22 5.光纤芯数：4芯 6.护套：夹带钢丝的钢-聚乙烯粘结护套，MDPE，黑色 7.允许拉伸力：长期：600N，短期：1500N 8.允许压扁力：长期：300N/100mm，短期：1000N/100mm 9.最小弯曲半径：动态：20D，静态：10D | D22: 一舟、普天天纪、罗格朗 | E22: 130000 | F22: m | H22: 一舟 | I22: D173-4 | J22: 1.标准：YD/T769，ISO/IEC11801，ANSI/TIA -568-C.3 2.全截面阻水结构，松套管填充纤膏，松套管和钢带之间填充缆膏，确保良好的阻水防潮性能 3.光纤规格：B1.3（OS2） 4.衰减＠20℃（dB/Km）：＠1310nm≤0.36，＠1550nm≤0.22 5.光纤芯数：4芯 6.护套：夹带钢丝的钢-聚乙烯粘结护套，MDPE，黑色 7.允许拉伸力：长期：600N，短期：1500N 8.允许压扁力：长期：300N/100mm，短期：1000N/100mm 9.最小弯曲半径：动态：20D，静态：10D | K22: 响应 | M22: 2.68 | N22: =E22*M22 -> 348400 | O22: 1.84 | P22: =E22*O22 -> 239200 | Q22: =ROUND((M22+O22)*E22,2) -> 587600 | S22: 修改型号
A23: 18 | B23: 24口光纤配线架（含尾纤、LC双工耦合器、熔接） | C23: 1.标准：YD/T778，ISO/IEC 11801，ANSI/TIA -568-C.3 2.安装方式：19″机架式安装 3.4个光缆进线口，带固定PG头，盒内配置光缆护套固定装置，光缆加强件固定装置 4.通用型设计，可兼容：LC双工、SC单工、FC、ST适配器，一个4口支架仅需一颗螺丝，便于安装和拆卸 5.进出光纤方便灵活，有充裕的光纤盘存空间，光纤和尾纤弯曲半径不小于30mm 6.端口数量： 24口，空余端口可安装空白功能件，高度：1U 7.表面处理：静电喷塑 8.材料：优质冷扎钢板 9.表面颜色：黑色 10.含LC双工耦合器 | D23: 一舟、普天天纪、罗格朗 | E23: 24 | F23: 个 | H23: 一舟 | I23: S952-24X+ 24*S905-7-1+ 48*S813 | J23: 1.标准：YD/T778，ISO/IEC 11801，ANSI/TIA -568-C.3 2.安装方式：19″机架式安装 3.4个光缆进线口，带固定PG头，盒内配置光缆护套固定装置，光缆加强件固定装置 4.通用型设计，可兼容：LC双工、SC单工、FC、ST适配器，一个4口支架仅需一颗螺丝，便于安装和拆卸 5.进出光纤方便灵活，有充裕的光纤盘存空间，光纤和尾纤弯曲半径不小于30mm 6.端口数量： 24口，空余端口可安装空白功能件，高度：1U 7.表面处理：静电喷塑 8.材料：优质冷扎钢板 9.表面颜色：黑色 10.含LC双工耦合器 | K23: 响应 | M23: 463.5 | N23: =E23*M23 -> 11124 | O23: 503.52 | P23: =E23*O23 -> 12084.48 | Q23: =ROUND((M23+O23)*E23,2) -> 23208.48
A24: 19 | B24: 光纤跳线 | C24: 单模双芯SC-LC优质2米光纤跳线； | D24: 一舟、普天天纪、罗格朗 | E24: =E20 -> 129 | F24: 个 | H24: 一舟 | I24: S928 | J24: 单模双芯SC-LC优质2米光纤跳线； | K24: 响应 | M24: 5.51 | N24: =E24*M24 -> 710.79 | O24: 23.08 | P24: =E24*O24 -> 2977.32 | Q24: =ROUND((M24+O24)*E24,2) -> 3688.11
A25: 20 | B25: 六类非屏蔽跳线（2m） | C25: 1.标准：不低于TIA/EIA568-C.2、ISO/IEC11801、IEC60332-1、GB 50311； 2.导体规格：多股绞合，软圆铜线，4×2×23AWG； 3.护套材料：PVC，护套外径：6.3±0.3mm； 4.插头规格：RJ45，8P8C； 5.插拔次数：≥1000次； 6.最高传输频率：不小于250MHz； 7.线缆外护套上间隔印有商标、电缆编号、电缆类别、线规、防火等级、标准； 8.支持以太网供电应用（POE/POE+）； 9.描述：用于办公桌桌面跳线，长度2米 10.为了保证性能的匹配性和稳定性，综合布线光纤系统、铜缆系统应采用同一品牌。 | D25: 一舟、普天天纪、罗格朗 | E25: =E20*2 -> 258 | F25: 个 | H25: 一舟 | I25: S0200-GY | J25: 1.标准：不低于TIA/EIA568-C.2、ISO/IEC11801、IEC60332-1、GB 50311； 2.导体规格：多股绞合，软圆铜线，4×2×23AWG； 3.护套材料：PVC，护套外径：6.3±0.3mm； 4.插头规格：RJ45，8P8C； 5.插拔次数：≥1000次； 6.最高传输频率：不小于250MHz； 7.线缆外护套上间隔印有商标、电缆编号、电缆类别、线规、防火等级、标准； 8.支持以太网供电应用（POE/POE+）； 9.描述：用于办公桌桌面跳线，长度2米 10.为了保证性能的匹配性和稳定性，综合布线光纤系统、铜缆系统应采用同一品牌。 | K25: 响应 | M25: 5.51 | N25: =E25*M25 -> 1421.58 | O25: 16.78 | P25: =E25*O25 -> 4329.24 | Q25: =ROUND((M25+O25)*E25,2) -> 5750.82
A26: 21 | B26: 24口接入交换机-单电源 | C26: ★在不插板卡情况下，单设备交换容量≥336Gbps，包转发率≥120Mpps，提供≥24个千兆电接口、≥4个千兆SFP光接口 1、支持堆叠技术或者虚拟化技术 2、支持 4K 802.1Q VLAN,支持Voice VLAN及Voice VLAN中可以同时识别多厂家的OUI地址，支持端口VLAN、MAC VLAN 3、支持标准IP ACL（基于IP地址的硬件ACL）支持扩展IP ACL（基于IP地址、TCP/UDP端口号的硬件ACL） 4、支持QOS 5、支持一对一、多对一、一对多的镜像 6、支持DHCP Server、DHCP Client、DHCP Snooping、DHCP Relay、DHCP Option82 7、支持广播风暴抑制 8、支持设备登陆管理的AAA安全认证、radius认证、支持802.1x、支持ssh2.0 9、支持STP/RSTP/MSTP协议 10、支持链路聚合（支持静态、动态链路聚合、千兆口聚合） 11、有标准的或私有的邻居发现协议 12、支持VLAN虚接口 13、支持 IPv4 /ipv6静态路由 14、支持OSPFv2、OSPFv3 15、支持SNMPv1/v2/v3，WEB网管，支持命令行接口配置，Telnet，SSH，Console口配置，支持系统日志，分级告警，调试信息输出，NTP/SNTP ★16、提供真实有效的工信部入网证复印件； ★17、原厂质保≥3年 ★18、考虑设备兼容性、项目实施、交付及售后服务，采用与核心交换机同一品牌。 | D26: 华三、锐捷（非睿易） | E26: 12 | F26: 台 | H26: 锐捷 | I26: RG-S2910-24GT4SFP-L | J26: 千兆接入交换机 | 24个10/100/1000M自适应电口，4个1G SFP光口，固化交流电源和无风扇设计。 | 不支持PoE | 交换容量598Gbps/5.98Tbps | 包转发率126Mpps | 支持动态路由协议（RIP、OSPF）、VSU、802.X认证、ERPS环网保护协议、链路聚合 | 支持云管理&本地管理 | 默认三年维保 | | K26: 响应 | M26: 144.2 | N26: =E26*M26 -> 1730.4 | O26: 1265 | P26: =E26*O26 -> 15180 | Q26: =ROUND((M26+O26)*E26,2) -> 16910.4 | S26: 修改型号
A27: 22 | B27: 千兆单模光模块 | C27: LC接口，单模千兆光纤（和交换机同品牌） | D27: 华三、锐捷（非睿易） | E27: 24 | F27: 个 | H27: 锐捷 | I27: MINI-GBIC-LX-SM1310 | J27: 1000BASE-LX mini GBIC转换模块（1310nm），10km | K27: 响应 | M27: 16.48 | N27: =E27*M27 -> 395.52 | O27: 110.15 | P27: =E27*O27 -> 2643.6 | Q27: =ROUND((M27+O27)*E27,2) -> 3039.12
A28: 23 | B28: 信号线 | C28: 国标，RVV2*1.0 | D28: 一舟、普天天纪、罗格朗 | E28: 3800 | F28: m | H28: 一舟 | I28: RVV2*1.0 | J28: 国标，RVV2*1.0 | K28: 响应 | M28: 2.06 | N28: =E28*M28 -> 7828 | O28: 3.04 | P28: =E28*O28 -> 11552 | Q28: =ROUND((M28+O28)*E28,2) -> 19380
A29: 24 | B29: 信号线 | C29: 国标，RVVP2*1.0 | D29: 一舟、普天天纪、罗格朗 | E29: 7200 | F29: m | H29: 一舟 | I29: RVVP2*1.0 | J29: 国标，RVVP2*1.0 | K29: 响应 | M29: 2.06 | N29: =E29*M29 -> 14832 | O29: 5.72 | P29: =E29*O29 -> 41184 | Q29: =ROUND((M29+O29)*E29,2) -> 56016
A30: 25 | B30: 信号线 | C30: 国标，RVVP4*1.0 | D30: 一舟、普天天纪、罗格朗 | E30: 5000 | F30: m | H30: 一舟 | I30: RVVP4*1.0 | J30: 国标，RVVP4*1.0 | K30: 响应 | M30: 2.52 | N30: =E30*M30 -> 12600 | O30: 8.97 | P30: =E30*O30 -> 44850 | Q30: =ROUND((M30+O30)*E30,2) -> 57450
A31: 26 | B31: 信号线 | C31: 国标，RVVP6*1.0 | D31: 一舟、普天天纪、罗格朗 | E31: 154 | F31: m | H31: 一舟 | I31: RVVP6*1.0 | J31: 国标，RVVP6*1.0 | K31: 响应 | M31: 2.52 | N31: =E31*M31 -> 388.08 | O31: 12.48 | P31: =E31*O31 -> 1921.92 | Q31: =ROUND((M31+O31)*E31,2) -> 2310
A32: 27 | B32: JDG20管 | C32: JDG管，壁厚不小于1.0MM,φ20；含主材、接头、固定扣件（含钢结构扣件）等辅材 | D32: 国产 | E32: 25000 | F32: m | H32: 国产 | I32: JDG20 | J32: JDG管，壁厚不小于1.0MM,φ20；含主材、接头、固定扣件（含钢结构扣件）等辅材 | K32: 响应 | M32: 9.79 | N32: =E32*M32 -> 244750 | O32: 3.67 | P32: =E32*O32 -> 91750 | Q32: =ROUND((M32+O32)*E32,2) -> 336500
A33: 28 | B33: 辅材 | C33: 设备安装配套辅材，水晶头，扎带等 | D33: 国产 | E33: 1 | F33: 项 | K33: 响应 | M33: 6180 | N33: =E33*M33 -> 6180 | O33: 10490 | P33: =E33*O33 -> 10490 | Q33: =ROUND((M33+O33)*E33,2) -> 16670
B34: 二、智慧安防系统 | N34: =E34*M34 -> 0 | P34: =E34*O34 -> 0
B35: 2.1、视频监控系统 | N35: =E35*M35 -> 0 | P35: =E35*O35 -> 0
A36: 1 | B36: 抗振防抖场景专用摄像机 | C36: 1.设备采用金属机身，主要接口：1个M12航空头网络接口、1个CVBS接口、1个音频输入接口，1个音频输出接口、1个RS485接口、1个报警输入接口、1个报警输出接口、1个SD卡卡槽（内置） 2.内置1/1.8英寸，400万像素CMOS传感器；最大亮度鉴别等级试验≥11级；最大帧率60fps；延时试验小于200ms；照度适应范围不小于140dB 3.外壳防护等级IP66/IP68 4.机身部分碰撞防护等级IK10 5.摄像机应能在额定电源电压DC9V-DC36V范围内正常工作，支持POE供电 6.设备支持红外和暖光补光灯，可通过IE浏览器或客户端切换补光灯类型 7.最低照度试验：彩色：0.0005 lx，黑白：0.0001 lx 8.支持开启、关闭畸变矫正功能 9.防抖功能检查：在水平X轴方向随机抖动频率范围5Hz-62Hz，加速度有效值：5.6m/s²，最大振幅3.39mm；相机配置：2560X1440，最大焦距，座装安装，镜头方向朝下；在图像中指定4个像素点，最大偏移应不超过±1%。 10.防抖功能检查：在水平Y轴方向随机抖动频率范围5Hz-62Hz，加速度有效值：5.6m/s²，最大振幅3.39mm；相机配置：2560X1440，最大焦距，座装安装，镜头方向朝下；在图像中指定4个像素点，最大偏移应不超过±1%。 11.防抖功能检查：在垂直Z轴方向随机抖动频率范围5Hz-26Hz，加速度有效值：5.6m/s²，最大振幅3.39mm；相机配置：2560X1440，最大焦距，座装安装，镜头方向朝下；在图像中指定4个像素点，最大偏移应不超过±1.5%。 12.在彩色模式下，当照度降低至一定值时，设备可自动开启白光灯补光，设备在白天、夜晚均可输出彩色视频图像 13.可通过扫描预览界面上生产的二维码获取设备资料。 14.当移动侦测、进入区域、离开区域、越界区域或区域入侵报警类型设置为人和/或车时，仅当检测区域中出现对应的人和/或车时，才触发报警；当报警产生时，可触发联动白光灯闪烁，白光灯闪烁的时间和频率可设置 15.设备具有APP管理功能，支持在线导入APP、删除APP、加载运行APP、配置APP操作，APP管理操作无需重启设备，操作期间预览画面无中断。 16.设备支持用户自定义最多16个AI算法库，可设置当前生效的算法库和显示当前算法库的运行状态，并支持修改、删除算法库及自定义算法库名称。 17.设备具有良好的环境适应性，工作温度范围可达-40℃～60℃。 | D36: 海康 | E36: 6 | F36: 台 | H36: 海康 | I36: DS-2XC7245/KZ | J36: 400万抗振防抖摄像机 产品具备抗振动及图像防抖能力，支持起重机械场景使用 内置大模型移动周界功能，支持AI开放平台及HEOP功能，支持自定义算法训练及三方算法集成 最高分辨率可达2560 × 1440，并在此分辨率下可输出最大60 fps实时图像 支持低延时，相机解码延时低至100 ms 采用双光阵列灯，低功耗，红外照射距离最远达80 m（2.8~12 mm红外支持50 m），白光照射距离最远达50 m（2.8~12 mm白光支持30 m） 支持DC9 V~36 V宽压和PoE at供电 支持除雾，防止设备内部起雾 支持雨刷 支持加热 彩色：0.0005 Lux @（F1.2，AGC ON）；黑白：0.0001 Lux @（F1.2，AGC ON）；0 Lux with IR 支持宽动态范围达120 dB，适合逆光环境监控 支持三码流技术，每路码流可独立配置分辨率及帧率 支持1路音频输入和1路音频输出、1路报警输入和1路报警输出、1路RS-485 、1路模拟视频输出 千兆自适应以太网口，M12航空头（8芯），标配防水对插头 支持防雷、防浪涌、防静电，IP68防护等级 C5-M、NEMA 4X、WF2防腐蚀标准，有效避免酸性、中性盐雾腐蚀 传感器类型：1/1.8" Progressive Scan CMOS 最低照度：彩色：0.0005 Lux @（F1.2, AGC ON），0 Lux with Light 黑白：0.0001 Lux @（F1.2, AGC ON），0 Lux with IR 调节角度：水平: -15°~15°；垂直: -120°~45° 焦距&视场角：2.8~12 mm：水平视场角：99.6°~39.8°，垂直视场角：52.3°~22.4°，对角视场角：119.9°~45.7° 8~32 mm：水平视场角：40.3°~14.5°，垂直视场角：22.1°~8.2°，对角视场角：46.9°~16.5° 补光灯类型：红外模式：红外灯 白光模式：白光灯 补光距离：2.8~12 mm：红外50米，白光30米 8~32 mm：红外80米，白光50米 最大分辨率：2560 × 1440 视频压缩标准：主码流：H.265/H.264 子码流：H.265/H.264/MJPEG 第三码流：H.265/H.264 宽动态：120dB 视频输出：1 Vp-p复合输出（75 Ω/CVBS） 网络：千兆自适应以太网口，M12航空头（8芯），标配防水对插头 SD卡扩展：内置MicroSD插槽，最大支持512 GB 音频：1路输入（Line in）（terminal block）（最大输入幅值：3.3 Vpp，输入阻抗：1 kΩ，接口类型：非平衡） 1路输出（Line out）（terminal block）（最大输出幅值：3.3 Vpp，输出阻抗：100 Ω，接口类型：非平衡） 报警：1路输入，1路输出（报警输出最大支持DC12 V，30mA） RS-485：支持1个RS-485 外壳材质：316L不锈钢 产品尺寸：199.7 × 201.9 × 209.2 mm 包装尺寸：340 × 298 × 290 mm 设备重量：5.6 kg 带包装重量：6.6 kg 启动和工作温湿度：-40 °C~60 °C，湿度小于95%（无凝结） 雨刷：支持 电流及功耗：DC：9~36 V，2.65~0.65 A，24 W Max PoE：802.3at，42.5 V~57 V，0.56 A~0.42 A，24 W Max 供电方式：DC：9 V~36 V，支持防反接保护；PoE：802.3at，Class 4 电源接口类型：2芯绿头 安装方式：壁装，座装 防腐蚀：WF2，C5，NEMA 4X 恢复出厂设置：支持 在线升级：支持 文件系统双备份：支持 | K36: 响应 | M36: 175.1 | N36: =E36*M36 -> 1050.6 | O36: 2989.65 | P36: =E36*O36 -> 17937.9 | Q36: =ROUND((M36+O36)*E36,2) -> 18988.5
A37: 2 | B37: 400万变焦筒型网络摄像机 | C37: 1.支持输出图像分辨率不低于2560x1440 2.最低照度彩色：0.005 lx，最大亮度鉴别等级不小于11级 3.补光距离：红外不低于50 m，白光不低于30 m 4.支持电动变焦 5.具备区域入侵、越界、进入区域、离开区域、人员聚集、快速移动、徘徊、物品移除、物品遗留、停车智能分析功能，当以上智能分析行为达到设定的阈值时，可通过客户端软件或IE浏览器给出报警提示 6.同一场景相同图像质量下设备在H.264或H265编码方式时，开启智能编码功能和不开启智能编码相比，码率节约80% 7.靶面尺寸为1/2.7英寸，内置1个麦克风，具有1个RJ45 网络接口，1路音频输入、1路音频输出、1路报警输入、1路报警输出、1 个复位按钮、1个 SD 卡槽、1个 DC12V 电压输出接口 8.支持H.264、H.265视频编码格式，且具有High Profile编码能力 9.支持电源电源在DC12V±25%范围内变化时正常工作，支持POE 10.IP67防护等级 | D37: 海康 | E37: 68 | F37: 台 | H37: 海康 | I37: DS-2CD2645V3-FD | J37: 最高分辨率可达400万像素（2688 × 1520），并在此分辨率下可输出30 fps实时图像 室外消防通道占用：可检测汽车是否占用区域，可根据停留时间上报信息，可支持车牌号识别 室内消防通道占道：可检测杂物堆放导致通道被长时间占用 支持smart事件，人脸抓拍，比对建模，车辆监控算法切换使用 支持室内通道占用与人脸抓拍并行运行 支持室内通道占用与smart事件并行运行 可支持AI开放平台训练模型包导入运行 支持电动变焦，方便远程调节图像，保证算法效果 内置2个内置麦克风，1个内置扬声器，支持远程对讲与智能联动语音 外部接口丰富：1路报警IO输入，1路报警IO输出；1路音频LINE IN输入，1路音频输出LINE OUT；1路485接口；1路DC12V电源反送 最大支持512GB MicroSD/MicroSDHC/MicroSDXC卡存储； 传感器类型：1/2.7" 逐行扫描 CMOS 最低照度：彩色：0.005 Lux @（F1.2，AGC ON），0 Lux with Light； 黑白：0.001 Lux @（F1.2，AGC ON），0 Lux with IR 焦距&视场角：2.7~13.5 mm：水平视场角：30.1°~99°，垂直视场角：17°~52.9°，对角视场角：34.6°~117.8° 补光灯类型：反射式补光，双光 (红外850nm+白光) 补光距离：红外最远可达50m，暖白最远可达30m 主码流帧率分辨率：50 Hz:25 fps(2688 × 1520,2560 × 1440,1920 × 1080,1280 × 720) 60 Hz:30 fps(2688 × 1520,2560 × 1440,1920 × 1080,1280 × 720) 视频压缩标准：主码流：H.265/H.265+/H.264/H.264 子码流：H.265/H.264/MJPEG 第三码流：H.265/H.264 网络传输类型：有线 宽动态：120 dB 连接方式：甩线式接口，线缆长度约35cm； 音频：1路输入（Line in），1路输出（Line out），2个内置麦克风，1个内置扬声器 报警：1路输入，湿接点，支持3.3 V~5 V范围电位 1路输出，三极管输出，电平量，湿接点，最大支持DC 12V，30 mA RS-485：1路RS-485接口，采用半双工模式，支持自适应HIKVISION，PELCO-P和PELCO-D协议 电源输出：1路DC12V输出，最大电流100mA。备注：为保证设备正常工作，电源输出外接延长线请控制在10米以内。 尺寸：设备尺寸：180.3 × 99.2 × 93 mm 包装尺寸：315 × 137 × 141 mm 重量：设备重量：1.0kg 带包装重量：1.3kg 存储温湿度：-30 °C~60 °C，湿度小于95%（无凝结） 启动和工作温湿度：-30 °C~60 °C，湿度小于95%（无凝结） 物理防护：防水防尘：IP67 电源：1、 电源输入类型：2芯接口 2、 电流及功耗： DC：12 V，1.2 A，最大功耗：14.4W PoE：PoE(IEEE 802.3at class 4)，最大功耗：16W | K37: 响应 | M37: 175.1 | N37: =E37*M37 -> 11906.8 | O37: 519.26 | P37: =E37*O37 -> 35309.68 | Q37: =ROUND((M37+O37)*E37,2) -> 47216.48
A38: 3 | B38: 热成像摄像机 | C38: ★热成像：分辨率：256×192；焦距：焦距可选：3/7/10mm； 可见光：分辨率：2688*1520，400万；焦距：焦距可选：4mm/8mm/12.4mm； 支持1路音频输入，1路音频输出； 支持2路报警输入，2路报警输出； 外壳防护等级：IP67； 电源电压在DC12V±20%范围内变化时，能正常工作； 可通过IE浏览器在热成像画面中设置点、线段、区域测温规则； 点测温、线测温、区域测温中存在高于或者低于报警或预报警温度时，可在客户端显示不同的报警颜色进行报警提示，联动报警输出，联动录像及联动抓拍； 支持声音联动报警功能。可对智能行为、温度超过阈值、出现高温点等行为进行检测并报警，报警声音可设置，同时支持自定义； ★噪声等效温差为8mk，最小可分辨温差为200mk（（公京检第2401130038号第100条） 热成像视频图像具有白热、黑热、融合1、融合2、彩虹1、铁红2、深褐色等42种显示模式 含安装支架 | D38: 海康 | E38: 199 | F38: 台 | H38: 海康 | I38: HM-TD2628-XX/T1A | J38: 双光谱筒型摄像机 【功能特性】 热成像像素256 × 192，像元大小12um，NETD ≤ 35 mK (25°C, F1.0) 支持区域入侵探测、越界探测、进入区域探测、离开区域探测、音频异常探测、高温物体检测等功能 支持测温功能:支持普通测温，专家测温检测；可以画最多10个点，1条线，10个区域检测。测温范围：-20 °C~300 °C，测温精度：±8 °C或者读数的±8%（取最大值） 支持吸烟检测、火点检测、烟雾检测 支持联动白光报警、支持联动声音报警，内置白光灯和扬声器 支持AI开放平台 智能功能资源配置：测温、周界功能支持同时开启。测温、火点检测、烟雾检测支持同时开启。测温、AI开放平台支持同时开启。周界功能不支持与火点、吸烟、烟雾检测两两同时开启。 支持线性、直方图、自适应等热成像AGC模式，支持DDE、3D DNR。 支持叉车去误报功能 【应用场景】 可通过外接温湿度传感器，在样机OSD界面显示传感器信息 周界防范：石油石化、电力系统、工商企业、政府大院、铁路沿线、机场、文博、学校、医院等； 烟火检测：物流仓储、博物馆、实验室、数据机房、配电房等； 吸烟检测：加油站、景区、博物馆、校园、医院、生产车间等； 热成像传感器类型：氧化钒非制冷型探测器 热成像像元尺寸：12 μm 热成像响应波段：8~14 μm 热成像分辨率：256 × 192 热成像焦距：10 mm 热成像视场角：18°×13.5° 热成像最大光圈值：F1.0 热成像数字变倍：×2,×4 热成像帧频：50 Hz: 25 fps 热成像近摄距：3.5m 噪声等效温差NETD：≤ 35 mk(@25 °C,F#=1.0) 空间分辨率MRAD：1.24 伪彩：白热、黑热、融合1、彩虹、融合2、铁红1、铁红2、深褐色、色彩1、色彩2、冰火、雨、红热、绿热、深蓝等15种 温度异常功能：全屏测温 专家模式：10个点，10个框，1条线总计21个测温规则 测温范围：测温范围：-20 °C~300 °C 测温精度：测温精度：±8 °C或者读数的±8%（取最大值） 人员最远报警距离（以1.8米*0.5米为准）：100m 车辆最远报警距离（以4米*1.4米为准）：300m 吸烟检测最远报警距离：15m 防火最远报警距离（以0.05㎡高温源或0.1㎡火焰为准）：70m 最远测温距离（满足测温精度，以0.1m*0.1m目标物为准）：15m 可见光传感器类型：400万星光级1/2.7" Progressive Scan CMOS 可见光焦距&视场角：12.4mm,24.6°×14° 烟雾最远报警距离（以1㎡烟雾为准）：70m 可见光分辨率：2688 × 1520 最低照度：0.0089Lux @(F1.6,AGC ON) ,0 Lux with IR 可见光补光功能：补光最远可达30米 可见光光圈值：F1.6 报警联动：内置混合补光灯（支持红外和白光补光）、内置扬声器，支持联动白光报警、支持联动声音报警 周界防范检测：热成像通道（默认）：越界侦探测,区域入侵探测,进入/离开区域探测 可见光通道：越界探测,区域入侵探测,进入/离开区域探测 防火应用检测：支持火点检测、烟雾检测、吸烟检测 最大预览路数：20路 视频压缩标准：H.265/H.264/MJPEG 音频压缩标准：G.711/G.722.1/G.726/MP2L2/PCM 客户端：iVMS-4200/萤石/HIK-CONNCET 浏览器：IE10+,Chrome 57+,Mozilla Firefox 52+,Mac Safari 12 报警输入：支持2路DC 0~5 V报警输入 报警输出：支持2路常开型继电器输出，报警类型可设置 音频输入：1路3.5 mm Mic in/Line in interface. Line input: 2-2.4 V[p-p] 音频输出：1路3.5mm Impedance: 600Ω 复位键：1个复位键 RS485控制接口：1路 网口：1路RJ45接口10/100 M自适应以太网口 SD卡存储：1个内置SD卡卡槽,最大支持内存256G 尺寸：312.1 mm × 105 mm × 104.9 mm 电源输入：12 VDC ± 25%，PoE (802.3at, class 4) 备注：需单独购买DC 12V电源适配器 功率：12 VDC ± 25%: 1.2A to 2A, max. 18W PoE (802.3at, class 4): 42.5 V to 57 V, 0.32 A to 0.43A, max. 18W 工作温度和湿度：-40°C~70°C，＜95% RH 测温环境温度：-20°C~50°C 防护等级：IP67 重量：1.53 kg 藏线盒：需单独购买 | K38: 响应 | M38: 195.7 | N38: =E38*M38 -> 38944.3 | O38: 2040.31 | P38: =E38*O38 -> 406021.69 | Q38: =ROUND((M38+O38)*E38,2) -> 444965.99
A39: 4 | B39: 高空球型鹰眼 | C39: 1.全景通道最高分辨率不小于6072 x 2640，细节通道最高分辨率不小于3840x2160。 2.全景通道内置4个镜头、靶面尺寸不小于1/1.8英寸的CMOS传感器，细节通道内置1个镜头，靶面尺寸不小于1/1.2英寸的CMOS传感器。 3.设备在全景拼接模式下，垂直视场角不小于110°，水平视场角不小于180°。可将4个全景视频图像进行拼接，实现不小于180°拼接画面显示，并抓拍拼接后的图片。 4.细节通道内置镜头支持不小于45倍光学变倍，镜头最大焦距不小于320mm。 5.设备具有光学防抖功能，将镜头倍率设置为最大，快门设置为1/25s，在振动台振幅不大于0.3°，振动频率不大于10Hz情况下，设备视场角应无明显变化，视频图像在振动过程中应保持稳定清晰 6.设备内置2个雨刷器，雨刷器1可清洁全景通道镜头表面玻璃，雨刷器2可清洁细节通道镜头表面玻璃。 7.设备细节通道水平手控最大速度不小于500°/s，垂直手控最大速度不小于350°/s。 8.设备具备双安装接口，一个为快速旋转安装接口，一个为多孔稳定安装接口。 9.支持不小于300个预置位，支持预置位冻结功能。 10.内置不少于3个GPU芯片。 11.支持智能行为分析功能，智能分析行为类型为区域入侵、越界入侵、进入区域、离开区域等，支持行为分析触发后联动聚焦、联动目标跟踪、报警上传等多种报警触发方式。 12.设备在全景视频图像中点击或框选移动目标至设备开始转动的时间小于0.3s，全景图像检测到且框选出移动目标至设备开始转动时间小于0.3s。 13.设备全景通道支持人员密度检测功能，可开启、关闭人员密度检测功能，最多可设置8个多边形（3～10条边）人员密度检测区域。每个区域的名称、人员数量报警阈值等级（低、中、高等级）可自定义。 14.设备全景通道车辆拥堵检测功能，开启车辆拥堵检测功能后，当设置区域内的车辆滞留时间超过设定值时，可通过IE浏览器给出报警提示。 15.设备可切换智能模式，当更换当前智能模式时设备不需重启，新智能模式即可生效。 16.设备全景通道具有默认拼接、手动拼接、自动拼接3种拼接模式；自动拼接模式下设备可自动获取特征并进行拼接。 17.设备具有AI-ISP图像质量提升功能，在低照度环境下，可自动调节预览场景视频画面中人脸、人体、车辆等目标及预览场景视频画面的区域曝光、亮度、色彩饱和度、对比度、锐度等。 18.设备具有不少于1个RJ45网络接口、1个光纤接口、7路报警输入、2路报警输出、1路音频输入、1路音频输出。内置的北斗定位模块，具有定位功能，可自动获取设备所在位置经纬度信息。 19.防护等级不低于IP67。 | D39: 海康 | E39: 3 | F39: 台 | H39: 海康 | I39: DS-2DP1618XS-LD | J39: 1600万180°AR鹰眼_800万45倍_雨刷_卫星定位_5G 1600万180° 无盲区球型5G AR鹰眼，全景采用4个F1.0大光圈全彩镜头拼接而成，可输出180°大场景拼接画面 全景画面可支持关注区域畸变矫正，细节内置45倍变焦光学防抖镜头 支持基于行业平台实现AR立体防控，可添加500个标签，结合前端多维感知设备和业务系统数据，将高点范围内的人、车、地、事、物叠加到实时视频画面中进行展示和联动，通过多维联动、全景回溯、移动标签、标记标绘等应用，为用户掌握重点区域的实时动向、及时响应指挥调度提供新方式 全景智能：Smart事件、人员密度、车辆拥堵；细节智能：全结构化、Smart事件；更好助力平安城市公共安全管理 适用于城市高点、机场车站、城管市政、水利枢纽、企业园区、景区、校园等重点场所 全景摄像机 4个1/1.8＂ 4MP Progressive Scan CMOS，最高分辨率及帧率可达6072x2640@30fps 视场角：水平180°，垂直110° 细节摄像机 1/1.2＂ 8MP Progressive Scan CMOS，最高分辨率及帧率可达3840x2160@30fps 45倍光学变倍，16倍数字变倍 【全景】支持区域入侵侦测、越界侦测、进入区域、离开区域事件侦测功能 【全景】支持人员密度检测功能，检测覆盖范围半径100米 【全景】支持车辆拥堵检测功能，检测覆盖范围半径150米，推荐：在封闭式道路中可以做拥堵事件检测，推荐在高速、环线、快速路或者主干线 【细节】支持区域入侵侦测、越界侦测、进入区域、离开区域事件侦测功能 【细节】支持全结构化：支持细节路混合目标检测，对检测区域内的人、非机动车、车进行同时抓拍上传，人脸人体关联输出，并实现对人脸、人体、车辆结构化属性特征信息提取 支持GB35114A级安全加密 AI-ISP：细节球机采用去噪卷积神经网络将深度结构、学习算法用于图像去噪，最终使画面成像更新清晰，噪点更小图像更干净 支持北斗卫星定位 支持光学防抖、光学透雾 支持雨刷，环动式双雨刷设计，可对全景4个镜头、细节球机镜头进行清洁 移动通信类型： 5G/4G/3G 传感器类型：【全景】1/1.8＂ progressive scan CMOS,【细节】1/1.2＂ progressive scan CMOS 最低照度：【全景】0.0005Lux/F1.0（彩色），0.0001Lux/F1.0（黑白）；【细节】星光级超低照度，0.0005Lux/F1.5（彩色），0.0001Lux/F1.5（黑白），0 Lux with IR 宽动态：全景不支持，细节支持120dB超宽动态 光学变倍：45倍 焦距：【全景】2 mm；【细节】7.2~320 mm 视场角：水平视场角61.0~1.8度（广角~望远） 垂直视场角35.9~1.1度（广角~望远） 对角线视场角68.5~2.1度（广角~望远） 红外照射距离：500m 防补光过曝：支持 水平范围：360° 垂直范围：-15°-90°(自动翻转) 水平速度：水平键控速度：0.1°-500°/s,速度可设;水平预置点速度：500°/s 垂直速度：垂直键控速度：0.1°-350°/s,速度可设;垂直预置点速度：350°/s 主码流帧率分辨率：全景：50Hz: 25fps (6072x2640,5520×2400, 4096×1800,3840×1680, 2784×1200) 60Hz: 30fps (6072x2640，5520×2400, 4096×1800，3840×1680, 2784×1200) 细节：50Hz:25fps (3840×2160,2560×1440,1920×1080,1280×960,1280×720) 60Hz:30fps(3840×2160,2560×1440,1920×1080,1280×960,1280×720) 视频压缩标准：主码流：H.264/H.265+/H.265/H.264+ 子码流：H.264/H.265/MJPEG 第三码流：H.264/H.265/MJPEG 移动通信类型：同时支持5G/4G/3G 无线频段：5G NR/LTE-FDD/LTE-TDD/WCDMA 无线制式：5G NR：n1/n5/n8/n28/n41/n78/n79 LTE-FDD：B1/B3/B5/B8 LTE-TDD：B34/B38/39/B40/B41 WCDMA：B1/B5/B8 无线传输速率：NR(SA)：DL 2 Gbps；UL 766 Mbps EN-DC：DL 2.2 Gbps；UL 458 Mbps LTE：DL 487 Mbps; UL 150 Mbps WCDMA：DL 42 Mbps; UL 11 Mbps SIM卡：nano SIM 卫星定位：支持北斗卫星定位 陀螺仪：支持 电子罗盘：支持 网络接口：RJ45网口;自适应10M/100M/1000M网络数据 光纤接口：FC接口;内置光纤模块;波长TX1310/RX1550nm;20km传输距离;单模单纤;1000M网络数据 SD卡扩展：内置Micro SD卡插槽，支持Micro SD/Micro SDHC/Micro SDXC卡（最大支持512G） 报警：7路报警输入，2路报警输出 音频：1路音频输入，1路音频输出 RS485接口：采用半双工模式，支持自适应HIKVISION，PELCO-P和PELCO-D(可添加)协议 供电方式：DC36V； 整机平均功耗85w.最大功耗 120w 工作温湿度：-40℃-70℃;湿度小于90% 恢复出厂设置：支持 雨刷：支持 除雾：支持 尺寸：Φ427.6x425.9mm 重量：净重 14.6kg 防护：IP67; 6000V 防雷、防浪涌、防突波，符合GB/T17626.2/3/4/5/6四级标准 | K39: 响应 | M39: 309 | N39: =E39*M39 -> 927 | O39: 28323 | P39: =E39*O39 -> 84969 | Q39: =ROUND((M39+O39)*E39,2) -> 85896
A40: 5 | B40: 人脸识别布控球 | C40: 1.单北斗5G双摄便携球套装 2.支持双摄：40倍光学变倍机芯，最大分辨率2560*1440，图像清晰、细腻，低照度，彩色0.0001Lux；全景镜头8M，分辨率2160×3840 3.支持自动彩转黑功能，实现昼夜监控 4.支持人脸比对，可存储30W张人脸名单（含一张1TB TF卡） 5.支持车辆检测及抓拍 6.支持抽烟、佩戴安全帽、玩手机、未穿工作服检测 7.支持3D-DNR 8.支持双TF卡存储 9.支持5G模块（天线内置），可额外扩展1个4G模块 10.配置可拆卸电池，单电池可支持8-9小时连续工作 11.支持双MIC、双扬声器，可选配支持LINE IN\LINE OUT 12.支持自定义语音导入，可关联智能分析报警 13.自带2.4寸LCD显示屏，可支持视频预览，云台控制等，可显示当前电池电量、定位状态、3G/4G/5G状态、录像状态、存储容量、蓝牙状态、平台连接状态、Wi-Fi状态、智能算法模式等 14.底部配置高吸力磁铁，安装便捷 | D40: 海康 | E40: 5 | F40: 台 | H40: 海康 | I40: iDS-MCD402-MF/40X+TF-P1/1T/TAY | J40: 5G双摄便携球套装 支持双摄：40倍光学变倍机芯，最大分辨率2560*1440，图像清晰、细腻，低照度，彩色0.0001Lux；全景镜头8M，分辨率2160×3840； 支持自动彩转黑功能，实现昼夜监控 支持人脸比对，可存储30W张人脸名单（需配TF卡） 支持车辆检测及抓拍 支持抽烟、佩戴安全帽、玩手机、未穿工作服检测 支持3D-DNR 支持双TF卡存储 支持5G模块（天线内置），可额外扩展1个4G模块 配置可拆卸电池，单电池可支持8-9小时连续工作 支持双MIC、双扬声器，可选配支持LINE IN\LINE OUT 支持自定义语音导入，可关联智能分析报警 自带2.4寸LCD显示屏，可支持视频预览，云台控制等，可显示当前电池电量、GPS状态、3G/4G/5G状态、录像状态、存储容量、蓝牙状态、平台连接状态、Wi-Fi状态、智能算法模式等 底部配置高吸力磁铁，安装便捷 传感器类型：变焦机芯：1/1.8" Progressive Scan CMOS 全景相机8M：1/1.8" Progressive Scan CMOS 彩色最低照度：变焦机芯：0.0001Lux @ (F1.6，AGC ON) 黑白最低照度：变焦机芯：0.00005Lux @(F1.6，AGC ON) 屏幕尺寸：2.4英寸 分辨率：240*320 材质：TFT 触摸屏：电容屏 镜头焦距：5.8-232mm 镜头光圈：F1.3-F4.6 光学变倍：40倍 水平视场角：59-2度(广角-望远) 子码流压缩码率：2Mbps 视频压缩标准：H.264;H.265;MJPEG 码率控制：定码率;变码率 录像格式：MP4 录像分辨率：变焦机芯：2560×1440 全景相机8M：3840×2160 图片分辨率：1920*1080;2560*1440 图片格式：JPEG 音频压缩标准：G.722.1;G.711alaw;G.711ulaw 人脸比对：支持 车辆抓拍：支持 车牌识别：支持 车辆特征识别：支持车牌、车身颜色、车型、车辆品牌、车辆子品牌识别 车辆黑名单：支持车辆黑名单 安全帽佩戴检测：支持未佩戴安全帽检测 目标抓拍：支持 支持人脸库个数：10个(需配置TF卡) 支持的人脸数量：300000张(需配置TF卡) 支持屏蔽区域设置 拨号：GSM/GPRS/EDGE：900/1800MHz WCDMA：B1/5/8 LTE：B1/3/5/8/34/38/39/40/41 5G：N1/5/8/28/41/77/78/79 定位：北斗 蓝牙：4.0 语音对讲：支持 指示灯：充电指示灯,工作指示灯 系统功耗：10W~30W 产品重量：带电池4.35kg~4.5kg 产品尺寸：高262mm，直径175mm 防护等级：IP66 供电方式：电池供电;外接电源 工作温度：-10℃~55℃ 工作湿度：湿度小于95% 材质：镁合金 水平旋转角度：360° 垂直旋转角度：-20°~90° 预置点：256个 巡航扫描：8条 花样扫描：4条 断电记忆：支持 红外：支持 红外补光距离：100m看清人体轮廓 扩展存储个数：2 扩展存储介质：TF 扩展存储容量：默认不含TF卡，最大支持1TB存储卡 充电接口：6芯航空头 外部接口：电源输出接口;RJ45;RS-232;RS-485;line-in;line-out;Alarm-in;Alarm-out 扬声器：支持 MIC：支持 存储卡卡槽：2 电源输出接口：5V 电池可拆卸：支持 电池容量：13400mAh 待机时间：8-9小时 关机充电时间：＜4小时 电池类型：锂离子电池 | K40: 响应 | M40: 412 | N40: =E40*M40 -> 2060 | O40: 17833 | P40: =E40*O40 -> 89165 | Q40: =ROUND((M40+O40)*E40,2) -> 91225
A41: 6 | B41: 智能融合应用主机 | C41: 1.整机最大支持512路普通视频流(2MP)接入或768路文搜相机(2MP/4MP)接入，实现大模型以文搜图算法、人脸算法、结构化算法并行分析 2.整机共搭载8张GPU计算卡，其中4张抓拍卡，用于视频全目标抓拍；4张计算卡，共6个虚拟引擎，可自定义配置以文搜图算法、人脸算法、结构化算法 3.设备支持1亿条目标抓拍图片、结构化属性、模型存储（人脸+结构化） 4.集成GCN聚类算法，实现二级人员聚类方案，提供更优的人员目标聚类效果 5.大模型以文搜图算法；支持1亿条图片数据秒级文本搜图 6.大模型文本预警：支持文本描述目标关键特征，快速开启布防任务；支持1000条文本语义预警布防；最大支持50路视频流文本预警 7.大模型文本微调：支持对搜索结果进行快速标定和文本微调训练，提升文本搜图和预警效果；单次最大支持50张图片进行微调 8.人脸应用：支持目标抓拍、比对报警，以图搜图、属性检索，高频报警，1V1比对，人员档案 9.支持300万人脸静态库，300万人脸名单库比对报警，128个名单库，1亿条抓拍数据秒级检索 10.结构化应用：支持人体/车辆/非机动车抓拍、建模，以图搜图、属性检索 11.CPU：2颗64位多核处理器 12.GPU：8张GPU计算卡 13.系统内存：160GB DDR4内存 14.系统盘：2×240GB SSD 15.数据盘：1×1.92T SSD（M.2 NVMe），1× 4TB SATA盘，8× 8TB SATA盘 16.网络接口：2×千兆电口 + 2×万兆光口 17.其它接口：2×VGA接口，4×USB接口 18.整机电源：1200W ，1+1冗余电源 | D41: 海康 | E41: 1 | F41: 台 | H41: 海康 | I41: DS-IX2512-U/SF | J41: 【智能应用】 整机最大支持512路普通视频流(2MP)接入或768路文搜相机(2MP/4MP)接入，实现智能目标抓拍、大模型以文搜图算法、人脸算法、结构化算法并行分析。 整机共搭载8张智能卡，其中4张抓拍卡，用于视频全目标抓拍；4张计算卡，共6个虚拟引擎，可自定义配置以文搜图算法、人脸算法、结构化算法； 设备支持1亿条目标抓拍图片、结构化属性、模型存储（人脸+结构化） 集成GCN聚类算法，实现二级人员聚类方案，提供更优的人员目标聚类效果 支持以下3大类算法： 1、大模型以文搜图算法 实时视频流/历史视频流：最大支持512路分析（512路2MP/256路4MP/128路8MP 视频流） 图片流：建模性能90张/秒（目标小图或 2MP/4MP大图+坐标）或65张/秒（8MP大图+坐标） 大模型图文建模：支持对目标进行大模型建模，通过建模引擎将目标图片转化成语义数据模型 大模型文本搜图：输入搜索目标的文本描述，可快速搜索对应的视图内容，支持搜人、车、非机动车、物品； 支持1亿条图片数据秒级文本搜图 大模型文本预警：支持文本描述目标关键特征，快速开启布防任务；支持1000条文本语义预警布防；最大支持50路视频流文本预警 大模型文本微调：支持对搜索结果进行快速标定和文本微调训练，提升文本搜图和预警效果；单次最大支持50张图片进行微调 单个虚拟引擎：90张/秒（目标小图或 2MP/4MP大图+坐标）或65张/秒（8MP大图+坐标），预分配1个虚拟引擎 2、人脸算法 人脸应用：支持目标抓拍、比对报警，以图搜图、属性检索，高频报警，1V1比对，人员档案 实时视频流/历史视频流：最大支持512路分析（512路2MP/256路4MP/128路8MP 视频流） 图片流：支持384张/秒（建模+比对+聚类） 离线录像导入，支持1TB空间，最大支持128倍速分析（128倍速2MP/64倍速4MP/32倍速8MP 视频文件） 支持300万人脸静态库，300万人脸名单库比对报警，128个名单库，1亿条抓拍数据秒级检索 单个虚拟引擎：128张/秒（建模+比对+聚类），预分配3个虚拟引擎 3、结构化算法 结构化应用：支持人体/车辆/非机动车抓拍、建模，以图搜图、属性检索 实时视频流/历史视频流：最大支持512路分析（512路2MP/256路4MP/128路8MP 视频流） 图片流：支持260张/秒 单个虚拟引擎：最大130张/秒，预分配2个虚拟引擎 离线录像导入，支持1TB空间，最大支持128倍速分析（128倍速2MP/64倍速4MP/32倍速8MP 视频文件） 【硬件规格】 处理器：64位多核处理器 智能卡：8张 系统内存：160GB DDR4，共32个内存槽位 系统盘：2×240GB SSD 数据盘：1×1.92TB SSD（U.2 NVMe），1× 4TB SATA盘，8× 8TB SATA盘 网络接口：2×千兆电口 + 2×万兆光口 阵列卡：1张 其它接口：2×VGA接口，4×USB接口 整机电源：1200W ，1+1冗余电源 系统风扇：4个可插拔风扇，支持PID调速 机箱尺寸：87.5 mm(高) × 446.6 mm（宽） × 835 mm（深） | K41: 响应 | M41: 216.3 | N41: =E41*M41 -> 216.3 | O41: 597930 | P41: =E41*O41 -> 597930 | Q41: =ROUND((M41+O41)*E41,2) -> 598146.3
A42: 7 | B42: AI服务器 | C42: 主处理器：配置2颗KP920处理器，核数≥24核，主频≥2.5GHz； 操作系统：openEuler-22.03-LTS-aarch64 智能卡数量：配置8张Atlas 300V 智能卡；最大可支持8个智能卡 场景以本表格《附录五硬件场景需求表》为准 要求算法识别准确率、设备监测准确率不低于95% | D42: 海康 | E42: 4 | F42: 台 | H42: 海康 | I42: DS-IF2008/AI | J42: K系列推理服务器 处理器：配置2颗KP920 7260处理器，核数≥64核，主频≥2.6GHz；支持2颗鲲鹏920处理器（每颗处理器32/48/64核，主频2.6GHz） 内存：配置 384G DDR4；最大支持32根内存插槽，其中32核机型16个DDR4内存插槽，48/64核机型32个DDR4内存插槽 存储方案：配置1块480G SSD；最多配置16个3.5英寸SAS/SATA硬盘 独显&GPU扩展：配置8张Atlas 300V Pro加速卡；最大可支持8个半高半长单宽AI加速卡 存储控制器：标配SAS_HBA 卡，支持RAID 0/1/10；可选支持 RAID 0, 1, 5, 6, 10, 50, 60，可选支持超级电容掉电保护 网络控制器：配置2个千兆电口、2个万兆光口；支持2个板载网络插卡，每个插卡支持4*G电口或者2*10GE/25GE光口；或支持2个OCP3.0网卡 PCI&PCI E扩展槽：最大可支持11个标准PCIe槽位；或2个PCIe4.0 x16+5个PCIe 4.0 x8；或9个PCIe 4.0 x8标准插槽 散热系统：支持4个热拔插风扇模组，支持N+1冗余 电源方案：配置2000W(1+1)冗余电源；2个热插拔900W或2000W交流电源模块；支持1+1冗余 其它端口：前面板提供2个USB3.0 、1个VGA、1个Type-C接口； 后面板提供2个USB3.0端口、1个DB15 VGA端口、1个3.5mm串口、1个RJ45系统管理端口 机箱尺寸：447 mm*814 mm*86.1 mm（宽*深*高） 操作系统兼容：HIKOS、openEuler、SUSE、Ubuntu、CentOS、中标麒麟、银河麒麟、普华、统信、中科红旗、麒麟信安、拓林思等操作系统等操作系统 管理功能：BMC支持IPMI、SOL、KVM over IP以及虚拟媒体，提供1个10/100/1000Mbps的RJ45管理网口 | K42: 响应 | M42: 216.3 | N42: =E42*M42 -> 865.2 | O42: 325190 | P42: =E42*O42 -> 1300760 | Q42: =ROUND((M42+O42)*E42,2) -> 1301625.2
A43: 8 | B43: 存储服务器 | C43: 1.服务器配置： 1颗64位多核处理器，8GB内存，内存支持扩展到≥256GB，内置SSD固态硬盘（可以扩展到4个SSD作为缓存盘），配置8个风扇，风扇支持热插拔并可冗余温控调速；支持热插拔1+1AC220V电源或1+1直流冗余电源供电 2. 设备具备1个定位灯、1个电源灯、1个设备报警灯、1个就绪灯、1个网络状态灯、1个系统盘状态灯、1个硬盘状态灯，机箱具备防尘滤网，采用双立柱防震设计。设备左右侧面各2个抬手，具备前面板抽拉标签卡 3. 4个2.5Gb网口，支持2个前置 USB2.0接口、2个后置USB3.0接口，支持1个前置VGA接口、1个后置HDMI接口，支持1个RS-232串口，支持4个PCI-E3.0 4. 可接入2T/3T/4T/6T/8T/10T/12T/14T/16T/18T/20T/25T/26T/30T SATA/SAS硬盘；支持NL-SAS 硬盘、HDD硬盘、SSD硬盘、氦气硬盘、空气硬盘；支持 CMR或SMR硬盘；支持硬盘交错/分时启动 5.支持SATA和SAS混插，支持不同品牌（希捷、西数、东芝、海康威视）的硬盘混插；支持不同大小的硬盘混合使用，可显示硬盘的总容量（各个硬盘容量之和） 6. 应能接入并存储总码流不超过4096Mbps的2048路2Mbps码流或1024路4Mbps码流的视(音)频图像;同时转发总码流不超过4096Mbps的2048路2MbpS码流或1024路4Mbps码流的视(音)频图像;同时下载总码流不超过4096Mbps的2Mbps码流的视(音)频图像;同时回放总码流不超过1400 Mbps的视(音)频图像。当RAID处于降级或重构状态时，存储业务正常。在转发模式下，可进行4096路2Mbps视频码流转发，在总带宽不变的情况下，接入、转发、回放间的性能值可自由调整 7. 支持 ONVIF、PSIA、TCP/IP、UDP、SIP、SIP2.0、RTSP、RTP、RTCP、iSCSI、CIFS(SMB)、NFS、FTP、HTTP、AFP、RSYNC、SNMP、IPV4、IPV6、HLS、S3、OSS等协议，支持IP组播 8.抓拍图片、弹出报警画面、发送语音提示、上传中心、蜂鸣报警以及日志 9.可扩展支持将前端一路视频流同时存入两台存储；支持双机间编码器和录像同步，故障时可进行互相接管 10.可对视音频、图片、结构化数据、对象等文件进行混合存储，并可通过http和https方式下载 11.支持查看硬盘体检报告、硬盘深度体检和磁盘档案；支持下载单个硬盘或批量硬盘的报告，支持按时间显示硬盘的坏扇区、温度、振动变化趋势的曲线图；支持硬盘体检报告打印输出；支持查看硬盘体检的历史记录、硬盘健康状态，包括健康、亚健康、故障等； 12.更换系统盘并配置好信息后，再次开机无需人工介入，可自动恢复业务，历史数据不应丢失。 13.配置48块8T硬盘 | D43: 海康 | E43: 3 | F43: 台 | H43: 海康 | I43: DS-A71148R/GR | J43: 6U机架式48盘位网络存储设备，搭载64位多核处理器，1+1冗余电源、冗余风扇，实现7×24小时稳定运行 【硬件规格】 处理器：1颗64位多核处理器 系统内存：32GB（可扩展至128GB） 系统盘：1×240GB SSD（后置） 数据盘：1×960GB SSD（数据存储） 存储接口：48个SATA接口，支持硬盘热插拔 网络接口：4个2.5G数据网口，1个千兆管理口 其他接口：1×COM，2×USB2.0（前置），2×USB3.0（后置），1×VGA（前置），1×HDMI（后置） 整机电源：1600W，1+1冗余电源 【产品性能】 以文搜图模式一：768路（文搜IPC） 或 200路2MP（普通IPC，视频流）+ 568路（文搜IPC） 以文搜图模式二：300路2MP（普通IPC，视频流） 检索数量：350W/天 视频性能：最大支持接入768路（最大接入带宽1920Mbps） 图片性能：最大支持100张/S（单张图片500KB） 回放性能：最大支持76路2Mbps 事件录像：最大支持200路2Mbps 【智能应用】 前端接入能力：支持接入智能相机、结构化相机、抓拍机，对图片中的目标进行多模态大模型建模 大模型图文建模：内置大模型算法引擎，支持对目标图像和自然语言的多模态大模型建模，建立目标图像和自然语言的对应关系 大模型以文搜图：内置图文搜索引擎，支持开放式语义检索，输入文字描述即可查找人、车、非机动车及附属物等目标 以文搜图应用展示：支持全通道录像检索，且通道和时间范围可设；支持搜索结果相似度自定义设置展示；支持自定义选择时间范围 模型微调：支持对搜索结果进行快速标定和文本微调训练，提升文本搜图 搜索结果精准定位：支持搜索结果按相似度排序展示，根据搜索结果，可一键关联录像片段及以图搜图，对目标进行二次精准检索定位，还原目标的跨通道行动轨迹 搜索结果快速筛选：以文搜图检索结果支持以相似度、时间、通道等条件对检出录像/图片进行排序或筛选 【产品功能】 支持视频流、图片直写 支持ONVIF、GB/T 28181、RTSP等标准协议 支持VRAID、RAID0、1、5、6、10等多种RAID模式 支持RAID降级可读写(VRAID)，支持全局热备 支持局部重构，原盘或其克隆盘拔出设备后再插回，未被覆盖数据可快速恢复 | K43: 响应 | M43: 216.3 | N43: =E43*M43 -> 648.9 | O43: 225755.29 | P43: =E43*O43 -> 677265.87 | Q43: =ROUND((M43+O43)*E43,2) -> 677914.77
A44: 9 | B44: 原有安防监控平台扩容 | C44: 本次项目新增的前端摄像机需接入原有监控管理平台进行统一管理，并实现如下功能： 一、视频预览 1、支持视频实时预览能力，实现预览窗口布局切换、预览画面自适应及全屏切换； 2、支持云台控制、实时抓图、紧急录像、即时回放、主子码流切换、声音开启\关闭、辅屏预览（1个辅屏）、对讲、广播、报警输出控制的能力； 3、支持智能规则展示的能力（如：针对热成像设备温度信息实时展示）； 4、支持资源视图管理能力，以视图形式管理监控点、视频预览轮巡等自定义资源组，其中视图类型包含公有视图和私有视图； 5、支持全景视频监控预览能力，支持球型鹰眼、全景摄像机的全景模式； 二、录像回放 1、支持录像计划管理能力，支持实时录像计划、录像回传计划； 2、支持录像回放能力，支持多画面同步回放和异步回放切换、超高倍速回放、分段回放、录像下载、录像剪辑、录像标签、录像锁定、录像抓图； 三、图片监控 1、支持视频预览与图片实时监控模式切换能力，实现图片监控模式； 2、支持图片查询回放能力，实现按监控点、时间段展示抓拍图片； 3、支持图片自动播放能力，支持图片自动播放速度可设置； 4、支持图片下载能力； 四、视频上墙 1、支持电视墙场景管理能力，实现场景窗口配置、场景切换计划配置以及轮巡计划的管理； 2、支持上墙控制能力，实现场景一键上墙、场景切换、电视墙切换、监控点上下墙、轮巡控制操作； 五、视频事件 1、支持视频事件布撤防能力，可按计划模版进行布防，事件类型包括移动侦测、视频丢失、视频遮挡、报警输入、报警输出； 六、事件录像管理 支持事件录像存储配置、事件录像检索和下载管理。 | D44: 海康 | E44: 281 | F44: 路 | H44: 海康 | K44: 响应 | M44: 5.51 | N44: =E44*M44 -> 1548.31 | O44: 31.47 | P44: =E44*O44 -> 8843.07 | Q44: =ROUND((M44+O44)*E44,2) -> 10391.38
A45: 10 | B45: 8口POE接入交换机（带光口） | C45: 千兆以太网交换机，PoE交换机； 端口描述：不低于10个10/100/1000M电口，不低于2个SFP口，1个console口； 背板带宽：不低于336Gbps/3.36Tbps； 包转发率：不低于27Mpps/102Mpps； 支持Console，Telnet，WEB，SNMP； PoE：1-8口支持（整机PoE供电不低于125W，最大同时支持8个PoE端口） PoE+：1-8口支持（整机PoE供电不低于125W，最大同时支持4个PoE+端口） | D45: 华三、锐捷（非睿易） | E45: 15 | F45: 台 | H45: 锐捷 | I45: RG-S2000-10GT2MS-P | J45: 二层 | 千兆接入交换机 | 10个10/100/1000M自适应电口，2个1G/2.5G SFP光口，固化单交流电源和风扇，1-8端口支持PoE/PoE+远程供电，125W POE供电。 | 支持PoE+ | 支持静态路由、链路聚合、EEE节能以太网技术、端口防雷能力10KV | 支持云管理＆本地管理 | 默认三年维保 | | K45: 响应 | M45: 121.54 | N45: =E45*M45 -> 1823.1 | O45: 1245 | P45: =E45*O45 -> 18675 | Q45: =ROUND((M45+O45)*E45,2) -> 20498.1 | S45: 修改型号
A46: 11 | B46: 24口POE接入交换机-单电源 | C46: 1.在不插板卡情况下，单设备交换容量≥336Gbps，包转发率≥126Mpps，提供≥24个千兆电接口、≥4个万兆SFP+光接口。 2.支持支持802.3at/POE+供电标准。 1、支持堆叠技术或者虚拟化技术 2、支持 4K 802.1Q VLAN,支持Voice VLAN及Voice VLAN中可以同时识别多厂家的OUI地址，支持端口VLAN、MAC VLAN 3、支持标准IP ACL（基于IP地址的硬件ACL）支持扩展IP ACL（基于IP地址、TCP/UDP端口号的硬件ACL） 4、支持QOS 5、支持一对一、多对一、一对多的镜像 6、支持DHCP Server、DHCP Client、DHCP Snooping、DHCP Relay、DHCP Option82 7、支持广播风暴抑制 8、支持设备登陆管理的AAA安全认证、radius认证、支持802.1x、支持ssh2.0 9、支持STP/RSTP/MSTP协议 10、支持链路聚合（支持静态、动态链路聚合、千兆口聚合、万兆口聚合） 11、有标准的或私有的邻居发现协议 12、支持VLAN虚接口 13、支持 IPv4 /ipv6静态路由 14、支持OSPFv2、OSPFv3 15、支持SNMPv1/v2/v3，WEB网管，支持命令行接口配置，Telnet，SSH，Console口配置，支持系统日志，分级告警，调试信息输出，NTP/SNTP ★15、提供真实有效的工信部入网证复印件； ★16、原厂质保≥3年 | D46: 华三、锐捷（非睿易） | E46: 17 | F46: 台 | H46: 锐捷 | I46: RG-S2910-24GT4SFP-P-L | J46: 千兆接入交换机 | 24个10/100/1000M自适应电口，4个1G SFP光口，1-24口支持PoE/PoE+，固化交流电源和风扇，整机PoE最大输出370W。 | 支持PoE+ | 交换容量598Gbps/5.98Tbps | 包转发率126Mpps | 支持动态路由协议（RIP、OSPF）、VSU、802.X认证、ERPS环网保护协议、链路聚合 | 支持云管理&本地管理 | 默认三年维保 | | K46: 响应 | M46: 144.2 | N46: =E46*M46 -> 2451.4 | O46: 2534 | P46: =E46*O46 -> 43078 | Q46: =ROUND((M46+O46)*E46,2) -> 45529.4 | S46: 修改型号
A47: 12 | B47: 千兆单模光模块 | C47: LC接口，单模千兆光纤（和交换机同品牌） | D47: 华三、锐捷（非睿易） | E47: 30 | F47: 个 | H47: 锐捷 | I47: MINI-GBIC-LX-SM1310 | J47: 1000BASE-LX mini GBIC转换模块（1310nm），10km | K47: 响应 | M47: 11.33 | N47: =E47*M47 -> 339.9 | O47: 110.15 | P47: =E47*O47 -> 3304.5 | Q47: =ROUND((M47+O47)*E47,2) -> 3644.4
A48: 13 | B48: 万兆单模光模块 | C48: SFP+万兆模块(1310nm,10km,LC) | D48: 华三、锐捷（非睿易） | E48: 34 | F48: 个 | H48: 锐捷 | I48: XG-SFP-LR-SM1310 | J48: 万兆LC接口模块（1310nm），10km，适用于SFP+接口 | K48: 响应 | M48: 11.33 | N48: =E48*M48 -> 385.22 | O48: 544 | P48: =E48*O48 -> 18496 | Q48: =ROUND((M48+O48)*E48,2) -> 18881.22
A49: 14 | B49: 六类非屏蔽双绞线 | C49: 1.标准：不低于TIA/EIA568-C.2、ISO/IEC11801、IEC60332-1、GB 50311； 2.最高传输频率不低于250MHz； 3.导体规格：单根导体直径不小于0.57±0.02； 4.屏蔽方式：U/UTP，线对采用“十”字骨架隔离； 5.护套材料：LSZH，护套外径：6.3±0.3mm； 6.支持以太网供电（Power over Ethernet）应用（POE/POE+）； 7.综合布线光纤系统、铜缆系统应采用同一品牌。 | D49: 一舟、普天天纪、罗格朗 | E49: 20000 | F49: m | H49: 一舟 | I49: D165-T-D | J49: 1.标准：不低于TIA/EIA568-C.2、ISO/IEC11801、IEC60332-1、GB 50311； 2.最高传输频率不低于250MHz； 3.导体规格：单根导体直径不小于0.57±0.02； 4.屏蔽方式：U/UTP，线对采用“十”字骨架隔离； 5.护套材料：LSZH，护套外径：6.3±0.3mm； 6.支持以太网供电（Power over Ethernet）应用（POE/POE+）； 7.综合布线光纤系统、铜缆系统应采用同一品牌。 | K49: 响应 | M49: 1.75 | N49: =E49*M49 -> 35000 | O49: 3.04 | P49: =E49*O49 -> 60800 | Q49: =ROUND((M49+O49)*E49,2) -> 95800
A50: 15 | B50: 电源线 | C50: 国标，RVV3*2.5 | D50: 一舟、普天天纪、罗格朗 | E50: =E51*70*1.1 -> 2464 | F50: m | H50: 一舟 | I50: RVV3*2.5 | J50: 国标，RVV3*2.5 | K50: 响应 | M50: 2.52 | N50: =E50*M50 -> 6209.28 | O50: 10.7 | P50: =E50*O50 -> 26364.8 | Q50: =ROUND((M50+O50)*E50,2) -> 32574.08
A51: 16 | B51: 背包箱 | C51: 1.尺寸：不低于400mmX300mmX500mm 2.配置空开、插线板，设备的安装附件和安装螺钉；满足现场使用需求。 3.结构：整体结构采用拼焊结构，牢固、钢性好、牢固可靠，表面采用热镀锌处理。 4.防护等级不低于IP55，保护内部设备不受外界恶劣环境的干扰； 5.箱体采用1.2mm的标号201不锈钢板，整体喷塑。 颜色和立杆保持一致。 | D51: 国产 | E51: =E45+E46 -> 32 | F51: 个 | H51: 国产 | I51: 400mmX300mmX500mm | J51: 1.尺寸：不低于400mmX300mmX500mm 2.配置空开、插线板，设备的安装附件和安装螺钉；满足现场使用需求。 3.结构：整体结构采用拼焊结构，牢固、钢性好、牢固可靠，表面采用热镀锌处理。 4.防护等级不低于IP55，保护内部设备不受外界恶劣环境的干扰； 5.箱体采用1.2mm的标号201不锈钢板，整体喷塑。 颜色和立杆保持一致。 | K51: 响应 | M51: 56.65 | N51: =E51*M51 -> 1812.8 | O51: 89.17 | P51: =E51*O51 -> 2853.44 | Q51: =ROUND((M51+O51)*E51,2) -> 4666.24
A52: 17 | B52: 3.5米监控立杆 | C52: 1.3.5米监控立杆，含地笼及混凝土基础； 2.颜色和背包箱保持一致。 | D52: 国产 | E52: 100 | F52: 个 | H52: 国产 | I52: 3.5米立杆 | J52: 1.3.5米监控立杆，含地笼及混凝土基础； 2.颜色和背包箱保持一致。 | K52: 响应 | M52: 309 | N52: =E52*M52 -> 30900 | O52: 681.85 | P52: =E52*O52 -> 68185 | Q52: =ROUND((M52+O52)*E52,2) -> 99085
A53: 18 | B53: 光纤熔接盒（含光纤熔纤） | C53: SC4芯单模满配含熔接尾纤、法兰、SC光跳线。 | D53: 一舟、普天天纪、罗格朗 | E53: =E45+E46 -> 32 | F53: 个 | H53: 一舟 | I53: S953-4X+ 4*S905-3+ 4*S812+ 2*S922 | J53: 含4个SC单工耦合器，4条SC单芯单模尾纤，2条SC-SC双芯单模跳纤 | K53: 响应 | M53: 97.85 | N53: =E53*M53 -> 3131.2 | O53: 111.19 | P53: =E53*O53 -> 3558.08 | Q53: =ROUND((M53+O53)*E53,2) -> 6689.28
A54: 19 | B54: 室外4芯单模光缆 | C54: 1.标准：YD/T769，ISO/IEC11801，ANSI/TIA -568-C.3 2.全截面阻水结构，松套管填充纤膏，松套管和钢带之间填充缆膏，确保良好的阻水防潮性能 3.光纤规格：B1.3（OS2） 4.衰减＠20℃（dB/Km）：＠1310nm≤0.36，＠1550nm≤0.22 5.光纤芯数：4芯 6.护套：夹带钢丝的钢-聚乙烯粘结护套，MDPE，黑色 7.允许拉伸力：长期：600N，短期：1500N 8.允许压扁力：长期：300N/100mm，短期：1000N/100mm 9.最小弯曲半径：动态：20D，静态：10D | D54: 一舟、普天天纪、罗格朗 | E54: 10560 | F54: m | H54: 一舟 | I54: D173-4 | J54: 1.标准：YD/T769，ISO/IEC11801，ANSI/TIA -568-C.3 2.全截面阻水结构，松套管填充纤膏，松套管和钢带之间填充缆膏，确保良好的阻水防潮性能 3.光纤规格：B1.3（OS2） 4.衰减＠20℃（dB/Km）：＠1310nm≤0.36，＠1550nm≤0.22 5.光纤芯数：4芯 6.护套：夹带钢丝的钢-聚乙烯粘结护套，MDPE，黑色 7.允许拉伸力：长期：600N，短期：1500N 8.允许压扁力：长期：300N/100mm，短期：1000N/100mm 9.最小弯曲半径：动态：20D，静态：10D | K54: 响应 | M54: 2.73 | N54: =E54*M54 -> 28828.8 | O54: 1.84 | P54: =E54*O54 -> 19430.4 | Q54: =ROUND((M54+O54)*E54,2) -> 48259.2 | S54: 修改型号
A55: 20 | B55: 24口光纤配线架（含尾纤、LC双工耦合器、熔接） | C55: 1.标准：YD/T778，ISO/IEC 11801，ANSI/TIA -568-C.3 2.安装方式：19″机架式安装 3.4个光缆进线口，带固定PG头，盒内配置光缆护套固定装置，光缆加强件固定装置 4.通用型设计，可兼容：LC双工、SC单工、FC、ST适配器，一个4口支架仅需一颗螺丝，便于安装和拆卸 5.进出光纤方便灵活，有充裕的光纤盘存空间，光纤和尾纤弯曲半径不小于30mm 6.端口数量： 24口，空余端口可安装空白功能件，高度：1U 7.表面处理：静电喷塑 8.材料：优质冷扎钢板 9.表面颜色：黑色 10.含LC双工耦合器 | D55: 一舟、普天天纪、罗格朗 | E55: 3 | F55: 个 | H55: 一舟 | I55: S952-24X+ 24*S905-7-1+ 48*S813 | J55: 1.标准：YD/T778，ISO/IEC 11801，ANSI/TIA -568-C.3 2.安装方式：19″机架式安装 3.4个光缆进线口，带固定PG头，盒内配置光缆护套固定装置，光缆加强件固定装置 4.通用型设计，可兼容：LC双工、SC单工、FC、ST适配器，一个4口支架仅需一颗螺丝，便于安装和拆卸 5.进出光纤方便灵活，有充裕的光纤盘存空间，光纤和尾纤弯曲半径不小于30mm 6.端口数量： 24口，空余端口可安装空白功能件，高度：1U 7.表面处理：静电喷塑 8.材料：优质冷扎钢板 9.表面颜色：黑色 10.含LC双工耦合器 | K55: 响应 | M55: 463.5 | N55: =E55*M55 -> 1390.5 | O55: 503.52 | P55: =E55*O55 -> 1510.56 | Q55: =ROUND((M55+O55)*E55,2) -> 2901.06
A56: 21 | B56: 光纤跳线 | C56: 单模双芯LC-LC优质3米光纤跳线； | D56: 一舟、普天天纪、罗格朗 | E56: =E53 -> 32 | F56: 个 | H56: 一舟 | I56: S928 | J56: 单模双芯SC-LC优质2米光纤跳线； | K56: 响应 | M56: 5.51 | N56: =E56*M56 -> 176.32 | O56: 23.08 | P56: =E56*O56 -> 738.56 | Q56: =ROUND((M56+O56)*E56,2) -> 914.88
A57: 22 | B57: JDG20管 | C57: JDG管，壁厚不小于1.0MM,φ20；含主材、接头、固定扣件（含钢结构扣件）等辅材 | D57: 国产 | E57: 15000 | F57: m | H57: 国产 | I57: JDG20 | J57: JDG管，壁厚不小于1.0MM,φ20；含主材、接头、固定扣件（含钢结构扣件）等辅材 | K57: 响应 | M57: 9.79 | N57: =E57*M57 -> 146850 | O57: 3.67 | P57: =E57*O57 -> 55050 | Q57: =ROUND((M57+O57)*E57,2) -> 201900
A58: 23 | B58: 辅材 | C58: 设备安装配套辅材，水晶头，扎带等 | E58: 1 | F58: 项 | K58: 响应 | M58: 6180 | N58: =E58*M58 -> 6180 | O58: 10490 | P58: =E58*O58 -> 10490 | Q58: =ROUND((M58+O58)*E58,2) -> 16670
B59: 2.2、无人机软硬件套装 | N59: =E59*M59 -> 0 | P59: =E59*O59 -> 0
A60: 1 | B60: 无人机 | C60: 最大飞行时间（无风环境）：＞50分钟 环境适应性：防护等级≥ IP55，最大抗风速度≥12 米/秒 环境感知：全向双目视觉系统，辅以机身底部三维红外传感器 广角：1/1.3 英寸 CMOS，有效像素 4800 万 中长焦：1/1.3 英寸 CMOS，有效像素 4800 万 长焦：1/1.5 英寸 CMOS，有效像素 4800 万 热成像相机：1280 × 1024@30fps 激光测距：正入射量程 1800 米（1 Hz）@20% 反射率目标 线缆级自动避障 | D60: 大疆、道通、复亚智能、云圣智能 | E60: 1 | F60: 台 | H60: 大疆 | I60: DJI Matrice 4TD（中国版）SP Plus | J60: 最大飞行时间（无风环境）：＞50分钟 环境适应性：防护等级≥ IP55，最大抗风速度≥12 米/秒 环境感知：全向双目视觉系统，辅以机身底部三维红外传感器 广角：1/1.3 英寸 CMOS，有效像素 4800 万 中长焦：1/1.3 英寸 CMOS，有效像素 4800 万 长焦：1/1.5 英寸 CMOS，有效像素 4800 万 热成像相机：1280 × 1024@30fps 激光测距：正入射量程 1800 米（1 Hz）@20% 反射率目标 线缆级自动避障 | K60: 响应 | M60: 206 | N60: =E60*M60 -> 206 | O60: 43112.85 | P60: =E60*O60 -> 43112.85 | Q60: =ROUND((M60+O60)*E60,2) -> 43318.85
A61: 2 | B61: 无人机巢及中继 | C61: 环境适应性：工作温度为 -30℃ 至 50℃ ，防护等级为 IP56 最大作业半径≥5 公里 充电时间＜30 分钟 舱内可直播相机分辨率：1920 × 1080 机巢图传系统 依据现场情况自行评估是否需要增加中继设备 | D61: 大疆、道通、复亚智能、云圣智能 | E61: 1 | F61: 套 | H61: 大疆 | I61: 大疆机场 3（中国版）SP Plus | J61: 环境适应性：工作温度为 -30℃ 至 50℃ ，防护等级为 IP56 最大作业半径≥5 公里 充电时间＜30 分钟 舱内可直播相机分辨率：1920 × 1080 机巢图传系统 依据现场情况自行评估是否需要增加中继设备 | K61: 响应 | M61: 206 | N61: =E61*M61 -> 206 | O61: 82766.1 | P61: =E61*O61 -> 82766.1 | Q61: =ROUND((M61+O61)*E61,2) -> 82972.1
A62: 3 | B62: 无人机平台 | C62: 私有化平台，支持算法和大模型，支持二次开发，可视化界面操作 支持本地建模，支持一键起飞，多航线设定（巡检航线和指令航线） 支持自定义模糊查找、导出照片 接入智慧安防系统 巡查管理支持无人机航线绘制和飞行任务管理，同时提供飞行实时监控： 1、航线绘制： 提供自定义航线，支持手动在地图上绘制航电，生成航线 2、飞行任务管理： 提供基础巡查任务管理，对指定航线进行巡检，支持单次、重复、定时、连续等飞行策略 3、飞行监控：支持全局视角、无人机视角多视角展示： 1）支持以2.5D地图可视化呈现无人机、机库、手持地面站、飞手等地理位置及相关信息，对禁飞区、电子围栏等区域分布进行图上统计展示。 2）支持展示地面站数量、无人机数量、任务数量、飞行里程、飞行架次、飞行时长等。 3）支持对当前执飞无人机进行实时动态监测，展示无人机当前位置、高度、速度等信息，可以查看当前无人机挂载视频实时画面。 4）支持无人机远程控制，包含一键起飞、一键返航等操作，可以针对无人机挂载设备进行广播喊话、拍照、云台控制等操作。 5）支持展示任务信息、航线信息、预警信息、地面站信息等。 6）支持按飞机、按飞手、按任务查询对应飞行任务的图片档案信息。 7）支持飞机、按飞手、按任务查询对应飞行任务的视频档案信息。 | D62: 大疆、道通、复亚智能、云圣智能 | E62: 1 | F62: 套 | H62: 大疆 | I62: 大疆司空 2 一体机套装（中国标准版） | J62: 私有化平台，支持算法和大模型，支持二次开发，可视化界面操作 支持本地建模，支持一键起飞，多航线设定（巡检航线和指令航线） 支持自定义模糊查找、导出照片 接入智慧安防系统 巡查管理支持无人机航线绘制和飞行任务管理，同时提供飞行实时监控： 1、航线绘制： 提供自定义航线，支持手动在地图上绘制航电，生成航线 2、飞行任务管理： 提供基础巡查任务管理，对指定航线进行巡检，支持单次、重复、定时、连续等飞行策略 3、飞行监控：支持全局视角、无人机视角多视角展示： 1）支持以2.5D地图可视化呈现无人机、机库、手持地面站、飞手等地理位置及相关信息，对禁飞区、电子围栏等区域分布进行图上统计展示。 2）支持展示地面站数量、无人机数量、任务数量、飞行里程、飞行架次、飞行时长等。 3）支持对当前执飞无人机进行实时动态监测，展示无人机当前位置、高度、速度等信息，可以查看当前无人机挂载视频实时画面。 4）支持无人机远程控制，包含一键起飞、一键返航等操作，可以针对无人机挂载设备进行广播喊话、拍照、云台控制等操作。 5）支持展示任务信息、航线信息、预警信息、地面站信息等。 6）支持按飞机、按飞手、按任务查询对应飞行任务的图片档案信息。 7）支持飞机、按飞手、按任务查询对应飞行任务的视频档案信息。 | K62: 响应 | M62: 206 | N62: =E62*M62 -> 206 | O62: 76459.51 | P62: =E62*O62 -> 76459.51 | Q62: =ROUND((M62+O62)*E62,2) -> 76665.51
B63: 2.3、巡更管理 | N63: =E63*M63 -> 0 | P63: =E63*O63 -> 0
A64: 1 | B64: 手持设备 | C64: 1.ARM八核2.0GHz处理器，4GB RAM，64GB ROM 2.图像采集：前置摄像头500万像素；后置摄像头1300万像素 3.支持二维码、NFC读卡、室外GPS定位+电子地图巡更方案 4.内置高灵敏度卫星定位模块，支持北斗，GPS，Glonass定位 5.防水、防尘、防摔（IP68）,支持1.5米防摔，适合全天候野外作业 6.支持NFC协议；支持ISO15693、ISO14443A/B 7.支持远程巡更任务接收，巡更任务管理 8.支持巡更人员登录注册，进行权限管理 9.支持巡更任务查询，巡更任务提醒等协助巡更的功能 10.有网络环境下支持巡更记录实时上传，无网络环境下支持巡更记录断点续传 | D64: 蓝卡、广拓、海康 | E64: 15 | F64: 台 | H64: 海康 | I64: DS-MDT102/MF | J64: 巡更手持机(C) ARM八核2.0GHz处理器，4GB RAM，64GB ROM 图像采集：前置摄像头500万像素；后置摄像头1300万像素 支持二维码、NFC读卡、室外GPS定位+电子地图巡更方案 内置高灵敏度卫星定位模块，支持北斗，GPS，Glonass定位 防水、防尘、防摔（IP68）,支持1.5米防摔，适合全天候野外作业 支持NFC协议；支持ISO15693、ISO14443A/B 支持远程巡更任务接收，巡更任务管理 支持巡更人员登录注册，进行权限管理 支持巡更任务查询，巡更任务提醒等协助巡更的功能 有网络环境下支持巡更记录实时上传，无网络环境下支持巡更记录断点续传 传感器类型：后置主相机1300万像素，前置500万相机 屏幕尺寸：5.5英寸 分辨率：1440*720 聚焦模式：前置：定焦 后置：自动 视频压缩标准：H.264 录像格式：3GP 图片分辨率：2M;5M;8M;13M 图片格式：JPEG 音频采样率：8 kHz;16 kHz;44.1 kHz;48 kHz 音频压缩标准：AAC;AAC+;AMR;AWB;VORBIS 音频压缩码率：8K,16K,32kbps,64kbps,128kbps,256kbps 拨号：TDD-LTE B38;TDD-LTE B39;TDD-LTE B40;TDD-LTE B41;FDD -LTE B1;FDD -LTE B3;FDD -LTE B5;FDD -LTE B8;WCDMA B1;WCDMA B8;TD-SCDMA B34;TD-SCDMA B39;CDMA EVDO BC0;GSM 900;GSM 1800 Wi-Fi工作模式：AP;STATION Wi-Fi频率范围：2.412-2.472 GHz;5.15-5.25 GHz;5.25-5.35 GHz;5.47-5.725 GHz;5.725-5.875 GHz 定位：GPS;北斗;GLONASS 蓝牙：5.0 NFC：支持 内置存储介质：Emmc 内置存储容量：64GB 充电接口：Type-C 扬声器：支持 MIC：支持 SIM卡槽：2 个 Nano SIM，与TF卡槽三选二 CPU：八核2.0 Ghz 操作系统：Android14 内存：4GB 闪光灯：支持 指示灯：充电指示灯;工作指示灯 震动：支持 按键：电源、音量+、音量-、自定义键、扫码键 产品重量：240g 产品尺寸：154.9*73.3*15mm 防护等级：IP68 跌落性能：1.5米跌落 供电方式：电池供电 工作温度：-20℃～+55℃ 工作湿度：<95% 电池可拆卸：不支持 电池容量：5000mAh（典型容量） 关机充电时间：3小时 电池类型：锂离子电池 | K64: 响应 | M64: 87.55 | N64: =E64*M64 -> 1313.25 | O64: 2042.4 | P64: =E64*O64 -> 30636 | Q64: =ROUND((M64+O64)*E64,2) -> 31949.25
A65: 2 | B65: 巡更牌 | C65: 1.NFC巡更打卡，使用单兵设备可直接进行巡更打卡 2.二维码扫描，通过系统权限验证的用户，可通过扫描二维码查看巡更记录 3.抬头预留空窗，可根据需求自主印刷 4.工作温度：-40℃～85℃ 5.工作湿度：5%～95% 无冷凝 | D65: 蓝卡、广拓、海康 | E65: 50 | F65: 台 | H65: 海康 | I65: DS-TRC100-8/X | J65: 巡更标签 NFC巡更打卡，使用单兵设备可直接进行巡更打卡 3M背胶设计，可直接粘贴于墙面，也可通过中间固定孔进行螺丝固定 【一般规范】 工作温度: -20~50℃ 工作湿度: 20%~60% | K65: 响应 | M65: 21.63 | N65: =E65*M65 -> 1081.5 | O65: 5.25 | P65: =E65*O65 -> 262.5 | Q65: =ROUND((M65+O65)*E65,2) -> 1344
A66: 3 | B66: 卡片录入仪 | C66: 1.支持发卡类型：ID卡、IC卡、身份证物料卡号（序列号）、普通CPU卡、国密CPU卡 2.USB2.0接口 3.具有2个Sim卡尺寸的PSAM卡座 4.工作电压：DC 5V 5.工作电流：0.2A | D66: 蓝卡、广拓、海康 | E66: 1 | F66: 台 | H66: 海康 | I66: DS-K1F100K | J66: 支持发卡类型：ID卡、IC卡、身份证物理卡号（序列号）、普通CPU卡、国密CPU卡； USB2.0接口； 具有2个Sim卡尺寸的PSAM卡座； 工作电压：DC 5V； 工作电流：0.2A； 尺寸：117*67.5*14.3mm | K66: 响应 | M66: 87.55 | N66: =E66*M66 -> 87.55 | O66: 604.22 | P66: =E66*O66 -> 604.22 | Q66: =ROUND((M66+O66)*E66,2) -> 691.77
A67: 4 | B67: 巡更管理软件 | C67: 一、巡更点 1、支持将门禁设备、近距离射频识别NFC、二维码等多种方式设置为巡更点打卡凭证； 2、支持根据实际管理需求自定义扩展巡更点类型； 二、巡更计划 1、支持有序巡更与无序巡更两种现场巡更模式。 2、支持对巡更计划进行全流程管理，可配置计划名称、有效期、任务执行周期（支持每天/每周/每月/每年或指定日期）、巡更点及执行人。执行人支持按具体人员、角色或组织进行灵活分配。 3、支持查看巡更计划列表，显示信息包括计划名称、巡更区域、巡更点数量、计划有效期等；同时支持按计划名称、状态、计划有效期、创建时间、巡更区域等多条件对计划进行检索。 三、巡更任务 1、支持系统根据巡更计划自动执行巡更任务的生成。 2、支持管理人员手动触发基于巡更计划的巡更任务生成。 3、支持通过待办任务方式提醒巡更人员按时执行巡更任务。 4、支持查看巡更任务列表，显示信息包括巡更任务编号、所属巡更计划、所属区域、任务类型、巡更点数量、发现问题数、任务开始时间等；同时支持按任务状态、任务类型、任务开始时间等多条件对任务进行检索。 3、支持离线巡更模式，可通过专用巡更棒或现场移动APP执行打卡操作。 四、巡更记录 1、支持查看巡更任务记录，显示信息包括巡更任务编号、所属区域、巡更计划模板、任务时间、巡更对象数等，并支持按条件检索及数据导出。 2、支持查看单次巡更任务的详细报告，并可支持打印。 | D67: 蓝卡、广拓、海康 | E67: 1 | F67: 套 | H67: 海康 | I67: 巡更管理软件 | J67: 一、巡更点 1、支持将门禁设备、近距离射频识别NFC、二维码等多种方式设置为巡更点打卡凭证； 2、支持根据实际管理需求自定义扩展巡更点类型； 二、巡更计划 1、支持有序巡更与无序巡更两种现场巡更模式。 2、支持对巡更计划进行全流程管理，可配置计划名称、有效期、任务执行周期（支持每天/每周/每月/每年或指定日期）、巡更点及执行人。执行人支持按具体人员、角色或组织进行灵活分配。 3、支持查看巡更计划列表，显示信息包括计划名称、巡更区域、巡更点数量、计划有效期等；同时支持按计划名称、状态、计划有效期、创建时间、巡更区域等多条件对计划进行检索。 三、巡更任务 1、支持系统根据巡更计划自动执行巡更任务的生成。 2、支持管理人员手动触发基于巡更计划的巡更任务生成。 3、支持通过待办任务方式提醒巡更人员按时执行巡更任务。 4、支持查看巡更任务列表，显示信息包括巡更任务编号、所属巡更计划、所属区域、任务类型、巡更点数量、发现问题数、任务开始时间等；同时支持按任务状态、任务类型、任务开始时间等多条件对任务进行检索。 3、支持离线巡更模式，可通过专用巡更棒或现场移动APP执行打卡操作。 四、巡更记录 1、支持查看巡更任务记录，显示信息包括巡更任务编号、所属区域、巡更计划模板、任务时间、巡更对象数等，并支持按条件检索及数据导出。 2、支持查看单次巡更任务的详细报告，并可支持打印。 | K67: 响应 | M67: 216.3 | N67: =E67*M67 -> 216.3 | O67: 5245 | P67: =E67*O67 -> 5245 | Q67: =ROUND((M67+O67)*E67,2) -> 5461.3
B68: 2.4、周界防护-定位型振动光纤系统 | N68: =E68*M68 -> 0 | P68: =E68*O68 -> 0
A69: 1 | B69: 传感光缆 | C69: 1.光纤类型: 4芯单模光纤 2.纤芯类型: G.652D 9/125μm 非色散位移单模光纤 3.光缆外径: 8.6mm(±5%) 4.抗压系数: 短期：1000N/10cm 5.长期：300N/10cm 6.拉伸强度: 短期：1500N 7.长期：600N 8.最小弯曲半径: 光缆外径的10倍（静态） 9.光缆外径的20倍（动态） 10.光缆传输衰减: 1310nm≤0.36dB/km；1550nm≤0.22dB/km 11.工作温度: -40~70℃ 12.工作湿度: 0~95%R.H 13.防护等级: IP68 | D69: 福科斯、广拓、海康 | E69: 22000 | F69: m | H69: 海康 | I69: DS-PO2-iDFM/S4/G | J69: 传感光缆 传感光缆防护等级高达IP68，且具有如下性能优势，探测振动响应灵敏，抗拉伸、耐磨损、抗压扁、抗冲击、抗鼠咬，可反复弯曲、扭转、曲绕、弯折、枪击等，具有很好的机械性能。 光缆信号传输快、传输距离远、传输信息完整性好、抗电磁场干扰、绝缘性好、化学稳定性好、尺寸小、重量轻、寿命长、损耗低具有很好的特性和经济效益。 环境适应性强：光纤具备柔性特点，可以随地形安装，适合地形复杂的周界 抗电磁干扰：前端全无源设计，不受取网供电条件制约，不受电磁干扰影响 耐腐蚀：抗恶劣环境，如潮湿、高低温干扰，可耐氨气、氯气、盐雾、酸雨等 【基本参数】 光纤类型: 4芯单模光纤 纤芯类型: G.652D 9/125μm 非色散位移单模光纤 光缆外径: 8.6mm(±5%) 抗压系数: 短期：1000N/10cm 长期：300N/10cm 拉伸强度: 短期：1500N 长期：600N 最小弯曲半径: 光缆外径的10倍（静态） 光缆外径的20倍（动态） 光缆传输衰减: 1310nm≤0.36dB/km 1550nm≤0.22dB/km 【一般规范】 工作温度: -40~70℃ 工作湿度: 0~95%R.H 包装规格: 3000米/卷 防护等级: IP68 | K69: 响应 | M69: 2.73 | N69: =E69*M69 -> 60060 | O69: 2.84 | P69: =E69*O69 -> 62480 | Q69: =ROUND((M69+O69)*E69,2) -> 122540
A70: 2 | B70: 定位型振动光纤处理器 | C70: 1.当在布防区域模拟触发入侵报警时，在1s的时间内输出入侵报警信号。 2.当出现断纤时，在1s的时间内通过系统输出断纤报警信号，且可通过显示/指示单元显示距光纤始端最近的断纤位置，该信号的输出形式应在说明书中明示且应区别于其他报警信号。 3.分布式定位型振动光纤系统的外壳设有防拆保护装置,当外壳被打开到足以触及其中的任何控制部件或机械固定的调节器时,防拆保护装置动作,并输出防拆报警信号,该信号的输出形式应区别于其他报瞥信号。 4.通道开关按键16个，支持通过通道开关按键启用/关闭通道功能 5.系统支持报警分级功能，共分为3个级别，由3至1报警紧迫或重要程度逐级增加。系统支持各等级独立设置阈值参数。 6.系统支持与摄像机联动，并支持通过摄像机对图片、视频进行分析复核 7.定位精度（检测结果）：探测距离≤5km，定位精度±2.0m；探测距离＞5km且≤20km，定位精度±5.0m；探测距离＞20km且≤40km，定位精度±5.0m；探测距离＞40km且≤80km，定位精度±5.0m 8.在固定的振动激励条件下（振幅及频率不变），系统探测到的振动幅度最大偏差在±10%以内。 9.在固定声源激励敏感部件的条件下，系统支持音频信号还原及播放。 10.抗风干扰符合III级风速干扰条件下，不产生误报警和漏报警：Ill级：7～8级风速、Ih、17.1m/s～20.7m/s 11.抗雨干扰符合满足III级暴雨干扰条件下，不产生误报警和漏报警：Ill级：暴雨、每24h降水强度100mm、lh 12.主机应支持至少8路输入(开关量),至少8路输出(开关量)接口扩展。 13.系统应具有远程参数配置与程序更新功能;应具有集中维护管理功能,应可在远端进行系统设备的日常维护管理。 14.单通道瀑布图数据应每分钟实时上报；瀑布图原始数据采样分辨率应能达到0.4m，时间分辨率应不大于0.1；系统应支持瀑布图数据输出和瀑布图数据管理 | D70: 福科斯、广拓、海康 | E70: 1 | F70: 台 | H70: 海康 | I70: DS-QFA3016DW | J70: 定位型振动光纤处理器 处理器： 定位型振动光纤处理器是一款基于相干检测技术的分布式光纤振动探测系统，通过PDC φ-OTDR光时域反射解调算法做到精确的定位，结合后端数据分析处理模块，实现对振动的有效监测。同时，设备具有对自然环境干扰的智能模式识别能力，显著降低误报。 利用光纤中的背向散射光，通过光的相干检测，得到扰动位置的相位或光强的变化，输出对应的振动信号。系统可以定位振动事件，精确到其空间分辨率，可同时定位检测多个位置的振动事件 环境适应性强：光纤具备柔性特点，可以随地形安装，适合地形复杂的周界 抗电磁干扰：前端全无源设计，不受取网供电条件制约，不受电磁干扰影响 探测灵敏：灵敏度高，可高保真识别振动声波 长距离监测：监测距离长，可达数十公里 精准定位：定位精度高，支持同时定位监测多点振动事件 耐腐蚀：抗恶劣环境，如潮湿、高低温干扰，可耐氨气、氯气、盐雾、酸雨等 服务器： 抗震驱动器托架，支持3个5.25",1个3.5"驱动器 电源和HDD状态LED指示灯 高效切换电源和易维护风扇 特殊的固定夹紧设计与橡胶垫，保护卡片免受冲击和振动 易维护空气滤网、前置USB接口 【基本参数】 光纤类型: 单模光纤 (ITU-T G.652D) 通道数: 1 单通道探测距离: 30km 定位精度: ±5m 单元数: 可配置，根据光纤长度和单位间隔进行配置。 报警响应时间: ≤1S 频率响应: 0.1Hz 到 1kHz 采集速率: 250MS/s 【功能】 指示灯: 服务器电源灯： 蓝灯常亮：设备已上电； 蓝灯不亮：设备未上点； 服务器HDD指示灯： 蓝灯闪烁：有数据传输； 蓝灯不亮：无数据传输 蜂鸣器: 服务器触发报警或防拆报警，蜂鸣器长鸣 按键: 服务器: 1个船型开关； 1个关机按键 【用户】 安装员: 1个 管理员: 1个 普通用户: 若干 【存储】 硬盘存储: 支持1个256G SSD和1个1T机械硬盘 【接口】 电源接口: 1个220V电源接口 功能接口: 6个USB 3.0接口； 2个RJ45 1000M自适应以太网接口； 1个VGA接口； 1个HDMI接口； 1个DVI接口； 2个RS232接口； 3个SMA接口 音频输入: 1个音频输入输出接口 【一般规范】 电源: 服务器：220V～50Hz, 1.0A 处理器：220V～50Hz, 1.0A 整机功耗: 60W 工作温度: -15℃~55℃ 工作湿度: 0~93%（±2%）无凝露 材质: 全金属 颜色: 黑色 产品尺寸: 服务器：186mm（高）*483mm（宽）*475mm（深） 处理器：145mm （高）x 483mm （宽）x 498mm (深） 裸机重量: 服务器：约15kg 处理器：约10kg 激光防护等级: Class 1 包装尺寸: 服务器：370 mm (高）x 660 mm（宽） x 650 mm (深) 处理器：270mm（高） x 615 mm（宽） x 635 mm（深） 【协议】 网络协议: 支持ISAPI、OTAP、TCP 【通信参数】 通信方式: 支持有线网络 | K70: 响应 | M70: 412 | N70: =E70*M70 -> 412 | O70: 248613 | P70: =E70*O70 -> 248613 | Q70: =ROUND((M70+O70)*E70,2) -> 249025
A71: 3 | B71: 抗紫外线扎带 | C71: 1.安装方式: 将扎线带尾巴穿过头部，即可束紧。 2.尺寸规格: 5*300mm 3.最大承受拉力: 200N±15N 4.包装数量: 250根/包 5.耐温: -40℃ ~ +80℃ 6.材料: 尼龙PA66抗紫外线（UV）原料 | D71: 福科斯、广拓、海康 | E71: 323 | F71: 包 | H71: 海康 | I71: DS-PO2-CTS/UV5300 | J71: 抗紫外线扎带 材质：NYLON PA66 制成，抗紫外线，低温脆化高温不软化，承受力强，不易老化。 特点：耐候原料（抗紫外线），适合户外使用。 用法：止退式设计，束紧后便不可退出。 【常规参数】 安装方式: 将扎线带尾巴穿过头部，即可束紧。 【基本参数】 尺寸规格: 5*300mm 最大承受拉力: 200N±15N 包装数量: 250根/包 耐温: -40℃ ~ +80℃ 材料: 尼龙PA66抗紫外线（UV）原料 | K71: 响应 | M71: 113.3 | N71: =E71*M71 -> 36595.9 | O71: 44.06 | P71: =E71*O71 -> 14231.38 | Q71: =ROUND((M71+O71)*E71,2) -> 50827.28
A72: 4 | B72: 光纤接续盒 | C72: 1.光纤接续盒 2.材质：ABS工程塑料 3.规格：进出缆数，二进二出 | D72: 福科斯、广拓、海康 | E72: 9 | F72: 只 | H72: 海康 | I72: DS-PO2-UG/ABS | J72: 光纤接续盒 材质：ABS工程塑料 规格：进出缆数，二进二出 【常规参数】 尺寸(宽x高x深): 460mm*170mm*110mm 外壳材质: ABS工程塑料 | K72: 响应 | M72: 131.84 | N72: =E72*M72 -> 1186.56 | O72: 163.64 | P72: =E72*O72 -> 1472.76 | Q72: =ROUND((M72+O72)*E72,2) -> 2659.32
A73: 5 | B73: 塑料格栅 | C73: 1.塑料格栅是用于埋地方式部署振动光纤时，用于埋地时承载探测光缆的承载物 2.尺寸(宽x高x深): 网格：3.2cm*3.5cm；边宽3.3mm；边厚：1.3mm | D73: 福科斯、广拓、海康 | E73: 8800 | F73: m2 | H73: 海康 | I73: DS-PO-PG | J73: 1.塑料格栅是用于埋地方式部署振动光纤时，用于埋地时承载探测光缆的承载物 2.尺寸(宽x高x深): 网格：3.2cm*3.5cm；边宽3.3mm；边厚：1.3mm | K73: 响应 | M73: 8.76 | N73: =E73*M73 -> 77088 | O73: 8.39 | P73: =E73*O73 -> 73832 | Q73: =ROUND((M73+O73)*E73,2) -> 150920
A74: 6 | B74: 周界防范大模型超脑 | C74: 1.存储接口：1个SATA接口，内置1TB硬盘 2.视频接口：1×HDMI，1×VGA 3.网络接口：2×RJ45 10/100/1000Mbps自适应以太网口 4.报警接口：4路报警输入，1路报警输出 5.串行接口：1路RS-232接口、1路RS-485接口 6.USB接口：1×USB 2.0，1×USB 3.0 7.整机搭载2颗高性能AI引擎，支持周界防范引擎模式 8.周界防范应用：支持对平台下发图片进行二次分析，检测图片中的人体，车辆目标，并将分析结果回传平台；图片流性能：4张/s；单颗AI引擎分析能力：2张/s | D74: 福科斯、广拓、海康 | E74: 1 | F74: 台 | H74: 海康 | I74: iDS-6716NX/S-ZD | J74: 1盘位1.5U嵌入式边缘计算主机，采用存算一体架构，内置高性能AI处理器 【硬件规格】 存储接口：1个SATA接口，内置1TB硬盘 视频接口：1×HDMI，1×VGA 网络接口：2×RJ45 10/100/1000Mbps自适应以太网口 报警接口：4路报警输入，1路报警输出 串行接口：1路RS-232接口、1路RS-485接口 USB接口：1×USB 2.0，1×USB 3.0 【智能应用】 整机搭载2颗高性能AI引擎，支持周界防范引擎模式 一、周界防范应用： 支持对平台下发图片进行二次分析，检测图片中的人体，车辆目标，并将分析结果回传平台； 图片流性能：4张/s 单颗AI引擎分析能力：2张/s | K74: 响应 | M74: 216.3 | N74: =E74*M74 -> 216.3 | O74: 8077.3 | P74: =E74*O74 -> 8077.3 | Q74: =ROUND((M74+O74)*E74,2) -> 8293.6
A75: 7 | B75: 振动光纤接入管理软件 | C75: 一、设备管理 1、支持以海康ISAPI协议接入，实现振动光纤单元采集的事件接收； 2、支持根据单元号、振动光纤主机名称查询振动光纤单元报警信息； 3、支持在地图上展示振动光纤实际部署位置、有效长度； 4、支持以列表方式展示振动设备信息，包含设备名称、IP等信息； 5、支持对振动光纤主机设备添加、删除、修改； 6、支持对振动光纤主机设备进行手动校时； 7、支持筛选出从未被平台连接成功的振动光纤主机设备。 二、光纤标定 1、支持通过振动曲线方式查询振动单元号，并支持与监控点位进行绑定； 2、支持通过导入导出的方式对单元号、监控点、经纬度进行绑定； 三、光纤上图 1、支持振动光纤主机上图，地图上可以查看主机的部署位置； 2、支持光纤上图，地图上可以查看光纤的铺设情况； 3、支持在地图上控制振动光纤的显示与隐藏； 4、支持查看振动光纤的主机数量、光纤长度（在线长度、离线长度）； 5、支持在地图上查看在线光纤分布及离线光纤分布情况； 6、支持在地图上查看光纤每个单元号与视频设备关联关系； 7、振动光纤报警时，支持在地图上高亮报警的光纤位置及关联球机高亮显示。 | D75: 福科斯、广拓、海康 | E75: 1 | F75: 套 | H75: 海康 | I75: 振动光纤接入管理软件 | J75: 一、设备管理 1、支持以海康ISAPI协议接入，实现振动光纤单元采集的事件接收； 2、支持根据单元号、振动光纤主机名称查询振动光纤单元报警信息； 3、支持在地图上展示振动光纤实际部署位置、有效长度； 4、支持以列表方式展示振动设备信息，包含设备名称、IP等信息； 5、支持对振动光纤主机设备添加、删除、修改； 6、支持对振动光纤主机设备进行手动校时； 7、支持筛选出从未被平台连接成功的振动光纤主机设备。 二、光纤标定 1、支持通过振动曲线方式查询振动单元号，并支持与监控点位进行绑定； 2、支持通过导入导出的方式对单元号、监控点、经纬度进行绑定； 三、光纤上图 1、支持振动光纤主机上图，地图上可以查看主机的部署位置； 2、支持光纤上图，地图上可以查看光纤的铺设情况； 3、支持在地图上控制振动光纤的显示与隐藏； 4、支持查看振动光纤的主机数量、光纤长度（在线长度、离线长度）； 5、支持在地图上查看在线光纤分布及离线光纤分布情况； 6、支持在地图上查看光纤每个单元号与视频设备关联关系； 7、振动光纤报警时，支持在地图上高亮报警的光纤位置及关联球机高亮显示。 | K75: 响应 | M75: 0 | N75: =E75*M75 -> 0 | O75: 5245 | P75: =E75*O75 -> 5245 | Q75: =ROUND((M75+O75)*E75,2) -> 5245
A76: 8 | B76: 周界监测预警软件 | C76: 一、光纤报警定位及处置 1、提供报警实时信息的展示及处置能力，； 2、支持实时报警信息展示，以及历史报警信息的查询和回看； 3、支持报警发生时报警信息弹窗，显示当前的报警信息以及报警联动信息，包括：视频、录像、抓图、报警位置。 二 、雷达轨迹 1、提供布防区域目标物的轨迹跟踪显示以及视频跟踪能力； 2、支持对布防区域内报警目标物体的轨迹跟踪和实时视频接力跟踪（仅雷达设备支持轨迹跟踪）； 3、支持目标物跟踪时，显示目标物的位置、速度、方向信息； 4、支持布防区域内单目标和多目标跟踪； 三、重点视频点位管理 1、提供地图上重点点位视频的布局配置、实时视频播放及广播能力； 2、支持显示重点点位实时视频，可以任意拖放具体位置。 四、预警策略编排 1、支持振动光纤联动、雷达联动、区域入侵等不同事件组合产生新组合预警。 2、支持组合预警发生的时间间隔配置。 3、支持事件的发生先后顺序进行配置。 4、支持配置组合策略生效的资源、时间。 五、图上数据展示 1、支持数据统计展示，可以自由拖放布局，包括：图上资源统计数据、报警统计数据、资源在线状态统计。 六、图上资源控制 1、支持地图上资源显示控制，包括：虚拟防区、监控点、岗亭、雷达、报警器、自定义资源等。 七、报警研判复核管理 1、从空间维度对报警进行处理，以虚拟防区为单位，对关联的物联设备的报警事件进行合并； 2、从时间维度对报警进行处理，提供周计划配置、有效期配置、临时失效时间配置等功能； 3、从报警的业务属性维度进行处理，例如温度报警的温度属性、雷达轨迹时间的速度属性。 八、预警事件管理 1、提供历史报警检索、报警统计报表。 | D76: 福科斯、广拓、海康 | E76: 1 | F76: 套 | H76: 海康 | I76: 周界监测预警软件 | J76: 一、光纤报警定位及处置 1、提供报警实时信息的展示及处置能力，； 2、支持实时报警信息展示，以及历史报警信息的查询和回看； 3、支持报警发生时报警信息弹窗，显示当前的报警信息以及报警联动信息，包括：视频、录像、抓图、报警位置。 二 、雷达轨迹 1、提供布防区域目标物的轨迹跟踪显示以及视频跟踪能力； 2、支持对布防区域内报警目标物体的轨迹跟踪和实时视频接力跟踪（仅雷达设备支持轨迹跟踪）； 3、支持目标物跟踪时，显示目标物的位置、速度、方向信息； 4、支持布防区域内单目标和多目标跟踪； 三、重点视频点位管理 1、提供地图上重点点位视频的布局配置、实时视频播放及广播能力； 2、支持显示重点点位实时视频，可以任意拖放具体位置。 四、预警策略编排 1、支持振动光纤联动、雷达联动、区域入侵等不同事件组合产生新组合预警。 2、支持组合预警发生的时间间隔配置。 3、支持事件的发生先后顺序进行配置。 4、支持配置组合策略生效的资源、时间。 五、图上数据展示 1、支持数据统计展示，可以自由拖放布局，包括：图上资源统计数据、报警统计数据、资源在线状态统计。 六、图上资源控制 1、支持地图上资源显示控制，包括：虚拟防区、监控点、岗亭、雷达、报警器、自定义资源等。 七、报警研判复核管理 1、从空间维度对报警进行处理，以虚拟防区为单位，对关联的物联设备的报警事件进行合并； 2、从时间维度对报警进行处理，提供周计划配置、有效期配置、临时失效时间配置等功能； 3、从报警的业务属性维度进行处理，例如温度报警的温度属性、雷达轨迹时间的速度属性。 八、预警事件管理 1、提供历史报警检索、报警统计报表。 | K76: 响应 | M76: 0 | N76: =E76*M76 -> 0 | O76: 5245 | P76: =E76*O76 -> 5245 | Q76: =ROUND((M76+O76)*E76,2) -> 5245
A77: 7 | B77: 土方开完及回填 | C77: 现场开挖回填 | E77: 3500 | F77: m | I77: 土方开完及回填 | J77: 现场开挖回填 | K77: 响应 | M77: 41.2 | N77: =E77*M77 -> 144200 | O77: 0 | P77: =E77*O77 -> 0 | Q77: =ROUND((M77+O77)*E77,2) -> 144200
A78: 8 | B78: 绿化破坏恢复 | C78: 绿化破坏恢复 | E78: 2000 | F78: 平方米 | I78: 绿化破坏恢复 | J78: 绿化破坏恢复 | K78: 响应 | M78: 32.96 | N78: =E78*M78 -> 65920 | O78: 26.23 | P78: =E78*O78 -> 52460 | Q78: =ROUND((M78+O78)*E78,2) -> 118380
B79: 2.5、红外对射报警 | N79: =E79*M79 -> 0 | P79: =E79*O79 -> 0
A80: 1 | B80: 四光束红外对射 | C80: 1.探测方式：主动红外 2.警戒距离：100米 3.光源类型：红外数字脉冲 4.光源波长：940nm 5.光束频率：750Hz 6.光轴角度：水平180°(±90°)；垂直 20°(±10°) 7.感应速度：50-700ms 8.防拆输出：NC 触点容量 DC30V0.5A max 9.光束数量：4光束 10.报警输出接口：NC/NO 触点容量 DC30V0.5A max 11.防护等级：IP55 12.工作温度及湿度：-25℃~+55℃；≤95%（无凝结） 13.产品重量：2265g（毛重） 14.产品尺寸：370mm*96mm*95mm 15.外壳材质：PC(外罩)+ABS(本体) 16.工作电压：DC12-24V / AC12-18V 17.工作电流：投光器+受光器≤130mA 18.最大功率：≤5W 19.含配套支架 | D80: 福科斯、广拓、海康 | E80: 11 | F80: 对 | H80: 海康 | I80: DS-PB401-4100 | J80: 四光束红外对射 采用抗白光凸透镜、抗太阳光外罩和滤光接收管，提升抗外光及恶劣环境干扰能力。 采用优质红外发射管和光学双凸透镜设计，提高发射功率和光束聚焦能力，增强信号强度、发射距离更远。 支持5种响应模式调整，防宠、防树叶遮挡误报能力更优。 宽电压设计，支持DC12-24V和AC12-18V，兼容集中供电，有效解决线路降压。 报警输出支持NO/NC两种干节点模式，系统融合更便捷。 内置防拆开关（常闭型），当外壳被拆开时触发警报。 光轴支持水平大角度、垂直多角度调整，方便对光，施工便捷高效。 双数码管实时呈现对光信号强度，施工便捷高效。 探测方式：主动红外 警戒距离：100米 光源类型：红外数字脉冲 光源波长：940nm 光束频率：750Hz 光轴角度：水平180°(±90°)；垂直 20°(±10°) 感应速度：50-700ms 防拆输出：NC 触点容量 DC30V0.5A max 光束数量：4光束 报警输出接口：NC/NO 触点容量 DC30V0.5A max 防护等级：IP55 工作温度及湿度：-25℃~+55℃；≤95%（无凝结） 产品重量：2265g（毛重） 产品尺寸：370mm*96mm*95mm 外壳材质：PC(外罩)+ABS(本体) 工作电压：DC12-24V / AC12-18V 工作电流：投光器+受光器≤130mA 最大功率：≤5W | K80: 响应 | M80: 164.8 | N80: =E80*M80 -> 1812.8 | O80: 650.38 | P80: =E80*O80 -> 7154.18 | Q80: =ROUND((M80+O80)*E80,2) -> 8966.98
A81: 2 | B81: 工控箱 | C81: 配套工控箱 | D81: 福科斯、广拓、海康 | E81: 6 | F81: 台 | H81: 海康 | I81: DS-PB-WPB01S | J81: 红外对射工控箱（不锈钢） 周界报警对射类产品户外弱电施工工控箱，工业级防护。 内置工业级漏电保护模块，施工、检修安全保障。 内置工业级浪涌防护模块，有效降低感应雷、浪涌电流对内接弱电设备的损害，保障其稳定运行。 内置工业级开关电源模块，为红外对射发射、接收端以及其他配套外设提供直流供电。 总供电输出规格：DC12V 2路；DC24V 4路 输出电流：1.5A Max 输出功率：30W Max 总供电输出保护：漏电防护：额定电压(V)：230/400 AC 额定电流(A)：16A 额定频率(Hz)：50/60 数 量：1个 （2P） 浪涌防护：额定电压：230V（相电压） 最大放电电流：20KA 响应时间：＜ 25ns 数 量：1个（2P） Ancillary Control Equipment (ACE)：接线端子：进线范围：10-35平方 出线范围：2.5-16平方 适用电流：100A 导件材质：黄铜镀锡 端口数量：1进2出 工作湿度：10%~90% （相对湿度，无冷凝） 工作温度：-20℃~+55℃ IP等级：IP55 安装方式：支持壁挂、抱箍、落地等三种安装方式 外壳材质：304不锈钢，壁厚 0.8mm±0.15mm 尺寸（宽 × 高 × 深）：含有帽沿（高*宽*深）：300mm*248mm*180mm 不含帽沿（高*宽*深）：300mm*248mm*160mm 重量：3.9Kg±0.2Kg | K81: 响应 | M81: 164.8 | N81: =E81*M81 -> 988.8 | O81: 514.01 | P81: =E81*O81 -> 3084.06 | Q81: =ROUND((M81+O81)*E81,2) -> 4072.86
A82: 3 | B82: 总线报警主机 | C82: 1.具有规定权限的用户应能对控制指示设备进行全部和/或部分设防操作。设防成功后，控制指示设备应有相应的指示。设防失败时，控制指示设备应能立即给出指示和/或报警信号和/或信息。 2.当控制指示设备的多个探测回路依次或同时被触发时，不应产生漏报警。 3.告警装置安装在机内时，报警声压应不小于80dB(A)，告警装置安装在机外时，报警声压应不小于100dB(A)。 4.控制指示设备在开机后，应能进行自检，并给出自检结果指示。 5.控制指示设备应具有主电源和备用电源，应能在主电源和备用电源之间转换，电源转换时，工作应正常，不应出现漏报警及误报警:当主电源断电时，应能自动转换至备用电源供电;当主电源恢复时，可自动转换至主电源供电，并对备用电源自动充电:在给备用电源充电的同时，工作应正常。 6.主机支持 MAC、IP 绑定或限制访问 7.主机防拆报警不额外占用主机防区 8.主机上报支持至少4个中心组 | D82: 福科斯、广拓、海康 | E82: 1 | F82: 台 | H82: 海康 | I82: DS-19A08-01BN | J82: 总线报警主机 报警管理：支持探测器/紧急报警装置触发信号的接收，进行入侵/紧急报警事件管理 防区特性：支持即时防区、延时防区、紧急防区、超时防区等场景化防区类型设置，满足细致化管理需求 分区管理：支持子系统分区，对探测器进行分区管理，支持布防、撤防、消警、旁路等功能 报警指示：支持报警键盘、警号、继电器联动、中心平台上报等报警事件指示功能 操作管理：支持报警键盘、客户端软件、中心平台进行报警管理操作 联动控制：支持报警事件联动，平台控制报警输出，实现场景化联动输出，进行个性化管理 断电报警：当市电断电时，设备可通过蓄电池正常工作（需配蓄电池），并将断电事件进行通知上报 断网续传：支持断网续传功能，设备离线状态下产生事件在与平台连接后会重新上传 快速移机：支持设备配置文件导出和导入功能，实现参数备份和快速移机 配置方式：iVMS-4200、键盘编程、SADP 操作系统：Linux 日志存储：40000条 系统校时：手动校时、NTP校时 子系统：8个 公共子系统：支持 板载防区：8路 扩展防区：最大可扩展248路（其中无线防区上限为64个） 板载警号输出：1路 板载继电器输出：4路 扩展输出：最大可扩展252路 键盘：32个 总线中继器：4个，单条总线最多2个 遥控器：32个（需搭配报警键盘支持） 卡片：32张（需搭配报警键盘支持） 总线类型：M-BUS 总线拓扑：手拉手 总线距离：2400m，每增加一个中继器延长2400m，单条线路最多增加2个中继器 总线线型：RVV2*1.5mm² 网络协议：SDK、NAL2300 接口协议：PSTN-CID 主电源：AC220V 电池接口：铅酸蓄电池接口x1 辅电输出：DC12V/1A 警号接口：1路 防区输入接口：8路 报警输出接口：4路 总线接口：2路 RS-485接口：1路 网络接口：1路，支持扩展 4G模块接口：1路，模块按需选配 电话线模块接口：1路，模块出厂标配 打印机接口：1路 使用场景：室内 安装方式：壁挂 供电方式：AC 220 V （出厂自带电源适配器转14.3V） 额定功率：5W（设备单机功率） 最大功率：60W (系统外设辅电满载) 颜色：白色 外壳材质：金属 认证等级：GA：4级 产品重量：≤3.5kg 产品尺寸：370mm（长）×320mm（宽）×86mm（厚） 工作温度及湿度：-10°C~55°C，湿度小于90%（无凝结） 存储温度及湿度：-25°C~60C，湿度小于90%（无凝结） | K82: 响应 | M82: 131.84 | N82: =E82*M82 -> 131.84 | O82: 1678.4 | P82: =E82*O82 -> 1678.4 | Q82: =ROUND((M82+O82)*E82,2) -> 1810.24
A83: 4 | B83: 控制键盘 | C83: 1.有线LCD键盘（支持遥控器&刷卡） 2.操作指令接收：支持对报警系统进行布防、撤防、消警、旁路、旁路恢复、紧急求助等操作 3.操作方式管理：支持密码、遥控器、刷卡方式对报警系统进行操作指令交互 4.报警状态指示：支持对报警系统防区报警状态进行实时指示，包括指示灯变化，提示音变化，文字内容变化等 5.系统状态展示：支持对报警系统运行状态进行展示，包括主电源状态、蓄电池状态、防拆状态、子系统布撤防状态，防区状态、扩展模块状态等 6.胁迫码功能：支持通过胁迫密码进行布撤防管理，并将警情进行中心上报 7.防区名称自定义：支持防区名称自定义配置，在键盘屏幕中展示对应文字内容 8.配置管理：支持通过键盘对报警主机进行参数配置，包括密码修改、防区类型配置、上报中心参数配置等 | D83: 福科斯、广拓、海康 | E83: 1 | F83: 台 | H83: 海康 | I83: DS-PK-LRT | J83: 有线LCD键盘（支持遥控器&刷卡） 操作指令接收：支持对报警系统进行布防、撤防、消警、旁路、旁路恢复、紧急求助等操作 操作方式管理：支持密码、遥控器、刷卡方式对报警系统进行操作指令交互 报警状态指示：支持对报警系统防区报警状态进行实时指示，包括指示灯变化，提示音变化，文字内容变化等 系统状态展示：支持对报警系统运行状态进行展示，包括主电源状态、蓄电池状态、防拆状态、子系统布撤防状态，防区状态、扩展模块状态等 胁迫码功能：支持通过胁迫密码进行布撤防管理，并将警情进行中心上报 防区名称自定义：支持防区名称自定义配置，在键盘屏幕中展示对应文字内容 配置管理：支持通过键盘对报警主机进行参数配置，包括密码修改、防区类型配置、上报中心参数配置等 操作系统：Linux 显示屏：LCD（尺寸80X25mm） 指示灯：5个 按键数量：20个 蜂鸣器：支持 遥控器：支持 卡片：支持 无线频率：RF433Mhz 双向无线通讯：支持 跳频技术：支持 无线加密：AES128 总线类型：RS485 总线距离：800米 总线线型：RVV4*1.0mm² 主电源：DC 12 V RS-485接口：1路 使用场景：室内 安装方式：壁挂 供电方式：DC 12 V 额定功率：1.2W 最大功率：1.8W 颜色：白色 外壳材质：塑料 产品重量：≤0.28 kg 产品尺寸：164 mm（宽）× 124 mm（深）× 31 mm（高） 工作温度及湿度：-10°C~55°C，湿度小于90%（无凝结） 存储温度及湿度：-20°C~60C，湿度小于90%（无凝结） | K83: 响应 | M83: 56.65 | N83: =E83*M83 -> 56.65 | O83: 225.54 | P83: =E83*O83 -> 225.54 | Q83: =ROUND((M83+O83)*E83,2) -> 282.19
A84: 5 | B84: 报警主机蓄电池 | C84: 1.电池类型：阀控密封式铅酸蓄电池 2.电池规格：DC12V7AH 3.停止供电电压：10.5V 4.电池放电温度及湿度：-20°C~50°C，湿度小于95%（无凝结） 5.电池充电温度及湿度：-20°C~50°C，湿度小于95%（无凝结） 6.安装方式：立式 7.颜色：黑色 8.外壳材质：ABS阻燃（V-1） 9.产品重量：2.0±3%Kg 10.产品尺寸：151mm*65mm*100mm 11.工作温度及湿度：-20°C~50°C，湿度小于95%（无凝结） | D84: 福科斯、广拓、海康 | E84: 1 | F84: 台 | H84: 海康 | I84: DS-PZ101VB-1207 | J84: 电池类型：阀控密封式铅酸蓄电池 电池规格：DC12V7AH 停止供电电压：10.5V 电池放电温度及湿度：-20°C~50°C，湿度小于95%（无凝结） 电池充电温度及湿度：-20°C~50°C，湿度小于95%（无凝结） 安装方式：立式 颜色：黑色 外壳材质：ABS阻燃（V-1） 产品重量：2.0±3%Kg 产品尺寸：151mm*65mm*100mm 工作温度及湿度：-20°C~50°C，湿度小于95%（无凝结） " | K84: 响应 | M84: 412 | N84: =E84*M84 -> 412 | O84: 79.72 | P84: =E84*O84 -> 79.72 | Q84: =ROUND((M84+O84)*E84,2) -> 491.72
A85: 6 | B85: 警灯警号 | C85: 1.设备类型：声光警号（声光报警器） 2.警灯颜色：红色 3.报警音量：105dB 4.硬件接口：红/黑线 5.使用环境：室内/外（IP54室外防水） 6.外壳材质：PC+ABS 7.安装方式：壁挂 8.工作电源：DC12V/220mA（宽压8-16V DC） 9.工作温度：-20 °C 至 60 °C 10.工作湿度：10% 至 90% 11.产品尺寸：140*134*33mm | D85: 福科斯、广拓、海康 | E85: 1 | F85: 个 | H85: 海康 | I85: DS-PS1-R | J85: 【技术参数】 1、设备类型：声光警号（声光报警器） 2、警灯颜色：红色 3、报警音量：105dB 4、硬件接口：红/黑线 5、使用环境：室内/外（IP54室外防水） 6、外壳材质：PC+ABS 7、安装方式：壁挂 8、工作电源：DC12V/220mA（宽压8-16V DC） 9、工作温度：-20 °C 至 60 °C 10、工作湿度：10% 至 90% 11、产品尺寸：140*134*33mm 【产品功能】 1、声光报警：提供警灯闪烁和报警音频输出，用于提示警情处置 2、模式切换：支持关闭报警音频输出，仅提供警灯闪烁模式输出 3、内置水平仪：可通过内置水平仪调节安装角度，方便调试安装" " | K85: 响应 | M85: 32.96 | N85: =E85*M85 -> 32.96 | O85: 47.21 | P85: =E85*O85 -> 47.21 | Q85: =ROUND((M85+O85)*E85,2) -> 80.17
A86: 7 | B86: 总线2防区扩展模块 | C86: 1.设备类型：总线2防区扩展模块 2.防区数量：2个 3.通讯接口：M-BUS 4.通讯线材：RVV2*1.5 5.通讯协议：M-BUS协议 6.外壳材质：塑料 7.使用环境：室内 8.工作电源：DC36V/20mA Max（主机总线供电） 9.工作温度：-10 °C 至 55 °C 10.工作湿度：10% 至 90% 11.产品尺寸：49.4*32*14.3mm | D86: 福科斯、广拓、海康 | E86: 11 | F86: 台 | H86: 海康 | I86: DS-19M02-ZS | J86: 【技术参数】 1、设备类型：总线2防区扩展模块 2、防区数量：2个 3、通讯接口：M-BUS 4、通讯线材：RVV2*1.5 5、通讯协议：M-BUS协议 6、外壳材质：塑料 7、使用环境：室内 8、工作电源：DC36V/20mA Max（主机总线供电） 9、工作温度：-10 °C 至 55 °C 10、工作湿度：10% 至 90% 11、产品尺寸：49.4*32*14.3mm 【产品功能】 1、防区扩展：通过RVV线方式接入报警主机，扩展2路有线防区 2、总线无极性：总线接口不区分极性，方便施工安装 3、地址设置：通过拨码方式设置模块地址，拨码地址不能重复 | K86: 响应 | M86: 21.63 | N86: =E86*M86 -> 237.93 | O86: 89.17 | P86: =E86*O86 -> 980.87 | Q86: =ROUND((M86+O86)*E86,2) -> 1218.8
A87: 8 | B87: 入侵报警软件 | C87: 1、支持报警子系统管理能力，包含布防、撤防、消警控制操作； 2、支持防区管理能力，包含旁路、旁路恢复操作； 3、支持实时入侵报警能力； 4、支持历史入侵报警事件查询及导出能力； | D87: 福科斯、广拓、海康 | E87: 1 | F87: 台 | H87: 海康 | I87: 入侵报警软件 | J87: 1、支持报警子系统管理能力，包含布防、撤防、消警控制操作； 2、支持防区管理能力，包含旁路、旁路恢复操作； 3、支持实时入侵报警能力； 4、支持历史入侵报警事件查询及导出能力； | K87: 响应 | M87: 0 | N87: =E87*M87 -> 0 | O87: 1049 | P87: =E87*O87 -> 1049 | Q87: =ROUND((M87+O87)*E87,2) -> 1049
A88: 9 | B88: 信号线 | C88: 国标，RVV2*1.5 | D88: 一舟、普天天纪、罗格朗 | E88: 2400 | F88: m | H88: 一舟 | I88: RVV2*1.5 | J88: 国标，RVV2*1.5 | K88: 响应 | M88: 2.16 | N88: =E88*M88 -> 5184 | O88: 4.41 | P88: =E88*O88 -> 10584 | Q88: =ROUND((M88+O88)*E88,2) -> 15768
A89: 10 | B89: 信号线 | C89: 国标，RVV4*0.75 | D89: 一舟、普天天纪、罗格朗 | E89: 200 | F89: m | H89: 一舟 | I89: RVV4*0.75 | J89: 国标，RVV4*0.75 | K89: 响应 | M89: 2.37 | N89: =E89*M89 -> 474 | O89: 4.56 | P89: =E89*O89 -> 912 | Q89: =ROUND((M89+O89)*E89,2) -> 1386
A90: 11 | B90: JDG20管 | C90: JDG管，壁厚不小于1.0MM,φ20；含主材、接头、固定扣件（含钢结构扣件）等辅材 | D90: 国产 | E90: 1000 | F90: m | H90: 国产 | I90: JDG20 | J90: JDG管，壁厚不小于1.0MM,φ20；含主材、接头、固定扣件（含钢结构扣件）等辅材 | K90: 响应 | M90: 9.79 | N90: =E90*M90 -> 9790 | O90: 3.67 | P90: =E90*O90 -> 3670 | Q90: =ROUND((M90+O90)*E90,2) -> 13460
B91: 2.6、其它硬件 | N91: =E91*M91 -> 0 | P91: =E91*O91 -> 0
A92: 1 | B92: 全局网络控制器 | C92: 1.名称：全局网络控制器 2.参数：单核 A8@1GHz，1GB DDR3 / 4GB microSD，2× 百兆，2×RS-485，可扩展4 个 I/O/ 现场总线模块。协议：BACnet IP/MS/TP + Modbus TCP/RTU + LonWorks + KNX + SNMP + oBIX，编程：Niagara 图形化编程，功能极强，适合复杂联锁 / 算法。满足现场现场功能所需的点位授权费 | D92: 霍尼韦尔、江森、西门子 | E92: 1 | F92: 台 | H92: 霍尼韦尔 | I92: ECC200-PE | J92: 边缘网络控制器，3条RS485总线；支持编程数据管理等功能 | K92: 响应 | M92: 131.84 | N92: =E92*M92 -> 131.84 | O92: 7240.88 | P92: =E92*O92 -> 7240.88 | Q92: =ROUND((M92+O92)*E92,2) -> 7372.72
A93: 2 | B93: 可编程网络控制器 | C93: 通讯接口：100M以太网，双网口 协议：BACnetIP/Modbus-TCP 扩展接口通讯：控制器内部协议 DI输入接口：数量最大24路，干接点接入 DO控制接口：8路，继电器负载能力2A/30VDC UI输入接口：最大16路，支持电阻型温度NTC20K，电压型湿度0~10V，电压型CO2,0~10V，电压型CO 0~10V,电流型水压4~20mA，电流型流量计4~20mA，执行器0~10V和2~10V反馈 AO输出接口：8路，支持4~20mA和0~10V输出 RS485接口数量：2个，其中一个支持多合一传感器接入，另外一路备用 支持PLC功能，支持PLC逻辑编程 尺寸：225x115x 57mm 外壳原料： UL 94 ABS 电源：DC24V/3A 重量：500g | D93: 霍尼韦尔、江森、西门子 | E93: 9 | F93: 台 | H93: 霍尼韦尔 | I93: WEBs系列控制器 | J93: 通讯接口：100M以太网，双网口 协议：BACnetIP/Modbus-TCP 扩展接口通讯：控制器内部协议 DI输入接口：数量最大24路，干接点接入 DO控制接口：8路，继电器负载能力2A/30VDC UI输入接口：最大16路，支持电阻型温度NTC20K，电压型湿度0~10V，电压型CO2,0~10V，电压型CO 0~10V,电流型水压4~20mA，电流型流量计4~20mA，执行器0~10V和2~10V反馈 AO输出接口：8路，支持4~20mA和0~10V输出 RS485接口数量：2个，其中一个支持多合一传感器接入，另外一路备用 | K93: 响应 | M93: 32.96 | N93: =E93*M93 -> 296.64 | O93: 7424.7 | P93: =E93*O93 -> 66822.3 | Q93: =ROUND((M93+O93)*E93,2) -> 67118.94
A94: 3 | B94: 可编程控制盘 | C94: 1、包含、空开、导轨及接线端子 2、国产优质箱体，根据实际安装设备测量后成套定制 | D94: 霍尼韦尔、江森、西门子 | E94: 9 | F94: 台 | H94: 定制 | I94: DDC-Panel-XL | J94: 1、包含：空开、导轨及接线端子 2、国产优质箱体，根据实际安装设备测量后成套定制 | K94: 响应 | M94: 164.8 | N94: =E94*M94 -> 1483.2 | O94: 1485.31 | P94: =E94*O94 -> 13367.79 | Q94: =ROUND((M94+O94)*E94,2) -> 14850.99
A95: 4 | B95: 电源模块 | C95: 输入：85–264VAC（全球宽压），50/60Hz 输出：24VDC 可调（约 24–26V） 电流：1.3A / 2.5A / 4A（常用 4A 配 DDC） 保护：过压、短路、过载、过热（自恢复） EMC：EN61000-6-2、EN61000-4 系列，工业级 安装：35mm DIN 导轨 外壳：UL94 V-0 阻燃塑料 工作温度：-20℃ ~ +60℃ | D95: 霍尼韦尔、江森、西门子 | E95: 9 | F95: 台 | H95: 同方泰德 | I95: 24VDC | J95: 输入：85–264VAC（全球宽压），50/60Hz 输出：24VDC 可调（约 24–26V） 电流：1.3A / 2.5A / 4A（常用 4A 配 DDC） 保护：过压、短路、过载、过热（自恢复） EMC：EN61000-6-2、EN61000-4 系列，工业级 安装：35mm DIN 导轨 外壳：UL94 V-0 阻燃塑料 工作温度：-20℃ ~ +60℃ | K95: 响应 | M95: 21.63 | N95: =E95*M95 -> 194.67 | O95: 102.8 | P95: =E95*O95 -> 925.2 | Q95: =ROUND((M95+O95)*E95,2) -> 1119.87
A96: 5 | B96: 水浸变送器 | C96: 漏水探测器;固定电极式;可设置 5 级灵敏度;继电器：1×SPST(3A-30VDC 或 250VAC) 工作环境：-10~50°C，5~95%RH，非凝露 | D96: 霍尼韦尔、江森、西门子 | E96: 39 | F96: 台 | H96: 霍尼韦尔 | I96: RS-48 | J96: 漏水探测器;固定电极式;可设置 5 级灵敏度;继电器：1×SPST(3A-30VDC 或 250VAC) 工作环境：-10~50°C，5~95%RH，非凝露 | K96: 响应 | M96: 154.5 | N96: =E96*M96 -> 6025.5 | O96: 240.22 | P96: =E96*O96 -> 9368.58 | Q96: =ROUND((M96+O96)*E96,2) -> 15394.08
A97: 6 | B97: 噪声监测传感器 | C97: 量程：30~120dBA（A 计权）。 精度：±0.5dB，分辨率 0.1dB。 频率：20Hz~12.5kHz。 供电：10~30VDC（建议 24V）。 防护：IP65，室外可用 输出信号为 0-10V。 | D97: 国产一线品牌 | E97: 14 | F97: 台 | H97: 国产一线品牌 | J97: 量程：30~120dBA（A 计权）。 精度：±0.5dB，分辨率 0.1dB。 频率：20Hz~12.5kHz。 供电：10~30VDC（建议 24V）。 防护：IP65，室外可用 输出信号为 0-10V。 | K97: 响应 | M97: 154.5 | N97: =E97*M97 -> 2163 | O97: 352.46 | P97: =E97*O97 -> 4934.44 | Q97: =ROUND((M97+O97)*E97,2) -> 7097.44
A98: 7 | B98: 光纤熔接盒（含光纤熔纤） | C98: SC4芯单模满配含熔接尾纤、法兰、SC光跳线 | D98: 一舟、普天天纪、罗格朗 | E98: =E92+E93 -> 10 | F98: 个 | H98: 一舟 | I98: S953-4X+ 4*S905-3+ 4*S812+ 2*S922 | J98: 含4个SC单工耦合器，4条SC单芯单模尾纤，2条SC-SC双芯单模跳纤 | K98: 响应 | M98: 97.85 | N98: =E98*M98 -> 978.5 | O98: 111.19 | P98: =E98*O98 -> 1111.9 | Q98: =ROUND((M98+O98)*E98,2) -> 2090.4
A99: 8 | B99: 光纤收发器 | C99: 1个10/100M/1000M网口，1个1000Mbps光口（SC），工作波长：1550nm（发送）、1310nm（接收），20km。 | D99: TP-LINK、山泽、烽火 | E99: =E92+E93 -> 10 | F99: 对 | H99: 普联 | I99: TL-FC311A-3 | J99: 普联（TP-LINK）TL-FC311A-3千兆单模单纤光纤收发器 光电转换器SC单芯3km（单只装） | K99: 响应 | M99: 32.96 | N99: =E99*M99 -> 329.6 | O99: 182.53 | P99: =E99*O99 -> 1825.3 | Q99: =ROUND((M99+O99)*E99,2) -> 2154.9
A100: 9 | B100: 光纤收发器架 | C100: 14槽光纤收发器机架；标准机柜安装； | D100: TP-LINK、山泽、烽火 | E100: 1 | F100: 个 | H100: 普联 | I100: TL-FC1400 | J100: 普联（TP-LINK） TL-FC1400单模多模光纤收发器14槽机架单纤双纤光电转换器整理箱机柜2U机箱 | K100: 响应 | M100: 87.55 | N100: =E100*M100 -> 87.55 | O100: 543.38 | P100: =E100*O100 -> 543.38 | Q100: =ROUND((M100+O100)*E100,2) -> 630.93
...

Sheet 附录五硬件场景需求表
A1: 项目范围 | B1: 系统 | C1: 序号 | D1: 设施设备 | E1: 数量 | F1: 涉及硬件类型
A2: 智慧消防系统 | B2: 消防水系统 | C2: 1 | D2: 消防水池 | E2: 水池数量 | F2: 水位仪传感器7个（包括电动力1个）
C3: 2 | D3: 消防水箱 | E3: 水箱数量 | F3: 水位仪传感器6个（包括电动力1个）、出水管流量传感器12个（包括电动力2个）
C4: 3 | D4: 消防泵/喷淋泵 | E4: 泵数量 | F4: 电气监控28个（包括电动力4个）
C5: 4 | D5: 稳压泵 | E5: 泵数量 | F5: 电气监控、启停状态/次数监测28个（包括电动力4个）
C6: 5 | D6: 隔膜气压罐 | E6: 罐体数量 | F6: 14个（包括电动力2个）
C7: 6 | D7: 配电柜 | E7: 柜体数量 | F7: 电气监控9个（包括电动力2个）
C8: 7 | D8: 控制柜 | E8: 柜体数量 | F8: 电气监控、远程手自动变更28个（包括电动力4个）
C9: 8 | D9: 消防测试栓 | E9: 屋面测试栓数量 | F9: 压力传感器 30
C10: 9 | D10: 末端测试 | E10: 末端数量 | F10: 压力传感器 200
C11: 10 | D11: 消防泵房 | E11: 泵房数量 | F11: 9个（包括电动力2个消防泵房/稳压泵房）
C12: 11 | D12: 进水阀 | E12: 水池、水箱水量 | F12: 流量计、压力传感器13个（包括电动力2个）
C13: 12 | D13: 关键管路（进出水主管） | E13: 进出水管数量 | F13: 阀门启闭状态检测、压力传感器、流量监测（50个阀门启闭状态、压力传感器、流量监测）
C14: 13 | D14: 湿式报警阀\预作用阀 | E14: 报警阀数量 | F14: 上下腔压力监测、判断，水力警铃传感69个报警阀、69个水力警铃
... C16: 15 | D16: 消防水炮主机 | E16: 水炮数量 | F16: 电磁阀启动信号 2
B17: 全淹没气灭 | C17: 16 | D17: 环境检测 | E17: 全淹没房间数量 | F17: 氧浓度监测接入消防平台 33个
C18: 17 | D18: 电磁阀、泄压口 | E18: 瓶体数量 | F18: 压力传感器/电磁阀启动监测（100个）
B19: 排烟系统 | C19: 18 | D19: 排烟风机 | E19: 风机数量 | F19: 排烟风速计量（含风向）110
C20: 19 | D20: 电动挡烟垂壁 | E20: / | F20: 释放状态
B21: 防火卷帘 | F21: 释放状态
B22: 排水系统 | C22: 20 | D22: 雨水截止阀 | F22: 自动灭火后联动对应雨水截止阀关闭
C23: 21 | D23: 关键机房、泵房排水泵 | E23: 水泵数量 | F23: 启闭监测 24个（6个消防泵房）
C24: 22 | D24: 关键机房、泵房 | F24: 防水浸监测（10个）
B25: 可燃气体 | C25: 23 | D25: 可燃气体报警主机 | E25: 主机数量 | F25: 可燃气体报警主机接入消防平台 8个
C26: 24 | D26: 可燃气体管路 | E26: 燃气管道数量 | F26: 燃气、压缩空气等管道加装可联动电磁阀 （2个）
B27: 电气火灾监控 | F27: 在线电压、剩余电流检测、电缆温度检测 数量太多400+
B28: 视频监控系统 | C28: 25 | D28: 自动报警系统 | F28: 自动报警系统联动范围摄像头、算法判断 数量太多1000+
C29: 26 | D29: 安全出口堵塞 | F29: 摄像头算法判断安全出口、疏散通道 150+
C30: 27 | D30: 屋面光伏摄像头 | F30: 烟雾、火焰摄像头 （60+）
D31: 电动自行车充电区 | F31: 40+
D32: 电动叉车充电区 | F32: 8
D33: AGV充电区 | F33: 15
D34: 电动汽车充电区 | F34: 60+
D35: 厨房灶台 | F35: 15+
B36: 关键岗位通讯设备 | C36: 28 | D36: 手持设备 | F36: 关键岗位用于设备点检、救援联动、保修维修等功能(12-15台）
A37: 智慧安防系统 | B37: 周界防护 | C37: 29 | D37: 震动光纤 | F37: 光纤、接收器等（4000米周长）
C38: 30 | D38: 周界监控 | F38: 基于算法和震动光纤提示报警（40台摄像机）
C39: 31 | D39: 红外对射报警 | F39: 对车辆道闸下口、窄小区域提示报警（11）
B40: 全面监控 | C40: 32 | D40: 屋面 | F40: 鹰眼相机 提供园区概状视频监控3-4台
C41: 33 | D41: 车道相机 | F41: 对违停、逆行等行为进行算法判断20台
C42: 34 | D42: 无人机 | F42: 按固定轨道轮训，视频上传算法1台
B43: 巡更系统 | C43: 35 | D43: 巡更点 | F43: 使用NFC等设备进行巡更管理40+
A45: 场景类型* | B45: 场所* | C45: 位置* | D45: 需求场景* | F45: 已有摄像头数量* | G45: 优先级*
A46: EHS | B46: M6 | C46: 一楼东侧和南侧老化测试区 | D46: 监测绝缘鞋火焰和烟雾，噪音监测； | F46: 24 | G46: 高
A47: EHS | B47: M6 | C47: 一楼东侧和南侧后的老化设备间 | D47: 监测绝缘鞋火焰和烟雾； | F47: 16 | G47: 高
A48: EHS | B48: M6 | C48: 一楼行车下方工作区域 | D48: 监测工人佩戴安全帽，防砸鞋；人员是否处于吊装物下方 | F48: 0 | G48: 中
A49: EHS | B49: M6 | C49: 一楼板链线旁检修口 | D49: 维修口打开会有信号数据，信号接入摄像头去判断人员是否佩戴安全帽； | F49: 1 | G49: 中
A50: EHS | B50: M6 | C50: 一楼生命线 | D50: 检测人员登高时人员是否配戴安全帽与安全带 | F50: 2 | G50: 中
A51: EHS | B51: M8 | C51: 一楼南边模组房机械臂区域 | D51: 需要进行人员安全帽监测； | F51: 1 | G51: 中
A52: EHS | B52: M8 | C52: 一楼南边的悬臂吊 | D52: 作业时监测下方人员的是否穿戴安全帽和防砸鞋；人员是否处于吊装物下方。 | F52: 1 | G52: 中
A53: EHS | B53: M8 | C53: 一楼南边悬臂吊旁边的调试区 | D53: 需要穿绝缘鞋，火焰烟雾监测； | F53: 0 | G53: 高
A54: EHS | B54: M9 | C54: 一楼南侧区域的老化测试区 | D54: 需要进行绝缘鞋和烟雾火焰监测，噪音监测； | F54: 1 | G54: 高
A55: EHS | B55: M9 | C55: 一楼南侧区域的老化设备间 | D55: 需要进行绝缘鞋、火焰和烟雾检测； | F55: 0 | G55: 高
A56: EHS | B56: M15 | C56: 车间内主次干道 | D56: 识别物料占道、超线摆放、地面垃圾5S问题 | F56: / | G56: 中
A57: EHS | B57: M15 | C57: 一楼电芯上线区 | D57: 监测安全帽、火焰和烟雾（考虑摄像头与火焰烟感联动）；监测噪声区域人员暴露时长。 | F57: 4 | G57: 高
A58: EHS | B58: M15 | C58: 一楼电芯堆叠区 | D58: 监测安全帽、火焰和烟雾（考虑摄像头与火焰烟感联动）；监测噪声区域人员暴露时长。 | F58: 3 | G58: 高
A59: EHS | B59: M15 | C59: 一楼西侧的悬臂吊工作区 | D59: 监测下方施工是否配戴安全帽和防砸鞋，火焰及烟雾监测（考虑摄像头与烟感联动）；人员是否处于吊装物下方 | F59: 0 | G59: 中
A60: EHS | B60: 化学品库 | C60: 园区东侧和西侧化学品库 | D60: 监测液体倾倒、泄漏，抽烟，手机监测，温度湿度监测报警；，火焰及烟雾监测（考虑摄像头与烟感联动）； | F60: 2 | G60: 高
A61: EHS | B61: 叉车充电区 | C61: M19西侧叉车充电区 | D61: 监测火焰及烟雾（考虑摄像头与烟感联动） | F61: 0 | G61: 中
A62: EHS | B62: 龙门吊 | C62: M9右侧堆场上方龙门吊 | D62: 监测龙门吊下方工作区，工人是否佩戴安全帽，人员是否处于吊装物下方 | F62: 0 | G62: 中
A63: EHS | B63: M8 | C63: M8南侧污水处理站 | D63: 监测污水站顶部进出口，识别有无开启动作，人员是否佩戴安全帽 | F63: 0 | G63: 中
A64: EHS | B64: M10 | C64: 一楼仓储区 | D64: 围栏内监测安全帽，火焰及烟雾监测（考虑摄像头与烟感联动）； | F64: 34 | G64: 中
A65: EHS | B65: M10 | C65: 一楼仓储区 | D65: 围栏外使用电动托盘车需要穿反光背心、防砸鞋。 | F65: 26 | G65: 中
A66: EHS | B66: M5 | C66: 二楼X射线监测室 | D66: 监测人员操作时是否穿戴铅衣 | F66: 1 | G66: 中
A67: EHS | B67: M5 | C67: 二楼工装清洗室 | D67: 监测防尘口罩，需加装摄像头与烟感联动 | F67: 1 | G67: 中
A68: EHS | B68: M5 | C68: 二楼波峰焊操作台 | D68: 操作时监测人员需佩戴防护口罩 | F68: 3 | G68: 中
... A71: EHS | B71: 园区 | C71: 园区道路 | D71: 叉车、托盘车驾驶人员是否穿反光马甲、操作托盘车是否穿防砸鞋；车辆驾驶是否超速（叉车15，托盘车8） | F71: 311 | G71: 高
A73: 场景类型* | B73: 场所* | C73: 位置* | D73: 需求场景* | F73: 已有摄像头数量* | G73: 优先级*
A74: 道路交通 | B74: 园区道路 | C74: 全部 | D74: 违停、堆物、人员聚集、 | F74: 311 | G74: 低
A75: 周界防护 | B75: 园区围墙 | C75: 全部 | D75: 翻越 | F75: 92 | G75: 中
A76: 屋面光伏 | B76: 屋面光伏安装场所 | C76: 全部 | D76: 烟雾、火焰 | F76: 0 | G76: 高
A77: 安全出口 | B77: 所有厂房 | C77: 全部 | D77: 安全出口堵塞 | F77: 150 | G77: 低
A78: 消防水池水箱 | B78: 水泵房 | C78: 7处 | D78: 液位仪传感器 | F78: 7 | G78: 高
B79: 稳压泵房 | C79: 6处 | D79: 液位传感器 | F79: 6 | G79: 高
A80: 水泵电气监控 | B80: 水泵房 | C80: 7处 | D80: 水泵电气监控 | F80: 28 | G80: 高
B81: 稳压泵房 | C81: 6处 | D81: 电气监控、启停状态/次数监测 | F81: 28 | G81: 高
A82: 配电柜 | B82: 水泵房 | C82: 7处 | D82: 电气监控 | F82: 9 | G82: 高
A83: 控制柜 | B83: 水泵房 | C83: 7处 | D83: 电气监控、远程手自动变更 | F83: 28 | G83: 高
A84: 消防测试栓 | B84: 屋面 | C84: 30处 | D84: 压力监控 | F84: 30 | G84: 高
A85: 末端测试 | B85: 厂房、宿舍各防火分区 | C85: 200处 | D85: 压力监控 | F85: 200 | G85: 高
A86: 补水阀 | B86: 水泵房、稳压泵房 | C86: 13处 | D86: 流量监控、压力监控 | F86: 13 | G86: 高
