Workbook

Sheet 总表
A1: 总表
A2: 序号 | B2: 项目 | C2: 金额（元）
A3: 1 | B3: 1#、3#、8#、15#数据中心非管控区五方对讲 | C3: ='1#、3#、8#、15#五方对讲系统'!N7 -> 4224
A4: 2 | B4: 1#楼数据中心—柴发区域自控及弱电工程-BA系统 | C4: ='1#数据中心BA系统'!N9 -> 29549.91
A5: 3 | B5: 1#楼数据中心—柴发区域自控及弱电工程-安防门禁系统 | C5: ='1#数据中心安防门禁系统'!N39 -> 209298.03
A6: 4 | B6: 1#楼数据中心—柴发区域自控及弱电工程-综合布线系统 | C6: ='1#数据中心综合布线系统'!N35 -> 68130.3
A7: 5 | B7: 3#楼数据中心—柴发区域自控及弱电工程-BA系统 | C7: ='3#数据中心BA系统'!N11 -> 29549.91
A8: 6 | B8: 3#楼数据中心—柴发区域自控及弱电工程-安防门禁系统 | C8: ='3#数据中心安防门禁系统'!N38 -> 200431.02
A9: 7 | B9: 3#楼数据中心—柴发区域自控及弱电工程-综合布线系统 | C9: ='3#数据中心综合布线系统'!N34 -> 67681.33
A10: 8 | B10: 8#、15#、及门卫数据中心非管控区-入侵报警系统工程 | C10: ='8#、15#非管区入侵报警系统'!N56 -> 124363.36
A11: 9 | B11: 8#、15#、及门卫数据中心非管控区-时钟同步系统工程 | C11: ='8#、15#非管区时钟同步系统'!N22 -> 255533.89
A12: 10 | B12: 8#、15#、及门卫数据中心非管控区-视频监控系统工程 | C12: ='8#、15#非管区视频监控系统'!N123 -> 4735454.7
A13: 11 | B13: 8#、15#、及门卫数据中心非管控区-巡更系统工程 | C13: ='8#、15#非管区巡更系统'!N14 -> 48299.94
A14: 12 | B14: 8#、15#、及门卫数据中心非管控区-一卡通系统工程 | C14: ='8#、15#非管区一卡通系统'!N108 -> 846622.44
A15: 13 | B15: 8#、15#、及门卫数据中心非管控区园区智能化管理平台系统工程 | C15: ='8#、15#非管区园区智能化管理平台系统'!N40 -> 241713.92
A16: 14 | B16: 8#、15#、及门卫数据中心非管控区-综合布线系统工程 | C16: ='8#、15#非管区综合布线系统'!N68 -> 1674589
A17: 15 | B17: 8#、15#数据中心非管控区-BA系统工程 | C17: ='8#、15#非管区BA系统'!N124 -> 496864.29
A18: 16 | B18: 8#、15#数据中心非管控区-多媒体会议系统工程 | C18: ='8#、15#非管区多媒体系统'!N509 -> 4749832.1
A19: 17 | B19: 8#、15#数据中心非管控区-信息发布系统工程 | C19: ='8#、15#非管区信息发布系统'!N45 -> 495770.62
A20: 18 | B20: 8#楼ECC非管控区-灯光控制工程 | C20: ='8#楼ECC非管区灯光控制工程'!N42 -> 100300.06
A21: 19 | B21: 8#楼ECC非管控区-电动窗帘控制工程 | C21: ='8#楼ECC非管区电动窗帘控制工程'!N23 -> 76041.54
A22: 20 | B22: 15#楼生产综合楼-灯光控制工程 | C22: ='15#楼生产综合楼灯光控制工程'!N41 -> 106164.59
A23: 21 | B23: 15#楼生产综合楼-电动窗帘控制工程 | C23: ='15#楼生产楼电动窗帘控制工程'!N24 -> 133556.53
A24: 22 | B24: 15#生产综合楼-值班室、机房、工具间 | C24: ='15#楼生产综合楼值班室、机房、工具间'!N151 -> 568252.22
B25: 总计 | C25: =SUM(C3:C24) -> 15262224

Sheet 1#、3#、8#、15#五方对讲系统
A1: 分部分项工程和单价措施项目清单与计价表
A2: 工程名称：1#、3#、8#、15#数据中心非管控区五方对讲 | G2: 标段：兴业银行贵安新区数据中心项目（一期）室内装修及机电配套工程 | L2: 第 1 页 共 1 页
A3: 序号 | B3: 项目编码 | C3: 项目名称 | D3: 项目特征描述 | E3: 计量单位 | F3: 工程量 | G3: 金额（元）
G4: 主材/设备费 | H4: 辅材 | I4: 机械措施 | J4: 人工 | K4: 管理费 | L4: 利润 | M4: 税金 | N4: 总价
A5: 1 | B5: 030411004092 | C5: 配线 | D5: 1.名称:五方对讲线缆 2.型号:RYYSP-6*1.0 3.其它:满足完成此项工作所需要的全部工作内容，包括设计图纸、技术规范书、答疑、招标文件、现行规范、图集、验收等全部要求 | E5: m | F5: 192 | G5: 803.23 | H5: 211.38 | I5: 105.69 | J5: 591.85 | K5: 169.1 | L5: 232.51 | M5: 190.24 | N5: =SUM(G5:M5) -> 2304
A6: 2 | B6: 030411004093 | C6: 配线 | D6: 1.名称:五方对讲线缆 2.型号:RYYSP-2*1.5 3.其它:满足完成此项工作所需要的全部工作内容，包括设计图纸、技术规范书、答疑、招标文件、现行规范、图集、验收等全部要求 | E6: m | F6: 192 | G6: 669.36 | H6: 176.15 | I6: 88.07 | J6: 493.21 | K6: 140.92 | L6: 193.76 | M6: 158.53 | N6: =SUM(G6:M6) -> 1920
A7: 本页小计 | N7: =SUM(N5:N6) -> 4224
A8: 总计 | N8: =N7 -> 4224

Sheet 1#数据中心BA系统
A1: 分部分项工程和单价措施项目清单与计价表
A2: 工程名称：1#楼数据中心—柴发区域自控及弱电工程-BA系统 | G2: 标段：兴业银行贵安新区数据中心项目（一期）室内装修及机电配套工程 | L2: 第 1 页 共 1 页
A3: 序号 | B3: 项目编码 | C3: 项目名称 | D3: 项目特征描述 | E3: 计量单位 | F3: 工程量 | G3: 金额（元）
G4: 主材/设备费 | H4: 辅材 | I4: 机械措施 | J4: 人工 | K4: 管理费 | L4: 利润 | M4: 税金 | N4: 总价
A5: 1 | B5: 080901001003 | C5: 交换机 | D5: 1.名称：接入交换机 2.参数： 支持交流或直流供电,支持冗余电源; ≥48个千兆以太网电接口; ≥4端口千兆以太网光接口; 工作环境温度-5℃~45℃; 工作环境相对湿度(非凝露) 5%~95%; 电源接口:支持双电源供电; 配10G上行光模块 3.其他:满足完成此项工作所需要的全部工作内容，包括设计图纸、技术规范书、答疑、招标文件、现行规范、图集、验收等全部要求 | E5: 台 | F5: 1 | G5: 2862.39 | H5: 110.09 | I5: 36.7 | J5: 146.79 | K5: 110.09 | L5: 403.67 | M5: 330.28 | N5: =SUM(G5:M5) -> 4000.01
A6: 2 | B6: 030503003005 | C6: DDC控制器 | D6: 1.名称：DDC控制箱（含控制器等） 2.其他:满足完成此项工作所需要的全部工作内容，包括设计图纸、技术规范书、答疑、招标文件、现行规范、图集、验收等全部要求 | E6: 台 | F6: 1 | G6: 2504.59 | H6: 96.33 | I6: 32.11 | J6: 128.44 | K6: 96.33 | L6: 353.21 | M6: 288.99 | N6: =SUM(G6:M6) -> 3500
A7: 3 | B7: 030503010002 | C7: 建筑设备自控化系统试运行 | D7: 1.名称:建筑设备自控化系统试运行 2.其他:满足完成此项工作所需要的全部工作内容，包括设计图纸、技术规范书、答疑、招标文件、现行规范、图集、验收等全部要求 | E7: 系统 | F7: 1 | G7: 7059.6 | H7: 1857.8 | I7: 928.9 | J7: 5201.8 | K7: 1486.2 | L7: 2043.6 | M7: 1672 | N7: =SUM(G7:M7) -> 20249.9
A8: 4 | B8: 031301017003 | C8: 脚手架搭拆 | D8: 1.脚手架费 2.按项包干 3.其它:满足完成此项工作所需要的全部工作内容，包括设计图纸、技术规范书、答疑、招标文件、现行规范、图集、验收等全部要求 | E8: 项 | F8: 1 | G8: 627.51 | H8: 165.15 | I8: 82.56 | J8: 462.39 | K8: 132.12 | L8: 181.65 | M8: 148.62 | N8: =SUM(G8:M8) -> 1800
A9: 本页小计 | N9: =SUM(N5:N8) -> 29549.91
A10: 总计 | N10: =N9 -> 29549.91

Sheet 1#数据中心安防门禁系统
A1: 分部分项工程和单价措施项目清单与计价表
A2: 分部分项工程和单价措施项目清单与计价表
A3: 序号 | B3: 项目编码 | C3: 项目名称 | D3: 项目特征描述 | E3: 计量单位 | F3: 工程量 | G3: 金额（元）
G4: 主材/设备费 | H4: 辅材 | I4: 机械措施 | J4: 人工 | K4: 管理费 | L4: 利润 | M4: 税金 | N4: 总价
A5: 1 | B5: 030503003001 | C5: 控制器 | D5: 1.名称：D1-1门禁控制器（配套安防箱） 2.参数：详见设计图纸及技术规范书 3.其他:满足完成此项工作所需要的全部工作内容，包括设计图纸、技术规范书、答疑、招标文件、现行规范、图集、验收等全部要求 | E5: 台 | F5: 2 | G5: 1452.66 | H5: 55.87 | I5: 18.62 | J5: 74.5 | K5: 55.87 | L5: 204.86 | M5: 167.61 | N5: =SUM(G5:M5) -> 2029.99
A6: 2 | B6: 030503003002 | C6: 控制器 | D6: 1.名称：D1-2门禁控制器（配套安防箱） 2.参数：详见设计图纸及技术规范书 3.其他:满足完成此项工作所需要的全部工作内容，包括设计图纸、技术规范书、答疑、招标文件、现行规范、图集、验收等全部要求 | E6: 台 | F6: 2 | G6: 1452.66 | H6: 55.87 | I6: 18.62 | J6: 74.5 | K6: 55.87 | L6: 204.86 | M6: 167.61 | N6: =SUM(G6:M6) -> 2029.99
A7: 3 | B7: 030503003003 | C7: 控制器 | D7: 1.名称：D2-2门禁控制器（配套安防箱） 2.参数：详见设计图纸及技术规范书 3.其他:满足完成此项工作所需要的全部工作内容，包括设计图纸、技术规范书、答疑、招标文件、现行规范、图集、验收等全部要求 | E7: 台 | F7: 23 | G7: 16705.6 | H7: 642.52 | I7: 214.17 | J7: 856.7 | K7: 642.52 | L7: 2355.92 | M7: 1927.57 | N7: =SUM(G7:M7) -> 23345
A8: 4 | B8: 030503003004 | C8: 控制器 | D8: 1.名称：D3-2门禁控制器（配套安防箱） 2.参数：详见设计图纸及技术规范书 3.其他:满足完成此项工作所需要的全部工作内容，包括设计图纸、技术规范书、答疑、招标文件、现行规范、图集、验收等全部要求 | E8: 台 | F8: 2 | G8: 1452.66 | H8: 55.87 | I8: 18.62 | J8: 74.5 | K8: 55.87 | L8: 204.86 | M8: 167.61 | N8: =SUM(G8:M8) -> 2029.99
A9: 本页小计 | N9: =SUM(N5:N8) -> 29434.97
A10: 5 | B10: 030507006001 | C10: 出入口控制设备 | D10: 1.名称：门禁读卡器 2.参数：详见设计图纸及技术规范书 3.其他:满足完成此项工作所需要的全部工作内容，包括设计图纸、技术规范书、答疑、招标文件、现行规范、图集、验收等全部要求 | E10: 台 | F10: 28 | G10: 9016.51 | H10: 346.79 | I10: 115.6 | J10: 462.39 | K10: 346.79 | L10: 1271.56 | M10: 1040.37 | N10: =SUM(G10:M10) -> 12600.01
A11: 6 | B11: 030507006002 | C11: 出入口控制设备 | D11: 1.名称：出门按钮 2.参数：详见设计图纸及技术规范书 3.其他:满足完成此项工作所需要的全部工作内容，包括设计图纸、技术规范书、答疑、招标文件、现行规范、图集、验收等全部要求 | E11: 台 | F11: 3 | G11: 30.06 | H11: 1.16 | I11: 0.39 | J11: 1.54 | K11: 1.16 | L11: 4.24 | M11: 3.47 | N11: =SUM(G11:M11) -> 42.02
A12: 7 | B12: 030507006003 | C12: 出入口控制设备 | D12: 1.名称：电控锁 2.参数：详见设计图纸及技术规范书 3.其他:满足完成此项工作所需要的全部工作内容，包括设计图纸、技术规范书、答疑、招标文件、现行规范、图集、验收等全部要求 | E12: 台 | F12: 52 | G12: 5295.41 | H12: 441.28 | I12: 176.51 | J12: 1323.85 | K12: 617.8 | L12: 970.83 | M12: 794.31 | N12: =SUM(G12:M12) -> 9619.99
A13: 8 | B13: 030507006004 | C13: 出入口控制设备 | D13: 1.名称：门磁开关 2.参数：详见设计图纸及技术规范书 3.其他:满足完成此项工作所需要的全部工作内容，包括设计图纸、技术规范书、答疑、招标文件、现行规范、图集、验收等全部要求 | E13: 台 | F13: 54 | G13: 1352.48 | H13: 52.02 | I13: 17.34 | J13: 69.36 | K13: 52.02 | L13: 190.73 | M13: 156.06 | N13: =SUM(G13:M13) -> 1890.01
A14: 本页小计 | N14: =SUM(N10:N13) -> 24152.03
A15: 9 | B15: 030507006005 | C15: 出入口控制设备 | D15: 1.名称：玻璃破碎应急按钮 2.参数：详见设计图纸及技术规范书 3.其他:满足完成此项工作所需要的全部工作内容，包括设计图纸、技术规范书、答疑、招标文件、现行规范、图集、验收等全部要求 | E15: 台 | F15: 27 | G15: 2975.45 | H15: 114.44 | I15: 38.15 | J15: 152.59 | K15: 114.44 | L15: 419.61 | M15: 343.32 | N15: =SUM(G15:M15) -> 4158
A16: 10 | B16: 030507005001 | C16: 出入口目标识别设备 | D16: 1.名称：人脸识别机 2.参数：详见设计图纸及技术规范书 3.其他:满足完成此项工作所需要的全部工作内容，包括设计图纸、技术规范书、答疑、招标文件、现行规范、图集、验收等全部要求 | E16: 台 | F16: 25 | G16: 23793.58 | H16: 915.14 | I16: 305.05 | J16: 1220.18 | K16: 915.14 | L16: 3355.5 | M16: 2745.41 | N16: =SUM(G16:M16) -> 33250
A17: 11 | B17: 030411006001 | C17: 接线盒 | D17: 1.名称:接线盒 2.参数：详见设计图纸及技术规范书 3.其他:满足完成此项工作所需要的全部工作内容，包括设计图纸、技术规范书、答疑、招标文件、现行规范、图集、验收等全部要求 | E17: 个 | F17: 25 | G17: 217.89 | H17: 57.34 | I17: 28.67 | J17: 160.55 | K17: 45.87 | L17: 63.07 | M17: 51.61 | N17: =SUM(G17:M17) -> 625
A18: 12 | B18: 030411001002 | C18: 配管 | D18: 1.名称:紧定式镀锌钢导管 2.材质:JDG25 3.敷设方式:综合考虑 4.其他:满足完成此项工作所需要的全部工作内容，满足设计图纸、技术规范书、答疑、招标文件、现行规范、图集、验收等全部要求 | E18: m | F18: 300 | G18: 522.94 | H18: 137.61 | I18: 68.81 | J18: 385.32 | K18: 110.09 | L18: 151.38 | M18: 123.85 | N18: =SUM(G18:M18) -> 1500
A19: 本页小计 | N19: =SUM(N15:N18) -> 39533
A20: 13 | B20: 030411001003 | C20: 配管 | D20: 1.名称:紧定式镀锌钢导管 2.材质:JGD20 3.敷设方式:综合考虑 4.其他:满足完成此项工作所需要的全部工作内容，满足设计图纸、技术规范书、答疑、招标文件、现行规范、图集、验收等全部要求 | E20: m | F20: 300 | G20: 470.64 | H20: 123.85 | I20: 61.93 | J20: 346.79 | K20: 99.08 | L20: 136.24 | M20: 111.47 | N20: =SUM(G20:M20) -> 1350
A21: 14 | B21: 030413002002 | C21: 凿（压)槽 | D21: 1.名称:二次结构凿槽 2.规格:DN32以内 3.类型:砼、砌筑结构 4.含填补恢复 5.满足完成此项工作所需要的全部工作内容，满足设计图纸、技术规范书、答疑、招标文件、现行规范、图集、验收等全部要求 | E21: m | F21: 200 | G21: 543.85 | H21: 143.12 | I21: 71.56 | J21: 400.73 | K21: 114.5 | L21: 157.43 | M21: 128.81 | N21: =SUM(G21:M21) -> 1560
A22: 15 | B22: 030413001003 | C22: 管道支架/综合支架 | D22: 1.名称:管道支架制作安装 2.材质：热镀锌 3.其它：满足完成此项工作所需要的全部工作内容，满足设计图纸、技术规范书、答疑、招标文件、现行规范、图集、验收等全部要求 | E22: kg | F22: 120 | G22: 543.85 | H22: 143.12 | I22: 71.56 | J22: 400.73 | K22: 114.5 | L22: 157.43 | M22: 128.81 | N22: =SUM(G22:M22) -> 1560
A23: 16 | B23: 030502007002 | C23: 光缆 | D23: 1.名称:光缆 2.规格:12芯单模光纤 3.敷设方式:桥架内敷设 4.其他:满足完成此项工作所需要的全部工作内容，满足设计图纸、技术规范书、答疑、招标文件、现行规范、图集、验收等全部要求 | E23: m | F23: 2700 | G23: 7728.44 | H23: 297.25 | I23: 99.08 | J23: 396.33 | K23: 297.25 | L23: 1089.91 | M23: 891.74 | N23: =SUM(G23:M23) -> 10800
A24: 本页小计 | N24: =SUM(N20:N23) -> 15270
A25: 17 | B25: 030502005002 | C25: 双绞线缆 | D25: 1.名称:六类八芯非屏蔽对绞线 2.规格:LSZH-UTP-Cat6-4x2x0.5 3.其他:满足完成此项工作所需要的全部工作内容，满足设计图纸、技术规范书、答疑、招标文件、现行规范、图集、验收等全部要求 | E25: m | F25: 3506 | G25: 5789.72 | H25: 482.48 | I25: 192.99 | J25: 1447.43 | K25: 675.47 | L25: 1061.45 | M25: 868.46 | N25: =SUM(G25:M25) -> 10518
A26: 18 | B26: 030411004001 | C26: 配线 | D26: 1.名称:配线 2.规格:WDZA-RYY2*1.0 3.其他:满足完成此项工作所需要的全部工作内容，满足设计图纸、技术规范书、答疑、招标文件、现行规范、图集、验收等全部要求 | E26: m | F26: 2700 | G26: 4235.78 | H26: 1114.68 | I26: 557.34 | J26: 3121.1 | K26: 891.74 | L26: 1226.15 | M26: 1003.21 | N26: =SUM(G26:M26) -> 12150
A27: 19 | B27: 030411004002 | C27: 配线 | D27: 1.名称:线缆 2.规格:WDZA-RYY-4*1.0 3.其他:满足完成此项工作所需要的全部工作内容，满足设计图纸、技术规范书、答疑、招标文件、现行规范、图集、验收等全部要求 | E27: m | F27: 2700 | G27: 4706.42 | H27: 1238.53 | I27: 619.27 | J27: 3467.89 | K27: 990.83 | L27: 1362.39 | M27: 1114.68 | N27: =SUM(G27:M27) -> 13500.01
A28: 20 | B28: 030411004003 | C28: 配线 | D28: 1.名称:线缆 2.规格:WDZA-RYSP-4*1.0 3.其他:满足完成此项工作所需要的全部工作内容，满足设计图纸、技术规范书、答疑、招标文件、现行规范、图集、验收等全部要求 | E28: m | F28: 2700 | G28: 5647.71 | H28: 1486.24 | I28: 743.12 | J28: 4161.47 | K28: 1188.99 | L28: 1634.86 | M28: 1337.61 | N28: =SUM(G28:M28) -> 16200
A29: 本页小计 | N29: =SUM(N25:N28) -> 52368.01
A30: 21 | B30: 030411004004 | C30: 配线 | D30: 1.名称:线缆 2.规格:WDZA-RYSP6*1.0 3.其他:满足完成此项工作所需要的全部工作内容，满足设计图纸、技术规范书、答疑、招标文件、现行规范、图集、验收等全部要求 | E30: m | F30: 2700 | G30: 7530.28 | H30: 1981.65 | I30: 990.83 | J30: 5548.62 | K30: 1585.32 | L30: 2179.82 | M30: 1783.49 | N30: =SUM(G30:M30) -> 21600.01
A31: 22 | B31: 030411004005 | C31: 配线 | D31: 1.名称:线缆 2.规格:WDZA-RYSP8*1.0 3.其他:满足完成此项工作所需要的全部工作内容，满足设计图纸、技术规范书、答疑、招标文件、现行规范、图集、验收等全部要求 | E31: m | F31: 2700 | G31: 7530.28 | H31: 1981.65 | I31: 990.83 | J31: 5548.62 | K31: 1585.32 | L31: 2179.82 | M31: 1783.49 | N31: =SUM(G31:M31) -> 21600.01
A32: 23 | B32: 030502019002 | C32: 双绞线缆测试 | D32: 1.双绞线缆测试 2.满足完成此项工作所需要的全部工作内容，包括设计图纸、技术规范书、答疑、招标文件、现行规范、图集、验收等全部要求 | E32: 链路 | F32: 86 | G32: 239.85 | H32: 63.12 | I32: 31.56 | J32: 176.73 | K32: 50.5 | L32: 69.43 | M32: 56.81 | N32: =SUM(G32:M32) -> 688
A33: 24 | B33: 030502020002 | C33: 光纤测试 | D33: 1.光纤测试 2.满足完成此项工作所需要的全部工作内容，包括设计图纸、技术规范书、答疑、招标文件、现行规范、图集、验收等全部要求 | E33: 链路 | F33: 19 | G33: 52.99 | H33: 13.94 | I33: 6.97 | J33: 39.05 | K33: 11.16 | L33: 15.34 | M33: 12.55 | N33: =SUM(G33:M33) -> 152
A34: 25 | B34: 030507019001 | C34: 安全防范系统调试 | D34: 1.系统调试及试运行 2.满足完成此项工作所需要的全部工作内容，包括设计图纸、技术规范书、答疑、招标文件、现行规范、图集、验收等全部要求 | E34: 系统 | F34: 1 | G34: 697.25 | H34: 183.49 | I34: 91.74 | J34: 513.76 | K34: 146.79 | L34: 201.83 | M34: 165.14 | N34: =SUM(G34:M34) -> 2000
A35: 本页小计 | N35: =SUM(N30:N34) -> 46040.02
A36: 26 | B36: 03B001 | C36: 系统综合及集成 | D36: 1.清单未列项、图纸中未表示或技术规格书未做要求，但为了实现本系统各项功能必须增加的配套及辅助的材料、设备的所有工作内容及费用； 2.施工深化设计增加的实现本系统设计功能必要的配套及辅助的材料、设备所需的所有工作内容及费用； 3.实现设计功能所做的满足图纸、技术规格书要求的各项综合与集成，包括不限于各项检测、试验、调试、软件开发、联动等所有工作内容及费用 | E36: 项 | F36: 1 | G36: 697.25 | H36: 183.49 | I36: 91.74 | J36: 513.76 | K36: 146.79 | L36: 201.83 | M36: 165.14 | N36: =SUM(G36:M36) -> 2000
A37: 27 | B37: 031301017002 | C37: 脚手架搭拆 | D37: 1.脚手架费 2.按项包干 3.其它:满足完成此项工作所需要的全部工作内容，包括设计图纸、技术规范书、答疑、招标文件、现行规范、图集、验收等全部要求 | E37: 项 | F37: 1 | G37: 174.31 | H37: 45.87 | I37: 22.94 | J37: 128.44 | K37: 36.7 | L37: 50.46 | M37: 41.28 | N37: =SUM(G37:M37) -> 500
A38: 本页小计 | N38: =SUM(N36:N37) -> 2500
A39: 总计 | N39: =N9+N14+N19+N24+N29+N35+N38 -> 209298.03

Sheet 1#数据中心综合布线系统
A1: 分部分项工程和单价措施项目清单与计价表
A2: 分部分项工程和单价措施项目清单与计价表
A3: 序号 | B3: 项目编码 | C3: 项目名称 | D3: 项目特征描述 | E3: 计量单位 | F3: 工程量 | G3: 金额（元）
G4: 主材/设备费 | H4: 辅材 | I4: 机械措施 | J4: 人工 | K4: 管理费 | L4: 利润 | M4: 税金 | N4: 总价
A5: 1 | B5: 080901001001 | C5: 交换机 | D5: 1.名称：汇聚交换机 2.参数：48口,万兆，40G上行光模块 3.详见图纸设计及相关验收规范要求等 4.其他:满足完成此项工作所需要的全部工作内容，包括设计图纸、技术规范书、答疑、招标文件、现行规范、图集、验收等全部要求 | E5: 台 | F5: 2 | G5: 10733.94 | H5: 412.84 | I5: 137.61 | J5: 550.46 | K5: 412.84 | L5: 1513.76 | M5: 1238.53 | N5: =SUM(G5:M5) -> 14999.98
A6: 2 | B6: 080901001002 | C6: 交换机 | D6: 1.名称：24口接入交换机 2.主要参数：配10G上行光模块 3.其他:满足完成此项工作所需要的全部工作内容，包括设计图纸、技术规范书、答疑、招标文件、现行规范、图集、验收等全部要求 | E6: 台 | F6: 1 | G6: 2719.27 | H6: 104.59 | I6: 34.86 | J6: 139.45 | K6: 104.59 | L6: 383.49 | M6: 313.76 | N6: =SUM(G6:M6) -> 3800.01
A7: 3 | B7: 030502010001 | C7: 配线架 | D7: 1.名称：配线架24口（含耦合器、尾纤等） 2.参数：详见设计图纸及技术规范书 3.其他:满足完成此项工作所需要的全部工作内容，包括设计图纸、技术规范书、答疑、招标文件、现行规范、图集、验收等全部要求 | E7: 个 | F7: 2 | G7: 500.92 | H7: 19.27 | I7: 6.42 | J7: 25.69 | K7: 19.27 | L7: 70.64 | M7: 57.8 | N7: =SUM(G7:M7) -> 700.01
A8: 4 | B8: 030502010002 | C8: 配线架 | D8: 1.名称：RJ45配线架 24口（含理线器、模块等） 2.参数：详见设计图纸及技术规范书 3.其他:满足完成此项工作所需要的全部工作内容，包括设计图纸、技术规范书、答疑、招标文件、现行规范、图集、验收等全部要求 | E8: 个 | F8: 1 | G8: 286.24 | H8: 11.01 | I8: 3.67 | J8: 14.68 | K8: 11.01 | L8: 40.37 | M8: 33.03 | N8: =SUM(G8:M8) -> 400.01
A9: 本页小计 | N9: =SUM(N5:N8) -> 19900.01
A10: 5 | B10: 030501005001 | C10: 插箱、机柜 | D10: 1.名称：19寸标准机柜(600*800) 42U,含风扇电源 2.其他:满足完成此项工作所需要的全部工作内容，包括设计图纸、技术规范书、答疑、招标文件、现行规范、图集、验收等全部要求 | E10: 台 | F10: 5 | G10: 6440.37 | H10: 247.71 | I10: 82.57 | J10: 330.28 | K10: 247.71 | L10: 908.26 | M10: 743.12 | N10: =SUM(G10:M10) -> 9000.02
A11: 6 | B11: 030502004001 | C11: 电视、电话插座 | D11: 1.名称：双孔信息插座（含模块） 2.参数：详见设计图纸及技术规范书 3.其它:满足完成此项工作所需要的全部工作内容，包括设计图纸、技术规范书、答疑、招标文件、现行规范、图集、验收等全部要求 | E11: 个 | F11: 3 | G11: 75.14 | H11: 2.89 | I11: 0.96 | J11: 3.85 | K11: 2.89 | L11: 10.6 | M11: 8.67 | N11: =SUM(G11:M11) -> 105
A12: 7 | B12: 030502003001 | C12: 分线接线箱（盒） | D12: 1.名称：铁质接线盒 2.参数：详见设计图纸及技术规范书 3.其它:满足完成此项工作所需要的全部工作内容，包括设计图纸、技术规范书、答疑、招标文件、现行规范、图集、验收等全部要求 | E12: 个 | F12: 3 | G12: 26.15 | H12: 6.88 | I12: 3.44 | J12: 19.27 | K12: 5.5 | L12: 7.57 | M12: 6.19 | N12: =SUM(G12:M12) -> 75
A13: 8 | B13: 030502009001 | C13: 跳线 | D13: 1.名称：跳线 2.其他:满足完成此项工作所需要的全部工作内容，包括设计图纸、技术规范书、答疑、招标文件、现行规范、图集、验收等全部要求 | E13: 条 | F13: 8 | G13: 114.5 | H13: 4.4 | I13: 1.47 | J13: 5.87 | K13: 4.4 | L13: 16.15 | M13: 13.21 | N13: =SUM(G13:M13) -> 160
A14: 9 | B14: 030502009002 | C14: LC-LC单模光纤跳线（3m） | D14: 1.名称:LC-LC单模光纤跳线（3m） 2.其它:满足完成此项工作所需要的全部工作内容，包括设计图纸、技术规范书、答疑、招标文件、现行规范、图集、验收等全部要求 | E14: 条 | F14: 12 | G14: 386.42 | H14: 14.86 | I14: 4.95 | J14: 19.82 | K14: 14.86 | L14: 54.5 | M14: 44.59 | N14: =SUM(G14:M14) -> 540
A15: 本页小计 | N15: =SUM(N10:N14) -> 9880.02
A16: 10 | B16: 030502009003 | C16: LC-LC多模光纤跳线（3m） | D16: 1.名称:LC-LC多模光纤跳线（3m） 2.其它:满足完成此项工作所需要的全部工作内容，包括设计图纸、技术规范书、答疑、招标文件、现行规范、图集、验收等全部要求 | E16: 条 | F16: 12 | G16: 343.49 | H16: 13.21 | I16: 4.4 | J16: 17.61 | K16: 13.21 | L16: 48.44 | M16: 39.63 | N16: =SUM(G16:M16) -> 479.99
A17: 11 | B17: 030502009004 | C17: 六类非屏蔽跳线（3m） | D17: 1.名称:六类非屏蔽跳线（3m） 2.其它:满足完成此项工作所需要的全部工作内容，包括设计图纸、技术规范书、答疑、招标文件、现行规范、图集、验收等全部要求 | E17: 条 | F17: 6 | G17: 107.34 | H17: 4.13 | I17: 1.38 | J17: 5.5 | K17: 4.13 | L17: 15.14 | M17: 12.39 | N17: =SUM(G17:M17) -> 150.01
A18: 12 | B18: 030411003001 | C18: 桥架 | D18: 1.名称:热浸锌钢制金属线槽 2.型号：400*100 3.包含但不限于桥架、弯头、三通或四通、盖板、隔板、附件安装、接地跨接等 4.其它:满足完成此项工作所需要的全部工作内容，满足设计图纸、技术规范书、答疑、招标文件、现行规范、图集、验收等全部要求 | E18: m | F18: 125 | G18: 4025.23 | H18: 154.82 | I18: 51.61 | J18: 206.42 | K18: 154.82 | L18: 567.66 | M18: 464.45 | N18: =SUM(G18:M18) -> 5625.01
A19: 13 | B19: 030411003002 | C19: 桥架 | D19: 1.名称:热浸锌钢制金属线槽 2.型号：200*100 3.包含但不限于桥架、弯头、三通或四通、盖板、隔板、附件安装、接地跨接等 4.其它:满足完成此项工作所需要的全部工作内容，满足设计图纸、技术规范书、答疑、招标文件、现行规范、图集、验收等全部要求 | E19: m | F19: 85.28 | G19: 4576.95 | H19: 176.04 | I19: 58.68 | J19: 234.72 | K19: 176.04 | L19: 645.48 | M19: 528.12 | N19: =SUM(G19:M19) -> 6396.03
A20: 本页小计 | N20: =SUM(N16:N19) -> 12651.04
A21: 14 | B21: 030413001001 | C21: 桥架支吊架制作及安装 | D21: 1.名称:桥架支吊架制作及安装 2.规格:综合、热浸镀锌 3.其它：满足完成此项工作所需要的全部工作内容，满足设计图纸、技术规范书、答疑、招标文件、现行规范、图集、验收等全部要求 | E21: kg | F21: 126.66 | G21: 529.88 | H21: 139.44 | I21: 69.72 | J21: 390.44 | K21: 111.55 | L21: 153.39 | M21: 125.5 | N21: =SUM(G21:M21) -> 1519.92
A22: 15 | B22: 030502005001 | C22: 双绞线缆 | D22: 1.名称:超六类非屏蔽四对双绞线 2.规格:CAT.6A UTP 3.其他:满足完成此项工作所需要的全部工作内容，包括设计图纸、技术规范书、答疑、招标文件、现行规范、图集、验收等全部要求 | E22: m | F22: 111 | G22: 183.3 | H22: 15.28 | I22: 6.11 | J22: 45.83 | K22: 21.39 | L22: 33.61 | M22: 27.5 | N22: =SUM(G22:M22) -> 333.02
A23: 16 | B23: 030411001001 | C23: 配管 | D23: 1.名称:紧定式镀锌钢导管 2.材质:JGD20 3.敷设方式:综合考虑 4.其他:满足完成此项工作所需要的全部工作内容，满足设计图纸、技术规范书、答疑、招标文件、现行规范、图集、验收等全部要求 | E23: m | F23: 15 | G23: 23.53 | H23: 6.19 | I23: 3.1 | J23: 17.34 | K23: 4.95 | L23: 6.81 | M23: 5.57 | N23: =SUM(G23:M23) -> 67.49
A24: 17 | B24: 030413002001 | C24: 凿（压)槽 | D24: 1.名称:二次结构凿槽 2.规格:DN32以内 3.类型:砼、砌筑结构 4.含填补恢复 5.满足完成此项工作所需要的全部工作内容，满足设计图纸、技术规范书、答疑、招标文件、现行规范、图集、验收等全部要求 | E24: m | F24: 10.5 | G24: 25.62 | H24: 6.74 | I24: 3.37 | J24: 18.88 | K24: 5.39 | L24: 7.42 | M24: 6.07 | N24: =SUM(G24:M24) -> 73.49
A25: 本页小计 | N25: =SUM(N21:N24) -> 1993.92
A26: 18 | B26: 030413001002 | C26: 管道支架/综合支架 | D26: 1.名称:管道支架制作安装 2.材质：热镀锌 3.其它：满足完成此项工作所需要的全部工作内容，满足设计图纸、技术规范书、答疑、招标文件、现行规范、图集、验收等全部要求 | E26: kg | F26: 0.78 | G26: 3.26 | H26: 0.86 | I26: 0.43 | J26: 2.4 | K26: 0.69 | L26: 0.94 | M26: 0.77 | N26: =SUM(G26:M26) -> 9.35
A27: 19 | B27: 030502007001 | C27: 光缆 | D27: 1.名称:光缆 2.规格:12芯单模光纤OS2 3.敷设方式:桥架内敷设 3.其他:满足完成此项工作所需要的全部工作内容，包括设计图纸、技术规范书、答疑、招标文件、现行规范、图集、验收等全部要求 | E27: m | F27: 1500 | G27: 4293.58 | H27: 165.14 | I27: 55.05 | J27: 220.18 | K27: 165.14 | L27: 605.5 | M27: 495.41 | N27: =SUM(G27:M27) -> 6000
A28: 20 | B28: 030502019001 | C28: 双绞线缆测试 | D28: 1.测试内容:4对双绞线缆 2.其他:满足完成此项工作所需要的全部工作内容，包括设计图纸、技术规范书、答疑、招标文件、现行规范、图集、验收等全部要求 | E28: 链路 | F28: 6 | G28: 16.73 | H28: 4.4 | I28: 2.2 | J28: 12.33 | K28: 3.52 | L28: 4.84 | M28: 3.96 | N28: =SUM(G28:M28) -> 47.98
A29: 21 | B29: 030502020001 | C29: 光纤测试 | D29: 1.测试内容:光纤 2.其他:满足完成此项工作所需要的全部工作内容，包括设计图纸、技术规范书、答疑、招标文件、现行规范、图集、验收等全部要求 | E29: 链路 | F29: 6 | G29: 16.73 | H29: 4.4 | I29: 2.2 | J29: 12.33 | K29: 3.52 | L29: 4.84 | M29: 3.96 | N29: =SUM(G29:M29) -> 47.98
A30: 22 | B30: 030503010001 | C30: 建筑设备自控化系统试运行 | D30: 1.名称:建筑设备自控化系统试运行 2.其他:满足完成此项工作所需要的全部工作内容，包括设计图纸、技术规范书、答疑、招标文件、现行规范、图集、验收等全部要求 | E30: 系统 | F30: 1 | G30: 5229.36 | H30: 1376.16 | I30: 688.08 | J30: 3853.2 | K30: 1100.91 | L30: 1513.77 | M30: 1238.52 | N30: =SUM(G30:M30) -> 15000
A31: 本页小计 | N31: =SUM(N26:N30) -> 21105.31
A32: 23 | B32: 03B001 | C32: 系统综合及集成 | D32: 1.清单未列项、图纸中未表示或技术规格书未做要求，但为了实现本系统各项功能必须增加的配套及辅助的材料、设备的所有工作内容及费用； 2.施工深化设计增加的实现本系统设计功能必要的配套及辅助的材料、设备所需的所有工作内容及费用； 3.实现设计功能所做的满足图纸、技术规格书要求的各项综合与集成，包括不限于各项检测、试验、调试、软件开发、联动等所有工作内容及费用 | E32: 项 | F32: 1 | G32: 697.25 | H32: 183.49 | I32: 91.74 | J32: 513.76 | K32: 146.79 | L32: 201.83 | M32: 165.14 | N32: =SUM(G32:M32) -> 2000
A33: 24 | B33: 031301017001 | C33: 脚手架搭拆 | D33: 1.脚手架费 2.按项包干 3.其它:满足完成此项工作所需要的全部工作内容，包括设计图纸、技术规范书、答疑、招标文件、现行规范、图集、验收等全部要求 | E33: 项 | F33: 1 | G33: 209.17 | H33: 55.05 | I33: 27.52 | J33: 154.13 | K33: 44.04 | L33: 60.55 | M33: 49.54 | N33: =SUM(G33:M33) -> 600
A34: 本页小计 | N34: =SUM(N32:N33) -> 2600
A35: 合 计 | N35: =N9+N15+N20+N25+N31+N34 -> 68130.3

Sheet 3#数据中心BA系统
A1: 分部分项工程和单价措施项目清单与计价表
A2: 分部分项工程和单价措施项目清单与计价表
A3: 序号 | B3: 项目编码 | C3: 项目名称 | D3: 项目特征描述 | E3: 计量单位 | F3: 工程量 | G3: 金额（元）
G4: 主材/设备费 | H4: 辅材 | I4: 机械措施 | J4: 人工 | K4: 管理费 | L4: 利润 | M4: 税金 | N4: 总价
A5: 1 | B5: 080901001006 | C5: 交换机 | D5: 1.名称：接入交换机 2.参数： 支持交流或直流供电,支持冗余电源; ≥48个千兆以太网电接口; ≥4端口千兆以太网光接口; 工作环境温度-5℃~45℃; 工作环境相对湿度(非凝露) 5%~95%; 电源接口:支持双电源供电; 配10G上行光模块 3.其他:满足完成此项工作所需要的全部工作内容，包括设计图纸、技术规范书、答疑、招标文件、现行规范、图集、验收等全部要求 | E5: 台 | F5: 1 | G5: 2862.39 | H5: 110.09 | I5: 36.7 | J5: 146.79 | K5: 110.09 | L5: 403.67 | M5: 330.28 | N5: =SUM(G5:M5) -> 4000.01
A6: 2 | B6: 030503003009 | C6: DDC控制器 | D6: 1.名称：DDC控制箱（含控制器） 2.其他:满足完成此项工作所需要的全部工作内容，包括设计图纸、技术规范书、答疑、招标文件、现行规范、图集、验收等全部要求 | E6: 台 | F6: 1 | G6: 2504.59 | H6: 96.33 | I6: 32.11 | J6: 128.44 | K6: 96.33 | L6: 353.21 | M6: 288.99 | N6: =SUM(G6:M6) -> 3500
A7: 3 | B7: 030503010004 | C7: 建筑设备自控化系统试运行 | D7: 1.名称:建筑设备自控化系统试运行 2.其他:满足完成此项工作所需要的全部工作内容，包括设计图纸、技术规范书、答疑、招标文件、现行规范、图集、验收等全部要求 | E7: 系统 | F7: 1 | G7: 7059.6 | H7: 1857.8 | I7: 928.9 | J7: 5201.8 | K7: 1486.2 | L7: 2043.6 | M7: 1672 | N7: =SUM(G7:M7) -> 20249.9
A8: 本页小计 | N8: =SUM(N5:N7) -> 27749.91
A9: 4 | B9: 031301017007 | C9: 脚手架搭拆 | D9: 1.脚手架费 2.按项包干 3.其它:满足完成此项工作所需要的全部工作内容，包括设计图纸、技术规范书、答疑、招标文件、现行规范、图集、验收等全部要求 | E9: 项 | F9: 1 | G9: 627.51 | H9: 165.15 | I9: 82.56 | J9: 462.39 | K9: 132.12 | L9: 181.65 | M9: 148.62 | N9: =SUM(G9:M9) -> 1800
A10: 本页小计 | N10: =N9 -> 1800
A11: 合 计 | N11: =N8+N10 -> 29549.91

Sheet 3#数据中心安防门禁系统
A1: 分部分项工程和单价措施项目清单与计价表
A2: 分部分项工程和单价措施项目清单与计价表
A3: 序号 | B3: 项目编码 | C3: 项目名称 | D3: 项目特征描述 | E3: 计量单位 | F3: 工程量 | G3: 金额（元）
G4: 主材/设备费 | H4: 辅材 | I4: 机械措施 | J4: 人工 | K4: 管理费 | L4: 利润 | M4: 税金 | N4: 总价
A5: 1 | B5: 030503003006 | C5: 控制器 | D5: 1.名称：D1-1门禁控制器（配套安防箱） 2.参数：详见设计图纸及技术规范书 3.其他:满足完成此项工作所需要的全部工作内容，包括设计图纸、技术规范书、答疑、招标文件、现行规范、图集、验收等全部要求 | E5: 台 | F5: 2 | G5: 1452.66 | H5: 55.87 | I5: 18.62 | J5: 74.5 | K5: 55.87 | L5: 204.86 | M5: 167.61 | N5: =SUM(G5:M5) -> 2029.99
A6: 2 | B6: 030503003007 | C6: 控制器 | D6: 1.名称：D2-2门禁控制器（配套安防箱） 2.参数：详见设计图纸及技术规范书 3.其他:满足完成此项工作所需要的全部工作内容，包括设计图纸、技术规范书、答疑、招标文件、现行规范、图集、验收等全部要求 | E6: 台 | F6: 22 | G6: 15979.27 | H6: 614.59 | I6: 204.86 | J6: 819.45 | K6: 614.59 | L6: 2253.49 | M6: 1843.76 | N6: =SUM(G6:M6) -> 22330.01
A7: 3 | B7: 030503003008 | C7: 控制器 | D7: 1.名称：D3-2门禁控制器（配套安防箱） 2.参数：详见设计图纸及技术规范书 3.其他:满足完成此项工作所需要的全部工作内容，包括设计图纸、技术规范书、答疑、招标文件、现行规范、图集、验收等全部要求 | E7: 台 | F7: 4 | G7: 2905.32 | H7: 111.74 | I7: 37.25 | J7: 148.99 | K7: 111.74 | L7: 409.72 | M7: 335.23 | N7: =SUM(G7:M7) -> 4059.99
A8: 4 | B8: 030507006006 | C8: 出入口控制设备 | D8: 1.名称：门禁读卡器 2.参数：详见设计图纸及技术规范书 3.其他:满足完成此项工作所需要的全部工作内容，包括设计图纸、技术规范书、答疑、招标文件、现行规范、图集、验收等全部要求 | E8: 台 | F8: 26 | G8: 8372.48 | H8: 322.02 | I8: 107.34 | J8: 429.36 | K8: 322.02 | L8: 1180.73 | M8: 966.06 | N8: =SUM(G8:M8) -> 11700.01
A9: 本页小计 | N9: =SUM(N5:N8) -> 40120
A10: 5 | B10: 030507006007 | C10: 出入口控制设备 | D10: 1.名称：出门按钮 2.参数：详见设计图纸及技术规范书 3.其他:满足完成此项工作所需要的全部工作内容，包括设计图纸、技术规范书、答疑、招标文件、现行规范、图集、验收等全部要求 | E10: 台 | F10: 2 | G10: 20.04 | H10: 0.77 | I10: 0.26 | J10: 1.03 | K10: 0.77 | L10: 2.83 | M10: 2.31 | N10: =SUM(G10:M10) -> 28.01
A11: 6 | B11: 030507006008 | C11: 出入口控制设备 | D11: 1.名称：电控锁 2.参数：详见设计图纸及技术规范书 3.其他:满足完成此项工作所需要的全部工作内容，包括设计图纸、技术规范书、答疑、招标文件、现行规范、图集、验收等全部要求 | E11: 台 | F11: 52 | G11: 5295.41 | H11: 441.28 | I11: 176.51 | J11: 1323.85 | K11: 617.8 | L11: 970.83 | M11: 794.31 | N11: =SUM(G11:M11) -> 9619.99
A12: 7 | B12: 030507006009 | C12: 出入口控制设备 | D12: 1.名称：门磁开关 2.参数：详见设计图纸及技术规范书 3.其他:满足完成此项工作所需要的全部工作内容，包括设计图纸、技术规范书、答疑、招标文件、现行规范、图集、验收等全部要求 | E12: 台 | F12: 52 | G12: 1302.39 | H12: 50.09 | I12: 16.7 | J12: 66.79 | K12: 50.09 | L12: 183.67 | M12: 150.28 | N12: =SUM(G12:M12) -> 1820.01
A13: 8 | B13: 030507006010 | C13: 出入口控制设备 | D13: 1.名称：玻璃破碎应急按钮 2.参数：详见设计图纸及技术规范书 3.其他:满足完成此项工作所需要的全部工作内容，包括设计图纸、技术规范书、答疑、招标文件、现行规范、图集、验收等全部要求 | E13: 台 | F13: 25 | G13: 2755.05 | H13: 105.96 | I13: 35.32 | J13: 141.28 | K13: 105.96 | L13: 388.53 | M13: 317.89 | N13: =SUM(G13:M13) -> 3849.99
A14: 本页小计 | N14: =SUM(N10:N13) -> 15318
A15: 9 | B15: 030507005002 | C15: 出入口目标识别设备 | D15: 1.名称：人脸识别机 2.参数：详见设计图纸及技术规范书 3.其他:满足完成此项工作所需要的全部工作内容，包括设计图纸、技术规范书、答疑、招标文件、现行规范、图集、验收等全部要求 | E15: 台 | F15: 25 | G15: 23793.58 | H15: 915.14 | I15: 305.05 | J15: 1220.18 | K15: 915.14 | L15: 3355.5 | M15: 2745.41 | N15: =SUM(G15:M15) -> 33250
A16: 10 | B16: 030411006002 | C16: 接线盒 | D16: 1.名称:接线盒 2.参数：详见设计图纸及技术规范书 3.其他:满足完成此项工作所需要的全部工作内容，包括设计图纸、技术规范书、答疑、招标文件、现行规范、图集、验收等全部要求 | E16: 个 | F16: 25 | G16: 217.89 | H16: 57.34 | I16: 28.67 | J16: 160.55 | K16: 45.87 | L16: 63.07 | M16: 51.61 | N16: =SUM(G16:M16) -> 625
A17: 11 | B17: 030411001005 | C17: 配管 | D17: 1.名称:紧定式镀锌钢导管 2.材质:JDG25 3.敷设方式:综合考虑 4.其他:满足完成此项工作所需要的全部工作内容，满足设计图纸、技术规范书、答疑、招标文件、现行规范、图集、验收等全部要求 | E17: m | F17: 300 | G17: 522.94 | H17: 137.61 | I17: 68.81 | J17: 385.32 | K17: 110.09 | L17: 151.38 | M17: 123.85 | N17: =SUM(G17:M17) -> 1500
A18: 12 | B18: 030411001006 | C18: 配管 | D18: 1.名称:紧定式镀锌钢导管 2.材质:JGD20 3.敷设方式:综合考虑 4.其他:满足完成此项工作所需要的全部工作内容，满足设计图纸、技术规范书、答疑、招标文件、现行规范、图集、验收等全部要求 | E18: m | F18: 300 | G18: 470.64 | H18: 123.85 | I18: 61.93 | J18: 346.79 | K18: 99.08 | L18: 136.24 | M18: 111.47 | N18: =SUM(G18:M18) -> 1350
A19: 本页小计 | N19: =SUM(N15:N18) -> 36725
A20: 13 | B20: 030413002004 | C20: 凿（压)槽 | D20: 1.名称:二次结构凿槽 2.规格:DN32以内 3.类型:砼、砌筑结构 4.含填补恢复 5.满足完成此项工作所需要的全部工作内容，满足设计图纸、技术规范书、答疑、招标文件、现行规范、图集、验收等全部要求 | E20: m | F20: 200 | G20: 543.85 | H20: 143.12 | I20: 71.56 | J20: 400.73 | K20: 114.5 | L20: 157.43 | M20: 128.81 | N20: =SUM(G20:M20) -> 1560
A21: 14 | B21: 030413001006 | C21: 管道支架/综合支架 | D21: 1.名称:管道支架制作安装 2.材质：热镀锌 3.其它：满足完成此项工作所需要的全部工作内容，满足设计图纸、技术规范书、答疑、招标文件、现行规范、图集、验收等全部要求 | E21: kg | F21: 120 | G21: 543.85 | H21: 143.12 | I21: 71.56 | J21: 400.73 | K21: 114.5 | L21: 157.43 | M21: 128.81 | N21: =SUM(G21:M21) -> 1560
A22: 15 | B22: 030502007004 | C22: 光缆 | D22: 1.名称:光缆 2.规格:12芯单模光纤 3.敷设方式:桥架内敷设 4.其他:满足完成此项工作所需要的全部工作内容，满足设计图纸、技术规范书、答疑、招标文件、现行规范、图集、验收等全部要求 | E22: m | F22: 2700 | G22: 7728.44 | H22: 297.25 | I22: 99.08 | J22: 396.33 | K22: 297.25 | L22: 1089.91 | M22: 891.74 | N22: =SUM(G22:M22) -> 10800
A23: 16 | B23: 030502005004 | C23: 双绞线缆 | D23: 1.名称:六类八芯非屏蔽对绞线 2.规格:LSZH-UTP-Cat6-4x2x0.5 3.其他:满足完成此项工作所需要的全部工作内容，满足设计图纸、技术规范书、答疑、招标文件、现行规范、图集、验收等全部要求 | E23: m | F23: 3506 | G23: 5789.72 | H23: 482.48 | I23: 192.99 | J23: 1447.43 | K23: 675.47 | L23: 1061.45 | M23: 868.46 | N23: =SUM(G23:M23) -> 10518
A24: 本页小计 | N24: =SUM(N20:N23) -> 24438
A25: 17 | B25: 030411004007 | C25: 配线 | D25: 1.名称:配线 2.规格:WDZA-RYY2*1.0 3.其他:满足完成此项工作所需要的全部工作内容，满足设计图纸、技术规范书、答疑、招标文件、现行规范、图集、验收等全部要求 | E25: m | F25: 2700 | G25: 4894.68 | H25: 1288.07 | I25: 644.04 | J25: 3606.61 | K25: 1030.46 | L25: 1416.88 | M25: 1159.27 | N25: =SUM(G25:M25) -> 14040.01
A26: 18 | B26: 030411004008 | C26: 配线 | D26: 1.名称:线缆 2.规格:WDZA-RYY-4*1.0 3.其他:满足完成此项工作所需要的全部工作内容，满足设计图纸、技术规范书、答疑、招标文件、现行规范、图集、验收等全部要求 | E26: m | F26: 2700 | G26: 4235.78 | H26: 1114.68 | I26: 557.34 | J26: 3121.1 | K26: 891.74 | L26: 1226.15 | M26: 1003.21 | N26: =SUM(G26:M26) -> 12150
A27: 19 | B27: 030411004009 | C27: 配线 | D27: 1.名称:线缆 2.规格:WDZA-RYSP-4*1.0 3.其他:满足完成此项工作所需要的全部工作内容，满足设计图纸、技术规范书、答疑、招标文件、现行规范、图集、验收等全部要求 | E27: m | F27: 2700 | G27: 4706.42 | H27: 1238.53 | I27: 619.27 | J27: 3467.89 | K27: 990.83 | L27: 1362.39 | M27: 1114.68 | N27: =SUM(G27:M27) -> 13500.01
A28: 20 | B28: 030411004010 | C28: 配线 | D28: 1.名称:线缆 2.规格:WDZA-RYSP6*1.0 3.其他:满足完成此项工作所需要的全部工作内容，满足设计图纸、技术规范书、答疑、招标文件、现行规范、图集、验收等全部要求 | E28: m | F28: 2700 | G28: 5647.71 | H28: 1486.24 | I28: 743.12 | J28: 4161.47 | K28: 1188.99 | L28: 1634.86 | M28: 1337.61 | N28: =SUM(G28:M28) -> 16200
A29: 21 | B29: 030411004011 | C29: 配线 | D29: 1.名称:线缆 2.规格:WDZA-RYSP8*1.0 3.其他:满足完成此项工作所需要的全部工作内容，满足设计图纸、技术规范书、答疑、招标文件、现行规范、图集、验收等全部要求 | E29: m | F29: 2700 | G29: 7530.28 | H29: 1981.65 | I29: 990.83 | J29: 5548.62 | K29: 1585.32 | L29: 2179.82 | M29: 1783.49 | N29: =SUM(G29:M29) -> 21600.01
A30: 本页小计 | N30: =SUM(N25:N29) -> 77490.03
A31: 22 | B31: 030502019004 | C31: 双绞线缆测试 | D31: 1.双绞线缆测试 2.满足完成此项工作所需要的全部工作内容，包括设计图纸、技术规范书、答疑、招标文件、现行规范、图集、验收等全部要求 | E31: 链路 | F31: 86 | G31: 239.85 | H31: 63.12 | I31: 31.56 | J31: 176.73 | K31: 50.5 | L31: 69.43 | M31: 56.81 | N31: =SUM(G31:M31) -> 688
A32: 23 | B32: 030502020004 | C32: 光纤测试 | D32: 1.光纤测试 2.满足完成此项工作所需要的全部工作内容，包括设计图纸、技术规范书、答疑、招标文件、现行规范、图集、验收等全部要求 | E32: 链路 | F32: 19 | G32: 52.99 | H32: 13.94 | I32: 6.97 | J32: 39.05 | K32: 11.16 | L32: 15.34 | M32: 12.55 | N32: =SUM(G32:M32) -> 152
A33: 24 | B33: 030507019002 | C33: 安全防范系统调试 | D33: 1.系统调试及试运行 2.满足完成此项工作所需要的全部工作内容，包括设计图纸、技术规范书、答疑、招标文件、现行规范、图集、验收等全部要求 | E33: 系统 | F33: 1 | G33: 697.25 | H33: 183.49 | I33: 91.74 | J33: 513.76 | K33: 146.79 | L33: 201.83 | M33: 165.14 | N33: =SUM(G33:M33) -> 2000
A34: 25 | B34: 03B003 | C34: 系统综合及集成 | D34: 1.清单未列项、图纸中未表示或技术规格书未做要求，但为了实现本系统各项功能必须增加的配套及辅助的材料、设备的所有工作内容及费用； 2.施工深化设计增加的实现本系统设计功能必要的配套及辅助的材料、设备所需的所有工作内容及费用； 3.实现设计功能所做的满足图纸、技术规格书要求的各项综合与集成，包括不限于各项检测、试验、调试、软件开发、联动等所有工作内容及费用 | E34: 项 | F34: 1 | G34: 1045.87 | H34: 275.23 | I34: 137.61 | J34: 770.64 | K34: 220.18 | L34: 302.75 | M34: 247.71 | N34: =SUM(G34:M34) -> 2999.99
A35: 本页小计 | N35: =SUM(N31:N34) -> 5839.99
A36: 26 | B36: 031301017006 | C36: 脚手架搭拆 | D36: 1.脚手架费 2.按项包干 3.其它:满足完成此项工作所需要的全部工作内容，包括设计图纸、技术规范书、答疑、招标文件、现行规范、图集、验收等全部要求 | E36: 项 | F36: 1 | G36: 174.31 | H36: 45.87 | I36: 22.94 | J36: 128.44 | K36: 36.7 | L36: 50.46 | M36: 41.28 | N36: =SUM(G36:M36) -> 500
A37: 本页小计 | N37: =N36 -> 500
A38: 合 计 | N38: =N9+N14+N19+N24+N30+N35+N37 -> 200431.02

Sheet 3#数据中心综合布线系统
A1: 分部分项工程和单价措施项目清单与计价表
A2: 分部分项工程和单价措施项目清单与计价表
A3: 序号 | B3: 项目编码 | C3: 项目名称 | D3: 项目特征描述 | E3: 计量单位 | F3: 工程量 | G3: 金额（元）
G4: 主材/设备费 | H4: 辅材 | I4: 机械措施 | J4: 人工 | K4: 管理费 | L4: 利润 | M4: 税金 | N4: 总价
A5: 1 | B5: 080901001004 | C5: 交换机 | D5: 1.名称：汇聚交换机 2.参数：48口,万兆，40G上行光模块 3.其他:满足完成此项工作所需要的全部工作内容，包括设计图纸、技术规范书、答疑、招标文件、现行规范、图集、验收等全部要求 | E5: 台 | F5: 2 | G5: 10733.94 | H5: 412.84 | I5: 137.61 | J5: 550.46 | K5: 412.84 | L5: 1513.76 | M5: 1238.53 | N5: =SUM(G5:M5) -> 14999.98
A6: 2 | B6: 080901001005 | C6: 交换机 | D6: 1.名称：24口接入交换机 2.主要参数：配10G上行光模块 3.其他:满足完成此项工作所需要的全部工作内容，包括设计图纸、技术规范书、答疑、招标文件、现行规范、图集、验收等全部要求 | E6: 台 | F6: 1 | G6: 2719.27 | H6: 104.59 | I6: 34.86 | J6: 139.45 | K6: 104.59 | L6: 383.49 | M6: 313.76 | N6: =SUM(G6:M6) -> 3800.01
A7: 3 | B7: 030502010003 | C7: 配线架 | D7: 1.名称：配线架24口（含耦合器、尾纤等） 2.参数：详见设计图纸及技术规范书 3.其他:满足完成此项工作所需要的全部工作内容，包括设计图纸、技术规范书、答疑、招标文件、现行规范、图集、验收等全部要求 | E7: 个 | F7: 2 | G7: 500.92 | H7: 19.27 | I7: 6.42 | J7: 25.69 | K7: 19.27 | L7: 70.64 | M7: 57.8 | N7: =SUM(G7:M7) -> 700.01
A8: 4 | B8: 030502010004 | C8: 配线架 | D8: 1.名称：RJ45配线架 24口（含理线器、模块等） 2.参数：详见设计图纸及技术规范书 3.其他:满足完成此项工作所需要的全部工作内容，包括设计图纸、技术规范书、答疑、招标文件、现行规范、图集、验收等全部要求 | E8: 个 | F8: 1 | G8: 286.24 | H8: 11.01 | I8: 3.67 | J8: 14.68 | K8: 11.01 | L8: 40.37 | M8: 33.03 | N8: =SUM(G8:M8) -> 400.01
A9: 本页小计 | N9: =SUM(N5:N8) -> 19900.01
A10: 5 | B10: 030501005002 | C10: 插箱、机柜 | D10: 1.名称：19寸标准机柜(600*800) 42U,含风扇电源 2.其他:满足完成此项工作所需要的全部工作内容，包括设计图纸、技术规范书、答疑、招标文件、现行规范、图集、验收等全部要求 | E10: 台 | F10: 5 | G10: 10018.35 | H10: 385.32 | I10: 128.44 | J10: 513.76 | K10: 385.32 | L10: 1412.84 | M10: 1155.96 | N10: =SUM(G10:M10) -> 13999.99
A11: 6 | B11: 030502004002 | C11: 电视、电话插座 | D11: 1.名称：双孔信息插座（含模块） 2.参数：详见设计图纸及技术规范书 3.其它:满足完成此项工作所需要的全部工作内容，包括设计图纸、技术规范书、答疑、招标文件、现行规范、图集、验收等全部要求 | E11: 个 | F11: 4 | G11: 343.49 | H11: 13.21 | I11: 4.4 | J11: 17.61 | K11: 13.21 | L11: 48.44 | M11: 39.63 | N11: =SUM(G11:M11) -> 479.99
A12: 7 | B12: 030502003002 | C12: 分线接线箱（盒） | D12: 1.名称：铁质接线盒 2.参数：详见设计图纸及技术规范书 3.其它:满足完成此项工作所需要的全部工作内容，包括设计图纸、技术规范书、答疑、招标文件、现行规范、图集、验收等全部要求 | E12: 个 | F12: 4 | G12: 209.17 | H12: 55.05 | I12: 27.52 | J12: 154.13 | K12: 44.04 | L12: 60.55 | M12: 49.54 | N12: =SUM(G12:M12) -> 600
A13: 8 | B13: 030502009005 | C13: LC-LC单模光纤跳线（3m） | D13: 1.名称:LC-LC单模光纤跳线（3m） 2.其它:满足完成此项工作所需要的全部工作内容，包括设计图纸、技术规范书、答疑、招标文件、现行规范、图集、验收等全部要求 | E13: 条 | F13: 12 | G13: 386.42 | H13: 14.86 | I13: 4.95 | J13: 19.82 | K13: 14.86 | L13: 54.5 | M13: 44.59 | N13: =SUM(G13:M13) -> 540
A14: 9 | B14: 030502009006 | C14: LC-LC多模光纤跳线（3m） | D14: 1.名称:LC-LC多模光纤跳线（3m） 2.其它:满足完成此项工作所需要的全部工作内容，包括设计图纸、技术规范书、答疑、招标文件、现行规范、图集、验收等全部要求 | E14: 条 | F14: 12 | G14: 300.55 | H14: 11.56 | I14: 3.85 | J14: 15.41 | K14: 11.56 | L14: 42.39 | M14: 34.68 | N14: =SUM(G14:M14) -> 420
A15: 本页小计 | N15: =SUM(N10:N14) -> 16039.98
A16: 10 | B16: 030502009007 | C16: 六类非屏蔽跳线（3m） | D16: 1.名称:六类非屏蔽跳线（3m） 2.其它:满足完成此项工作所需要的全部工作内容，包括设计图纸、技术规范书、答疑、招标文件、现行规范、图集、验收等全部要求 | E16: 条 | F16: 6 | G16: 107.34 | H16: 4.13 | I16: 1.38 | J16: 5.5 | K16: 4.13 | L16: 15.14 | M16: 12.39 | N16: =SUM(G16:M16) -> 150.01
A17: 11 | B17: 030411003003 | C17: 桥架 | D17: 1.名称:热浸锌钢制金属线槽 2.型号：400*100 3.包含但不限于桥架、弯头、三通或四通、盖板、隔板、附件安装、接地跨接等 4.其它:满足完成此项工作所需要的全部工作内容，满足设计图纸、技术规范书、答疑、招标文件、现行规范、图集、验收等全部要求 | E17: m | F17: 125 | G17: 4025.23 | H17: 154.82 | I17: 51.61 | J17: 206.42 | K17: 154.82 | L17: 567.66 | M17: 464.45 | N17: =SUM(G17:M17) -> 5625.01
A18: 12 | B18: 030411003004 | C18: 桥架 | D18: 1.名称:热浸锌钢制金属线槽 2.型号：200*100 3.包含但不限于桥架、弯头、三通或四通、盖板、隔板、附件安装、接地跨接等 4.其它:满足完成此项工作所需要的全部工作内容，满足设计图纸、技术规范书、答疑、招标文件、现行规范、图集、验收等全部要求 | E18: m | F18: 85.28 | G18: 1525.65 | H18: 58.68 | I18: 19.56 | J18: 78.24 | K18: 58.68 | L18: 215.16 | M18: 176.04 | N18: =SUM(G18:M18) -> 2132.01
A19: 13 | B19: 030413001004 | C19: 桥架支吊架制作及安装 | D19: 1.名称:桥架支吊架制作及安装 2.规格:综合、热浸镀锌 3.其它：满足完成此项工作所需要的全部工作内容，满足设计图纸、技术规范书、答疑、招标文件、现行规范、图集、验收等全部要求 | E19: kg | F19: 126.66 | G19: 529.88 | H19: 139.44 | I19: 69.72 | J19: 390.44 | K19: 111.55 | L19: 153.39 | M19: 125.5 | N19: =SUM(G19:M19) -> 1519.92
A20: 本页小计 | N20: =SUM(N16:N19) -> 9426.95
A21: 14 | B21: 030502005003 | C21: 双绞线缆 | D21: 1.名称:超六类非屏蔽四对双绞线 2.规格:CAT.6A UTP 3.其他:满足完成此项工作所需要的全部工作内容，包括设计图纸、技术规范书、答疑、招标文件、现行规范、图集、验收等全部要求 | E21: m | F21: 176 | G21: 871.93 | H21: 72.66 | I21: 29.06 | J21: 217.98 | K21: 101.72 | L21: 159.85 | M21: 130.79 | N21: =SUM(G21:M21) -> 1583.99
A22: 15 | B22: 030411001004 | C22: 配管 | D22: 1.名称:紧定式镀锌钢导管 2.材质:JGD20 3.敷设方式:综合考虑 4.其他:满足完成此项工作所需要的全部工作内容，满足设计图纸、技术规范书、答疑、招标文件、现行规范、图集、验收等全部要求 | E22: m | F22: 20 | G22: 55.78 | H22: 14.68 | I22: 7.34 | J22: 41.1 | K22: 11.74 | L22: 16.15 | M22: 13.21 | N22: =SUM(G22:M22) -> 160
A23: 16 | B23: 030413002003 | C23: 凿（压)槽 | D23: 1.名称:二次结构凿槽 2.规格:DN32以内 3.类型:砼、砌筑结构 4.含填补恢复 5.满足完成此项工作所需要的全部工作内容，满足设计图纸、技术规范书、答疑、招标文件、现行规范、图集、验收等全部要求 | E23: m | F23: 14 | G23: 73.21 | H23: 19.27 | I23: 9.63 | J23: 53.94 | K23: 15.41 | L23: 21.19 | M23: 17.34 | N23: =SUM(G23:M23) -> 209.99
A24: 17 | B24: 030413001005 | C24: 管道支架/综合支架 | D24: 1.名称:管道支架制作安装 2.材质：热镀锌 3.其它：满足完成此项工作所需要的全部工作内容，满足设计图纸、技术规范书、答疑、招标文件、现行规范、图集、验收等全部要求 | E24: kg | F24: 1.04 | G24: 3.63 | H24: 0.95 | I24: 0.48 | J24: 2.67 | K24: 0.76 | L24: 1.05 | M24: 0.86 | N24: =SUM(G24:M24) -> 10.4
A25: 本页小计 | N25: =SUM(N21:N24) -> 1964.38
A26: 18 | B26: 030502007003 | C26: 光缆 | D26: 1.名称:光缆 2.规格:12芯多模光纤OS2 3.敷设方式:桥架内敷设 4.其他:满足完成此项工作所需要的全部工作内容，包括设计图纸、技术规范书、答疑、招标文件、现行规范、图集、验收等全部要求 | E26: m | F26: 1500 | G26: 3756.88 | H26: 144.5 | I26: 48.17 | J26: 192.66 | K26: 144.5 | L26: 529.82 | M26: 433.49 | N26: =SUM(G26:M26) -> 5250.02
A27: 19 | B27: 030502019003 | C27: 双绞线缆测试 | D27: 1.测试内容:双绞线缆 2.其他:满足完成此项工作所需要的全部工作内容，包括设计图纸、技术规范书、答疑、招标文件、现行规范、图集、验收等全部要求 | E27: 链路 | F27: 6 | G27: 313.76 | H27: 82.57 | I27: 41.28 | J27: 231.19 | K27: 66.06 | L27: 90.83 | M27: 74.31 | N27: =SUM(G27:M27) -> 900
A28: 20 | B28: 030502020003 | C28: 光纤测试 | D28: 1.测试内容:光纤 2.其他:满足完成此项工作所需要的全部工作内容，包括设计图纸、技术规范书、答疑、招标文件、现行规范、图集、验收等全部要求 | E28: 链路 | F28: 6 | G28: 418.35 | H28: 110.09 | I28: 55.05 | J28: 308.26 | K28: 88.07 | L28: 121.1 | M28: 99.08 | N28: =SUM(G28:M28) -> 1200
A29: 21 | B29: 030503010003 | C29: 建筑设备自控化系统试运行 | D29: 1.名称:建筑设备自控化系统试运行 2.其他:满足完成此项工作所需要的全部工作内容，包括设计图纸、技术规范书、答疑、招标文件、现行规范、图集、验收等全部要求 | E29: 系统 | F29: 1 | G29: 1045.87 | H29: 275.23 | I29: 137.61 | J29: 770.64 | K29: 220.18 | L29: 302.75 | M29: 247.71 | N29: =SUM(G29:M29) -> 2999.99
A30: 本页小计 | N30: =SUM(N26:N29) -> 10350.01
A31: 22 | B31: 03B001 | C31: 系统综合及集成 | D31: 1.清单未列项、图纸中未表示或技术规格书未做要求，但为了实现本系统各项功能必须增加的配套及辅助的材料、设备的所有工作内容及费用； 2.施工深化设计增加的实现本系统设计功能必要的配套及辅助的材料、设备所需的所有工作内容及费用； 3.实现设计功能所做的满足图纸、技术规格书要求的各项综合与集成，包括不限于各项检测、试验、调试、软件开发、联动等所有工作内容及费用 | E31: 项 | F31: 1 | G31: 2788.99 | H31: 733.94 | I31: 366.97 | J31: 2055.05 | K31: 587.16 | L31: 807.34 | M31: 660.55 | N31: =SUM(G31:M31) -> 8000
A32: 23 | B32: 031301017005 | C32: 脚手架搭拆 | D32: 1.脚手架费 2.按项包干 3.其它:满足完成此项工作所需要的全部工作内容，包括设计图纸、技术规范书、答疑、招标文件、现行规范、图集、验收等全部要求 | E32: 项 | F32: 1 | G32: 697.25 | H32: 183.49 | I32: 91.74 | J32: 513.76 | K32: 146.79 | L32: 201.83 | M32: 165.14 | N32: =SUM(G32:M32) -> 2000
A33: 本页小计 | N33: =SUM(N31:N32) -> 10000
A34: 合 计 | N34: =N9+N15+N20+N25+N30+N33 -> 67681.33

Sheet 8#、15#非管区入侵报警系统
A1: 分部分项工程和单价措施项目清单与计价表
A2: 分部分项工程和单价措施项目清单与计价表
A3: 序号 | B3: 项目编码 | C3: 项目名称 | D3: 项目特征描述 | E3: 计量单位 | F3: 工程量 | G3: 金额（元）
G4: 主材/设备费 | H4: 辅材 | I4: 机械措施 | J4: 人工 | K4: 管理费 | L4: 利润 | M4: 税金 | N4: 总价
A5: 1 | B5: 030507001001 | C5: 红外微波双鉴探测器 | D5: 1.名称:红外微波双鉴探测器 2.技术参数:三鉴移动探测器(红外+微波+智能芯片)，吸顶安装,探测范围:360°，直径6米(安装高度3.6米)，CCC认证，自动脉冲计数，采用多普勒(效应)+ 能量分析，全范围自动温度补偿，超强抗误报能力，工作电压: DC9-16V 3.其它:满足完成此项工作所需要的全部工作内容，包括设计图纸、技术规范书、答疑、招标文件、现行规范、图集、验收等全部要求 | E5: 套 | F5: 62 | G5: 9760.73 | H5: 375.41 | I5: 125.14 | J5: 500.55 | K5: 375.41 | L5: 1376.51 | M5: 1126.24 | N5: =SUM(G5:M5) -> 13639.99
A6: 2 | B6: 030507008014 | C6: 探测器电源 | D6: 1.名称:探测器电源 2.规格:开关电源12V 3A（探测器集中供电） 3.其它:满足完成此项工作所需要的全部工作内容，包括设计图纸、技术规范书、答疑、招标文件、现行规范、图集、验收等全部要求 | E6: 台 | F6: 2 | G6: 257.61 | H6: 9.91 | I6: 3.3 | J6: 13.21 | K6: 9.91 | L6: 36.33 | M6: 29.72 | N6: =SUM(G6:M6) -> 359.99
A7: 3 | B7: 030507001002 | C7: 玻璃破碎报警器 | D7: 1.名称:玻璃破碎报警器 2.技术参数:标准结构：选用防火材料，红色； 电气性能：最大耐用电流3A@36VDC； 适用门型：安全门、逃生门、安全系统等； 3.其它:满足完成此项工作所需要的全部工作内容，包括设计图纸、技术规范书、答疑、招标文件、现行规范、图集、验收等全部要求 | E7: 套 | F7: 62 | G7: 6655.05 | H7: 255.96 | I7: 85.32 | J7: 341.28 | K7: 255.96 | L7: 938.53 | M7: 767.89 | N7: =SUM(G7:M7) -> 9299.99
A8: 本页小计 | N8: =SUM(N5:N7) -> 23299.97
A9: 4 | B9: 030904003002 | C9: 紧急报警按钮 | D9: 1.名称:紧急报警按钮 2.安装方式:暗装,底距地1.4m 3.其它:满足完成此项工作所需要的全部工作内容，包括设计图纸、技术规范书、答疑、招标文件、现行规范、图集、验收等全部要求 | E9: 个 | F9: 14 | G9: 585.69 | H9: 154.13 | I9: 77.06 | J9: 431.56 | K9: 123.3 | L9: 169.54 | M9: 138.72 | N9: =SUM(G9:M9) -> 1680
A10: 5 | B10: 030507002002 | C10: 四防区模块 | D10: 1.名称:四防区模块（含模块箱和电源等） 2.其它:满足完成此项工作所需要的全部工作内容，包括设计图纸、技术规范书、答疑、招标文件、现行规范、图集、验收等全部要求 | E10: 套 | F10: 13 | G10: 6046.79 | H10: 232.57 | I10: 77.52 | J10: 310.09 | K10: 232.57 | L10: 852.75 | M10: 697.71 | N10: =SUM(G10:M10) -> 8450
A11: 6 | B11: 030507002003 | C11: 八防区模块 | D11: 1.名称:八防区模块（含模块箱和电源等） 2.其它:满足完成此项工作所需要的全部工作内容，包括设计图纸、技术规范书、答疑、招标文件、现行规范、图集、验收等全部要求 | E11: 套 | F11: 21 | G11: 12773.39 | H11: 491.28 | I11: 163.76 | J11: 655.05 | K11: 491.28 | L11: 1801.38 | M11: 1473.85 | N11: =SUM(G11:M11) -> 17849.99
A12: 7 | B12: 030507002004 | C12: 总线式报警主机 | D12: 1.名称:总线式报警主机（含总线延长器、软件等） 2.规格:专业级总线制网络报警主机，自带8防区，可扩展至256防区/自带4路继电器，可扩展至256路继电器输出/串口输出/电话/网络上报/8个独立子系统/总线可达2400米/8.2K 线尾组，支持本地8路防区/2线制防区防拆/支持定时撤布防/时控输出 3.其它:满足完成此项工作所需要的全部工作内容，包括设计图纸、技术规范书、答疑、招标文件、现行规范、图集、验收等全部要求 | E12: 套 | F12: 2 | G12: 8587.16 | H12: 330.28 | I12: 110.09 | J12: 440.37 | K12: 330.28 | L12: 1211.01 | M12: 990.83 | N12: =SUM(G12:M12) -> 12000.02
A13: 本页小计 | N13: =SUM(N9:N12) -> 39980.01
A14: 8 | B14: 030904016001 | C14: 主机电源 | D14: 1.名称:主机电源 2.规格:充电后备电池（12V7AH） 标准电压 12V 额定容量 7.0Ah 3.其它:满足完成此项工作所需要的全部工作内容，包括设计图纸、技术规范书、答疑、招标文件、现行规范、图集、验收等全部要求 | E14: 套 | F14: 2 | G14: 500.92 | H14: 19.27 | I14: 6.42 | J14: 25.69 | K14: 19.27 | L14: 70.64 | M14: 57.8 | N14: =SUM(G14:M14) -> 700.01
A15: 本页小计 | N15: =N14 -> 700.01
A16: 9 | B16: 030507013002 | C16: 报警控制键盘 | D16: 1.名称:报警控制键盘 2.技术参数:LCD报警键盘；连接到报警主机，可以对报警主机进行操作和编程，通过指示灯和报警音提示报警； 主机状态指示灯：系统故障（橙色），网络链接状态（绿色），报警（红色），布撤防（蓝色），配置状态（红绿双色） 功能键：8个，工程、查询，旁路，一键，火警，紧急，左键，右键； 防拆功能：支持；与主机通讯：485；键盘警情输出：蜂鸣器； 功能特性：对主机编程、撤布防、消警、旁路/旁路恢复、工程测试、子系统操作、继电器操作、主机状态查询； 支持刷卡布撤防，但刷卡不支持消警功能，卡片数量由主机限制，目前网络主机最大可添加32张卡片； 支持连接遥控器进行远程布撤防，键盘最多所能支持的无线遥控器数量由主机决定，最多支持32个遥控器； 支持双向遥控器，遥控器LED显示操作结果； 功耗：1.8W；工作温度：-10℃～＋55℃；工作湿度：10％～90％； 3.其它:满足完成此项工作所需要的全部工作内容，包括设计图纸、技术规范书、答疑、招标文件、现行规范、图集、验收等全部要求 | E16: 台 | F16: 2 | G16: 2576.15 | H16: 99.08 | I16: 33.03 | J16: 132.11 | K16: 99.08 | L16: 363.3 | M16: 297.25 | N16: =SUM(G16:M16) -> 3600
A17: 本页小计 | N17: =N16 -> 3600
A18: 10 | B18: 030904005002 | C18: 声光报警器 | D18: 1.名称:声光报警器 2.规格:声光报警器(红/白双色外观),12VDC 压电警号,防火ABS阻燃外壳,声压(VDC)：110±3 3.其它:满足完成此项工作所需要的全部工作内容，包括设计图纸、技术规范书、答疑、招标文件、现行规范、图集、验收等全部要求 | E18: 个 | F18: 5 | G18: 161.01 | H18: 6.19 | I18: 2.06 | J18: 8.26 | K18: 6.19 | L18: 22.71 | M18: 18.58 | N18: =SUM(G18:M18) -> 225
A19: 11 | B19: 030507017004 | C19: 安全防范分系统调试 | D19: 1.名称：入侵报警系统调试 2.其它:满足完成此项工作所需要的全部工作内容，包括设计图纸、技术规范书、答疑、招标文件、现行规范、图集、验收等全部要求 | E19: 系统 | F19: 1 | G19: 41.83 | H19: 11.01 | I19: 5.5 | J19: 30.83 | K19: 8.81 | L19: 12.11 | M19: 9.91 | N19: =SUM(G19:M19) -> 120
A20: 12 | B20: 03B027 | C20: 系统综合及集成 | D20: 1.清单未列项、图纸中未表示或技术规格书未做要求，但为了实现本系统各项功能必须增加的配套及辅助的材料、设备的所有工作内容及费用； 2.施工深化设计增加的实现本系统设计功能必要的配套及辅助的材料、设备所需的所有工作内容及费用； 3.实现设计功能所做的满足图纸、技术规格书要求的各项综合与集成，包括不限于各项检测、试验、调试、软件开发、联动等所有工作内容及费用 | E20: 项 | F20: 1 | G20: 1394.5 | H20: 366.97 | I20: 183.49 | J20: 1027.52 | K20: 293.58 | L20: 403.67 | M20: 330.28 | N20: =SUM(G20:M20) -> 4000.01
A21: 本页小计 | N21: =SUM(N18:N20) -> 4345.01
A22: 13 | B22: 030411001066 | C22: 配管 | D22: 1.名称：紧定式镀锌钢导管 2.规格：JDG20 3.敷设方式：明配 4.其它:满足完成此项工作所需要的全部工作内容，包括设计图纸、技术规范书、答疑、招标文件、现行规范、图集、验收等全部要求 | E22: m | F22: 284.6 | G22: 446.48 | H22: 117.5 | I22: 58.75 | J22: 328.99 | K22: 94 | L22: 129.24 | M22: 105.75 | N22: =SUM(G22:M22) -> 1280.71
A23: 14 | B23: 030411001067 | C23: 配管 | D23: 1.名称：紧定式镀锌钢导管 2.规格：JDG20 3.敷设方式：暗配 4.其它:满足完成此项工作所需要的全部工作内容，包括设计图纸、技术规范书、答疑、招标文件、现行规范、图集、验收等全部要求 | E23: m | F23: 12 | G23: 18.83 | H23: 4.95 | I23: 2.48 | J23: 13.87 | K23: 3.96 | L23: 5.45 | M23: 4.46 | N23: =SUM(G23:M23) -> 54
A24: 15 | B24: 030413002019 | C24: 凿（压)槽 | D24: 1.名称:管线剔槽及恢复 2.满足完成此项工作所需要的全部工作内容，满足设计图纸、答疑、招标文件、现行规范、图集、验收等全部要求 | E24: m | F24: 12 | G24: 51.52 | H24: 4.29 | I24: 1.72 | J24: 12.88 | K24: 6.01 | L24: 9.45 | M24: 7.73 | N24: =SUM(G24:M24) -> 93.6
A25: 16 | B25: 030413001035 | C25: 管道支架/综合支架 | D25: 1.名称:管道支架制作安装 2.材质:热镀锌 3.安装高度:综合考虑 4.满足完成此项工作所需要的全部工作内容，满足设计图纸、技术规范书、答疑、招标文件、现行规范、图集、验收等全部要求 | E25: kg | F25: 50.85 | G25: 230.46 | H25: 60.65 | I25: 30.32 | J25: 169.81 | K25: 48.52 | L25: 66.71 | M25: 54.58 | N25: =SUM(G25:M25) -> 661.05
A26: 17 | B26: 030411004060 | C26: 配线 | D26: 1.名称：配线 2.规格：RYYP-4*1.0 3.敷设方式：管内穿线 4.其它:满足完成此项工作所需要的全部工作内容，包括设计图纸、技术规范书、答疑、招标文件、现行规范、图集、验收等全部要求 | E26: m | F26: 237.4 | G26: 662.11 | H26: 174.24 | I26: 87.12 | J26: 487.87 | K26: 139.39 | L26: 191.66 | M26: 156.81 | N26: =SUM(G26:M26) -> 1899.2
A27: 本页小计 | N27: =SUM(N22:N26) -> 3988.56
A28: 18 | B28: 030411004061 | C28: 配线 | D28: 1.名称：配线 2.规格：RYYP-4*1.0 3.敷设方式：线槽配线 4.其它:满足完成此项工作所需要的全部工作内容，包括设计图纸、技术规范书、答疑、招标文件、现行规范、图集、验收等全部要求 | E28: m | F28: 775.5 | G28: 2162.86 | H28: 569.17 | I28: 284.59 | J28: 1593.69 | K28: 455.34 | L28: 626.09 | M28: 512.26 | N28: =SUM(G28:M28) -> 6204
A29: 19 | B29: 030411004062 | C29: 配线 | D29: 1.名称：配线 2.规格：RYYP-2*1.0 3.敷设方式：管内穿线 4.其它:满足完成此项工作所需要的全部工作内容，包括设计图纸、技术规范书、答疑、招标文件、现行规范、图集、验收等全部要求 | E29: m | F29: 59.2 | G29: 92.87 | H29: 24.44 | I29: 12.22 | J29: 68.43 | K29: 19.55 | L29: 26.88 | M29: 22 | N29: =SUM(G29:M29) -> 266.39
A30: 20 | B30: 030411004063 | C30: 配线 | D30: 1.名称：配线 2.规格：RYYP-2*1.0 3.敷设方式：线槽配线 4.其它:满足完成此项工作所需要的全部工作内容，包括设计图纸、技术规范书、答疑、招标文件、现行规范、图集、验收等全部要求 | E30: m | F30: 156.2 | G30: 245.05 | H30: 64.49 | I30: 32.24 | J30: 180.56 | K30: 51.59 | L30: 70.93 | M30: 58.04 | N30: =SUM(G30:M30) -> 702.9
A31: 21 | B31: 030411006018 | C31: 接线盒 | D31: 1.名称:铁接线盒 2.安装形式:满足设计及规范验收要求 3.其它:满足完成此项工作所需要的全部工作内容，包括设计图纸、技术规范书、答疑、招标文件、现行规范、图集、验收等全部要求 | E31: 个 | F31: 29 | G31: 121.32 | H31: 31.93 | I31: 15.96 | J31: 89.39 | K31: 25.54 | L31: 35.12 | M31: 28.73 | N31: =SUM(G31:M31) -> 347.99
A32: 本页小计 | N32: =SUM(N28:N31) -> 7521.28
A33: 22 | B33: 030411001068 | C33: 配管 | D33: 1.名称：紧定式镀锌钢导管 2.规格：JDG20 3.敷设方式：明配 4.其它:满足完成此项工作所需要的全部工作内容，包括设计图纸、技术规范书、答疑、招标文件、现行规范、图集、验收等全部要求 | E33: m | F33: 2.3 | G33: 3.61 | H33: 0.95 | I33: 0.47 | J33: 2.66 | K33: 0.76 | L33: 1.04 | M33: 0.85 | N33: =SUM(G33:M33) -> 10.34
A34: 23 | B34: 030411004064 | C34: 配线 | D34: 1.名称：配线 2.规格：RYYP-4*1.0 3.敷设方式：管内穿线 4.其它:满足完成此项工作所需要的全部工作内容，包括设计图纸、技术规范书、答疑、招标文件、现行规范、图集、验收等全部要求 | E34: m | F34: 2.3 | G34: 3.61 | H34: 0.95 | I34: 0.47 | J34: 2.66 | K34: 0.76 | L34: 1.04 | M34: 0.85 | N34: =SUM(G34:M34) -> 10.34
A35: 24 | B35: 030411004065 | C35: 配线 | D35: 1.名称：配线 2.规格：RYYP-4*1.0 3.敷设方式：线槽配线 4.其它:满足完成此项工作所需要的全部工作内容，包括设计图纸、技术规范书、答疑、招标文件、现行规范、图集、验收等全部要求 | E35: m | F35: 55 | G35: 86.28 | H35: 22.71 | I35: 11.35 | J35: 63.58 | K35: 18.17 | L35: 24.98 | M35: 20.44 | N35: =SUM(G35:M35) -> 247.51
A36: 25 | B36: 030411006019 | C36: 接线盒 | D36: 1.名称:铁接线盒 2.安装形式:满足设计及规范验收要求 3.其它:满足完成此项工作所需要的全部工作内容，包括设计图纸、技术规范书、答疑、招标文件、现行规范、图集、验收等全部要求 | E36: 个 | F36: 1 | G36: 4.18 | H36: 1.1 | I36: 0.55 | J36: 3.08 | K36: 0.88 | L36: 1.21 | M36: 0.99 | N36: =SUM(G36:M36) -> 11.99
A37: 本页小计 | N37: =SUM(N33:N36) -> 280.18
A38: 26 | B38: 030411001069 | C38: 配管 | D38: 1.名称：紧定式镀锌钢导管 2.规格：JDG20 3.敷设方式：明配 4.其它:满足完成此项工作所需要的全部工作内容，包括设计图纸、技术规范书、答疑、招标文件、现行规范、图集、验收等全部要求 | E38: m | F38: 533.6 | G38: 837.12 | H38: 220.29 | I38: 110.15 | J38: 616.82 | K38: 176.23 | L38: 242.32 | M38: 198.26 | N38: =SUM(G38:M38) -> 2401.19
A39: 27 | B39: 030411001070 | C39: 配管 | D39: 1.名称：紧定式镀锌钢导管 2.规格：JDG20 3.敷设方式：暗配 4.其它:满足完成此项工作所需要的全部工作内容，包括设计图纸、技术规范书、答疑、招标文件、现行规范、图集、验收等全部要求 | E39: m | F39: 60.93 | G39: 95.59 | H39: 25.15 | I39: 12.58 | J39: 70.43 | K39: 20.12 | L39: 27.67 | M39: 22.64 | N39: =SUM(G39:M39) -> 274.18
A40: 28 | B40: 030413002020 | C40: 凿（压)槽 | D40: 1.名称:管线剔槽及恢复 2.满足完成此项工作所需要的全部工作内容，满足设计图纸、答疑、招标文件、现行规范、图集、验收等全部要求 | E40: m | F40: 60 | G40: 257.61 | H40: 21.47 | I40: 8.59 | J40: 64.4 | K40: 30.06 | L40: 47.23 | M40: 38.64 | N40: =SUM(G40:M40) -> 468
A41: 29 | B41: 030413001036 | C41: 管道支架/综合支架 | D41: 1.名称:管道支架制作安装 2.材质:热镀锌 3.安装高度:综合考虑 4.满足完成此项工作所需要的全部工作内容，满足设计图纸、技术规范书、答疑、招标文件、现行规范、图集、验收等全部要求 | E41: kg | F41: 95.23 | G41: 398.39 | H41: 104.84 | I41: 52.42 | J41: 293.55 | K41: 83.87 | L41: 115.32 | M41: 94.36 | N41: =SUM(G41:M41) -> 1142.75
A42: 30 | B42: 030411004066 | C42: 配线 | D42: 1.名称：配线 2.规格：RYYP-4*1.0 3.敷设方式：管内穿线 4.其它:满足完成此项工作所需要的全部工作内容，包括设计图纸、技术规范书、答疑、招标文件、现行规范、图集、验收等全部要求 | E42: m | F42: 909.49 | G42: 1426.81 | H42: 375.48 | I42: 187.74 | J42: 1051.34 | K42: 300.38 | L42: 413.03 | M42: 337.93 | N42: =SUM(G42:M42) -> 4092.71
A43: 本页小计 | N43: =SUM(N38:N42) -> 8378.83
A44: 31 | B44: 030411004067 | C44: 配线 | D44: 1.名称：配线 2.规格：RYYP-4*1.0 3.敷设方式：线槽配线 4.其它:满足完成此项工作所需要的全部工作内容，包括设计图纸、技术规范书、答疑、招标文件、现行规范、图集、验收等全部要求 | E44: m | F44: 5714.93 | G44: 8965.62 | H44: 2359.37 | I44: 1179.69 | J44: 6606.25 | K44: 1887.5 | L44: 2595.31 | M44: 2123.44 | N44: =SUM(G44:M44) -> 25717.18
A45: 32 | B45: 030411004068 | C45: 配线 | D45: 1.名称：配线 2.规格：RYY-2*1.0 3.敷设方式：管内穿线 4.其它:满足完成此项工作所需要的全部工作内容，包括设计图纸、技术规范书、答疑、招标文件、现行规范、图集、验收等全部要求 | E45: m | F45: 78 | G45: 108.77 | H45: 28.62 | I45: 14.31 | J45: 80.15 | K45: 22.9 | L45: 31.49 | M45: 25.76 | N45: =SUM(G45:M45) -> 312
A46: 33 | B46: 030411004069 | C46: 配线 | D46: 1.名称：配线 2.规格：RYY-2*1.0 3.敷设方式：线槽配线 4.其它:满足完成此项工作所需要的全部工作内容，包括设计图纸、技术规范书、答疑、招标文件、现行规范、图集、验收等全部要求 | E46: m | F46: 905 | G46: 1262.02 | H46: 332.11 | I46: 166.06 | J46: 929.91 | K46: 265.69 | L46: 365.32 | M46: 298.9 | N46: =SUM(G46:M46) -> 3620.01
A47: 34 | B47: 030411006020 | C47: 接线盒 | D47: 1.名称:铁接线盒 2.安装形式:满足设计及规范验收要求 3.其它:满足完成此项工作所需要的全部工作内容，包括设计图纸、技术规范书、答疑、招标文件、现行规范、图集、验收等全部要求 | E47: 个 | F47: 88 | G47: 368.15 | H47: 96.88 | I47: 48.44 | J47: 271.27 | K47: 77.5 | L47: 106.57 | M47: 87.19 | N47: =SUM(G47:M47) -> 1056
A48: 本页小计 | N48: =SUM(N44:N47) -> 30705.19
A49: 35 | B49: 030411001071 | C49: 配管 | D49: 1.名称：紧定式镀锌钢导管 2.规格：JDG20 3.敷设方式：暗配 4.其它:满足完成此项工作所需要的全部工作内容，包括设计图纸、技术规范书、答疑、招标文件、现行规范、图集、验收等全部要求 | E49: m | F49: 23.9 | G49: 37.49 | H49: 9.87 | I49: 4.93 | J49: 27.63 | K49: 7.89 | L49: 10.85 | M49: 8.88 | N49: =SUM(G49:M49) -> 107.54
A50: 36 | B50: 030413002021 | C50: 凿（压)槽 | D50: 1.名称:管线剔槽及恢复 2.满足完成此项工作所需要的全部工作内容，满足设计图纸、答疑、招标文件、现行规范、图集、验收等全部要求 | E50: m | F50: 23.9 | G50: 102.62 | H50: 8.55 | I50: 3.42 | J50: 25.65 | K50: 11.97 | L50: 18.81 | M50: 15.39 | N50: =SUM(G50:M50) -> 186.41
A51: 37 | B51: 030411004070 | C51: 配线 | D51: 1.名称：配线 2.规格：RYY-2*1.0 3.敷设方式：管内穿线 4.其它:满足完成此项工作所需要的全部工作内容，包括设计图纸、技术规范书、答疑、招标文件、现行规范、图集、验收等全部要求 | E51: m | F51: 27.2 | G51: 42.67 | H51: 11.23 | I51: 5.61 | J51: 31.44 | K51: 8.98 | L51: 12.35 | M51: 10.11 | N51: =SUM(G51:M51) -> 122.39
A52: 38 | B52: 030411006021 | C52: 接线盒 | D52: 1.名称:铁接线盒 2.安装形式:满足设计及规范验收要求 3.其它:满足完成此项工作所需要的全部工作内容，包括设计图纸、技术规范书、答疑、招标文件、现行规范、图集、验收等全部要求 | E52: 个 | F52: 4 | G52: 16.73 | H52: 4.4 | I52: 2.2 | J52: 12.33 | K52: 3.52 | L52: 4.84 | M52: 3.96 | N52: =SUM(G52:M52) -> 47.98
A53: 39 | B53: 031301017024 | C53: 脚手架搭拆 | D53: 1.脚手架费 2.按项包干 3.其它:满足完成此项工作所需要的全部工作内容，包括设计图纸、技术规范书、答疑、招标文件、现行规范、图集、验收等全部要求 | E53: 项 | F53: 1 | G53: 209.17 | H53: 55.05 | I53: 27.52 | J53: 154.13 | K53: 44.04 | L53: 60.55 | M53: 49.54 | N53: =SUM(G53:M53) -> 600
A54: 40 | B54: 03B030 | C54: 超高费 | E54: 项 | F54: 1 | G54: 275.23 | H54: 22.94 | I54: 9.17 | J54: 68.81 | K54: 32.11 | L54: 50.46 | M54: 41.28 | N54: =SUM(G54:M54) -> 500
A55: 本页小计 | N55: =SUM(N49:N54) -> 1564.32
A56: 合 计 | N56: =N8+N13+N15+N17+N21+N27+N32+N37+N43+N48+N55 -> 124363.36

Sheet 8#、15#非管区时钟同步系统
A1: 分部分项工程和单价措施项目清单与计价表
A2: 分部分项工程和单价措施项目清单与计价表
A3: 序号 | B3: 项目编码 | C3: 项目名称 | D3: 项目特征描述 | E3: 计量单位 | F3: 工程量 | G3: 金额（元）
G4: 主材/设备费 | H4: 辅材 | I4: 机械措施 | J4: 人工 | K4: 管理费 | L4: 利润 | M4: 税金 | N4: 总价
A5: 1 | B5: 030504001003 | C5: 时间同步服务器 | D5: 1.名称:时间同步服务器 2.技术参数：处理器：≥2颗Intel 至强 4510处理器，单颗核数≥12核， ≥2.40 GHz或以上；内存：≥128G；操作系统： 支持Microsoft Windows Server 2019、 RedHat Enterprise Linux 、 SUSE Linux Enterprise Server、 CentOS、 Ubuntu、 Vmware EXSI；内置SAS硬盘，RAID5，配备4x3TB热插拔硬盘，10000rpm以上；2个千兆以太网口；冗余电源、风扇，可以365天24小时运行；1块单口8Gb HBA卡。 3.其它:满足完成此项工作所需要的全部工作内容，包括设计图纸、技术规范书、答疑、招标文件、现行规范、图集、验收等全部要求 | E5: 台 | F5: 2 | G5: 51522.94 | H5: 1981.66 | I5: 660.56 | J5: 2642.2 | K5: 1981.66 | L5: 7266.06 | M5: 5944.96 | N5: =SUM(G5:M5) -> 72000.04
A6: 2 | B6: 030404001001 | C6: 时间母钟 | D6: 1.名称:时间母钟 2.其它:满足完成此项工作所需要的全部工作内容，包括设计图纸、技术规范书、答疑、招标文件、现行规范、图集、验收等全部要求 | E6: 台 | F6: 2 | G6: 66055.04 | H6: 5504.58 | I6: 2201.84 | J6: 16513.76 | K6: 7706.42 | L6: 12110.1 | M6: 9908.26 | N6: =SUM(G6:M6) -> 120000
A7: 3 | B7: 030404001002 | C7: 网络显示子钟 | D7: 1.名称:网络显示子钟 2.其它:满足完成此项工作所需要的全部工作内容，包括设计图纸、技术规范书、答疑、招标文件、现行规范、图集、验收等全部要求 | E7: 台 | F7: 1 | G7: 3522.94 | H7: 293.58 | I7: 117.44 | J7: 880.74 | K7: 411 | L7: 645.88 | M7: 528.44 | N7: =SUM(G7:M7) -> 6400.02
A8: 本页小计 | N8: =SUM(N5:N7) -> 198400.06
A9: 4 | B9: 031102003001 | C9: GPS天线 | D9: 1.名称:GPS天线 2.其它:满足完成此项工作所需要的全部工作内容，包括设计图纸、技术规范书、答疑、招标文件、现行规范、图集、验收等全部要求 | E9: 副 | F9: 2 | G9: 5944.95 | H9: 495.42 | I9: 198.18 | J9: 1486.23 | K9: 693.57 | L9: 1089.9 | M9: 891.75 | N9: =SUM(G9:M9) -> 10800
A10: 5 | B10: 031102004001 | C10: GPS馈线 | D10: 1.名称:GPS馈线 2.其它:满足完成此项工作所需要的全部工作内容，包括设计图纸、技术规范书、答疑、招标文件、现行规范、图集、验收等全部要求 | E10: m | F10: 500 | G10: 8256.87 | H10: 688.08 | I10: 275.22 | J10: 2064.21 | K10: 963.3 | L10: 1513.77 | M10: 1238.52 | N10: =SUM(G10:M10) -> 14999.97
A11: 6 | B11: 030505008001 | C11: GPS接收机 | D11: 1.名称:GPS接收机 2.其它:满足完成此项工作所需要的全部工作内容，包括设计图纸、技术规范书、答疑、招标文件、现行规范、图集、验收等全部要求 | E11: 台 | F11: 1 | G11: 3853.22 | H11: 321.1 | I11: 128.44 | J11: 963.3 | K11: 449.54 | L11: 706.42 | M11: 577.98 | N11: =SUM(G11:M11) -> 7000
A12: 7 | B12: 030502003006 | C12: 多路输出接口箱 | D12: 1.名称:多路输出接口箱 2.其它:满足完成此项工作所需要的全部工作内容，包括设计图纸、技术规范书、答疑、招标文件、现行规范、图集、验收等全部要求 | E12: 个 | F12: 1 | G12: 3743.12 | H12: 311.93 | I12: 124.77 | J12: 935.78 | K12: 436.7 | L12: 686.24 | M12: 561.47 | N12: =SUM(G12:M12) -> 6800.01
A13: 8 | B13: 030501012028 | C13: 24口接入交换机 | D13: 1.名称:24口接入交换机 2.其它:满足完成此项工作所需要的全部工作内容，包括设计图纸、技术规范书、答疑、招标文件、现行规范、图集、验收等全部要求 | E13: 台 | F13: 2 | G13: 3317.53 | H13: 127.6 | I13: 42.53 | J13: 170.13 | K13: 127.6 | L13: 467.86 | M13: 382.79 | N13: =SUM(G13:M13) -> 4636.04
A14: 本页小计 | N14: =SUM(N9:N13) -> 44236.02
A15: 9 | B15: 03B047 | C15: 系统综合及集成 | D15: 1.清单未列项、图纸中未表示或技术规格书未做要求，但为了实现本系统各项功能必须增加的配套及辅助的材料、设备的所有工作内容及费用； 2.施工深化设计增加的实现本系统设计功能必要的配套及辅助的材料、设备所需的所有工作内容及费用； 3.实现设计功能所做的满足图纸、技术规格书要求的各项综合与集成，包括不限于各项检测、试验、调试、软件开发、联动等所有工作内容及费用 | E15: 项 | F15: 1 | G15: 697.25 | H15: 183.49 | I15: 91.74 | J15: 513.76 | K15: 146.79 | L15: 201.83 | M15: 165.14 | N15: =SUM(G15:M15) -> 2000
A16: 10 | B16: 03B048 | C16: 平台对接 | D16: 1.平台对接 2.其它:满足完成此项工作所需要的全部工作内容，包括设计图纸、技术规范书、答疑、招标文件、现行规范、图集、验收等全部要求 | E16: 项 | F16: 1 | G16: 2752.29 | H16: 229.36 | I16: 91.74 | J16: 688.07 | K16: 321.1 | L16: 504.59 | M16: 412.84 | N16: =SUM(G16:M16) -> 4999.99
A17: 11 | B17: 03B049 | C17: 软件开发 | D17: 1.软件开发 2.其它:满足完成此项工作所需要的全部工作内容，包括设计图纸、技术规范书、答疑、招标文件、现行规范、图集、验收等全部要求 | E17: 项 | F17: 1 | G17: 2752.29 | H17: 229.36 | I17: 91.74 | J17: 688.07 | K17: 321.1 | L17: 504.59 | M17: 412.84 | N17: =SUM(G17:M17) -> 4999.99
A18: 12 | B18: 031301017029 | C18: 脚手架搭拆 | D18: 1.综合考虑项目脚手架搭拆或其他替代措施项目 2.场内外材料搬运 3.拆除脚手架后材料的堆放 4.满足完成此项工作所需要的全部工作内容，满足设计图纸、答疑、招标文件、现行规范、图集、验收等全部要求 | E18: 项 | F18: 1 | G18: 45.58 | H18: 12 | I18: 6 | J18: 33.59 | K18: 9.6 | L18: 13.19 | M18: 10.8 | N18: =SUM(G18:M18) -> 130.76
A19: 本页小计 | N19: =SUM(N15:N18) -> 12130.74
A20: 13 | B20: 03B050 | C20: 超高费 | E20: 项 | F20: 1 | G20: 422.24 | H20: 35.19 | I20: 14.07 | J20: 105.56 | K20: 49.26 | L20: 77.41 | M20: 63.34 | N20: =SUM(G20:M20) -> 767.07
A21: 本页小计 | N21: =N20 -> 767.07
A22: 合 计 | N22: =N8+N14+N19+N21 -> 255533.89

Sheet 8#、15#非管区视频监控系统
A1: 分部分项工程和单价措施项目清单与计价表
A2: 分部分项工程和单价措施项目清单与计价表
A3: 序号 | B3: 项目编码 | C3: 项目名称 | D3: 项目特征描述 | E3: 计量单位 | F3: 工程量 | G3: 金额（元）
G4: 主材/设备费 | H4: 辅材 | I4: 机械措施 | J4: 人工 | K4: 管理费 | L4: 利润 | M4: 税金 | N4: 总价
A5: 1 | B5: 030507008001 | C5: 高清彩色半球摄像机 | D5: 1.名称:高清彩色半球摄像机 2.技术参数:详见技术规范书及图纸，含电源 3.安装方式:吸顶安装 4.其它:满足完成此项工作所需要的全部工作内容，包括设计图纸、技术规范书、答疑、招标文件、现行规范、图集、验收等全部要求 | E5: 台 | F5: 366 | G5: 125715.96 | H5: 4835.23 | I5: 1611.74 | J5: 6446.97 | K5: 4835.23 | L5: 17729.17 | M5: 14505.69 | N5: =SUM(G5:M5) -> 175679.99
A6: 2 | B6: 030507008002 | C6: 高清彩色枪式摄像机 | D6: 1.名称:高清彩色枪式摄像机 2.技术参数:详见技术规范书及图纸，含电源 3.安装方式:支架安装 4.其它:满足完成此项工作所需要的全部工作内容，包括设计图纸、技术规范书、答疑、招标文件、现行规范、图集、验收等全部要求 | E6: 台 | F6: 90 | G6: 32201.83 | H6: 1238.53 | I6: 412.84 | J6: 1651.38 | K6: 1238.53 | L6: 4541.28 | M6: 3715.6 | N6: =SUM(G6:M6) -> 44999.99
A7: 3 | B7: 030507008003 | C7: 室外高清彩色枪式摄像机 | D7: 1.名称:室外高清彩色枪式摄像机2160P 2.技术参数:详见技术规范书及图纸，含电源 3.安装方式:支架安装 | E7: 台 | F7: 37 | G7: 12708.99 | H7: 488.81 | I7: 162.94 | J7: 651.74 | K7: 488.81 | L7: 1792.29 | M7: 1466.42 | N7: =SUM(G7:M7) -> 17760
A8: 4 | B8: 030507008004 | C8: 枪式摄像机支架 | D8: 1.名称:枪式摄像机支架 2.材质:白色、铝合金 3.安装方式:壁装支架 4.其它:满足完成此项工作所需要的全部工作内容，包括设计图纸、技术规范书、答疑、招标文件、现行规范、图集、验收等全部要求 | E8: 台 | F8: 127 | G8: 885.5 | H8: 233.03 | I8: 116.51 | J8: 652.48 | K8: 186.42 | L8: 256.33 | M8: 209.72 | N8: =SUM(G8:M8) -> 2539.99
A9: 本页小计 | N9: =SUM(N5:N8) -> 240979.97
A10: 5 | B10: 030507008005 | C10: 电梯轿厢内暗装彩色广角摄像机 | D10: 1.名称:电梯轿厢内暗装彩色广角摄像机（含楼层叠加器） 2.技术参数详见技术规范书及图纸，含电源 3.安装方式:吸顶安装 4.其它:满足完成此项工作所需要的全部工作内容，包括设计图纸、技术规范书、答疑、招标文件、现行规范、图集、验收等全部要求 | E10: 台 | F10: 10 | G10: 3577.98 | H10: 137.61 | I10: 45.87 | J10: 183.49 | K10: 137.61 | L10: 504.59 | M10: 412.84 | N10: =SUM(G10:M10) -> 4999.99
A11: 6 | B11: 030507008006 | C11: 室外云台摄像机 | D11: 1.名称:室外云台摄像机，技术参数详见技术规范书及图纸，含电源 2.安装方式:支架安装 3.其它:满足完成此项工作所需要的全部工作内容，包括设计图纸、技术规范书、答疑、招标文件、现行规范、图集、验收等全部要求 | E11: 台 | F11: 9 | G11: 30913.76 | H11: 1188.99 | I11: 396.33 | J11: 1585.32 | K11: 1188.99 | L11: 4359.63 | M11: 3566.97 | N11: =SUM(G11:M11) -> 43199.99
A12: 7 | B12: 030502009008 | C12: HDMI线缆 | D12: 1.名称:HDMI线缆 2.规格:9根15m 3.其它:满足完成此项工作所需要的全部工作内容，包括设计图纸、技术规范书、答疑、招标文件、现行规范、图集、验收等全部要求 | E12: 项 | F12: 1 | G12: 990.83 | H12: 82.57 | I12: 33.03 | J12: 247.71 | K12: 115.6 | L12: 181.65 | M12: 148.62 | N12: =SUM(G12:M12) -> 1800.01
A13: 8 | B13: 030501012001 | C13: 24口接入交换机 | D13: 1.名称:24口接入交换机 2.技术参数:接入交换机 2.技术参数:非POE交换机，24个10/100/1000M自适应电口，4个1G/10G SFP+光口，含光模块 3.其它:满足完成此项工作所需要的全部工作内容，包括设计图纸、技术规范书、答疑、招标文件、现行规范、图集、验收等全部要求 | E13: 台 | F13: 35 | G13: 60110.09 | H13: 2311.93 | I13: 770.64 | J13: 3082.57 | K13: 2311.93 | L13: 8477.06 | M13: 6935.78 | N13: =SUM(G13:M13) -> 84000
A14: 本页小计 | N14: =SUM(N10:N13) -> 133999.99
A15: 9 | B15: 030502001008 | C15: 弱电机柜 | D15: 1.名称:弱电机柜 2.技术参数:800*800*2000，电池后备1小时，提供柜内电池监控，含2个PDU，详见技术规范书及图纸，含电源 3.安装方式:落地安装 4.其它:满足完成此项工作所需要的全部工作内容，包括设计图纸、技术规范书、答疑、招标文件、现行规范、图集、验收等全部要求 | E15: 台 | F15: 14 | G15: 18033.03 | H15: 693.58 | I15: 231.19 | J15: 924.77 | K15: 693.58 | L15: 2543.12 | M15: 2080.73 | N15: =SUM(G15:M15) -> 25200
A16: 10 | B16: 030502001009 | C16: 弱电机柜 | D16: 1.名称:弱电机柜 2.技术参数:600*1200*2000，含2个PDU 3.安装方式:落地安装 4.其它:满足完成此项工作所需要的全部工作内容，包括设计图纸、技术规范书、答疑、招标文件、现行规范、图集、验收等全部要求 | E16: 台 | F16: 3 | G16: 6011.01 | H16: 231.19 | I16: 77.06 | J16: 308.26 | K16: 231.19 | L16: 847.71 | M16: 693.58 | N16: =SUM(G16:M16) -> 8400
A17: 11 | B17: 030502003003 | C17: 弱电设备箱 | D17: 1.名称:弱电设备箱 2.规格:600x800x200 3.其它:满足完成此项工作所需要的全部工作内容，包括设计图纸、技术规范书、答疑、招标文件、现行规范、图集、验收等全部要求 | E17: 个 | F17: 5 | G17: 963.3 | H17: 80.28 | I17: 32.11 | J17: 240.83 | K17: 112.39 | L17: 176.61 | M17: 144.5 | N17: =SUM(G17:M17) -> 1750.02
A18: 本页小计 | N18: =SUM(N15:N17) -> 35350.02
A19: 12 | B19: 030904008005 | C19: 摄像机防雷模块 | D19: 1.名称:摄像机防雷模块 2.规格:In=10KA Imax=20KA 静态门槛电压 1.5Un 动态电压 2Un 插入损耗 ＜0.2dB 传输速率 10Mbps 响应时间 ＜1ns 3.其它:满足完成此项工作所需要的全部工作内容，包括设计图纸、技术规范书、答疑、招标文件、现行规范、图集、验收等全部要求 | E19: 个 | F19: 56 | G19: 7413.58 | H19: 285.14 | I19: 95.05 | J19: 380.18 | K19: 285.14 | L19: 1045.5 | M19: 855.41 | N19: =SUM(G19:M19) -> 10360
A20: 13 | B20: 030502007007 | C20: 12芯单模光缆 | D20: 1.名称：12芯单模光缆 2.敷设方式：桥架敷设 3.其它:满足完成此项工作所需要的全部工作内容，包括设计图纸、技术规范书、答疑、招标文件、现行规范、图集、验收等全部要求 | E20: m | F20: 4756.07 | G20: 13613.7 | H20: 523.6 | I20: 174.53 | J20: 698.14 | K20: 523.6 | L20: 1919.88 | M20: 1570.81 | N20: =SUM(G20:M20) -> 19024.26
A21: 14 | B21: 030502014001 | C21: 光纤连接 | D21: 1.名称：单模光纤熔接 2.其它:满足完成此项工作所需要的全部工作内容，包括设计图纸、技术规范书、答疑、招标文件、现行规范、图集、验收等全部要求 | E21: 芯 | F21: 480 | G21: 5152.29 | H21: 198.17 | I21: 66.06 | J21: 264.22 | K21: 198.17 | L21: 726.61 | M21: 594.5 | N21: =SUM(G21:M21) -> 7200.02
A22: 15 | B22: 030411003011 | C22: 桥架 | D22: 1.名称：弱电热镀锌桥架 2.规格：400*100 3.其它:满足完成此项工作所需要的全部工作内容，包括设计图纸、技术规范书、答疑、招标文件、现行规范、图集、验收等全部要求 | E22: m | F22: 1433.39 | G22: 49234.97 | H22: 1893.65 | I22: 631.22 | J22: 2524.87 | K22: 1893.65 | L22: 6943.39 | M22: 5680.96 | N22: =SUM(G22:M22) -> 68802.71
A23: 本页小计 | N23: =SUM(N19:N22) -> 105386.99
A24: 16 | B24: 030411003012 | C24: 桥架 | D24: 1.名称：弱电热镀锌桥架 2.规格：300*100 3.其它:满足完成此项工作所需要的全部工作内容，包括设计图纸、技术规范书、答疑、招标文件、现行规范、图集、验收等全部要求 | E24: m | F24: 63.67 | G24: 2050.29 | H24: 78.86 | I24: 26.29 | J24: 105.14 | K24: 78.86 | L24: 289.14 | M24: 236.57 | N24: =SUM(G24:M24) -> 2865.15
A25: 17 | B25: 030411003013 | C25: 桥架 | D25: 1.名称：弱电热镀锌桥架 2.规格：200*100 3.其它:满足完成此项工作所需要的全部工作内容，包括设计图纸、技术规范书、答疑、招标文件、现行规范、图集、验收等全部要求 | E25: m | F25: 1240.94 | G25: 33744.46 | H25: 1297.86 | I25: 432.62 | J25: 1730.49 | K25: 1297.86 | L25: 4758.83 | M25: 3893.59 | N25: =SUM(G25:M25) -> 47155.71
A26: 18 | B26: 030411003014 | C26: 桥架 | D26: 1.名称：弱电热镀锌桥架 2.规格：100*100 3.其它:满足完成此项工作所需要的全部工作内容，包括设计图纸、技术规范书、答疑、招标文件、现行规范、图集、验收等全部要求 | E26: m | F26: 64.94 | G26: 1301.18 | H26: 50.05 | I26: 16.68 | J26: 66.73 | K26: 50.05 | L26: 183.5 | M26: 150.14 | N26: =SUM(G26:M26) -> 1818.33
A27: 19 | B27: 030411003015 | C27: 桥架 | D27: 1.名称：弱电热镀锌桥架 2.规格：600*80 3.其它:满足完成此项工作所需要的全部工作内容，包括设计图纸、技术规范书、答疑、招标文件、现行规范、图集、验收等全部要求 | E27: m | F27: 78.59 | G27: 2699.46 | H27: 103.83 | I27: 34.61 | J27: 138.43 | K27: 103.83 | L27: 380.69 | M27: 311.48 | N27: =SUM(G27:M27) -> 3772.33
A28: 20 | B28: 030411003016 | C28: 桥架 | D28: 1.名称：弱电热镀锌桥架 2.规格：400*80 3.其它:满足完成此项工作所需要的全部工作内容，包括设计图纸、技术规范书、答疑、招标文件、现行规范、图集、验收等全部要求 | E28: m | F28: 191.89 | G28: 6591.16 | H28: 253.51 | I28: 84.5 | J28: 338.01 | K28: 253.51 | L28: 929.52 | M28: 760.52 | N28: =SUM(G28:M28) -> 9210.73
A29: 本页小计 | N29: =SUM(N24:N28) -> 64822.25
A30: 21 | B30: 030411003017 | C30: 桥架 | D30: 1.名称：弱电热镀锌桥架 2.规格：200*80 3.其它:满足完成此项工作所需要的全部工作内容，包括设计图纸、技术规范书、答疑、招标文件、现行规范、图集、验收等全部要求 | E30: m | F30: 636.77 | G30: 12758.77 | H30: 490.72 | I30: 163.57 | J30: 654.3 | K30: 490.72 | L30: 1799.31 | M30: 1472.17 | N30: =SUM(G30:M30) -> 17829.56
A31: 22 | B31: 030411003018 | C31: 桥架 | D31: 1.名称：弱电热镀锌桥架 2.规格：100*80 3.其它:满足完成此项工作所需要的全部工作内容，包括设计图纸、技术规范书、答疑、招标文件、现行规范、图集、验收等全部要求 | E31: m | F31: 387.65 | G31: 7212.42 | H31: 277.4 | I31: 92.47 | J31: 369.87 | K31: 277.4 | L31: 1017.14 | M31: 832.2 | N31: =SUM(G31:M31) -> 10078.9
A32: 23 | B32: 030413001026 | C32: 铁构件 | D32: 1.名称:桥架等支吊架制作与安装 2.规格:综合 3.材质：热镀锌 4.其它:满足完成此项工作所需要的全部工作内容，包括设计图纸、技术规范书、答疑、招标文件、现行规范、图集、验收等全部要求 | E32: kg | F32: 4240.1 | G32: 19216.6 | H32: 5057 | I32: 2528.5 | J32: 14159.6 | K32: 4045.6 | L32: 5562.7 | M32: 4551.3 | N32: =SUM(G32:M32) -> 55121.3
A33: 24 | B33: 030411001047 | C33: 配管 | D33: 1.名称：紧定式镀锌钢导管 2.规格：JDG20 3.敷设方式：明配 4.其它:满足完成此项工作所需要的全部工作内容，包括设计图纸、技术规范书、答疑、招标文件、现行规范、图集、验收等全部要求 | E33: m | F33: 1679.89 | G33: 2635.42 | H33: 693.53 | I33: 346.77 | J33: 1941.89 | K33: 554.83 | L33: 762.89 | M33: 624.18 | N33: =SUM(G33:M33) -> 7559.51
A34: 本页小计 | N34: =SUM(N30:N33) -> 90589.27
A35: 25 | B35: 030411001048 | C35: 配管 | D35: 1.名称：紧定式镀锌钢导管 2.规格：JDG20 3.敷设方式：暗配 4.其它:满足完成此项工作所需要的全部工作内容，包括设计图纸、技术规范书、答疑、招标文件、现行规范、图集、验收等全部要求 | E35: m | F35: 248.85 | G35: 390.4 | H35: 102.74 | I35: 51.37 | J35: 287.66 | K35: 82.19 | L35: 113.01 | M35: 92.46 | N35: =SUM(G35:M35) -> 1119.83
A36: 26 | B36: 030411001049 | C36: 配管 | D36: 1.名称：可挠金属套管 2.规格：DN20 3.敷设方式：明配 4.其它:满足完成此项工作所需要的全部工作内容，包括设计图纸、技术规范书、答疑、招标文件、现行规范、图集、验收等全部要求 | E36: m | F36: 155.05 | G36: 243.24 | H36: 64.01 | I36: 32.01 | J36: 179.23 | K36: 51.21 | L36: 70.41 | M36: 57.61 | N36: =SUM(G36:M36) -> 697.72
A37: 27 | B37: 030413002013 | C37: 凿（压)槽 | D37: 1.名称:管线剔槽及恢复 2.满足完成此项工作所需要的全部工作内容，满足设计图纸、答疑、招标文件、现行规范、图集、验收等全部要求 | E37: m | F37: 150 | G37: 577.98 | H37: 48.17 | I37: 19.27 | J37: 144.5 | K37: 67.43 | L37: 105.96 | M37: 86.7 | N37: =SUM(G37:M37) -> 1050.01
A38: 28 | B38: 030413001027 | C38: 管道支架/综合支架 | D38: 1.名称:管道支架制作安装 2.材质:热镀锌 3.安装高度:综合考虑 4.满足完成此项工作所需要的全部工作内容，满足设计图纸、技术规范书、答疑、招标文件、现行规范、图集、验收等全部要求 | E38: kg | F38: 461.99 | G38: 773.09 | H38: 203.45 | I38: 101.72 | J38: 569.65 | K38: 162.76 | L38: 223.79 | M38: 183.1 | N38: =SUM(G38:M38) -> 2217.56
A39: 29 | B39: 030502005008 | C39: 双绞线缆 | D39: 1.名称：六类网线 2.规格： Cat.6 UTP 3.敷设方式：桥架敷设 4.其它:满足完成此项工作所需要的全部工作内容，包括设计图纸、技术规范书、答疑、招标文件、现行规范、图集、验收等全部要求 | E39: m | F39: 31930.62 | G39: 33395.33 | H39: 8788.24 | I39: 4394.12 | J39: 24607.08 | K39: 7030.6 | L39: 9667.07 | M39: 7909.42 | N39: =SUM(G39:M39) -> 95791.86
A40: 本页小计 | N40: =SUM(N35:N39) -> 100876.98
A41: 30 | B41: 030502005009 | C41: 双绞线缆 | D41: 1.名称：六类网线 2.规格： Cat.6 UTP 3.敷设方式：管内敷设 4.其它:满足完成此项工作所需要的全部工作内容，包括设计图纸、技术规范书、答疑、招标文件、现行规范、图集、验收等全部要求 | E41: m | F41: 2405.63 | G41: 2515.98 | H41: 662.1 | I41: 331.05 | J41: 1853.88 | K41: 529.68 | L41: 728.31 | M41: 595.89 | N41: =SUM(G41:M41) -> 7216.89
A42: 31 | B42: 030411004028 | C42: 配线 | D42: 1.名称：配线 2.规格：RYY-2*1.5 3.敷设方式：管内穿线 4.其它:满足完成此项工作所需要的全部工作内容，包括设计图纸、技术规范书、答疑、招标文件、现行规范、图集、验收等全部要求 | E42: m | F42: 34336.25 | G42: 41896.53 | H42: 11025.4 | I42: 5512.7 | J42: 30871.12 | K42: 8820.32 | L42: 12127.94 | M42: 9922.86 | N42: =SUM(G42:M42) -> 120176.87
A43: 32 | B43: 030411006011 | C43: 接线盒 | D43: 1.名称:铁接线盒 2.安装形式:满足设计及规范验收要求 3.其它:满足完成此项工作所需要的全部工作内容，包括设计图纸、技术规范书、答疑、招标文件、现行规范、图集、验收等全部要求 | E43: 个 | F43: 493 | G43: 2062.46 | H43: 542.75 | I43: 271.38 | J43: 1519.71 | K43: 434.2 | L43: 597.03 | M43: 488.48 | N43: =SUM(G43:M43) -> 5916.01
A44: 33 | B44: 030507017001 | C44: 安全防范分系统调试 | D44: 1.名称：电视监视系统调试 2.其它:满足完成此项工作所需要的全部工作内容，包括设计图纸、技术规范书、答疑、招标文件、现行规范、图集、验收等全部要求 | E44: 系统 | F44: 1 | G44: 2091.74 | H44: 550.46 | I44: 275.23 | J44: 1541.28 | K44: 440.37 | L44: 605.5 | M44: 495.41 | N44: =SUM(G44:M44) -> 5999.99
A45: 34 | B45: 030507019003 | C45: 安全防范系统工程试运行 | D45: 1.名称：安全防范系统工程试运行 2.其它:满足完成此项工作所需要的全部工作内容，包括设计图纸、技术规范书、答疑、招标文件、现行规范、图集、验收等全部要求 | E45: 系统 | F45: 1 | G45: 1743.12 | H45: 458.72 | I45: 229.36 | J45: 1284.4 | K45: 366.97 | L45: 504.59 | M45: 412.84 | N45: =SUM(G45:M45) -> 5000
A46: 本页小计 | N46: =SUM(N41:N45) -> 144309.76
A47: 35 | B47: 030507008007 | C47: 高清彩色半球摄像机 | D47: 1.名称:高清彩色半球摄像机 2.技术参数:详见技术规范书及图纸，含电源 3.安装方式:吸顶安装 4.其它:满足完成此项工作所需要的全部工作内容，包括设计图纸、技术规范书、答疑、招标文件、现行规范、图集、验收等全部要求 | E47: 台 | F47: 92 | G47: 31600.73 | H47: 1215.41 | I47: 405.14 | J47: 1620.55 | K47: 1215.41 | L47: 4456.51 | M47: 3646.24 | N47: =SUM(G47:M47) -> 44159.99
A48: 36 | B48: 030507008008 | C48: 高清彩色枪式摄像机 | D48: 1.名称:高清彩色枪式摄像机 2.技术参数:详见技术规范书及图纸，含电源 3.安装方式:支架安装 4.其它:满足完成此项工作所需要的全部工作内容，包括设计图纸、技术规范书、答疑、招标文件、现行规范、图集、验收等全部要求 | E48: 台 | F48: 51 | G48: 18247.71 | H48: 701.83 | I48: 233.94 | J48: 935.78 | K48: 701.83 | L48: 2573.39 | M48: 2105.5 | N48: =SUM(G48:M48) -> 25499.98
A49: 37 | B49: 030507008009 | C49: 室外高清彩色枪式摄像机 | D49: 1.名称:室外高清彩色枪式摄像机 2.技术参数:详见技术规范书及图纸，含电源 3.安装方式:支架安装 4.其它:满足完成此项工作所需要的全部工作内容，包括设计图纸、技术规范书、答疑、招标文件、现行规范、图集、验收等全部要求 | E49: 台 | F49: 21 | G49: 7213.21 | H49: 277.43 | I49: 92.48 | J49: 369.91 | K49: 277.43 | L49: 1017.25 | M49: 832.29 | N49: =SUM(G49:M49) -> 10080
A50: 38 | B50: 030507008010 | C50: 室外云台摄像机 | D50: 1.名称:室外云台摄像机，技术参数详见技术规范书及图纸，含电源 2.安装方式:支架安装 3.其它:满足完成此项工作所需要的全部工作内容，包括设计图纸、技术规范书、答疑、招标文件、现行规范、图集、验收等全部要求 | E50: 台 | F50: 5 | G50: 17174.31 | H50: 660.55 | I50: 220.18 | J50: 880.73 | K50: 660.55 | L50: 2422.02 | M50: 1981.65 | N50: =SUM(G50:M50) -> 23999.99
A51: 本页小计 | N51: =SUM(N47:N50) -> 103739.96
A52: 39 | B52: 030507008011 | C52: 枪式摄像机支架 | D52: 1.名称:枪式摄像机支架 2.材质:白色、铝合金 3.安装方式:壁装支架 4.其它:满足完成此项工作所需要的全部工作内容，包括设计图纸、技术规范书、答疑、招标文件、现行规范、图集、验收等全部要求 | E52: 台 | F52: 72 | G52: 502.02 | H52: 132.11 | I52: 66.06 | J52: 369.91 | K52: 105.69 | L52: 145.32 | M52: 118.9 | N52: =SUM(G52:M52) -> 1440.01
A53: 40 | B53: 030507008012 | C53: 电梯轿厢内暗装彩色广角摄像机 | D53: 1.名称:电梯轿厢内暗装彩色广角摄像机（含楼层叠加器） 2.技术参数:详见技术规范书及图纸，含电源 3.安装方式:吸顶安装 4.其它:满足完成此项工作所需要的全部工作内容，包括设计图纸、技术规范书、答疑、招标文件、现行规范、图集、验收等全部要求 | E53: 台 | F53: 4 | G53: 1854.83 | H53: 71.34 | I53: 23.78 | J53: 95.12 | K53: 71.34 | L53: 261.58 | M53: 214.02 | N53: =SUM(G53:M53) -> 2592.01
A54: 41 | B54: 030501004001 | C54: 磁盘阵列 | D54: 1.名称:48盘位磁盘阵列 2.技术参数:机架式/8U48盘位/SATA硬盘/可接SAS扩展柜/1536Mbps接入带宽/64位多核处理器、4GB（可扩展至32G）2个千兆数据网口，1个千兆管理网口/冗余电源/支持流媒体1:1:1接入存储转发/视频流、图片、SMART、视频文件混合直写/智能事件检索、精确定位、浓缩播放/RAID 0、1、3、5、6、10、50，60/网络协议：RTSP/ONVIF/PSIA/SIP（GB/T28181）. 3.其它:满足完成此项工作所需要的全部工作内容，包括设计图纸、技术规范书、答疑、招标文件、现行规范、图集、验收等全部要求 | E54: 台 | F54: 10 | G54: 200366.97 | H54: 7706.42 | I54: 2568.81 | J54: 10275.23 | K54: 7706.42 | L54: 28256.88 | M54: 23119.27 | N54: =SUM(G54:M54) -> 280000
A55: 本页小计 | N55: =SUM(N52:N54) -> 284032.02
A56: 42 | B56: 030501004002 | C56: 存储设备 | D56: 1.名称：16TB企业硬盘 2.技术参数：3.5英寸 4000G 7200 128M SATA3 6Gb/S 3.其它:满足完成此项工作所需要的全部工作内容，包括设计图纸、技术规范书、答疑、招标文件、现行规范、图集、验收等全部要求 | E56: 台 | F56: 480 | G56: 1808455 | H56: 69555.962 | I56: 23185.317 | J56: 92741.29 | K56: 69555.962 | L56: 255038.53 | M56: 208667.89 | N56: =SUM(G56:M56) -> 2527200
A57: 43 | B57: 030502009009 | C57: HDMI线缆 | D57: 1.名称:HDMI线缆 2.规格:15m 3.其它:满足完成此项工作所需要的全部工作内容，包括设计图纸、技术规范书、答疑、招标文件、现行规范、图集、验收等全部要求 | E57: 条 | F57: 2 | G57: 165.14 | H57: 13.76 | I57: 5.5 | J57: 41.28 | K57: 19.27 | L57: 30.28 | M57: 24.77 | N57: =SUM(G57:M57) -> 300
A58: 44 | B58: 030507012001 | C58: 解码器 | D58: 1.名称:解码器 2.规格:32路 3.其它:满足完成此项工作所需要的全部工作内容，包括设计图纸、技术规范书、答疑、招标文件、现行规范、图集、验收等全部要求 | E58: 台 | F58: 2 | G58: 64403.67 | H58: 2477.06 | I58: 825.69 | J58: 3302.75 | K58: 2477.06 | L58: 9082.57 | M58: 7431.19 | N58: =SUM(G58:M58) -> 89999.99
A59: 45 | B59: 030507013001 | C59: 控制键盘 | D59: 1.名称:控制键盘 2.技术参数:网络键盘，网络/串口（232/485）接入方式，4维摇杆控制，7 英寸800*480 的触摸式液晶屏，音频输入/输出口，1个USB接口，1路1080P。 3.其它:满足完成此项工作所需要的全部工作内容，包括设计图纸、技术规范书、答疑、招标文件、现行规范、图集、验收等全部要求 | E59: 台 | F59: 2 | G59: 6165.14 | H59: 513.76 | I59: 205.5 | J59: 1541.28 | K59: 719.27 | L59: 1130.28 | M59: 924.77 | N59: =SUM(G59:M59) -> 11200
A60: 本页小计 | N60: =SUM(N56:N59) -> 2628700
A61: 47 | B61: 030501013008 | C61: 视频管理服务器 | D61: 1.名称:视频管理服务器（含鼠标键盘、显示器、软件等） 2.技术参数：处理器：≥2颗Intel 至强 4510处理器，单颗核数≥12核， ≥2.40 GHz或以上；内存：≥128G；操作系统： 支持Microsoft Windows Server 2019、 RedHat Enterprise Linux 、 SUSE Linux Enterprise Server、 CentOS、 Ubuntu、 Vmware EXSI；内置SAS硬盘，RAID5，配备4x3TB热插拔硬盘，10000rpm以上；2个千兆以太网口；冗余电源、风扇，可以365天24小时运行；1块单口8Gb HBA卡。 3.其它:满足完成此项工作所需要的全部工作内容，包括设计图纸、技术规范书、答疑、招标文件、现行规范、图集、验收等全部要求 | E61: 台 | F61: 2 | G61: 64403.67 | H61: 2477.06 | I61: 825.69 | J61: 3302.75 | K61: 2477.06 | L61: 9082.57 | M61: 7431.19 | N61: =SUM(G61:M61) -> 89999.99
A62: 本页小计 | N62: =N61 -> 89999.99
A63: 48 | B63: 030501013009 | C63: 视频比对服务器 | D63: 1.名称:视频比对服务器（含鼠标键盘、显示器、软件等） 2.技术参数：处理器：≥2颗Intel 至强 4510处理器，单颗核数≥12核， ≥2.40 GHz或以上；内存：≥128G；操作系统： 支持Microsoft Windows Server 2019、 RedHat Enterprise Linux 、 SUSE Linux Enterprise Server、 CentOS、 Ubuntu、 Vmware EXSI；内置SAS硬盘，RAID5，配备4x3TB热插拔硬盘，10000rpm以上；2个千兆以太网口；冗余电源、风扇，可以365天24小时运行；1块单口8Gb HBA卡。 3.其它:满足完成此项工作所需要的全部工作内容，包括设计图纸、技术规范书、答疑、招标文件、现行规范、图集、验收等全部要求 | E63: 台 | F63: 1 | G63: 32201.83 | H63: 1238.53 | I63: 412.84 | J63: 1651.38 | K63: 1238.53 | L63: 4541.28 | M63: 3715.6 | N63: =SUM(G63:M63) -> 44999.99
A64: 本页小计 | N64: =N63 -> 44999.99
A65: 49 | B65: 030501013010 | C65: 流媒体服务器 | D65: 1.名称:流媒体服务器（含鼠标键盘、显示器、软件等） 2.技术参数：处理器：≥2颗Intel 至强 4510处理器，单颗核数≥12核， ≥2.40 GHz或以上；内存：≥128G；操作系统： 支持Microsoft Windows Server 2019、 RedHat Enterprise Linux 、 SUSE Linux Enterprise Server、 CentOS、 Ubuntu、 Vmware EXSI；内置SAS硬盘，RAID5，配备4x3TB热插拔硬盘，10000rpm以上；2个千兆以太网口；冗余电源、风扇，可以365天24小时运行；1块单口8Gb HBA卡。 3.其它:满足完成此项工作所需要的全部工作内容，包括设计图纸、技术规范书、答疑、招标文件、现行规范、图集、验收等全部要求 | E65: 台 | F65: 3 | G65: 96605.5 | H65: 3715.6 | I65: 1238.53 | J65: 4954.13 | K65: 3715.6 | L65: 13623.85 | M65: 11146.79 | N65: =SUM(G65:M65) -> 135000
A66: 50 | B66: 030501012002 | C66: 24口交换机 | D66: 1.名称:24口交换机 2.技术参数:非POE交换机,24个10/100/1000M自适应电口，4个1G/10G SFP+光口，支持PoE+/PoE,含光模块 3.其它:满足完成此项工作所需要的全部工作内容，包括设计图纸、技术规范书、答疑、招标文件、现行规范、图集、验收等全部要求 | E66: 台 | F66: 13 | G66: 22326.61 | H66: 858.72 | I66: 286.24 | J66: 1144.95 | K66: 858.72 | L66: 3148.62 | M66: 2576.15 | N66: =SUM(G66:M66) -> 31200.01
A67: 本页小计 | N67: =SUM(N65:N66) -> 166200.01
A68: 51 | B68: 030501012003 | C68: 48口交换机 | D68: 1.名称:48口交换机 2.技术参数:非POE交换机,48个10/100/1000M自适应电口，4个1G/10G SFP+光口，支持PoE+/PoE,含光模块 3.其它:满足完成此项工作所需要的全部工作内容，包括设计图纸、技术规范书、答疑、招标文件、现行规范、图集、验收等全部要求 | E68: 台 | F68: 2 | G68: 5724.77 | H68: 220.18 | I68: 73.39 | J68: 293.58 | K68: 220.18 | L68: 807.34 | M68: 660.55 | N68: =SUM(G68:M68) -> 7999.99
A69: 52 | B69: 030501012004 | C69: 设备网核心交换机 | D69: 1.名称:设备网核心交换机 2.技术参数:包含主机箱2台，共8个槽位，包含2个引擎槽位和6个业务槽位。交换容量≥19T，包转发性能≥2880Mpps。高性能一代主控引擎4个，电源模块4个（可以冗余，交流，600W），36端口千兆以太网电口(RJ45)+12端口千兆以太网光口(SFP,LC)+4端口万兆以太网光口(SFP+,LC)2块，24端口千兆以太网光口(SFP,LC)+12端口千兆以太网电口复用(RJ45)+4端口万兆以太网光口(SFP+,LC)2块，10G Base SFP+ 光纤线缆（包含两边的模块）3米。 3.其它:满足完成此项工作所需要的全部工作内容，包括设计图纸、技术规范书、答疑、招标文件、现行规范、图集、验收等全部要求 | E69: 台 | F69: 2 | G69: 64403.67 | H69: 2477.06 | I69: 825.69 | J69: 3302.75 | K69: 2477.06 | L69: 9082.57 | M69: 7431.19 | N69: =SUM(G69:M69) -> 89999.99
A70: 本页小计 | N70: =SUM(N68:N69) -> 97999.98
A71: 53 | B71: 030502009010 | C71: LC-LC单模光纤跳线（3m） | D71: 1.名称:LC-LC单模光纤跳线（3m） 2.其它:满足完成此项工作所需要的全部工作内容，包括设计图纸、技术规范书、答疑、招标文件、现行规范、图集、验收等全部要求 | E71: 条 | F71: 208 | G71: 8186.42 | H71: 314.86 | I71: 104.95 | J71: 419.82 | K71: 314.86 | L71: 1154.5 | M71: 944.59 | N71: =SUM(G71:M71) -> 11440
A72: 54 | B72: 030502009011 | C72: LC-LC多模光纤跳线（3m） | D72: 1.名称:LC-LC多模光纤跳线（3m） 2.其它:满足完成此项工作所需要的全部工作内容，包括设计图纸、技术规范书、答疑、招标文件、现行规范、图集、验收等全部要求 | E72: 条 | F72: 208 | G72: 8632.95 | H72: 332.04 | I72: 110.68 | J72: 442.72 | K72: 332.04 | L72: 1217.47 | M72: 996.11 | N72: =SUM(G72:M72) -> 12064.01
A73: 55 | B73: 030502009012 | C73: 六类非屏蔽跳线（3m） | D73: 1.名称:六类非屏蔽跳线（3m） 2.其它:满足完成此项工作所需要的全部工作内容，包括设计图纸、技术规范书、答疑、招标文件、现行规范、图集、验收等全部要求 | E73: 条 | F73: 1000 | G73: 17889.91 | H73: 688.07 | I73: 229.36 | J73: 917.43 | K73: 688.07 | L73: 2522.94 | M73: 2064.22 | N73: =SUM(G73:M73) -> 25000
A74: 56 | B74: 030501013011 | C74: 台式工作站 | D74: 1.名称:台式工作站（含鼠标键盘、显示器、软件等） 2.其它:满足完成此项工作所需要的全部工作内容，包括设计图纸、技术规范书、答疑、招标文件、现行规范、图集、验收等全部要求 | E74: 台 | F74: 5 | G74: 17889.91 | H74: 688.07 | I74: 229.36 | J74: 917.43 | K74: 688.07 | L74: 2522.94 | M74: 2064.22 | N74: =SUM(G74:M74) -> 25000
A75: 57 | B75: 030501011001 | C75: 防火墙 | D75: 1.名称:防火墙 2.其它:满足完成此项工作所需要的全部工作内容，包括设计图纸、技术规范书、答疑、招标文件、现行规范、图集、验收等全部要求 | E75: 台 | F75: 1 | G75: 8944.95 | H75: 344.04 | I75: 114.68 | J75: 458.72 | K75: 344.04 | L75: 1261.47 | M75: 1032.11 | N75: =SUM(G75:M75) -> 12500.01
A76: 本页小计 | N76: =SUM(N71:N75) -> 86004.02
A77: 58 | B77: 030501017003 | C77: 行为管理 | D77: 1.名称:行为管理 2.其它:满足完成此项工作所需要的全部工作内容，包括设计图纸、技术规范书、答疑、招标文件、现行规范、图集、验收等全部要求 | E77: 套 | F77: 1 | G77: 4733.94 | H77: 394.5 | I77: 157.8 | J77: 1183.49 | K77: 552.29 | L77: 867.89 | M77: 710.09 | N77: =SUM(G77:M77) -> 8600
A78: 59 | B78: 030501013012 | C78: 数据库服务器 | D78: 1.名称:数据库服务器（含鼠标键盘、显示器、软件等） 2.技术参数：处理器：≥2颗Intel 至强 4510处理器，单颗核数≥12核， ≥2.40 GHz或以上；内存：≥128G；操作系统： 支持Microsoft Windows Server 2019、 RedHat Enterprise Linux 、 SUSE Linux Enterprise Server、 CentOS、 Ubuntu、 Vmware EXSI；内置SAS硬盘，RAID5，配备4x3TB热插拔硬盘，10000rpm以上；2个千兆以太网口；冗余电源、风扇，可以365天24小时运行；1块单口8Gb HBA卡。 3.其它:满足完成此项工作所需要的全部工作内容，包括设计图纸、技术规范书、答疑、招标文件、现行规范、图集、验收等全部要求 | E78: 台 | F78: 1 | G78: 16816.51 | H78: 646.79 | I78: 215.6 | J78: 862.39 | K78: 646.79 | L78: 2371.56 | M78: 1940.37 | N78: =SUM(G78:M78) -> 23500.01
A79: 本页小计 | N79: =SUM(N77:N78) -> 32100.01
A80: 60 | B80: 030502001010 | C80: 弱电机柜 | D80: 1.名称:弱电机柜 2.技术参数:800*800*2000，每台机柜含机架式3kW的UPS，电池后备1小时，提供柜内电池监控，含2个PDU，详见技术规范书及图纸，含电源 3.安装方式:落地安装 4.其它:满足完成此项工作所需要的全部工作内容，包括设计图纸、技术规范书、答疑、招标文件、现行规范、图集、验收等全部要求 | E80: 台 | F80: 5 | G80: 6440.37 | H80: 247.71 | I80: 82.57 | J80: 330.28 | K80: 247.71 | L80: 908.26 | M80: 743.12 | N80: =SUM(G80:M80) -> 9000.02
A81: 61 | B81: 030502001011 | C81: 弱电机柜 | D81: 1.名称:弱电机柜 2.技术参数:600*1200*2000，含2个PDU 3.安装方式:落地安装 4.其它:满足完成此项工作所需要的全部工作内容，包括设计图纸、技术规范书、答疑、招标文件、现行规范、图集、验收等全部要求 | E81: 台 | F81: 10 | G81: 20036.7 | H81: 770.64 | I81: 256.88 | J81: 1027.52 | K81: 770.64 | L81: 2825.69 | M81: 2311.93 | N81: =SUM(G81:M81) -> 28000
A82: 62 | B82: 030502003004 | C82: 弱电设备箱 | D82: 1.名称:弱电设备箱 2.规格:600x800x200 3.其它:满足完成此项工作所需要的全部工作内容，包括设计图纸、技术规范书、答疑、招标文件、现行规范、图集、验收等全部要求 | E82: 个 | F82: 10 | G82: 2477.06 | H82: 206.42 | I82: 82.57 | J82: 619.27 | K82: 288.99 | L82: 454.13 | M82: 371.56 | N82: =SUM(G82:M82) -> 4500
A83: 本页小计 | N83: =SUM(N80:N82) -> 41500.02
A84: 63 | B84: 030904008006 | C84: 摄像机防雷模块 | D84: 1.名称:摄像机防雷模块 2.规格:In=10KA Imax=20KA 静态门槛电压 1.5Un 动态电压 2Un 插入损耗 ＜0.2dB 传输速率 10Mbps 响应时间 ＜1ns 3.其它:满足完成此项工作所需要的全部工作内容，包括设计图纸、技术规范书、答疑、招标文件、现行规范、图集、验收等全部要求 | E84: 个 | F84: 35 | G84: 4633.49 | H84: 178.21 | I84: 59.4 | J84: 237.61 | K84: 178.21 | L84: 653.44 | M84: 534.63 | N84: =SUM(G84:M84) -> 6474.99
A85: 64 | B85: 030502007008 | C85: 12芯单模光缆 | D85: 1.名称：12芯单模光缆 2.敷设方式：桥架敷设 3.其它:满足完成此项工作所需要的全部工作内容，包括设计图纸、技术规范书、答疑、招标文件、现行规范、图集、验收等全部要求 | E85: m | F85: 16800 | G85: 48088.07 | H85: 1849.54 | I85: 616.51 | J85: 2466.06 | K85: 1849.54 | L85: 6781.65 | M85: 5548.62 | N85: =SUM(G85:M85) -> 67199.99
A86: 65 | B86: 030502007009 | C86: 12芯多模光缆 | D86: 1.名称：12芯多模光缆 2.敷设方式：桥架敷设 3.其它:满足完成此项工作所需要的全部工作内容，包括设计图纸、技术规范书、答疑、招标文件、现行规范、图集、验收等全部要求 | E86: m | F86: 842.85 | G86: 3618.84 | H86: 139.19 | I86: 46.4 | J86: 185.58 | K86: 139.19 | L86: 510.35 | M86: 417.56 | N86: =SUM(G86:M86) -> 5057.11
A87: 66 | B87: 030502020005 | C87: 光纤测试 | D87: 1.光纤测试 2.满足完成此项工作所需要的全部工作内容，包括设计图纸、技术规范书、答疑、招标文件、现行规范、图集、验收等全部要求 | E87: 链路 | F87: 92 | G87: 256.59 | H87: 67.52 | I87: 33.76 | J87: 189.06 | K87: 54.02 | L87: 74.28 | M87: 60.77 | N87: =SUM(G87:M87) -> 736
A88: 67 | B88: 030502014002 | C88: 光纤连接 | D88: 1.名称：光纤熔接 2.其它:满足完成此项工作所需要的全部工作内容，包括设计图纸、技术规范书、答疑、招标文件、现行规范、图集、验收等全部要求 | E88: 芯 | F88: 2208 | G88: 23700.55 | H88: 911.56 | I88: 303.85 | J88: 1215.41 | K88: 911.56 | L88: 3342.39 | M88: 2734.68 | N88: =SUM(G88:M88) -> 33120
A89: 本页小计 | N89: =SUM(N84:N88) -> 112588.09
A90: 68 | B90: 030411003019 | C90: 桥架 | D90: 1.名称：热镀锌综合桥架 2.规格：500*200 3.其它:满足完成此项工作所需要的全部工作内容，包括设计图纸、技术规范书、答疑、招标文件、现行规范、图集、验收等全部要求 | E90: m | F90: 1.8 | G90: 70.84 | H90: 2.72 | I90: 0.91 | J90: 3.63 | K90: 2.72 | L90: 9.99 | M90: 8.17 | N90: =SUM(G90:M90) -> 98.98
A91: 69 | B91: 030411003020 | C91: 桥架 | D91: 1.名称：热镀锌综合桥架 2.规格：400*100 3.其它:满足完成此项工作所需要的全部工作内容，包括设计图纸、技术规范书、答疑、招标文件、现行规范、图集、验收等全部要求 | E91: m | F91: 496.1 | G91: 17040.35 | H91: 655.4 | I91: 218.47 | J91: 873.86 | K91: 655.4 | L91: 2403.13 | M91: 1966.19 | N91: =SUM(G91:M91) -> 23812.8
A92: 70 | B92: 030411003021 | C92: 桥架 | D92: 1.名称：热镀锌综合桥架 2.规格：200*100 3.其它:满足完成此项工作所需要的全部工作内容，包括设计图纸、技术规范书、答疑、招标文件、现行规范、图集、验收等全部要求 | E92: m | F92: 679.27 | G92: 13610.33 | H92: 523.47 | I92: 174.49 | J92: 697.97 | K92: 523.47 | L92: 1919.41 | M92: 1570.42 | N92: =SUM(G92:M92) -> 19019.56
A93: 71 | B93: 030411003022 | C93: 桥架 | D93: 1.名称：热镀锌综合桥架 2.规格：100*100 3.其它:满足完成此项工作所需要的全部工作内容，包括设计图纸、技术规范书、答疑、招标文件、现行规范、图集、验收等全部要求 | E93: m | F93: 34.6 | G93: 643.75 | H93: 24.76 | I93: 8.25 | J93: 33.01 | K93: 24.76 | L93: 90.79 | M93: 74.28 | N93: =SUM(G93:M93) -> 899.6
A94: 72 | B94: 030413001028 | C94: 铁构件 | D94: 1.名称:桥架等支吊架 2.规格:综合 3.材质：热镀锌 4.其它:满足完成此项工作所需要的全部工作内容，包括设计图纸、技术规范书、答疑、招标文件、现行规范、图集、验收等全部要求 | E94: kg | F94: 1141 | G94: 1909.34 | H94: 502.46 | I94: 251.23 | J94: 1406.88 | K94: 401.97 | L94: 552.7 | M94: 452.21 | N94: =SUM(G94:M94) -> 5476.79
A95: 本页小计 | N95: =SUM(N90:N94) -> 49307.73
A96: 73 | B96: 030411001050 | C96: 配管 | D96: 1.名称：紧定式镀锌钢导管 2.规格：JDG20 3.敷设方式：明配 4.其它:满足完成此项工作所需要的全部工作内容，包括设计图纸、技术规范书、答疑、招标文件、现行规范、图集、验收等全部要求 | E96: m | F96: 721.49 | G96: 1131.88 | H96: 297.86 | I96: 148.93 | J96: 834.02 | K96: 238.29 | L96: 327.65 | M96: 268.08 | N96: =SUM(G96:M96) -> 3246.71
A97: 74 | B97: 030411001051 | C97: 配管 | D97: 1.名称：紧定式镀锌钢导管 2.规格：JDG20 3.敷设方式：暗配 4.其它:满足完成此项工作所需要的全部工作内容，包括设计图纸、技术规范书、答疑、招标文件、现行规范、图集、验收等全部要求 | E97: m | F97: 143.6 | G97: 225.28 | H97: 59.28 | I97: 29.64 | J97: 166 | K97: 47.43 | L97: 65.21 | M97: 53.36 | N97: =SUM(G97:M97) -> 646.2
A98: 75 | B98: 030413002014 | C98: 凿（压)槽 | D98: 1.名称:管线剔槽及恢复 2.满足完成此项工作所需要的全部工作内容，满足设计图纸、答疑、招标文件、现行规范、图集、验收等全部要求 | E98: m | F98: 143.6 | G98: 616.56 | H98: 51.38 | I98: 20.55 | J98: 154.14 | K98: 71.93 | L98: 113.04 | M98: 92.48 | N98: =SUM(G98:M98) -> 1120.08
A99: 76 | B99: 030411001052 | C99: 配管 | D99: 1.名称：可挠金属套管 2.规格：DN20 3.敷设方式：明配 4.其它:满足完成此项工作所需要的全部工作内容，包括设计图纸、技术规范书、答疑、招标文件、现行规范、图集、验收等全部要求 | E99: m | F99: 76.5 | G99: 120.01 | H99: 31.58 | I99: 15.79 | J99: 88.43 | K99: 25.27 | L99: 34.74 | M99: 28.42 | N99: =SUM(G99:M99) -> 344.24
A100: 77 | B100: 030413001029 | C100: 管道支架/综合支架 | D100: 1.名称:管道支架制作安装 2.材质:热镀锌 3.安装高度:综合考虑 4.满足完成此项工作所需要的全部工作内容，满足设计图纸、技术规范书、答疑、招标文件、现行规范、图集、验收等全部要求 | E100: kg | F100: 128.91 | G100: 584.23 | H100: 153.75 | I100: 76.87 | J100: 430.49 | K100: 123 | L100: 169.12 | M100: 138.37 | N100: =SUM(G100:M100) -> 1675.83
...

Sheet 8#、15#非管区巡更系统
A1: 分部分项工程和单价措施项目清单与计价表
A2: 分部分项工程和单价措施项目清单与计价表
A3: 序号 | B3: 项目编码 | C3: 项目名称 | D3: 项目特征描述 | E3: 计量单位 | F3: 工程量 | G3: 金额（元）
G4: 主材/设备费 | H4: 辅材 | I4: 机械措施 | J4: 人工 | K4: 管理费 | L4: 利润 | M4: 税金 | N4: 总价
A5: 1 | B5: 030507005007 | C5: 巡逻终端 | D5: 1.名称:巡逻终端（含数据采集底座、充电器、巡更软件等） 2.其它:满足完成此项工作所需要的全部工作内容，包括设计图纸、技术规范书、答疑、招标文件、现行规范、图集、验收等全部要求 | E5: 台 | F5: 10 | G5: 9660.54 | H5: 371.55 | I5: 123.84 | J5: 495.42 | K5: 371.55 | L5: 1362.39 | M5: 1114.68 | N5: =SUM(G5:M5) -> 13499.97
A6: 2 | B6: 03B031 | C6: 巡更标签 | D6: 1.名称:巡更标签 2.其它:满足完成此项工作所需要的全部工作内容，包括设计图纸、技术规范书、答疑、招标文件、现行规范、图集、验收等全部要求 | E6: 张 | F6: 1000 | G6: 21467.88 | H6: 825.69 | I6: 275.22 | J6: 1100.91 | K6: 825.69 | L6: 3027.51 | M6: 2477.07 | N6: =SUM(G6:M6) -> 29999.97
A7: 3 | B7: 030507017005 | C7: 安全防范分系统调试 | D7: 1.名称：电子巡更系统调试 2.其它:满足完成此项工作所需要的全部工作内容，包括设计图纸、技术规范书、答疑、招标文件、现行规范、图集、验收等全部要求 | E7: 系统 | F7: 1 | G7: 522.93 | H7: 137.61 | I7: 68.82 | J7: 385.32 | K7: 110.1 | L7: 151.38 | M7: 123.84 | N7: =SUM(G7:M7) -> 1500
A8: 4 | B8: 03B032 | C8: 系统综合及集成 | D8: 1.清单未列项、图纸中未表示或技术规格书未做要求，但为了实现本系统各项功能必须增加的配套及辅助的材料、设备的所有工作内容及费用； 2.施工深化设计增加的实现本系统设计功能必要的配套及辅助的材料、设备所需的所有工作内容及费用； 3.实现设计功能所做的满足图纸、技术规格书要求的各项综合与集成，包括不限于各项检测、试验、调试、软件开发、联动等所有工作内容及费用 | E8: 项 | F8: 1 | G8: 836.7 | H8: 220.17 | I8: 110.1 | J8: 616.5 | K8: 176.16 | L8: 242.19 | M8: 198.18 | N8: =SUM(G8:M8) -> 2400
A9: 本页小计 | N9: =SUM(N5:N8) -> 47399.94
A10: 5 | B10: 031301017025 | C10: 脚手架搭拆 | D10: 1.脚手架费 2.按项包干 3.其它:满足完成此项工作所需要的全部工作内容，包括设计图纸、技术规范书、答疑、招标文件、现行规范、图集、验收等全部要求 | E10: 项 | F10: 1 | G10: 104.59 | H10: 27.52 | I10: 13.76 | J10: 77.06 | K10: 22.02 | L10: 30.28 | M10: 24.77 | N10: =SUM(G10:M10) -> 300
A11: 6 | B11: 031301018001 | C11: 操作高度增加费 | D11: 1.结合本工程实际安装情况，综合考虑操作高度施工产生的降效，进行综合报价。 2.满足完成此项工作所需要的全部工作内容，满足设计图纸、答疑、招标文件、现行规范、图集、验收等全部要求 | E11: 项 | F11: 1 | G11: 139.45 | H11: 36.7 | I11: 18.35 | J11: 102.75 | K11: 29.36 | L11: 40.37 | M11: 33.03 | N11: =SUM(G11:M11) -> 400.01
A12: 7 | B12: 031301018002 | C12: 高层建筑增加费 | D12: 1.结合本工程实际安装情况，综合考虑建筑物檐口高度施工产生的降效，进行综合报价。 2.满足完成此项工作所需要的全部工作内容，满足设计图纸、答疑、招标文件、现行规范、图集、验收等全部要求 | E12: 项 | F12: 1 | G12: 69.72 | H12: 18.35 | I12: 9.17 | J12: 51.38 | K12: 14.68 | L12: 20.18 | M12: 16.51 | N12: =SUM(G12:M12) -> 199.99
A13: 本页小计 | N13: =SUM(N10:N12) -> 900
A14: 合 计 | N14: =N9+N13 -> 48299.94

Sheet 8#、15#非管区一卡通系统
A1: 分部分项工程和单价措施项目清单与计价表
A2: 分部分项工程和单价措施项目清单与计价表
A3: 序号 | B3: 项目编码 | C3: 项目名称 | D3: 项目特征描述 | E3: 计量单位 | F3: 工程量 | G3: 金额（元）
G4: 主材/设备费 | H4: 辅材 | I4: 机械措施 | J4: 人工 | K4: 管理费 | L4: 利润 | M4: 税金 | N4: 总价
A5: 1 | B5: 030507005003 | C5: 指纹录入设备 | D5: 1.名称:指纹录入设备 2.技术参数:详见图纸及技术规格书 3.其它:满足完成此项工作所需要的全部工作内容，包括设计图纸、技术规范书、答疑、招标文件、现行规范、图集、验收等全部要求 | E5: 台 | F5: 2 | G5: 500.92 | H5: 19.27 | I5: 6.42 | J5: 25.69 | K5: 19.27 | L5: 70.64 | M5: 57.8 | N5: =SUM(G5:M5) -> 700.01
A6: 2 | B6: 030507016001 | C6: 发卡器 | D6: 1.名称:发卡器 2.技术参数:USB 1.1接口 工作电压5V,USB总线供电 工作电源：< 100mA 读卡距离： > 5cm 红色LED电源指示灯，绿色LED通信指示灯 3.其它:满足完成此项工作所需要的全部工作内容，包括设计图纸、技术规范书、答疑、招标文件、现行规范、图集、验收等全部要求 | E6: 台 | F6: 2 | G6: 457.98 | H6: 17.61 | I6: 5.87 | J6: 23.49 | K6: 17.61 | L6: 64.59 | M6: 52.84 | N6: =SUM(G6:M6) -> 639.99
A7: 3 | B7: 03B023 | C7: 门禁卡 | D7: 1.名称:门禁卡 2.其它:满足完成此项工作所需要的全部工作内容，包括设计图纸、技术规范书、答疑、招标文件、现行规范、图集、验收等全部要求 | E7: 张 | F7: 1000 | G7: 2146.79 | H7: 82.57 | I7: 27.52 | J7: 110.09 | K7: 82.57 | L7: 302.75 | M7: 247.71 | N7: =SUM(G7:M7) -> 3000
A8: 本页小计 | N8: =SUM(N5:N7) -> 4340
A9: 4 | B9: 030507006011 | C9: 四门控制器 | D9: 1.名称:四门控制器（含箱、电源等） 2.技术参数:处理器：32位处理器 管控门数：4门 通讯方式：上行TCP/IP、RS485 读卡器接口：RS485和Wiegand双通讯接口 存储容量：10万张卡和30万记录存储 工作电压：自带机箱和供电电源（AC220V输入），工作电压DC 12V，功耗≤4W（不带负载） 3.其它:满足完成此项工作所需要的全部工作内容，包括设计图纸、技术规范书、答疑、招标文件、现行规范、图集、验收等全部要求 | E9: 台 | F9: 103 | G9: 50120.37 | H9: 1927.71 | I9: 642.57 | J9: 2570.28 | K9: 1927.71 | L9: 7068.26 | M9: 5783.12 | N9: =SUM(G9:M9) -> 70040.02
A10: 5 | B10: 030507006012 | C10: 双门控制器 | D10: 1.名称:双门控制器（含箱、电源等） 2.技术参数:处理器：32位处理器 管控门数：2门 通讯方式：上行TCP/IP、RS485 读卡器接口：RS485和Wiegand双通讯接口 存储容量：10万张卡和30万记录存储 工作电压：自带机箱和供电电源（AC220V输入），工作电压DC 12V，功耗≤4W（不带负载） 3.其它:满足完成此项工作所需要的全部工作内容，包括设计图纸、技术规范书、答疑、招标文件、现行规范、图集、验收等全部要求 | E10: 台 | F10: 2 | G10: 644.04 | H10: 24.77 | I10: 8.26 | J10: 33.03 | K10: 24.77 | L10: 90.83 | M10: 74.31 | N10: =SUM(G10:M10) -> 900.01
A11: 本页小计 | N11: =SUM(N9:N10) -> 70940.03
A12: 6 | B12: 030404034020 | C12: 紧急破碎按钮 | D12: 1.名称:紧急破碎按钮 2.技术参数:标准结构：选用防火材料； 电气性能：最大耐用电流3A@36VDC； 适用门型：安全门、逃生门、安全系统等； 尺寸：86*86*50mm 3.其它:满足完成此项工作所需要的全部工作内容，包括设计图纸、技术规范书、答疑、招标文件、现行规范、图集、验收等全部要求 | E12: 个 | F12: 341 | G12: 26842.02 | H12: 1032.39 | I12: 344.13 | J12: 1376.51 | K12: 1032.39 | L12: 3785.41 | M12: 3097.16 | N12: =SUM(G12:M12) -> 37510.01
A13: 7 | B13: 030507005004 | C13: 门禁读卡器 | D13: 1.名称:门禁读卡器 2.技术参数:读卡频率：13.56MHz 按键方式：无 可识别卡：Mifare卡号、Mifare卡内容、CPU卡序列号 通讯方式：RS485+Wiegand 工作电压：DC 12V 功耗：≤2W 安装方式：预埋120或86底盒安装 工作环境：室内，IP64 外型尺寸:121mm(高)x86.5mm（宽）x14mm（厚） 注意：默认出货为金属背板，如果现场需要刷异形卡，则需将背板更换为塑料背板 3.其它:满足完成此项工作所需要的全部工作内容，包括设计图纸、技术规范书、答疑、招标文件、现行规范、图集、验收等全部要求 | E13: 台 | F13: 480 | G13: 87588.99 | H13: 3368.81 | I13: 1122.94 | J13: 4491.74 | K13: 3368.81 | L13: 12352.29 | M13: 10106.42 | N13: =SUM(G13:M13) -> 122400
A14: 本页小计 | N14: =SUM(N12:N13) -> 159910.01
A15: 8 | B15: 030507002001 | C15: 可视对讲分机 | D15: 1.名称:可视对讲 2.安装方式:壁装 3.其它:满足完成此项工作所需要的全部工作内容，包括设计图纸、技术规范书、答疑、招标文件、现行规范、图集、验收等全部要求 | E15: 套 | F15: 2 | G15: 1289.91 | H15: 339.45 | I15: 169.72 | J15: 950.46 | K15: 271.56 | L15: 373.39 | M15: 305.5 | N15: =SUM(G15:M15) -> 3699.99
A16: 9 | B16: 030507005005 | C16: 人脸门禁读卡器 | D16: 1.名称:人脸门禁读卡器 2.其它:满足完成此项工作所需要的全部工作内容，包括设计图纸、技术规范书、答疑、招标文件、现行规范、图集、验收等全部要求 | E16: 台 | F16: 16 | G16: 2919.63 | H16: 112.29 | I16: 37.43 | J16: 149.72 | K16: 112.29 | L16: 411.74 | M16: 336.88 | N16: =SUM(G16:M16) -> 4079.98
A17: 10 | B17: 030507005006 | C17: 出入门按钮 | D17: 1.名称:出入门按钮 2.规格:结构：塑料面板； 性能：最大耐电流1.25A，电压250V； 输出：常开； 类型：适合埋入式电器盒使用； 尺寸：86*86mm； 重量：0.07kg； 3.其它:满足完成此项工作所需要的全部工作内容，包括设计图纸、技术规范书、答疑、招标文件、现行规范、图集、验收等全部要求 | E17: 台 | F17: 384 | G17: 4121.83 | H17: 158.53 | I17: 52.84 | J17: 211.38 | K17: 158.53 | L17: 581.28 | M17: 475.6 | N17: =SUM(G17:M17) -> 5759.99
A18: 本页小计 | N18: =SUM(N15:N17) -> 13539.96
A19: 11 | B19: 030507007001 | C19: 单门磁力锁 | D19: 1.名称:单门磁力锁 2.类别:上锁时NO输出 开锁时NC输出 最大拉力280kg静态直线拉力 锁体240x48.5x26.5mm 吸板180x38x11mm 适用于木门、金属门、防火门/国内中性 输入电压 DC12V或DC24V 支持门磁输出,含支架 使用环境：室内 工作电流 12V/500mA ; 24V/250mA 功耗 6W 3.其它:满足完成此项工作所需要的全部工作内容，包括设计图纸、技术规范书、答疑、招标文件、现行规范、图集、验收等全部要求 | E19: 台 | F19: 203 | G19: 12347.61 | H19: 474.91 | I19: 158.3 | J19: 633.21 | K19: 474.91 | L19: 1741.33 | M19: 1424.72 | N19: =SUM(G19:M19) -> 17254.99
A20: 12 | B20: 030507007002 | C20: 双门磁力锁 | D20: 1.名称:双门磁力锁 2.技术参数:上锁时NO输出 开锁时NC输出 最大拉力280kg*2静态直线拉力 锁体长480x宽48.5x厚26.5(mm) 吸板180x38x11mm 适用于木门、金属门、防火门/国内标配 输入电压 DC12V或DC24V 支持门磁输出,含支架 使用环境：室内 工作电流 12V/500mA x2 ;24V/250mAx2 功耗 12W 3.其它:满足完成此项工作所需要的全部工作内容，包括设计图纸、技术规范书、答疑、招标文件、现行规范、图集、验收等全部要求 | E20: 台 | F20: 283 | G20: 36452.48 | H20: 1402.02 | I20: 467.34 | J20: 1869.36 | K20: 1402.02 | L20: 5140.73 | M20: 4206.06 | N20: =SUM(G20:M20) -> 50940.01
A21: 本页小计 | N21: =SUM(N19:N20) -> 68195
A22: 13 | B22: 030503003015 | C22: 速通门子系统 | D22: 1.名称:速通门子系统 2.技术参数:技术参数:含摆闸,门禁控制器,读卡器(支持人脸+刷卡) 1）三通道:1)摆闸（边件）2个:机箱尺寸：1400*185*1020MM ;电源电压： AC220±10% V,50HZ ;电机：24V/20W直流高速电机 ; 通信接口： RS485电气标准; 输入信号：干接点信号; LED指示灯板：4个;读卡窗口： 2个; 通行速度：约40人/分钟（常开） 30人/分钟（常闭）; 工作温度：-25℃～70℃; 工作环境：室内/室外; 相对湿度：≤90%，不凝露.2)摆闸（中间件）2个:双机芯 机箱尺寸：1400*185*1020MM ; 电源电压： AC220±10% V,50HZ ;电机：24V/20W直流高速电机 ; 通信接口： RS485电气标准;输入信号：干接点信号; LED指示灯板：4个; 读卡窗口： 2个; 通行速度：约40人/分钟（常开） 30人/分钟（常闭）; 工作温度：-25℃～70℃;工作环境：室内/室外; 相对湿度：≤90%，不凝露 .3)四门门禁控制器5个:铁壳，内置36W+100W电源，工作电压DC12V，额定电流0.5A；带键，液晶显示；可连八个读卡器，控制四扇门进出；管制30000卡，50000条事件 | E22: 套 | F22: 2 | G22: 4007.34 | H22: 154.13 | I22: 51.38 | J22: 205.5 | K22: 154.13 | L22: 565.14 | M22: 462.39 | N22: =SUM(G22:M22) -> 5600.01
A23: 本页小计 | N23: =N22 -> 5600.01
A24: 14 | B24: 030503003016 | C24: 速通门子系统 | D24: 1.名称:室外速通门子系统 2.技术参数:技术参数:含摆闸,门禁控制器,读卡器(支持人脸+刷卡) 1）三通道:1)摆闸（边件）2个:机箱尺寸：1400*185*1020MM ;电源电压： AC220±10% V,50HZ ;电机：24V/20W直流高速电机 ; 通信接口： RS485电气标准; 输入信号：干接点信号; LED指示灯板：4个;读卡窗口： 2个; 通行速度：约40人/分钟（常开） 30人/分钟（常闭）; 工作温度：-25℃～70℃; 工作环境：室内/室外; 相对湿度：≤90%，不凝露.2)摆闸（中间件）2个:双机芯 机箱尺寸：1400*185*1020MM ; 电源电压： AC220±10% V,50HZ ;电机：24V/20W直流高速电机 ; 通信接口： RS485电气标准;输入信号：干接点信号; LED指示灯板：4个; 读卡窗口： 2个; 通行速度：约40人/分钟（常开） 30人/分钟（常闭）; 工作温度：-25℃～70℃;工作环境：室内/室外; 相对湿度：≤90%，不凝露 .3)四门门禁控制器5个:铁壳，内置36W+100W电源，工作电压DC12V，额定电流0.5A；带键，液晶显示；可连八个读卡器，控制四扇门进出；管制 | E24: 套 | F24: 3 | G24: 6011.01 | H24: 231.19 | I24: 77.06 | J24: 308.26 | K24: 231.19 | L24: 847.71 | M24: 693.58 | N24: =SUM(G24:M24) -> 8400
A25: 本页小计 | N25: =SUM(N24) -> 8400
A26: 15 | B26: 030503003017 | C26: 速通门子系统 | D26: 1.名称:室外速通门子系统 2.技术参数:技术参数:含摆闸,门禁控制器,读卡器(支持人脸+刷卡) 1）四通道:1)摆闸（边件）2个:机箱尺寸：1400*185*1020MM ;电源电压： AC220±10% V,50HZ ;电机：24V/20W直流高速电机 ; 通信接口： RS485电气标准; 输入信号：干接点信号; LED指示灯板：4个;读卡窗口： 2个; 通行速度：约40人/分钟（常开） 30人/分钟（常闭）; 工作温度：-25℃～70℃; 工作环境：室内/室外; 相对湿度：≤90%，不凝露.2)摆闸（中间件）3个:双机芯 机箱尺寸：1400*185*1020MM ; 电源电压： AC220±10% V,50HZ ;电机：24V/20W直流高速电机 ; 通信接口： RS485电气标准;输入信号：干接点信号; LED指示灯板：4个; 读卡窗口： 2个; 通行速度：约40人/分钟（常开） 30人/分钟（常闭）; 工作温度：-25℃～70℃;工作环境：室内/室外; 相对湿度：≤90%，不凝露 .3)四门门禁控制器:铁壳，内置36W+100W电源，工作电压DC12V，额定电流0.5A；带键，液晶显示；可连八个读卡器，控制四扇门进出；管制30000 | E26: 套 | F26: 2 | G26: 4007.34 | H26: 154.13 | I26: 51.38 | J26: 205.5 | K26: 154.13 | L26: 565.14 | M26: 462.39 | N26: =SUM(G26:M26) -> 5600.01
A27: 本页小计 | N27: =N26 -> 5600.01
A28: 16 | B28: 030507016002 | C28: 发卡机 | D28: 1.名称:发卡机 2.其它:满足完成此项工作所需要的全部工作内容，包括设计图纸、技术规范书、答疑、招标文件、现行规范、图集、验收等全部要求 | E28: 台 | F28: 2 | G28: 280.73 | H28: 23.39 | I28: 9.36 | J28: 70.18 | K28: 32.75 | L28: 51.47 | M28: 42.11 | N28: =SUM(G28:M28) -> 509.99
A29: 17 | B29: 010801006002 | C29: 门锁安装 | D29: 1.锁品种:智能门锁 2.其它:满足完成此项工作所需要的全部工作内容，包括设计图纸、技术规范书、答疑、招标文件、现行规范、图集、验收等全部要求 | E29: 个 | F29: 220 | G29: 23009.17 | H29: 6055.05 | I29: 3027.52 | J29: 16954.13 | K29: 4844.04 | L29: 6660.55 | M29: 5449.54 | N29: =SUM(G29:M29) -> 66000
A30: 本页小计 | N30: =SUM(N28:N29) -> 66509.99
A31: 18 | B31: 030501009005 | C31: 网关 | D31: 1.名称:网关 2.其它:满足完成此项工作所需要的全部工作内容，包括设计图纸、技术规范书、答疑、招标文件、现行规范、图集、验收等全部要求 | E31: 台 | F31: 44 | G31: 10899.08 | H31: 908.26 | I31: 363.3 | J31: 2724.77 | K31: 1271.56 | L31: 1998.17 | M31: 1634.86 | N31: =SUM(G31:M31) -> 19800
A32: 19 | B32: 030502009013 | C32: 六类非屏蔽跳线（3m） | D32: 1.名称:六类非屏蔽跳线（3m） 2.其它:满足完成此项工作所需要的全部工作内容，包括设计图纸、技术规范书、答疑、招标文件、现行规范、图集、验收等全部要求 | E32: 条 | F32: 1100 | G32: 2361.47 | H32: 90.83 | I32: 30.28 | J32: 121.1 | K32: 90.83 | L32: 333.03 | M32: 272.48 | N32: =SUM(G32:M32) -> 3300.02
A33: 20 | B33: 030507017003 | C33: 安全防范分系统调试 | D33: 1.名称：出入口控制系统调试 2.其它:满足完成此项工作所需要的全部工作内容，包括设计图纸、技术规范书、答疑、招标文件、现行规范、图集、验收等全部要求 | E33: 系统 | F33: 1 | G33: 2091.74 | H33: 550.46 | I33: 275.23 | J33: 1541.28 | K33: 440.37 | L33: 605.5 | M33: 495.41 | N33: =SUM(G33:M33) -> 5999.99
A34: 21 | B34: 03B024 | C34: 系统综合及集成 | D34: 1.清单未列项、图纸中未表示或技术规格书未做要求，但为了实现本系统各项功能必须增加的配套及辅助的材料、设备的所有工作内容及费用； 2.施工深化设计增加的实现本系统设计功能必要的配套及辅助的材料、设备所需的所有工作内容及费用； 3.实现设计功能所做的满足图纸、技术规格书要求的各项综合与集成，包括不限于各项检测、试验、调试、软件开发、联动等所有工作内容及费用 | E34: 项 | F34: 1 | G34: 1743.12 | H34: 458.72 | I34: 229.36 | J34: 1284.4 | K34: 366.97 | L34: 504.59 | M34: 412.84 | N34: =SUM(G34:M34) -> 5000
A35: 本页小计 | N35: =SUM(N31:N34) -> 34100.01
A36: 22 | B36: 030411001055 | C36: 配管 | D36: 1.名称：紧定式镀锌钢导管 2.规格：JDG25 3.敷设方式：明配 4.其它:满足完成此项工作所需要的全部工作内容，包括设计图纸、技术规范书、答疑、招标文件、现行规范、图集、验收等全部要求 | E36: m | F36: 534.57 | G36: 931.82 | H36: 245.22 | I36: 122.61 | J36: 686.6 | K36: 196.17 | L36: 269.74 | M36: 220.69 | N36: =SUM(G36:M36) -> 2672.85
A37: 23 | B37: 030411001056 | C37: 配管 | D37: 1.名称：紧定式镀锌钢导管 2.规格：JDG25 3.敷设方式：暗配 4.其它:满足完成此项工作所需要的全部工作内容，包括设计图纸、技术规范书、答疑、招标文件、现行规范、图集、验收等全部要求 | E37: m | F37: 508.4 | G37: 886.2 | H37: 233.21 | I37: 116.61 | J37: 652.99 | K37: 186.57 | L37: 256.53 | M37: 209.89 | N37: =SUM(G37:M37) -> 2542
A38: 24 | B38: 030411001057 | C38: 配管 | D38: 1.名称：紧定式镀锌钢导管 2.规格：JDG20 3.敷设方式：明配 4.其它:满足完成此项工作所需要的全部工作内容，包括设计图纸、技术规范书、答疑、招标文件、现行规范、图集、验收等全部要求 | E38: m | F38: 594 | G38: 931.87 | H38: 245.23 | I38: 122.61 | J38: 686.64 | K38: 196.18 | L38: 269.75 | M38: 220.71 | N38: =SUM(G38:M38) -> 2672.99
A39: 25 | B39: 030413002015 | C39: 凿（压)槽 | D39: 1.名称:管线剔槽及恢复 2.满足完成此项工作所需要的全部工作内容，满足设计图纸、答疑、招标文件、现行规范、图集、验收等全部要求 | E39: m | F39: 26.1 | G39: 112.06 | H39: 9.34 | I39: 3.74 | J39: 28.02 | K39: 13.07 | L39: 20.54 | M39: 16.81 | N39: =SUM(G39:M39) -> 203.58
A40: 本页小计 | N40: =SUM(N36:N39) -> 8091.42
A41: 26 | B41: 030413001031 | C41: 管道支架/综合支架 | D41: 1.名称:管道支架制作安装 2.材质:热镀锌 3.安装高度:综合考虑 4.满足完成此项工作所需要的全部工作内容，满足设计图纸、技术规范书、答疑、招标文件、现行规范、图集、验收等全部要求 | E41: kg | F41: 88.51 | G41: 401.14 | H41: 105.56 | I41: 52.78 | J41: 295.57 | K41: 84.45 | L41: 116.12 | M41: 95.01 | N41: =SUM(G41:M41) -> 1150.63
A42: 27 | B42: 030411004031 | C42: 配线 | D42: 1.名称：配线 2.规格：RYYP-2*1.0 3.敷设方式：管内穿线 4.其它:满足完成此项工作所需要的全部工作内容，包括设计图纸、技术规范书、答疑、招标文件、现行规范、图集、验收等全部要求 | E42: m | F42: 894.2 | G42: 1402.83 | H42: 369.17 | I42: 184.58 | J42: 1033.66 | K42: 295.33 | L42: 406.08 | M42: 332.25 | N42: =SUM(G42:M42) -> 4023.9
A43: 28 | B43: 030411004032 | C43: 配线 | D43: 1.名称：配线 2.规格：RYYP-2*1.0 3.敷设方式：线槽配线 4.其它:满足完成此项工作所需要的全部工作内容，包括设计图纸、技术规范书、答疑、招标文件、现行规范、图集、验收等全部要求 | E43: m | F43: 2520.5 | G43: 3954.18 | H43: 1040.57 | I43: 520.29 | J43: 2913.61 | K43: 832.46 | L43: 1144.63 | M43: 936.52 | N43: =SUM(G43:M43) -> 11342.26
A44: 29 | B44: 030411004033 | C44: 配线 | D44: 1.名称：配线 2.规格：RYYP-4*1.0 3.敷设方式：管内穿线 4.其它:满足完成此项工作所需要的全部工作内容，包括设计图纸、技术规范书、答疑、招标文件、现行规范、图集、验收等全部要求 | E44: m | F44: 773.1 | G44: 2156.17 | H44: 567.41 | I44: 283.71 | J44: 1588.76 | K44: 453.93 | L44: 624.15 | M44: 510.67 | N44: =SUM(G44:M44) -> 6184.8
A45: 本页小计 | N45: =SUM(N41:N44) -> 22701.59
A46: 30 | B46: 030411004034 | C46: 配线 | D46: 1.名称：配线 2.规格：RYYP-4*1.0 3.敷设方式：线槽配线 4.其它:满足完成此项工作所需要的全部工作内容，包括设计图纸、技术规范书、答疑、招标文件、现行规范、图集、验收等全部要求 | E46: m | F46: 2234.4 | G46: 4673.79 | H46: 1229.94 | I46: 614.97 | J46: 3443.85 | K46: 983.96 | L46: 1352.94 | M46: 1106.95 | N46: =SUM(G46:M46) -> 13406.4
A47: 31 | B47: 030411004035 | C47: 配线 | D47: 1.名称：配线 2.规格：RYYP-6*1.0 3.敷设方式：管内穿线 4.其它:满足完成此项工作所需要的全部工作内容，包括设计图纸、技术规范书、答疑、招标文件、现行规范、图集、验收等全部要求 | E47: m | F47: 1049.4 | G47: 2926.77 | H47: 770.2 | I47: 385.1 | J47: 2156.57 | K47: 616.16 | L47: 847.22 | M47: 693.18 | N47: =SUM(G47:M47) -> 8395.2
A48: 32 | B48: 030411004036 | C48: 配线 | D48: 1.名称：配线 2.规格：RYYP-6*1.0 3.敷设方式：线槽配线 4.其它:满足完成此项工作所需要的全部工作内容，包括设计图纸、技术规范书、答疑、招标文件、现行规范、图集、验收等全部要求 | E48: m | F48: 2872 | G48: 6007.49 | H48: 1580.92 | I48: 790.46 | J48: 4426.57 | K48: 1264.73 | L48: 1739.01 | M48: 1422.83 | N48: =SUM(G48:M48) -> 17232.01
A49: 33 | B49: 030502005013 | C49: 双绞线缆 | D49: 1.名称：六类网线 2.规格： Cat.6 UTP 3.敷设方式：桥架敷设 4.其它:满足完成此项工作所需要的全部工作内容，包括设计图纸、技术规范书、答疑、招标文件、现行规范、图集、验收等全部要求 | E49: m | F49: 461.8 | G49: 482.98 | H49: 127.1 | I49: 63.55 | J49: 355.88 | K49: 101.68 | L49: 139.81 | M49: 114.39 | N49: =SUM(G49:M49) -> 1385.39
A50: 34 | B50: 030502005014 | C50: 双绞线缆 | D50: 1.名称：六类网线 2.规格： Cat.6 UTP 3.敷设方式：管内敷设 4.其它:满足完成此项工作所需要的全部工作内容，包括设计图纸、技术规范书、答疑、招标文件、现行规范、图集、验收等全部要求 | E50: m | F50: 154.5 | G50: 161.59 | H50: 42.52 | I50: 21.26 | J50: 119.06 | K50: 34.02 | L50: 46.78 | M50: 38.27 | N50: =SUM(G50:M50) -> 463.5
A51: 本页小计 | N51: =SUM(N46:N50) -> 40882.5
A52: 35 | B52: 030411004037 | C52: 配线 | D52: 1.名称：配线 2.规格：RYY-6*0.75 3.敷设方式：管内穿线 4.其它:满足完成此项工作所需要的全部工作内容，包括设计图纸、技术规范书、答疑、招标文件、现行规范、图集、验收等全部要求 | E52: m | F52: 594 | G52: 1201.08 | H52: 316.07 | I52: 158.04 | J52: 885.01 | K52: 252.86 | L52: 347.68 | M52: 284.47 | N52: =SUM(G52:M52) -> 3445.21
A53: 36 | B53: 030411004038 | C53: 配线 | D53: 1.名称：配线 2.规格：RYY-2*1.0 3.敷设方式：管内穿线 4.其它:满足完成此项工作所需要的全部工作内容，包括设计图纸、技术规范书、答疑、招标文件、现行规范、图集、验收等全部要求 | E53: m | F53: 891 | G53: 1087.18 | H53: 286.1 | I53: 143.05 | J53: 801.08 | K53: 228.88 | L53: 314.71 | M53: 257.49 | N53: =SUM(G53:M53) -> 3118.49
A54: 37 | B54: 030411006014 | C54: 接线盒 | D54: 1.名称:铁接线盒 2.安装形式:满足设计及规范验收要求 3.其它:满足完成此项工作所需要的全部工作内容，包括设计图纸、技术规范书、答疑、招标文件、现行规范、图集、验收等全部要求 | E54: 个 | F54: 87 | G54: 454.95 | H54: 119.72 | I54: 59.86 | J54: 335.23 | K54: 95.78 | L54: 131.7 | M54: 107.75 | N54: =SUM(G54:M54) -> 1304.99
A55: 38 | B55: 030411001058 | C55: 配管 | D55: 1.名称：紧定式镀锌钢导管 2.规格：JDG25 3.敷设方式：明配 4.其它:满足完成此项工作所需要的全部工作内容，包括设计图纸、技术规范书、答疑、招标文件、现行规范、图集、验收等全部要求 | E55: m | F55: 191.3 | G55: 333.46 | H55: 87.75 | I55: 43.88 | J55: 245.71 | K55: 70.2 | L55: 96.53 | M55: 78.98 | N55: =SUM(G55:M55) -> 956.51
A56: 本页小计 | N56: =SUM(N52:N55) -> 8825.2
A57: 39 | B57: 030411001059 | C57: 配管 | D57: 1.名称：紧定式镀锌钢导管 2.规格：JDG25 3.敷设方式：暗配 4.其它:满足完成此项工作所需要的全部工作内容，包括设计图纸、技术规范书、答疑、招标文件、现行规范、图集、验收等全部要求 | E57: m | F57: 6 | G57: 10.46 | H57: 2.75 | I57: 1.38 | J57: 7.71 | K57: 2.2 | L57: 3.03 | M57: 2.48 | N57: =SUM(G57:M57) -> 30.01
A58: 40 | B58: 030411001060 | C58: 配管 | D58: 1.名称：紧定式镀锌钢导管 2.规格：JDG20 3.敷设方式：明配 4.其它:满足完成此项工作所需要的全部工作内容，包括设计图纸、技术规范书、答疑、招标文件、现行规范、图集、验收等全部要求 | E58: m | F58: 120 | G58: 188.26 | H58: 49.54 | I58: 24.77 | J58: 138.72 | K58: 39.63 | L58: 54.5 | M58: 44.59 | N58: =SUM(G58:M58) -> 540.01
A59: 41 | B59: 030413002016 | C59: 凿（压)槽 | D59: 1.名称:管线剔槽及恢复 2.满足完成此项工作所需要的全部工作内容，满足设计图纸、答疑、招标文件、现行规范、图集、验收等全部要求 | E59: m | F59: 6 | G59: 25.76 | H59: 2.15 | I59: 0.86 | J59: 6.44 | K59: 3.01 | L59: 4.72 | M59: 3.86 | N59: =SUM(G59:M59) -> 46.8
A60: 42 | B60: 030413001032 | C60: 管道支架/综合支架 | D60: 1.名称:管道支架制作安装 2.材质:热镀锌 3.安装高度:综合考虑 4.满足完成此项工作所需要的全部工作内容，满足设计图纸、技术规范书、答疑、招标文件、现行规范、图集、验收等全部要求 | E60: kg | F60: 12.74 | G60: 57.74 | H60: 15.19 | I60: 7.6 | J60: 42.54 | K60: 12.16 | L60: 16.71 | M60: 13.68 | N60: =SUM(G60:M60) -> 165.62
A61: 43 | B61: 030411004039 | C61: 配线 | D61: 1.名称：配线 2.规格：RYYP-2*1.0 3.敷设方式：管内穿线 4.其它:满足完成此项工作所需要的全部工作内容，包括设计图纸、技术规范书、答疑、招标文件、现行规范、图集、验收等全部要求 | E61: m | F61: 77.3 | G61: 94.32 | H61: 24.82 | I61: 12.41 | J61: 69.5 | K61: 19.86 | L61: 27.3 | M61: 22.34 | N61: =SUM(G61:M61) -> 270.55
A62: 本页小计 | N62: =SUM(N57:N61) -> 1052.99
A63: 44 | B63: 030411004040 | C63: 配线 | D63: 1.名称：配线 2.规格：RYYP-2*1.0 3.敷设方式：线槽配线 4.其它:满足完成此项工作所需要的全部工作内容，包括设计图纸、技术规范书、答疑、招标文件、现行规范、图集、验收等全部要求 | E63: m | F63: 1515.5 | G63: 2377.53 | H63: 625.67 | I63: 312.83 | J63: 1751.86 | K63: 500.53 | L63: 688.23 | M63: 563.1 | N63: =SUM(G63:M63) -> 6819.75
A64: 45 | B64: 030411004041 | C64: 配线 | D64: 1.名称：配线 2.规格：RYYP-4*1.0 3.敷设方式：管内穿线 4.其它:满足完成此项工作所需要的全部工作内容，包括设计图纸、技术规范书、答疑、招标文件、现行规范、图集、验收等全部要求 | E64: m | F64: 77.3 | G64: 161.69 | H64: 42.55 | I64: 21.28 | J64: 119.14 | K64: 34.04 | L64: 46.81 | M64: 38.3 | N64: =SUM(G64:M64) -> 463.81
A65: 46 | B65: 030411004042 | C65: 配线 | D65: 1.名称：配线 2.规格：RYYP-4*1.0 3.敷设方式：线槽配线 4.其它:满足完成此项工作所需要的全部工作内容，包括设计图纸、技术规范书、答疑、招标文件、现行规范、图集、验收等全部要求 | E65: m | F65: 1515.5 | G65: 2377.53 | H65: 625.67 | I65: 312.83 | J65: 1751.86 | K65: 500.53 | L65: 688.23 | M65: 563.1 | N65: =SUM(G65:M65) -> 6819.75
A66: 47 | B66: 030411004043 | C66: 配线 | D66: 1.名称：配线 2.规格：RYYP-6*1.0 3.敷设方式：管内穿线 4.其它:满足完成此项工作所需要的全部工作内容，包括设计图纸、技术规范书、答疑、招标文件、现行规范、图集、验收等全部要求 | E66: m | F66: 77.3 | G66: 161.69 | H66: 42.55 | I66: 21.28 | J66: 119.14 | K66: 34.04 | L66: 46.81 | M66: 38.3 | N66: =SUM(G66:M66) -> 463.81
A67: 48 | B67: 030411004044 | C67: 配线 | D67: 1.名称：配线 2.规格：RYYP-6*1.0 3.敷设方式：线槽配线 4.其它:满足完成此项工作所需要的全部工作内容，包括设计图纸、技术规范书、答疑、招标文件、现行规范、图集、验收等全部要求 | E67: m | F67: 1515.5 | G67: 3170.04 | H67: 834.22 | I67: 417.11 | J67: 2335.82 | K67: 667.38 | L67: 917.64 | M67: 750.8 | N67: =SUM(G67:M67) -> 9093.01
A68: 本页小计 | N68: =SUM(N63:N67) -> 23660.13
A69: 49 | B69: 030411004045 | C69: 配线 | D69: 1.名称：配线 2.规格：RYY-6*0.75 3.敷设方式：管内穿线 4.其它:满足完成此项工作所需要的全部工作内容，包括设计图纸、技术规范书、答疑、招标文件、现行规范、图集、验收等全部要求 | E69: m | F69: 120 | G69: 209.17 | H69: 55.05 | I69: 27.52 | J69: 154.13 | K69: 44.04 | L69: 60.55 | M69: 49.54 | N69: =SUM(G69:M69) -> 600
A70: 50 | B70: 030411004046 | C70: 配线 | D70: 1.名称：配线 2.规格：RYY-2*1.0 3.敷设方式：管内穿线 4.其它:满足完成此项工作所需要的全部工作内容，包括设计图纸、技术规范书、答疑、招标文件、现行规范、图集、验收等全部要求 | E70: m | F70: 180 | G70: 219.63 | H70: 57.8 | I70: 28.9 | J70: 161.83 | K70: 46.24 | L70: 63.58 | M70: 52.02 | N70: =SUM(G70:M70) -> 630
A71: 51 | B71: 030411006015 | C71: 接线盒 | D71: 1.名称:铁接线盒 2.安装形式:满足设计及规范验收要求 3.其它:满足完成此项工作所需要的全部工作内容，包括设计图纸、技术规范书、答疑、招标文件、现行规范、图集、验收等全部要求 | E71: 个 | F71: 20 | G71: 104.59 | H71: 27.52 | I71: 13.76 | J71: 77.06 | K71: 22.02 | L71: 30.28 | M71: 24.77 | N71: =SUM(G71:M71) -> 300
A72: 52 | B72: 030411001061 | C72: 配管 | D72: 1.名称：紧定式镀锌钢导管 2.规格：JDG25 3.敷设方式：暗配 4.其它:满足完成此项工作所需要的全部工作内容，包括设计图纸、技术规范书、答疑、招标文件、现行规范、图集、验收等全部要求 | E72: m | F72: 194.36 | G72: 338.79 | H72: 89.16 | I72: 44.58 | J72: 249.64 | K72: 71.32 | L72: 98.07 | M72: 80.24 | N72: =SUM(G72:M72) -> 971.8
A73: 本页小计 | N73: =SUM(N69:N72) -> 2501.8
A74: 53 | B74: 030411001062 | C74: 配管 | D74: 1.名称：紧定式镀锌钢导管 2.规格：JDG20 3.敷设方式：明配 4.其它:满足完成此项工作所需要的全部工作内容，包括设计图纸、技术规范书、答疑、招标文件、现行规范、图集、验收等全部要求 | E74: m | F74: 56 | G74: 87.85 | H74: 23.12 | I74: 11.56 | J74: 64.73 | K74: 18.5 | L74: 25.43 | M74: 20.81 | N74: =SUM(G74:M74) -> 252
A75: 54 | B75: 030413001033 | C75: 管道支架/综合支架 | D75: 1.名称:管道支架制作安装 2.材质:热镀锌 3.安装高度:综合考虑 4.满足完成此项工作所需要的全部工作内容，满足设计图纸、技术规范书、答疑、招标文件、现行规范、图集、验收等全部要求 | E75: kg | F75: 6.72 | G75: 30.46 | H75: 8.01 | I75: 4.01 | J75: 22.44 | K75: 6.41 | L75: 8.82 | M75: 7.21 | N75: =SUM(G75:M75) -> 87.36
A76: 55 | B76: 030413002017 | C76: 凿（压)槽 | D76: 1.名称:管线剔槽及恢复 2.满足完成此项工作所需要的全部工作内容，满足设计图纸、答疑、招标文件、现行规范、图集、验收等全部要求 | E76: m | F76: 138.36 | G76: 594.06 | H76: 49.5 | I76: 19.8 | J76: 148.51 | K76: 69.31 | L76: 108.91 | M76: 89.11 | N76: =SUM(G76:M76) -> 1079.2
A77: 56 | B77: 030411004047 | C77: 配线 | D77: 1.名称：配线 2.规格：RYYP-2*1.0 3.敷设方式：管内穿线 4.其它:满足完成此项工作所需要的全部工作内容，包括设计图纸、技术规范书、答疑、招标文件、现行规范、图集、验收等全部要求 | E77: m | F77: 429.6 | G77: 524.19 | H77: 137.94 | I77: 68.97 | J77: 386.25 | K77: 110.36 | L77: 151.74 | M77: 124.15 | N77: =SUM(G77:M77) -> 1503.6
A78: 57 | B78: 030411004048 | C78: 配线 | D78: 1.名称：配线 2.规格：RYYP-4*1.0 3.敷设方式：管内穿线 4.其它:满足完成此项工作所需要的全部工作内容，包括设计图纸、技术规范书、答疑、招标文件、现行规范、图集、验收等全部要求 | E78: m | F78: 292.2 | G78: 458.41 | H78: 120.63 | I78: 60.32 | J78: 337.77 | K78: 96.51 | L78: 132.7 | M78: 108.57 | N78: =SUM(G78:M78) -> 1314.91
A79: 本页小计 | N79: =SUM(N74:N78) -> 4237.07
A80: 58 | B80: 030411004049 | C80: 配线 | D80: 1.名称：配线 2.规格：RYYP-6*1.0 3.敷设方式：管内穿线 4.其它:满足完成此项工作所需要的全部工作内容，包括设计图纸、技术规范书、答疑、招标文件、现行规范、图集、验收等全部要求 | E80: m | F80: 292.2 | G80: 611.21 | H80: 160.84 | I80: 80.42 | J80: 450.36 | K80: 128.68 | L80: 176.93 | M80: 144.76 | N80: =SUM(G80:M80) -> 1753.2
A81: 59 | B81: 030502005015 | C81: 双绞线缆 | D81: 1.名称：六类网线 2.规格： Cat.6 UTP 3.敷设方式：管内敷设 4.其它:满足完成此项工作所需要的全部工作内容，包括设计图纸、技术规范书、答疑、招标文件、现行规范、图集、验收等全部要求 | E81: m | F81: 272.3 | G81: 284.79 | H81: 74.94 | I81: 37.47 | J81: 209.85 | K81: 59.96 | L81: 82.44 | M81: 67.45 | N81: =SUM(G81:M81) -> 816.9
A82: 60 | B82: 030411004050 | C82: 配线 | D82: 1.名称：配线 2.规格：RYY-6*0.75 3.敷设方式：管内穿线 4.其它:满足完成此项工作所需要的全部工作内容，包括设计图纸、技术规范书、答疑、招标文件、现行规范、图集、验收等全部要求 | E82: m | F82: 168 | G82: 351.41 | H82: 92.48 | I82: 46.24 | J82: 258.94 | K82: 73.98 | L82: 101.72 | M82: 83.23 | N82: =SUM(G82:M82) -> 1008
A83: 61 | B83: 030411004051 | C83: 配线 | D83: 1.名称：配线 2.规格：RYY-2*1.0 3.敷设方式：管内穿线 4.其它:满足完成此项工作所需要的全部工作内容，包括设计图纸、技术规范书、答疑、招标文件、现行规范、图集、验收等全部要求 | E83: m | F83: 252 | G83: 298.7 | H83: 78.61 | I83: 39.3 | J83: 220.1 | K83: 62.88 | L83: 86.47 | M83: 70.74 | N83: =SUM(G83:M83) -> 856.8
A84: 62 | B84: 030411006016 | C84: 接线盒 | D84: 1.名称:铁接线盒 2.安装形式:满足设计及规范验收要求 3.其它:满足完成此项工作所需要的全部工作内容，包括设计图纸、技术规范书、答疑、招标文件、现行规范、图集、验收等全部要求 | E84: 个 | F84: 16 | G84: 83.67 | H84: 22.02 | I84: 11.01 | J84: 61.65 | K84: 17.61 | L84: 24.22 | M84: 19.82 | N84: =SUM(G84:M84) -> 240
A85: 本页小计 | N85: =SUM(N80:N84) -> 4674.9
A86: 63 | B86: 030411001063 | C86: 配管 | D86: 1.名称：紧定式镀锌钢导管 2.规格：JDG25 3.敷设方式：明配 4.其它:满足完成此项工作所需要的全部工作内容，包括设计图纸、技术规范书、答疑、招标文件、现行规范、图集、验收等全部要求 | E86: m | F86: 1622.94 | G86: 2828.98 | H86: 744.47 | I86: 372.23 | J86: 2084.51 | K86: 595.57 | L86: 818.91 | M86: 670.02 | N86: =SUM(G86:M86) -> 8114.69
A87: 64 | B87: 030411001064 | C87: 配管 | D87: 1.名称：紧定式镀锌钢导管 2.规格：JDG25 3.敷设方式：暗配 4.其它:满足完成此项工作所需要的全部工作内容，包括设计图纸、技术规范书、答疑、招标文件、现行规范、图集、验收等全部要求 | E87: m | F87: 1046.4 | G87: 1824 | H87: 480 | I87: 240 | J87: 1344 | K87: 384 | L87: 528 | M87: 432 | N87: =SUM(G87:M87) -> 5232
A88: 65 | B88: 030411001065 | C88: 配管 | D88: 1.名称：紧定式镀锌钢导管 2.规格：JDG20 3.敷设方式：明配 4.其它:满足完成此项工作所需要的全部工作内容，包括设计图纸、技术规范书、答疑、招标文件、现行规范、图集、验收等全部要求 | E88: m | F88: 382 | G88: 599.28 | H88: 157.71 | I88: 78.85 | J88: 441.58 | K88: 126.17 | L88: 173.48 | M88: 141.94 | N88: =SUM(G88:M88) -> 1719.01
A89: 66 | B89: 030413002018 | C89: 凿（压)槽 | D89: 1.名称:管线剔槽及恢复 2.满足完成此项工作所需要的全部工作内容，满足设计图纸、答疑、招标文件、现行规范、图集、验收等全部要求 | E89: m | F89: 523 | G89: 2245.54 | H89: 187.13 | I89: 74.85 | J89: 561.39 | K89: 261.98 | L89: 411.68 | M89: 336.83 | N89: =SUM(G89:M89) -> 4079.4
A90: 本页小计 | N90: =SUM(N86:N89) -> 19145.1
A91: 67 | B91: 030413001034 | C91: 管道支架/综合支架 | D91: 1.名称:管道支架制作安装 2.材质:热镀锌 3.安装高度:综合考虑 4.满足完成此项工作所需要的全部工作内容，满足设计图纸、技术规范书、答疑、招标文件、现行规范、图集、验收等全部要求 | E91: kg | F91: 289.8 | G91: 1313.41 | H91: 345.63 | I91: 172.82 | J91: 967.77 | K91: 276.51 | L91: 380.2 | M91: 311.07 | N91: =SUM(G91:M91) -> 3767.41
A92: 68 | B92: 030411004052 | C92: 配线 | D92: 1.名称：配线 2.规格：RYYP-2*1.0 3.敷设方式：管内穿线 4.其它:满足完成此项工作所需要的全部工作内容，包括设计图纸、技术规范书、答疑、招标文件、现行规范、图集、验收等全部要求 | E92: m | F92: 2136.11 | G92: 2606.45 | H92: 685.91 | I92: 342.95 | J92: 1920.54 | K92: 548.73 | L92: 754.5 | M92: 617.32 | N92: =SUM(G92:M92) -> 7476.4
A93: 69 | B93: 030411004053 | C93: 配线 | D93: 1.名称：配线 2.规格：RYYP-2*1.0 3.敷设方式：线槽配线 4.其它:满足完成此项工作所需要的全部工作内容，包括设计图纸、技术规范书、答疑、招标文件、现行规范、图集、验收等全部要求 | E93: m | F93: 13773.37 | G93: 16806.04 | H93: 4422.64 | I93: 2211.32 | J93: 12383.4 | K93: 3538.11 | L93: 4864.91 | M93: 3980.38 | N93: =SUM(G93:M93) -> 48206.8
A94: 70 | B94: 030411004054 | C94: 配线 | D94: 1.名称：配线 2.规格：RYYP-4*1.0 3.敷设方式：管内穿线 4.其它:满足完成此项工作所需要的全部工作内容，包括设计图纸、技术规范书、答疑、招标文件、现行规范、图集、验收等全部要求 | E94: m | F94: 2136.11 | G94: 4468.19 | H94: 1175.84 | I94: 587.92 | J94: 3292.35 | K94: 940.67 | L94: 1293.42 | M94: 1058.26 | N94: =SUM(G94:M94) -> 12816.65
A95: 本页小计 | N95: =SUM(N91:N94) -> 72267.26
A96: 71 | B96: 030411004055 | C96: 配线 | D96: 1.名称：配线 2.规格：RYYP-4*1.0 3.敷设方式：线槽配线 4.其它:满足完成此项工作所需要的全部工作内容，包括设计图纸、技术规范书、答疑、招标文件、现行规范、图集、验收等全部要求 | E96: m | F96: 13773.37 | G96: 28810.35 | H96: 7581.67 | I96: 3790.84 | J96: 21228.68 | K96: 6065.34 | L96: 8339.84 | M96: 6823.5 | N96: =SUM(G96:M96) -> 82640.22
A97: 72 | B97: 030411004056 | C97: 配线 | D97: 1.名称：配线 2.规格：RYYP-6*1.0 3.敷设方式：管内穿线 4.其它:满足完成此项工作所需要的全部工作内容，包括设计图纸、技术规范书、答疑、招标文件、现行规范、图集、验收等全部要求 | E97: m | F97: 2136.11 | G97: 4468.19 | H97: 1175.84 | I97: 587.92 | J97: 3292.35 | K97: 940.67 | L97: 1293.42 | M97: 1058.26 | N97: =SUM(G97:M97) -> 12816.65
A98: 73 | B98: 030411004057 | C98: 配线 | D98: 1.名称：配线 2.规格：RYYP-6*1.0 3.敷设方式：线槽配线 4.其它:满足完成此项工作所需要的全部工作内容，包括设计图纸、技术规范书、答疑、招标文件、现行规范、图集、验收等全部要求 | E98: m | F98: 13773.37 | G98: 28810.35 | H98: 7581.67 | I98: 3790.84 | J98: 21228.68 | K98: 6065.34 | L98: 8339.84 | M98: 6823.5 | N98: =SUM(G98:M98) -> 82640.22
A99: 74 | B99: 030411004058 | C99: 配线 | D99: 1.名称：配线 2.规格：RYY-6*0.75 3.敷设方式：管内穿线 4.其它:满足完成此项工作所需要的全部工作内容，包括设计图纸、技术规范书、答疑、招标文件、现行规范、图集、验收等全部要求 | E99: m | F99: 1146 | G99: 2397.14 | H99: 630.83 | I99: 315.41 | J99: 1766.31 | K99: 504.66 | L99: 693.91 | M99: 567.74 | N99: =SUM(G99:M99) -> 6876
A100: 75 | B100: 030411004059 | C100: 配线 | D100: 1.名称：配线 2.规格：RYY-2*1.0 3.敷设方式：管内穿线 4.其它:满足完成此项工作所需要的全部工作内容，包括设计图纸、技术规范书、答疑、招标文件、现行规范、图集、验收等全部要求 | E100: m | F100: 1719 | G100: 2696.78 | H100: 709.68 | I100: 354.84 | J100: 1987.1 | K100: 567.74 | L100: 780.65 | M100: 638.71 | N100: =SUM(G100:M100) -> 7735.5
...

Sheet 8#、15#非管区园区智能化管理平台系统
A1: 分部分项工程和单价措施项目清单与计价表
A2: 分部分项工程和单价措施项目清单与计价表
A3: 序号 | B3: 项目编码 | C3: 项目名称 | D3: 项目特征描述 | E3: 计量单位 | F3: 工程量 | G3: 金额（元）
G4: 主材/设备费 | H4: 辅材 | I4: 机械措施 | J4: 人工 | K4: 管理费 | L4: 利润 | M4: 税金 | N4: 总价
A5: 1 | B5: 030501013015 | C5: 园区智能化管理平台平台系统集成服务器 | D5: 1.名称：园区智能化管理平台平台系统集成服务器（含鼠标键盘、显示器、软件等） 2.技术参数：处理器：≥2颗Intel 至强 4510处理器，单颗核数≥12核， ≥2.40 GHz或以上；内存：≥128G；操作系统： 支持Microsoft Windows Server 2019、 RedHat Enterprise Linux 、 SUSE Linux Enterprise Server、 CentOS、 Ubuntu、 Vmware EXSI；内置SAS硬盘，RAID5，配备4x3TB热插拔硬盘，10000rpm以上；2个千兆以太网口；冗余电源、风扇，可以365天24小时运行；1块单口8Gb HBA卡。 3.其它:满足完成此项工作所需要的全部工作内容，包括设计图纸、技术规范书、答疑、招标文件、现行规范、图集、验收等全部要求 | E5: 台 | F5: 2 | G5: 27550.46 | H5: 1059.635 | I5: 353.21 | J5: 1412.845 | K5: 1059.635 | L5: 3885.32 | M5: 3178.9 | N5: =SUM(G5:M5) -> 38500.005
A6: 本页小计 | N6: =N5 -> 38500.005
A7: 2 | B7: 030501013016 | C7: 园区智能化管理平台平台系统管理服务器 | D7: 1.名称：园区智能化管理平台平台系统管理服务器（含鼠标键盘、显示器、软件等） 2.技术参数：处理器：≥2颗Intel 至强 4510处理器，单颗核数≥12核， ≥2.40 GHz或以上；内存：≥128G；操作系统： 支持Microsoft Windows Server 2019、 RedHat Enterprise Linux 、 SUSE Linux Enterprise Server、 CentOS、 Ubuntu、 Vmware EXSI；内置SAS硬盘，RAID5，配备4x3TB热插拔硬盘，10000rpm以上；2个千兆以太网口；冗余电源、风扇，可以365天24小时运行；1块单口8Gb HBA卡。 3.其它:满足完成此项工作所需要的全部工作内容，包括设计图纸、技术规范书、答疑、招标文件、现行规范、图集、验收等全部要求 | E7: 台 | F7: 1 | G7: 13775.23 | H7: 529.815 | I7: 176.605 | J7: 706.42 | K7: 529.815 | L7: 1942.66 | M7: 1589.45 | N7: =SUM(G7:M7) -> 19249.995
A8: 3 | B8: 030501013017 | C8: 园区智能化管理平台系统管理平台图形 | D8: 1.名称：园区智能化管理平台系统管理平台图形 2.其它:满足完成此项工作所需要的全部工作内容，包括设计图纸、技术规范书、答疑、招标文件、现行规范、图集、验收等全部要求 | E8: 台 | F8: 1 | G8: 12385.32 | H8: 1032.11 | I8: 412.845 | J8: 3096.33 | K8: 1444.955 | L8: 2270.64 | M8: 1857.8 | N8: =SUM(G8:M8) -> 22500
A9: 本页小计 | N9: =SUM(N7:N8) -> 41749.995
A10: 4 | B10: 030501013018 | C10: 园区智能化管理平台平台系统数据库 | D10: 1.名称：园区智能化管理平台平台系统数据库 2.其它:满足完成此项工作所需要的全部工作内容，包括设计图纸、技术规范书、答疑、招标文件、现行规范、图集、验收等全部要求 | E10: 台 | F10: 2 | G10: 15412.845 | H10: 1284.405 | I10: 513.76 | J10: 3853.21 | K10: 1798.165 | L10: 2825.69 | M10: 2311.925 | N10: =SUM(G10:M10) -> 28000
A11: 5 | B11: 080901003002 | C11: 园区智能化管理平台平台软件 | D11: 1.名称:园区智能化管理平台可视化展示 2.含建模、BIM运维、三维展示等内容 3.其它:满足完成此项工作所需要的全部工作内容，包括设计图纸、技术规范书、答疑、招标文件、现行规范、图集、验收等全部要求 | E11: 台 | F11: 1 | G11: 22018.35 | H11: 1834.86 | I11: 733.945 | J11: 5504.585 | K11: 2568.805 | L11: 4036.695 | M11: 3302.75 | N11: =SUM(G11:M11) -> 39999.99
A12: 6 | B12: 030501013019 | C12: 园区智能化管理平台系统工作站（含授权） | D12: 1.名称:园区智能化管理平台系统工作站（含授权） 2.其它:满足完成此项工作所需要的全部工作内容，包括设计图纸、技术规范书、答疑、招标文件、现行规范、图集、验收等全部要求 | E12: 台 | F12: 2 | G12: 8587.155 | H12: 330.275 | I12: 110.09 | J12: 440.365 | K12: 330.275 | L12: 1211.01 | M12: 990.825 | N12: =SUM(G12:M12) -> 11999.995
A13: 7 | B13: 030501016001 | C13: 园区智能化管理平台系统开发调试、运行 | D13: 1.名称:园区智能化管理平台系统开发调试 2.其它:满足完成此项工作所需要的全部工作内容，包括设计图纸、技术规范书、答疑、招标文件、现行规范、图集、验收等全部要求 | E13: 系统 | F13: 1 | G13: 2788.99 | H13: 733.94 | I13: 366.97 | J13: 2055.05 | K13: 587.16 | L13: 807.34 | M13: 660.55 | N13: =SUM(G13:M13) -> 8000
A14: 本页小计 | N14: =SUM(N10:N13) -> 87999.985
A15: 8 | B15: 080901003003 | C15: 告警管理组件 | D15: 1.名称:告警管理组件 2.技术参数:告警信息管理、告警屏蔽、告警通知发送，提供统一的告警中心展示界面 3.其它:满足完成此项工作所需要的全部工作内容，包括设计图纸、技术规范书、答疑、招标文件、现行规范、图集、验收等全部要求 | E15: 台 | F15: 1 | G15: 550.46 | H15: 45.87 | I15: 18.35 | J15: 137.615 | K15: 64.22 | L15: 100.915 | M15: 82.57 | N15: =SUM(G15:M15) -> 1000
A16: 9 | B16: 080901003004 | C16: 模型管理组件 | D16: 1.名称:模型管理组件 2.技术参数:提供建筑、设施、网络、车辆等模型对象，支持项目快速实施使用。 3.其它:满足完成此项工作所需要的全部工作内容，包括设计图纸、技术规范书、答疑、招标文件、现行规范、图集、验收等全部要求 | E16: 台 | F16: 1 | G16: 550.46 | H16: 45.87 | I16: 18.35 | J16: 137.615 | K16: 64.22 | L16: 100.915 | M16: 82.57 | N16: =SUM(G16:M16) -> 1000
A17: 10 | B17: 080901003005 | C17: 用户管理组件 | D17: 1.名称:用户管理组件 2.技术参数:用户增删改、角色管理、权限分配、用户登陆操作日志记录 3.其它:满足完成此项工作所需要的全部工作内容，包括设计图纸、技术规范书、答疑、招标文件、现行规范、图集、验收等全部要求 | E17: 台 | F17: 1 | G17: 550.46 | H17: 45.87 | I17: 18.35 | J17: 137.615 | K17: 64.22 | L17: 100.915 | M17: 82.57 | N17: =SUM(G17:M17) -> 1000
A18: 11 | B18: 080901003006 | C18: 数据分析组件 | D18: 1.名称:数据分析组件 2.技术参数:同比、环比数据分析规则定制，基于园区数据沉淀提供数据分析能力 3.其它:满足完成此项工作所需要的全部工作内容，包括设计图纸、技术规范书、答疑、招标文件、现行规范、图集、验收等全部要求 | E18: 台 | F18: 1 | G18: 825.69 | H18: 68.805 | I18: 27.525 | J18: 206.42 | K18: 96.33 | L18: 151.375 | M18: 123.855 | N18: =SUM(G18:M18) -> 1500
A19: 本页小计 | N19: =SUM(N15:N18) -> 4500
A20: 12 | B20: 080901003007 | C20: 集成管理组件 | D20: 1.名称:集成管理组件 2.技术参数:支持RestAPI、JDBC、MQ、HTTP等各类通用协议接口，用于与弱电及IT子系统对接，获取相关业务数据。 3.其它:满足完成此项工作所需要的全部工作内容，包括设计图纸、技术规范书、答疑、招标文件、现行规范、图集、验收等全部要求 | E20: 台 | F20: 1 | G20: 825.69 | H20: 68.805 | I20: 27.525 | J20: 206.42 | K20: 96.33 | L20: 151.375 | M20: 123.855 | N20: =SUM(G20:M20) -> 1500
A21: 13 | B21: 080901003008 | C21: 综合态势管理 | D21: 1.名称:综合态势管理 2.技术参数:通过智慧园区综合安防、人员通行、车辆通行系统的数据接入，通过物联网、AI分析等技术将园区信息整合分析和统计，多维度呈现智慧园区运营与安防态势，展示设施分布、综合信息和日志，实时接入安监、应急、运营等监测管理数据和报警。通过对关键管理指标、设施可用性、运营参数、运行告警数据分析，整体展现智慧园区的安保、应急、运营综合态势。 3.其它:满足完成此项工作所需要的全部工作内容，包括设计图纸、技术规范书、答疑、招标文件、现行规范、图集、验收等全部要求 | E21: 台 | F21: 1 | G21: 2201.835 | H21: 183.485 | I21: 73.395 | J21: 550.46 | K21: 256.88 | L21: 403.67 | M21: 330.275 | N21: =SUM(G21:M21) -> 4000
A22: 本页小计 | N22: =SUM(N20:N21) -> 5500
A23: 14 | B23: 080901003009 | C23: 园区导览管理 | D23: 1.名称:园区导览管理 2.技术参数:通过三维构建园区，包含两栋7层建筑组成。实现园区功能区域、楼宇等信息、职能、导航的综合展示与查询。 3.其它:满足完成此项工作所需要的全部工作内容，包括设计图纸、技术规范书、答疑、招标文件、现行规范、图集、验收等全部要求 | E23: 台 | F23: 1 | G23: 1651.375 | H23: 137.615 | I23: 55.045 | J23: 412.845 | K23: 192.66 | L23: 302.75 | M23: 247.705 | N23: =SUM(G23:M23) -> 2999.995
A24: 15 | B24: 080901003010 | C24: 综合态势管理统计 | D24: 1.名称:综合态势管理统计 2.技术参数:以饼图、趋势图、柱状图等图表展示智慧园区综合态势、安防管理、人员管理、车辆管理、应急管理等数据分析综合展示。 3.其它:满足完成此项工作所需要的全部工作内容，包括设计图纸、技术规范书、答疑、招标文件、现行规范、图集、验收等全部要求 | E24: 台 | F24: 1 | G24: 1651.375 | H24: 137.615 | I24: 55.045 | J24: 412.845 | K24: 192.66 | L24: 302.75 | M24: 247.705 | N24: =SUM(G24:M24) -> 2999.995
A25: 16 | B25: 080901003011 | C25: 信息引导及发布管理 | D25: 1.名称:信息引导及发布管理 2.技术参数:提供信息发布设施位置可视、设施运行状态可视、告警可视。 3.其它:满足完成此项工作所需要的全部工作内容，包括设计图纸、技术规范书、答疑、招标文件、现行规范、图集、验收等全部要求 | E25: 台 | F25: 1 | G25: 1045.87 | H25: 275.23 | I25: 137.615 | J25: 770.64 | K25: 220.185 | L25: 302.75 | M25: 247.705 | N25: =SUM(G25:M25) -> 2999.995
A26: 本页小计 | N26: =SUM(N23:N25) -> 8999.985
A27: 17 | B27: 080901003012 | C27: 公共/应急广播系统 | D27: 1.名称:公共/应急广播系统 2.技术参数:提供广播系统设施位置可视、设施运行状态可视、告警可视。 3.其它:满足完成此项工作所需要的全部工作内容，包括设计图纸、技术规范书、答疑、招标文件、现行规范、图集、验收等全部要求 | E27: 台 | F27: 1 | G27: 2862.385 | H27: 110.09 | I27: 36.695 | J27: 146.79 | K27: 110.09 | L27: 403.67 | M27: 330.275 | N27: =SUM(G27:M27) -> 3999.995
A28: 18 | B28: 080901003013 | C28: 新风管理 | D28: 1.名称:新风管理 2.技术参数:大楼综合体的排风，风压，状态管理。 3.其它:满足完成此项工作所需要的全部工作内容，包括设计图纸、技术规范书、答疑、招标文件、现行规范、图集、验收等全部要求 | E28: 台 | F28: 1 | G28: 6055.045 | H28: 504.585 | I28: 201.835 | J28: 1513.76 | K28: 706.42 | L28: 1110.09 | M28: 908.255 | N28: =SUM(G28:M28) -> 10999.99
A29: 19 | B29: 080901003014 | C29: 空调管理 | D29: 1.名称:空调管理 2.技术参数:大楼综合体的空调的开关，状态的管理。 3.其它:满足完成此项工作所需要的全部工作内容，包括设计图纸、技术规范书、答疑、招标文件、现行规范、图集、验收等全部要求 | E29: 台 | F29: 1 | G29: 2862.385 | H29: 110.09 | I29: 36.695 | J29: 146.79 | K29: 110.09 | L29: 403.67 | M29: 330.275 | N29: =SUM(G29:M29) -> 3999.995
A30: 20 | B30: 080901003015 | C30: 充电桩管理 | D30: 1.名称:充电桩管理 2.技术参数:对园区的充电桩的资源可视化，电流，电压，状态的管理。 3.其它:满足完成此项工作所需要的全部工作内容，包括设计图纸、技术规范书、答疑、招标文件、现行规范、图集、验收等全部要求 | E30: 台 | F30: 1 | G30: 2201.835 | H30: 183.485 | I30: 73.395 | J30: 550.46 | K30: 256.88 | L30: 403.67 | M30: 330.275 | N30: =SUM(G30:M30) -> 4000
A31: 本页小计 | N31: =SUM(N27:N30) -> 22999.98
A32: 21 | B32: 080901003016 | C32: 能耗管理 | D32: 1.名称:能耗管理 2.技术参数:掌握用能趋势。实时动态 监测当前用电功率。通过设置每日用能的计划值，实现用能的定额管理，并与实际用能 进行对比，对可能出现的用能突增进行预警。将各类用能折算为标准煤，全局掌握用能情况。通过用能趋势图，快速定位用能负荷高峰，并逐级定位高峰能耗的组成，为移峰填谷找到依据。按需定制的各类报表，包括分户能耗、设备能耗、数据集抄等，并可将数据导出到 Excel等电子文件，方便日常管理工作。 3.其它:满足完成此项工作所需要的全部工作内容，包括设计图纸、技术规范书、答疑、招标文件、现行规范、图集、验收等全部要求 | E32: 台 | F32: 1 | G32: 2201.835 | H32: 183.485 | I32: 73.395 | J32: 550.46 | K32: 256.88 | L32: 403.67 | M32: 330.275 | N32: =SUM(G32:M32) -> 4000
A33: 22 | B33: 080901003017 | C33: 电动窗帘管理 | D33: 1.名称:电动窗帘管理 2.技术参数:大楼综合体的窗帘状态的管理。 3.其它:满足完成此项工作所需要的全部工作内容，包括设计图纸、技术规范书、答疑、招标文件、现行规范、图集、验收等全部要求 | E33: 台 | F33: 1 | G33: 1073.395 | H33: 41.285 | I33: 13.76 | J33: 55.045 | K33: 41.285 | L33: 151.375 | M33: 123.855 | N33: =SUM(G33:M33) -> 1500
A34: 本页小计 | N34: =SUM(N32:N33) -> 5500
A35: 23 | B35: 080901003018 | C35: 三维数据加工 | D35: 1.名称:三维数据加工 2.技术参数:对园区室内外建筑、立面电梯、监控系统、消防系统、安保等数据进行3D加工，用于可视化系统呈现. 3.其它:满足完成此项工作所需要的全部工作内容，包括设计图纸、技术规范书、答疑、招标文件、现行规范、图集、验收等全部要求 | E35: 台 | F35: 1 | G35: 5504.585 | H35: 458.715 | I35: 183.485 | J35: 1376.145 | K35: 642.2 | L35: 1009.175 | M35: 825.69 | N35: =SUM(G35:M35) -> 9999.995
A36: 24 | B36: 03B055 | C36: 系统综合及集成 | D36: 1.清单未列项、图纸中未表示或技术规格书未做要求，但为了实现本系统各项功能必须增加的配套及辅助的材料、设备的所有工作内容及费用； 2.施工深化设计增加的实现本系统设计功能必要的配套及辅助的材料、设备所需的所有工作内容及费用； 3.实现设计功能所做的满足图纸、技术规格书要求的各项综合与集成，包括不限于各项检测、试验、调试、软件开发、联动等所有工作内容及费用 | E36: 项 | F36: 1 | G36: 6450.2195 | H36: 917.43 | I36: 458.715 | J36: 2568.805 | K36: 733.945 | L36: 1009.175 | M36: 825.69 | N36: =SUM(G36:M36) -> 12963.979
A37: 25 | B37: 031301017031 | C37: 脚手架搭拆 | D37: 1.综合考虑项目脚手架搭拆或其他替代措施项目 2.场内外材料搬运 3.拆除脚手架后材料的堆放 4.满足完成此项工作所需要的全部工作内容，满足设计图纸、答疑、招标文件、现行规范、图集、验收等全部要求 | E37: 项 | F37: 1 | G37: 697.25 | H37: 183.49 | I37: 91.74 | J37: 513.76 | K37: 146.79 | L37: 201.83 | M37: 165.14 | N37: =SUM(G37:M37) -> 2000
A38: 26 | B38: 03B057 | C38: 超高费 | E38: 项 | F38: 1 | G38: 550.46 | H38: 45.87 | I38: 18.35 | J38: 137.61 | K38: 64.22 | L38: 100.92 | M38: 82.57 | N38: =SUM(G38:M38) -> 1000
A39: 本页小计 | N39: =SUM(N35:N38) -> 25963.975
A40: 合 计 | N40: =N6+N9+N14+N19+N22+N26+N31+N34+N39 -> 241713.92
G42: =G36+2963.9795 -> 9414.199

Sheet 8#、15#非管区综合布线系统
A1: 分部分项工程和单价措施项目清单与计价表
A2: 分部分项工程和单价措施项目清单与计价表
A3: 序号 | B3: 项目编码 | C3: 项目名称 | D3: 项目特征描述 | E3: 计量单位 | F3: 工程量 | G3: 金额（元）
G4: 主材/设备费 | H4: 辅材 | I4: 机械措施 | J4: 人工 | K4: 管理费 | L4: 利润 | M4: 税金 | N4: 总价
A5: 1 | B5: 030501012005 | C5: 万兆核心交换机 | D5: 1.名称:万兆核心交换机 2.规格:核心满足不少于48光口,48电口 3.其它:满足完成此项工作所需要的全部工作内容，包括设计图纸、技术规范书、答疑、招标文件、现行规范、图集、验收等全部要求 | E5: 台 | F5: 1 | G5: 19321.098 | H5: 743.118 | I5: 247.704 | J5: 990.828 | K5: 743.118 | L5: 2724.768 | M5: 2229.36 | N5: =SUM(G5:M5) -> 26999.994
A6: 2 | B6: 030502007010 | C6: 光缆 | D6: 1.名称：144芯室外单模光缆 2.敷设方式：室外埋地敷设 3.其它:满足完成此项工作所需要的全部工作内容，包括设计图纸、技术规范书、答疑、招标文件、现行规范、图集、验收等全部要求 | E6: m | F6: 1400 | G6: 5856.88 | H6: 1541.28 | I6: 770.64 | J6: 4315.6 | K6: 1233.03 | L6: 1695.41 | M6: 1387.16 | N6: =SUM(G6:M6) -> 16800
A7: 3 | B7: 030502007011 | C7: 光缆 | D7: 1.名称：48芯室外单模光缆 2.敷设方式：室外埋地敷设 3.其它:满足完成此项工作所需要的全部工作内容，包括设计图纸、技术规范书、答疑、招标文件、现行规范、图集、验收等全部要求 | E7: m | F7: 1400 | G7: 3904.59 | H7: 1027.52 | I7: 513.76 | J7: 2877.06 | K7: 822.02 | L7: 1130.28 | M7: 924.77 | N7: =SUM(G7:M7) -> 11200
A8: 4 | B8: 030502007012 | C8: 光缆 | D8: 1.名称：24芯多模光缆 2.敷设方式：桥架敷设 3.其它:满足完成此项工作所需要的全部工作内容，包括设计图纸、技术规范书、答疑、招标文件、现行规范、图集、验收等全部要求 | E8: m | F8: 6856.45 | G8: 39251.6 | H8: 1509.68 | I8: 503.23 | J8: 2012.9 | K8: 1509.68 | L8: 5535.48 | M8: 4529.03 | N8: =SUM(G8:M8) -> 54851.6
A9: 5 | B9: 030502007013 | C9: 光缆 | D9: 1.名称：48芯多模光缆 2.敷设方式：桥架敷设 3.其它:满足完成此项工作所需要的全部工作内容，包括设计图纸、技术规范书、答疑、招标文件、现行规范、图集、验收等全部要求 | E9: m | F9: 411.4 | G9: 4710.34 | H9: 181.17 | I9: 60.39 | J9: 241.56 | K9: 181.17 | L9: 664.28 | M9: 543.5 | N9: =SUM(G9:M9) -> 6582.41
A10: 本页小计 | N10: =SUM(N5:N9) -> 116434
A11: 6 | B11: 030502007014 | C11: 12芯多模光缆 | D11: 1.名称：12芯多模光缆 2.敷设方式：桥架敷设 3.其它:满足完成此项工作所需要的全部工作内容，包括设计图纸、技术规范书、答疑、招标文件、现行规范、图集、验收等全部要求 | E11: m | F11: 196.94 | G11: 704.65 | H11: 27.1 | I11: 9.03 | J11: 36.14 | K11: 27.1 | L11: 99.37 | M11: 81.31 | N11: =SUM(G11:M11) -> 984.7
A12: 7 | B12: 030502010005 | C12: 配线架 | D12: 1.名称:48芯光纤配线架 2.含尾纤、耦合器、光纤面板、光纤托盘 3.其它:满足完成此项工作所需要的全部工作内容，包括设计图纸、技术规范书、答疑、招标文件、现行规范、图集、验收等全部要求 | E12: 个 | F12: 16 | G12: 3205.87 | H12: 123.3 | I12: 41.1 | J12: 164.4 | K12: 123.3 | L12: 452.11 | M12: 369.91 | N12: =SUM(G12:M12) -> 4479.99
A13: 8 | B13: 030502010006 | C13: 配线架 | D13: 1.名称::24芯光纤配线架 2.含尾纤、耦合器、光纤面板、光纤托盘 3.其它:满足完成此项工作所需要的全部工作内容，包括设计图纸、技术规范书、答疑、招标文件、现行规范、图集、验收等全部要求。 | E13: 个 | F13: 81 | G13: 34777.98 | H13: 1337.61 | I13: 445.86 | J13: 1783.5 | K13: 1337.61 | L13: 4904.58 | M13: 4012.83 | N13: =SUM(G13:M13) -> 48599.97
A14: 9 | B14: 030502010007 | C14: 理线器 | D14: 1.名称:理线器 2.其它:满足完成此项工作所需要的全部工作内容，包括设计图纸、技术规范书、答疑、招标文件、现行规范、图集、验收等全部要求 | E14: 个 | F14: 22 | G14: 363.3 | H14: 30.28 | I14: 12.11 | J14: 90.83 | K14: 42.39 | L14: 66.61 | M14: 54.5 | N14: =SUM(G14:M14) -> 660.02
A15: 10 | B15: 030502010008 | C15: 配线架 24口 | D15: 1.名称：六类24口配线架 2.规格：非屏蔽,24端口,含模块 3.其它:满足完成此项工作所需要的全部工作内容，包括设计图纸、技术规范书、答疑、招标文件、现行规范、图集、验收等全部要求 | E15: 个 | F15: 293 | G15: 83867.88 | H15: 3225.68 | I15: 1075.22 | J15: 4300.92 | K15: 3225.68 | L15: 11827.52 | M15: 9677.06 | N15: =SUM(G15:M15) -> 117199.96
A16: 本页小计 | N16: =SUM(N11:N15) -> 171924.64
A17: 11 | B17: 030502009014 | C17: LC-LC单模光纤跳线（3m） | D17: 1.名称:LC-LC单模光纤跳线（3m） 2.其它:满足完成此项工作所需要的全部工作内容，包括设计图纸、技术规范书、答疑、招标文件、现行规范、图集、验收等全部要求 | E17: 条 | F17: 48 | G17: 686.97 | H17: 26.42 | I17: 8.81 | J17: 35.23 | K17: 26.42 | L17: 96.88 | M17: 79.27 | N17: =SUM(G17:M17) -> 960
A18: 12 | B18: 030502009015 | C18: LC-LC多模光纤跳线（3m） | D18: 1.名称:LC-LC多模光纤跳线（3m） 2.其它:满足完成此项工作所需要的全部工作内容，包括设计图纸、技术规范书、答疑、招标文件、现行规范、图集、验收等全部要求 | E18: 条 | F18: 48 | G18: 858.72 | H18: 33.03 | I18: 11.01 | J18: 44.04 | K18: 33.03 | L18: 121.1 | M18: 99.08 | N18: =SUM(G18:M18) -> 1200.01
A19: 13 | B19: 030502009016 | C19: 六类非屏蔽跳线 | D19: 1.名称:六类非屏蔽跳线 2.其它:满足完成此项工作所需要的全部工作内容，包括设计图纸、技术规范书、答疑、招标文件、现行规范、图集、验收等全部要求 | E19: 条 | F19: 402 | G19: 7191.74 | H19: 276.61 | I19: 92.2 | J19: 368.81 | K19: 276.61 | L19: 1014.22 | M19: 829.82 | N19: =SUM(G19:M19) -> 10050.01
A20: 14 | B20: 030501012006 | C20: 交换机 | D20: 1.名称：24口接入交换机 2.规格：24口,含模块 3.其它:满足完成此项工作所需要的全部工作内容，包括设计图纸、技术规范书、答疑、招标文件、现行规范、图集、验收等全部要求 | E20: 台 | F20: 11 | G20: 11335.044 | H20: 435.966 | I20: 145.32 | J20: 581.286 | K20: 435.966 | L20: 1598.532 | M20: 1307.892 | N20: =SUM(G20:M20) -> 15840.006
A21: 15 | B21: 030502009017 | C21: 跳线 | D21: 1.名称:六类网线跳线 2.其它:满足完成此项工作所需要的全部工作内容，包括设计图纸、技术规范书、答疑、招标文件、现行规范、图集、验收等全部要求 | E21: 条 | F21: 10460 | G21: 164673.03 | H21: 6333.58 | I21: 2111.1904 | J21: 8444.7704 | K21: 6333.58 | L21: 23223.121 | M21: 19000.731 | N21: =SUM(G21:M21) -> 230120
A22: 本页小计 | N22: =SUM(N17:N21) -> 258170.03
A23: 16 | B23: 030502001012 | C23: 弱电机柜 | D23: 1.名称:弱电机柜 2.技术参数:800*800*2000，每台机柜含机架式3kW的UPS，电池后备1小时，含2个PDU 3.安装方式:落地安装 4.其它:满足完成此项工作所需要的全部工作内容，包括设计图纸、技术规范书、答疑、招标文件、现行规范、图集、验收等全部要求 | E23: 台 | F23: 14 | G23: 42077.07 | H23: 1618.35 | I23: 539.445 | J23: 2157.795 | K23: 1618.35 | L23: 5933.94 | M23: 4855.05 | N23: =SUM(G23:M23) -> 58800
A24: 17 | B24: 030502014003 | C24: 光线熔接 | D24: 1.名称:光线熔接 2.其它:满足完成此项工作所需要的全部工作内容，包括设计图纸、技术规范书、答疑、招标文件、现行规范、图集、验收等全部要求 | E24: 芯 | F24: 4056 | G24: 55727.214 | H24: 4643.9328 | I24: 1857.5648 | J24: 13931.798 | K24: 6501.4976 | L24: 10216.648 | M24: 8359.0832 | N24: =SUM(G24:M24) -> 101237.74
A25: 18 | B25: 03B040 | C25: 系统综合及集成 | D25: 1.清单未列项、图纸中未表示或技术规格书未做要求，但为了实现本系统各项功能必须增加的配套及辅助的材料、设备的所有工作内容及费用； 2.施工深化设计增加的实现本系统设计功能必要的配套及辅助的材料、设备所需的所有工作内容及费用； 3.实现设计功能所做的满足图纸、技术规格书要求的各项综合与集成，包括不限于各项检测、试验、调试、软件开发、联动等所有工作内容及费用 | E25: 项 | F25: 1 | G25: 1394.5 | H25: 366.97 | I25: 183.49 | J25: 1027.52 | K25: 293.58 | L25: 403.67 | M25: 330.28 | N25: =SUM(G25:M25) -> 4000.01
A26: 本页小计 | N26: =SUM(N23:N25) -> 164037.75
A27: 19 | B27: 030411001079 | C27: 配管 | D27: 1.名称：紧定式镀锌钢导管 2.规格：JDG20 3.敷设方式：暗配 4.其它:满足完成此项工作所需要的全部工作内容，包括设计图纸、技术规范书、答疑、招标文件、现行规范、图集、验收等全部要求 | E27: m | F27: 94.4 | G27: 148.1 | H27: 38.97 | I27: 19.49 | J27: 109.12 | K27: 31.18 | L27: 42.87 | M27: 35.08 | N27: =SUM(G27:M27) -> 424.81
A28: 20 | B28: 030411001080 | C28: 配管 | D28: 1.名称：紧定式镀锌钢导管 2.规格：JDG20 3.敷设方式：明配 4.其它:满足完成此项工作所需要的全部工作内容，包括设计图纸、技术规范书、答疑、招标文件、现行规范、图集、验收等全部要求 | E28: m | F28: 153.8 | G28: 241.28 | H28: 63.5 | I28: 31.75 | J28: 177.79 | K28: 50.8 | L28: 69.84 | M28: 57.15 | N28: =SUM(G28:M28) -> 692.11
A29: 21 | B29: 030413002022 | C29: 凿（压)槽 | D29: 1.名称:管线剔槽及恢复 2.满足完成此项工作所需要的全部工作内容，满足设计图纸、答疑、招标文件、现行规范、图集、验收等全部要求 | E29: m | F29: 94.4 | G29: 405.31 | H29: 33.78 | I29: 13.51 | J29: 101.33 | K29: 47.29 | L29: 74.31 | M29: 60.8 | N29: =SUM(G29:M29) -> 736.33
A30: 22 | B30: 030413001039 | C30: 管道支架/综合支架 | D30: 1.名称:管道支架制作安装 2.材质:热镀锌 3.安装高度:综合考虑 4.满足完成此项工作所需要的全部工作内容，满足设计图纸、技术规范书、答疑、招标文件、现行规范、图集、验收等全部要求 | E30: kg | F30: 27.48 | G30: 45.98 | H30: 12.1 | I30: 6.05 | J30: 33.88 | K30: 9.68 | L30: 13.31 | M30: 10.89 | N30: =SUM(G30:M30) -> 131.89
A31: 23 | B31: 030502005022 | C31: 双绞线缆 | D31: 1.名称：六类网线 2.规格： Cat.6 UTP 3.敷设方式：桥架敷设 4.其它:满足完成此项工作所需要的全部工作内容，包括设计图纸、技术规范书、答疑、招标文件、现行规范、图集、验收等全部要求 | E31: m | F31: 4592.6 | G31: 4803.27 | H31: 1264.02 | I31: 632.01 | J31: 3539.25 | K31: 1011.21 | L31: 1390.42 | M31: 1137.62 | N31: =SUM(G31:M31) -> 13777.8
A32: 本页小计 | N32: =SUM(N27:N31) -> 15762.94
A33: 24 | B33: 030502005023 | C33: 双绞线缆 | D33: 1.名称：六类网线 2.规格： Cat.6 UTP 3.敷设方式：管内敷设 4.其它:满足完成此项工作所需要的全部工作内容，包括设计图纸、技术规范书、答疑、招标文件、现行规范、图集、验收等全部要求 | E33: m | F33: 806.1 | G33: 843.08 | H33: 221.86 | I33: 110.93 | J33: 621.21 | K33: 177.49 | L33: 244.05 | M33: 199.68 | N33: =SUM(G33:M33) -> 2418.3
A34: 25 | B34: 030502012006 | C34: 双孔数据点 | D34: 1.名称：双孔数据点（含模块） 2.其它:满足完成此项工作所需要的全部工作内容，包括设计图纸、技术规范书、答疑、招标文件、现行规范、图集、验收等全部要求 | E34: 个 | F34: 44 | G34: 1448.37 | H34: 55.71 | I34: 18.57 | J34: 74.28 | K34: 55.71 | L34: 204.26 | M34: 167.12 | N34: =SUM(G34:M34) -> 2024.02
A35: 26 | B35: 030502012007 | C35: 双孔数据语音信息点 | D35: 1.名称：双孔数据语音信息点（含模块） 2.其它:满足完成此项工作所需要的全部工作内容，包括设计图纸、技术规范书、答疑、招标文件、现行规范、图集、验收等全部要求 | E35: 个 | F35: 26 | G35: 855.85 | H35: 32.92 | I35: 10.97 | J35: 43.89 | K35: 32.92 | L35: 120.7 | M35: 98.75 | N35: =SUM(G35:M35) -> 1196
A36: 27 | B36: 030502012008 | C36: 语音信息点位面板 | D36: 1.名称：语音信息点位面板（含模块） 2.其它:满足完成此项工作所需要的全部工作内容，包括设计图纸、技术规范书、答疑、招标文件、现行规范、图集、验收等全部要求 | E36: 个 | F36: 32 | G36: 618.28 | H36: 23.78 | I36: 7.93 | J36: 31.71 | K36: 23.78 | L36: 87.19 | M36: 71.34 | N36: =SUM(G36:M36) -> 864.01
A37: 28 | B37: 030502012009 | C37: 信息点面板底盒 | D37: 1.名称：信息点面板底盒 2.结构：混凝土结构内或随家具安装 3.其它:满足完成此项工作所需要的全部工作内容，包括设计图纸、技术规范书、答疑、招标文件、现行规范、图集、验收等全部要求 | E37: 个 | F37: 102 | G37: 729.91 | H37: 28.07 | I37: 9.36 | J37: 37.43 | K37: 28.07 | L37: 102.94 | M37: 84.22 | N37: =SUM(G37:M37) -> 1020
A38: 本页小计 | N38: =SUM(N33:N37) -> 7522.33
A39: 29 | B39: 030502019008 | C39: 双绞线缆测试 | D39: 1.名称：信息点调试 2.其它:满足完成此项工作所需要的全部工作内容，包括设计图纸、技术规范书、答疑、招标文件、现行规范、图集、验收等全部要求 | E39: 链路 | F39: 172 | G39: 479.71 | H39: 126.24 | I39: 63.12 | J39: 353.47 | K39: 100.99 | L39: 138.86 | M39: 113.61 | N39: =SUM(G39:M39) -> 1376
A40: 30 | B40: 030411001081 | C40: 配管 | D40: 1.名称：紧定式镀锌钢导管 2.规格：JDG20 3.敷设方式：暗配 4.其它:满足完成此项工作所需要的全部工作内容，包括设计图纸、技术规范书、答疑、招标文件、现行规范、图集、验收等全部要求 | E40: m | F40: 2935.63 | G40: 13816.32 | H40: 3635.88 | I40: 1817.94 | J40: 10180.44 | K40: 2908.71 | L40: 3999.45 | M40: 3272.28 | N40: =SUM(G40:M40) -> 39631.02
A41: 31 | B41: 030411001082 | C41: 配管 | D41: 1.名称：紧定式镀锌钢导管 2.规格：JDG20 3.敷设方式：明配 4.其它:满足完成此项工作所需要的全部工作内容，包括设计图纸、技术规范书、答疑、招标文件、现行规范、图集、验收等全部要求 | E41: m | F41: 6226.36 | G41: 29303.88 | H41: 7711.56 | I41: 3855.78 | J41: 21592.32 | K41: 6169.23 | L41: 8482.71 | M41: 6940.38 | N41: =SUM(G41:M41) -> 84055.86
A42: 32 | B42: 030413002023 | C42: 凿（压)槽 | D42: 1.名称:管线剔槽及恢复 2.满足完成此项工作所需要的全部工作内容，满足设计图纸、答疑、招标文件、现行规范、图集、验收等全部要求 | E42: m | F42: 1467.5 | G42: 6300.83 | H42: 525.07 | I42: 210.03 | J42: 1575.21 | K42: 735.1 | L42: 1155.15 | M42: 945.12 | N42: =SUM(G42:M42) -> 11446.51
A43: 33 | B43: 030413001040 | C43: 管道支架/综合支架 | D43: 1.名称:管道支架制作安装 2.材质:热镀锌 3.安装高度:综合考虑 4.满足完成此项工作所需要的全部工作内容，满足设计图纸、技术规范书、答疑、招标文件、现行规范、图集、验收等全部要求 | E43: kg | F43: 1112.37 | G43: 5041.38 | H43: 1326.68 | I43: 663.34 | J43: 3714.7 | K43: 1061.34 | L43: 1459.35 | M43: 1194.01 | N43: =SUM(G43:M43) -> 14460.8
A44: 本页小计 | N44: =SUM(N39:N43) -> 150970.19
A45: 34 | B45: 030502005024 | C45: 双绞线缆 | D45: 1.名称：六类网线 2.规格： Cat.6 UTP 3.敷设方式：桥架敷设 4.其它:满足完成此项工作所需要的全部工作内容，包括设计图纸、技术规范书、答疑、招标文件、现行规范、图集、验收等全部要求 | E45: m | F45: 121282.98 | G45: 164900.35 | H45: 43394.832 | I45: 21697.416 | J45: 121505.51 | K45: 34715.863 | L45: 47734.31 | M45: 39055.341 | N45: =SUM(G45:M45) -> 473003.62
A46: 35 | B46: 030502005025 | C46: 双绞线缆 | D46: 1.名称：六类网线 2.规格： Cat.6 UTP 3.敷设方式：管内敷设 4.其它:满足完成此项工作所需要的全部工作内容，包括设计图纸、技术规范书、答疑、招标文件、现行规范、图集、验收等全部要求 | E46: m | F46: 24205.49 | G46: 32910.579 | H46: 8660.678 | I46: 4330.339 | J46: 24249.901 | K46: 6928.545 | L46: 9526.751 | M46: 7794.618 | N46: =SUM(G46:M46) -> 94401.411
A47: 36 | B47: 030502012010 | C47: 双孔数据点 | D47: 1.名称：双孔数据点（含模块） 2.其它:满足完成此项工作所需要的全部工作内容，包括设计图纸、技术规范书、答疑、招标文件、现行规范、图集、验收等全部要求 | E47: 个 | F47: 1053 | G47: 34662.06 | H47: 1333.16 | I47: 444.39 | J47: 1777.54 | K47: 1333.16 | L47: 4888.24 | M47: 3999.47 | N47: =SUM(G47:M47) -> 48438.02
A48: 37 | B48: 030502012011 | C48: 双孔数据点 | D48: 1.名称：单孔数据点（含模块） 2.其它:满足完成此项工作所需要的全部工作内容，包括设计图纸、技术规范书、答疑、招标文件、现行规范、图集、验收等全部要求 | E48: 个 | F48: 274 | G48: 9019.38 | H48: 346.9 | I48: 115.63 | J48: 462.53 | K48: 346.9 | L48: 1271.96 | M48: 1040.7 | N48: =SUM(G48:M48) -> 12604
A49: 38 | B49: 030502012012 | C49: 双孔数据点 | D49: 1.名称：办公网信息点地插（含模块） 2.其它:满足完成此项工作所需要的全部工作内容，包括设计图纸、技术规范书、答疑、招标文件、现行规范、图集、验收等全部要求 | E49: 个 | F49: 133 | G49: 4378.02 | H49: 168.39 | I49: 56.13 | J49: 224.51 | K49: 168.39 | L49: 617.41 | M49: 505.16 | N49: =SUM(G49:M49) -> 6118.01
A50: 本页小计 | N50: =SUM(N45:N49) -> 634565.06
A51: 39 | B51: 030502012013 | C51: 双孔数据语音信息点 | D51: 1.名称：双孔数据语音信息点（含模块） 2.其它:满足完成此项工作所需要的全部工作内容，包括设计图纸、技术规范书、答疑、招标文件、现行规范、图集、验收等全部要求 | E51: 个 | F51: 364 | G51: 23963.88 | H51: 921.68 | I51: 307.22 | J51: 1228.92 | K51: 921.68 | L51: 3379.52 | M51: 2765.06 | N51: =SUM(G51:M51) -> 33487.96
A52: 40 | B52: 030502012014 | C52: 金属网络地插 | D52: 1.名称:金属网络地插 2.规格:金属材质，含模块，单口 3.其它:满足完成此项工作所需要的全部工作内容，包括设计图纸、技术规范书、答疑、招标文件、现行规范、图集、验收等全部要求。 | E52: 个 | F52: 132 | G52: 20403.12 | H52: 784.72 | I52: 261.6 | J52: 1046.32 | K52: 784.72 | L52: 2877.36 | M52: 2354.24 | N52: =SUM(G52:M52) -> 28512.08
A53: 41 | B53: 030502012015 | C53: 语音信息点位面板 | D53: 1.名称：语音信息点位面板（含模块） 2.其它:满足完成此项工作所需要的全部工作内容，包括设计图纸、技术规范书、答疑、招标文件、现行规范、图集、验收等全部要求 | E53: 个 | F53: 1043 | G53: 20151.91 | H53: 775.07 | I53: 258.36 | J53: 1033.43 | K53: 775.07 | L53: 2841.94 | M53: 2325.22 | N53: =SUM(G53:M53) -> 28161
A54: 42 | B54: 030502012016 | C54: 信息点面板底盒 | D54: 1.名称：信息点面板底盒 2.结构：混凝土结构内或随家具安装 3.其它:满足完成此项工作所需要的全部工作内容，包括设计图纸、技术规范书、答疑、招标文件、现行规范、图集、验收等全部要求 | E54: 个 | F54: 2999 | G54: 21460.73 | H54: 825.41 | I54: 275.14 | J54: 1100.55 | K54: 825.41 | L54: 3026.51 | M54: 2476.24 | N54: =SUM(G54:M54) -> 29989.99
A55: 43 | B55: 030502019009 | C55: 双绞线缆测试 | D55: 1.名称：信息点调试 2.其它:满足完成此项工作所需要的全部工作内容，包括设计图纸、技术规范书、答疑、招标文件、现行规范、图集、验收等全部要求 | E55: 链路 | F55: 3884 | G55: 10832.44 | H55: 2850.64 | I55: 1425.32 | J55: 7981.8 | K55: 2280.51 | L55: 3135.71 | M55: 2565.58 | N55: =SUM(G55:M55) -> 31072
A56: 本页小计 | N56: =SUM(N51:N55) -> 151223.03
A57: 44 | B57: 030411001083 | C57: 配管 | D57: 1.名称：配管 2.规格：JDG20 3.敷设方式：暗配 4.其它:满足完成此项工作所需要的全部工作内容，包括设计图纸、技术规范书、答疑、招标文件、现行规范、图集、验收等全部要求 | E57: m | F57: 19.7 | G57: 30.91 | H57: 8.13 | I57: 4.07 | J57: 22.77 | K57: 6.51 | L57: 8.95 | M57: 7.32 | N57: =SUM(G57:M57) -> 88.66
A58: 45 | B58: 030413002024 | C58: 凿（压)槽 | D58: 1.名称:管线剔槽及恢复 2.满足完成此项工作所需要的全部工作内容，满足设计图纸、答疑、招标文件、现行规范、图集、验收等全部要求 | E58: m | F58: 19.7 | G58: 84.58 | H58: 7.05 | I58: 2.82 | J58: 21.15 | K58: 9.87 | L58: 15.51 | M58: 12.69 | N58: =SUM(G58:M58) -> 153.67
A59: 46 | B59: 030502005026 | C59: 双绞线缆 | D59: 1.名称：六类网线 2.规格： Cat.6 UTP 3.敷设方式：管内敷设 4.其它:满足完成此项工作所需要的全部工作内容，包括设计图纸、技术规范书、答疑、招标文件、现行规范、图集、验收等全部要求 | E59: m | F59: 68.9 | G59: 93.68 | H59: 24.65 | I59: 12.33 | J59: 69.03 | K59: 19.72 | L59: 27.12 | M59: 22.19 | N59: =SUM(G59:M59) -> 268.72
A60: 47 | B60: 030502012017 | C60: 双孔数据点 | D60: 1.名称：双孔数据点（含模块） 2.其它:满足完成此项工作所需要的全部工作内容，包括设计图纸、技术规范书、答疑、招标文件、现行规范、图集、验收等全部要求 | E60: 个 | F60: 4 | G60: 131.67 | H60: 5.06 | I60: 1.69 | J60: 6.75 | K60: 5.06 | L60: 18.57 | M60: 15.19 | N60: =SUM(G60:M60) -> 183.99
A61: 48 | B61: 030502012018 | C61: 语音信息点位面板 | D61: 1.名称：语音信息点位面板（含模块） 2.其它:满足完成此项工作所需要的全部工作内容，包括设计图纸、技术规范书、答疑、招标文件、现行规范、图集、验收等全部要求 | E61: 个 | F61: 4 | G61: 77.28 | H61: 2.97 | I61: 0.99 | J61: 3.96 | K61: 2.97 | L61: 10.9 | M61: 8.92 | N61: =SUM(G61:M61) -> 107.99
A62: 本页小计 | N62: =SUM(N57:N61) -> 803.03
A63: 49 | B63: 030502012019 | C63: 信息点面板底盒 | D63: 1.名称：信息点面板底盒 2.结构：混凝土结构内或随家具安装 3.其它:满足完成此项工作所需要的全部工作内容，包括设计图纸、技术规范书、答疑、招标文件、现行规范、图集、验收等全部要求 | E63: 个 | F63: 8 | G63: 57.25 | H63: 2.2 | I63: 0.73 | J63: 2.94 | K63: 2.2 | L63: 8.07 | M63: 6.61 | N63: =SUM(G63:M63) -> 80
A64: 50 | B64: 030502019010 | C64: 双绞线缆测试 | D64: 1.名称：信息点调试 2.其它:满足完成此项工作所需要的全部工作内容，包括设计图纸、技术规范书、答疑、招标文件、现行规范、图集、验收等全部要求 | E64: 链路 | F64: 12 | G64: 33.47 | H64: 8.81 | I64: 4.4 | J64: 24.66 | K64: 7.05 | L64: 9.69 | M64: 7.93 | N64: =SUM(G64:M64) -> 96.01
A65: 51 | B65: 031301017027 | C65: 脚手架搭拆 | D65: 1.综合考虑项目脚手架搭拆或其他替代措施项目 2.场内外材料搬运 3.拆除脚手架后材料的堆放 4.满足完成此项工作所需要的全部工作内容，满足设计图纸、答疑、招标文件、现行规范、图集、验收等全部要求 | E65: 项 | F65: 1 | G65: 697.25 | H65: 183.49 | I65: 91.74 | J65: 513.76 | K65: 146.79 | L65: 201.83 | M65: 165.14 | N65: =SUM(G65:M65) -> 2000
A66: 52 | B66: 03B041 | C66: 超高费 | E66: 项 | F66: 1 | G66: 550.46 | H66: 45.87 | I66: 18.35 | J66: 137.61 | K66: 64.22 | L66: 100.92 | M66: 82.57 | N66: =SUM(G66:M66) -> 1000
A67: 本页小计 | N67: =SUM(N63:N66) -> 3176.01
A68: 合 计 | N68: =N10+N16+N22+N26+N32+N38+N44+N50+N56+N62+N67 -> 1674589

Sheet 8#、15#非管区BA系统
A1: 分部分项工程和单价措施项目清单与计价表
A2: 分部分项工程和单价措施项目清单与计价表
A3: 序号 | B3: 项目编码 | C3: 项目名称 | D3: 项目特征描述 | E3: 计量单位 | F3: 工程量 | G3: 金额（元）
G4: 主材/设备费 | H4: 辅材 | I4: 机械措施 | J4: 人工 | K4: 管理费 | L4: 利润 | M4: 税金 | N4: 总价
A5: 1 | B5: 030504001001 | C5: 系统服务器 | D5: 1.名称:系统服务器（含鼠标键盘、显示器、软件等） 2.技术参数：处理器：≥2颗Intel 至强 4510处理器，单颗核数≥12核， ≥2.40 GHz或以上；内存：≥128G；操作系统： 支持Microsoft Windows Server 2019、 RedHat Enterprise Linux 、 SUSE Linux Enterprise Server、 CentOS、 Ubuntu、 Vmware EXSI；内置SAS硬盘，RAID5，配备4x3TB热插拔硬盘，10000rpm以上；2个千兆以太网口；冗余电源、风扇，可以365天24小时运行；1块单口8Gb HBA卡。 3.其它:满足完成此项工作所需要的全部工作内容，包括设计图纸、技术规范书、答疑、招标文件、现行规范、图集、验收等全部要求 | E5: 台 | F5: 2 | G5: 10376.145 | H5: 399.085 | I5: 133.03 | J5: 532.11 | K5: 399.085 | L5: 1463.305 | M5: 1197.25 | N5: =SUM(G5:M5) -> 14500.01
A6: 2 | B6: 080904002001 | C6: 管理电脑 | D6: 1.名称:管理电脑（含鼠标键盘、显示器、软件等） 2.规格:台式电脑，不低于CPU：i5，内存容量: 4GB；硬盘容量: 500GB；显存容量:1GB；正版win操作系统,显示屏：22寸 3.其它:满足完成此项工作所需要的全部工作内容，包括设计图纸、技术规范书、答疑、招标文件、现行规范、图集、验收等全部要求 | E6: 台 | F6: 3 | G6: 5366.97 | H6: 206.42 | I6: 68.805 | J6: 275.23 | K6: 206.42 | L6: 756.88 | M6: 619.265 | N6: =SUM(G6:M6) -> 7499.99
A7: 本页小计 | N7: =SUM(N5:N6) -> 22000
A8: 3 | B8: 030504001002 | C8: 服务器双机热备 | D8: 1.名称:服务器双机热备 2.技术参数:双机热备应具备免维护功能，正常主服务器掉电关机，BA软件意外停止，应用网线断开都可以自动切换到备用服务器 3.其它:满足完成此项工作所需要的全部工作内容，包括设计图纸、技术规范书、答疑、招标文件、现行规范、图集、验收等全部要求 | E8: 套 | F8: 1 | G8: 12522.94 | H8: 481.65 | I8: 160.55 | J8: 642.2 | K8: 481.65 | L8: 1766.06 | M8: 1444.95 | N8: =SUM(G8:M8) -> 17500
A9: 4 | B9: 080901003001 | C9: BA系统软件 | D9: 1.名称:BA系统软件 2.规格:B/S结构，图形化界面，提供包括服务器软件及用户编程工具软件，最少10个用户可同时使用,软件监控点总数大于8000点，具备工作站电脑界面报警弹出功能，用户操作历史记录查询功能，系统运行报表设置功能等。 3.其它:满足完成此项工作所需要的全部工作内容，包括设计图纸、技术规范书、答疑、招标文件、现行规范、图集、验收等全部要求 | E9: 套 | F9: 1 | G9: 26834.86 | H9: 1032.11 | I9: 344.035 | J9: 1376.145 | K9: 1032.11 | L9: 3784.405 | M9: 3096.33 | N9: =SUM(G9:M9) -> 37499.995
A10: 本页小计 | N10: =SUM(N8:N9) -> 54999.995
A11: 5 | B11: 03B034 | C11: 系统综合及集成 | D11: 1.清单未列项、图纸中未表示或技术规格书未做要求，但为了实现本系统各项功能必须增加的配套及辅助的材料、设备的所有工作内容及费用； 2.施工深化设计增加的实现本系统设计功能必要的配套及辅助的材料、设备所需的所有工作内容及费用； 3.实现设计功能所做的满足图纸、技术规格书要求的各项综合与集成，包括不限于各项检测、试验、调试、软件开发、联动等所有工作内容及费用 | E11: 项 | F11: 1 | G11: 1394.495 | H11: 366.97 | I11: 183.485 | J11: 1027.525 | K11: 293.58 | L11: 403.67 | M11: 330.275 | N11: =SUM(G11:M11) -> 4000
A12: 6 | B12: 03B035 | C12: 平台对接 | D12: 1.平台对接 2.其它:满足完成此项工作所需要的全部工作内容，包括设计图纸、技术规范书、答疑、招标文件、现行规范、图集、验收等全部要求 | E12: 项 | F12: 1 | G12: 2311.925 | H12: 192.661 | I12: 77.063 | J12: 577.983 | K12: 269.724 | L12: 423.85 | M12: 346.787 | N12: =SUM(G12:M12) -> 4199.993
A13: 本页小计 | N13: =SUM(N11:N12) -> 8199.993
A14: 7 | B14: 030503003018 | C14: 群控制器 | D14: 1.名称:群控制器 2.技术参数:控制柜电源：双电源断电自动切换，双电源状态显示，开关量输出（含控制柜） 监控设备组成：可编程网络控制器+I/O模块： 可编程网络控制器：BACnet/IP，图形化自由编程，多种逻辑算法可用 I/O模块模拟量输入点：不少于86个AI点（包括20%冗余） I/O模块模拟量输出点：不少于17个AO点（包括20%冗余） I/O模块数字量输入点：不少于41个DI点（包括20%冗余） I/O模块数字量输出点：不少于24个DO点（包括20%冗余） 3.其它:满足完成此项工作所需要的全部工作内容，包括设计图纸、技术规范书、答疑、招标文件、现行规范、图集、验收等全部要求 | E14: 台 | F14: 1 | G14: 12522.935 | H14: 481.65 | I14: 160.55 | J14: 642.2 | K14: 481.65 | L14: 1766.055 | M14: 1444.955 | N14: =SUM(G14:M14) -> 17499.995
A15: 本页小计 | N15: =N14 -> 17499.995
A16: 8 | B16: 030503003019 | C16: 风冷热泵机组单元控制器 | D16: 1.名称:风冷热泵机组单元控制器 2.技术参数:控制柜电源：双电源断电自动切换，双电源状态显示，开关量输出 控制柜尺寸：2000mm（高）×1000mm（宽）×400mm（厚） 监控设备组成：可编程网络控制器+I/O模块+通讯网关： 可编程网络控制器：BACnet/IP，图形化自由编程，多种逻辑算法可用 I/O模块模拟量输入点：不少于29个AI点（包括20%冗余） I/O模块模拟量输出点：不少于9个AO点（包括20%冗余） I/O模块数字量输入点：不少于52个DI点（包括20%冗余） I/O模块数字量输出点：不少于34个DO点（包括20%冗余） 通讯网关1：冷水机组通讯数据RS-485转BACnet MSTP 通讯网关2：变频器通讯数据RS-485转BACnet MSTP 3.其它:满足完成此项工作所需要的全部工作内容，包括设计图纸、技术规范书、答疑、招标文件、现行规范、图集、验收等全部要求 | E16: 台 | F16: 3 | G16: 26834.86 | H16: 1032.11 | I16: 344.035 | J16: 1376.145 | K16: 1032.11 | L16: 3784.405 | M16: 3096.33 | N16: =SUM(G16:M16) -> 37499.995
A17: 本页小计 | N17: =N16 -> 37499.995
A18: 9 | B18: 030503003020 | C18: 冷却水泵控制器 | D18: 1.名称:冷却水泵控制器 2.技术参数:控制柜电源：双电源断电自动切换，双电源状态显示，开关量输出 控制柜尺寸：2000mm（高）×1000mm（宽）×400mm（厚） 监控设备组成：可编程网络控制器+I/O模块+通讯网关： 可编程网络控制器：BACnet/IP，图形化自由编程，多种逻辑算法可用 I/O模块模拟量输入点：不少于29个AI点（包括20%冗余） I/O模块模拟量输出点：不少于9个AO点（包括20%冗余） I/O模块数字量输入点：不少于52个DI点（包括20%冗余） I/O模块数字量输出点：不少于34个DO点（包括20%冗余） 通讯网关1：冷水机组通讯数据RS-485转BACnet MSTP 通讯网关2：变频器通讯数据RS-485转BACnet MSTP 3.其它:满足完成此项工作所需要的全部工作内容，包括设计图纸、技术规范书、答疑、招标文件、现行规范、图集、验收等全部要求 | E18: 台 | F18: 4 | G18: 35779.815 | H18: 1376.145 | I18: 458.715 | J18: 1834.86 | K18: 1376.145 | L18: 5045.87 | M18: 4128.44 | N18: =SUM(G18:M18) -> 49999.99
A19: 本页小计 | N19: =N18 -> 49999.99
A20: 10 | B20: 030503006010 | C20: 室外温湿度传感器 | D20: 1.名称:室外温湿度传感器 2.规格:24VDC，4~20mA，±0.3℃，3%RH 防水接线盒 3.其它:满足完成此项工作所需要的全部工作内容，包括设计图纸、技术规范书、答疑、招标文件、现行规范、图集、验收等全部要求 | E20: 支 | F20: 2 | G20: 429.36 | H20: 16.51 | I20: 5.5 | J20: 22.02 | K20: 16.51 | L20: 60.55 | M20: 49.54 | N20: =SUM(G20:M20) -> 599.99
A21: 11 | B21: 030503006011 | C21: 水管压力传感器 | D21: 1.名称:水管压力传感器 2.规格:24VDC，4~20mA，0~16Bar，±0.3% 带减压管及球阀 3.其它:满足完成此项工作所需要的全部工作内容，包括设计图纸、技术规范书、答疑、招标文件、现行规范、图集、验收等全部要求 | E21: 支 | F21: 20 | G21: 2862.385 | H21: 110.09 | I21: 36.695 | J21: 146.79 | K21: 110.09 | L21: 403.67 | M21: 330.275 | N21: =SUM(G21:M21) -> 3999.995
A22: 12 | B22: 030503006012 | C22: 水管压差传感器 | D22: 1.名称:水管压差传感器 2.规格:24VDC，4~20mA，0~10Bar，±0.3%， 带减压管及球阀 3.其它:满足完成此项工作所需要的全部工作内容，包括设计图纸、技术规范书、答疑、招标文件、现行规范、图集、验收等全部要求 | E22: 支 | F22: 20 | G22: 17991.525 | H22: 691.98 | I22: 230.66 | J22: 922.64 | K22: 691.98 | L22: 2537.265 | M22: 2075.945 | N22: =SUM(G22:M22) -> 25141.995
A23: 13 | B23: 030503006013 | C23: 水管温度传感器 | D23: 1.名称:水管温度传感器 2.规格:24VDC，4~20mA，4"探针 不锈钢套筒 3.其它:满足完成此项工作所需要的全部工作内容，包括设计图纸、技术规范书、答疑、招标文件、现行规范、图集、验收等全部要求 | E23: 支 | F23: 20 | G23: 2504.585 | H23: 96.33 | I23: 32.11 | J23: 128.44 | K23: 96.33 | L23: 353.21 | M23: 288.99 | N23: =SUM(G23:M23) -> 3499.995
A24: 本页小计 | N24: =SUM(N20:N23) -> 33241.975
A25: 14 | B25: 030503006014 | C25: 水管流量传感器DN300 | D25: 1.名称:水管流量传感器DN300 2.规格:24VDC，4~20mA，DN300，PN16，±0.5% 3.其它:满足完成此项工作所需要的全部工作内容，包括设计图纸、技术规范书、答疑、招标文件、现行规范、图集、验收等全部要求 | E25: 支 | F25: 5 | G25: 12522.935 | H25: 481.65 | I25: 160.55 | J25: 642.2 | K25: 481.65 | L25: 1766.055 | M25: 1444.955 | N25: =SUM(G25:M25) -> 17499.995
A26: 15 | B26: 030503006015 | C26: 水管流量传感器DN350 | D26: 1.名称:水管流量传感器DN350 2.规格:24VDC，4~20mA，DN350，PN16，±0.5% 3.其它:满足完成此项工作所需要的全部工作内容，包括设计图纸、技术规范书、答疑、招标文件、现行规范、图集、验收等全部要求 | E26: 支 | F26: 5 | G26: 12522.935 | H26: 481.65 | I26: 160.55 | J26: 642.2 | K26: 481.65 | L26: 1766.055 | M26: 1444.955 | N26: =SUM(G26:M26) -> 17499.995
A27: 16 | B27: 030503006016 | C27: 水管流量传感器DN400 | D27: 1.名称:水管流量传感器DN400 2.规格:24VDC，4~20mA，DN400，PN16，±0.5% 3.其它:满足完成此项工作所需要的全部工作内容，包括设计图纸、技术规范书、答疑、招标文件、现行规范、图集、验收等全部要求 | E27: 支 | F27: 5 | G27: 12522.935 | H27: 481.65 | I27: 160.55 | J27: 642.2 | K27: 481.65 | L27: 1766.055 | M27: 1444.955 | N27: =SUM(G27:M27) -> 17499.995
A28: 17 | B28: 030503006017 | C28: 水管流量传感器DN600 | D28: 1.名称:水管流量传感器DN600 2.规格:24VDC，4~20mA，DN600，PN16，±0.5% 3.其它:满足完成此项工作所需要的全部工作内容，包括设计图纸、技术规范书、答疑、招标文件、现行规范、图集、验收等全部要求 | E28: 支 | F28: 5 | G28: 16100.915 | H28: 619.265 | I28: 206.42 | J28: 825.69 | K28: 619.265 | L28: 2270.64 | M28: 1857.8 | N28: =SUM(G28:M28) -> 22499.995
A29: 本页小计 | N29: =SUM(N25:N28) -> 74999.98
A30: 18 | B30: 03B036 | C30: 系统综合及集成 | D30: 1.清单未列项、图纸中未表示或技术规格书未做要求，但为了实现本系统各项功能必须增加的配套及辅助的材料、设备的所有工作内容及费用； 2.施工深化设计增加的实现本系统设计功能必要的配套及辅助的材料、设备所需的所有工作内容及费用； 3.实现设计功能所做的满足图纸、技术规格书要求的各项综合与集成，包括不限于各项检测、试验、调试、软件开发、联动等所有工作内容及费用 | E30: 项 | F30: 1 | G30: 1394.5 | H30: 366.97 | I30: 183.49 | J30: 1027.52 | K30: 293.58 | L30: 403.67 | M30: 330.28 | N30: =SUM(G30:M30) -> 4000.01
A31: 19 | B31: 03B037 | C31: 平台对接 | D31: 1.平台对接 2.其它:满足完成此项工作所需要的全部工作内容，包括设计图纸、技术规范书、答疑、招标文件、现行规范、图集、验收等全部要求 | E31: 项 | F31: 1 | G31: 2752.29 | H31: 229.36 | I31: 91.74 | J31: 688.07 | K31: 321.1 | L31: 504.59 | M31: 412.84 | N31: =SUM(G31:M31) -> 4999.99
A32: 本页小计 | N32: =SUM(N30:N31) -> 9000
A33: 20 | B33: 030503003021 | C33: 标准网络控制器 | D33: 1.名称:标准网络控制器（含控制柜） 2.技术参数:可同时支持LonWorks、Modbus或BACnet等通讯协议；IBM Power PC 440 250MHz处理器；256MB SDRAM和128MB闪存；支持无电池操作；内置两个通讯卡槽位，可根据实际需求灵活配置各种接口通讯卡和相应的驱动； 通讯卡：技术参数:BACnet MS/TP驱动;通过RS-23或RS-485连接 控制器通用型电源：热插拔 15VDC 导轨安装 3.其它:满足完成此项工作所需要的全部工作内容，包括设计图纸、技术规范书、答疑、招标文件、现行规范、图集、验收等全部要求 | E33: 台 | F33: 1 | G33: 10733.945 | H33: 412.845 | I33: 137.615 | J33: 550.46 | K33: 412.845 | L33: 1513.76 | M33: 1238.53 | N33: =SUM(G33:M33) -> 15000
A34: 21 | B34: 030503004001 | C34: DDC控制箱DDC-8#-1F-01 | D34: 1.名称:DDC控制箱DDC-8#-1F-01 2.技术参数:1）根据点表定制，内含DDC控制器 ,支持Bacnet通讯协议，通讯转换网关； 2）内置外部线路接线端子排、独立电源接线端子排、导轨、变压器；控制点不少于UI:5 DI:10 AO:2 DO:3；通讯转换网关支持多路485通讯； 3.其它:满足完成此项工作所需要的全部工作内容，包括设计图纸、技术规范书、答疑、招标文件、现行规范、图集、验收等全部要求 | E34: 套 | F34: 1 | G34: 2146.79 | H34: 82.57 | I34: 27.525 | J34: 110.09 | K34: 82.57 | L34: 302.75 | M34: 247.705 | N34: =SUM(G34:M34) -> 3000
A35: 本页小计 | N35: =SUM(N33:N34) -> 18000
A36: 22 | B36: 030503004002 | C36: DDC一体化箱DDC-8#-1F-02 | D36: 1.名称:DDC一体化箱DDC-8#-1F-02 2.技术参数:1）根据点表定制，内含DDC控制器 ，支持Bacnet通讯协议；通讯转换网关； 2）内置外部线路接线端子排、独立电源接线端子排、导轨、变压器；控制点不少于UI:5 DI:4 AO:3 DO:1；通讯转换网关支持多路485通讯； 3.其它:满足完成此项工作所需要的全部工作内容，包括设计图纸、技术规范书、答疑、招标文件、现行规范、图集、验收等全部要求 | E36: 套 | F36: 1 | G36: 2146.79 | H36: 82.57 | I36: 27.525 | J36: 110.09 | K36: 82.57 | L36: 302.75 | M36: 247.705 | N36: =SUM(G36:M36) -> 3000
A37: 23 | B37: 030503004003 | C37: DDC控制箱DDC-8#-2F-01 | D37: 1.名称:DDC控制箱DDC-8#-2F-01 2.技术参数:1）根据点表定制，内含DDC控制器 ，支持Bacnet通讯协议；通讯转换网关；2）内置外部线路接线端子排、独立电源接线端子排、导轨、变压器；控制点不少于UI:10 DI:8 AO:4 DO:2；通讯转换网关支持多路485通讯。 3.其它:满足完成此项工作所需要的全部工作内容，包括设计图纸、技术规范书、答疑、招标文件、现行规范、图集、验收等全部要求 | E37: 套 | F37: 1 | G37: 2504.585 | H37: 96.33 | I37: 32.11 | J37: 128.44 | K37: 96.33 | L37: 353.21 | M37: 288.99 | N37: =SUM(G37:M37) -> 3499.995
A38: 本页小计 | N38: =SUM(N36:N37) -> 6499.995
A39: 24 | B39: 030503004004 | C39: DDC控制箱DDC-8#-GK-01 | D39: 1.名称:DDC控制箱DDC-8#-GK-01 2.技术参数:1）根据点表定制，内含DDC控制器 ，支持Bacnet通讯协议；通讯转换网关；2）内置外部线路接线端子排、独立电源接线端子排、导轨、变压器；控制点不少于UI:5 DI:3 AO:0 DO:1；通讯转换网关支持多路485通讯。 3.其它:满足完成此项工作所需要的全部工作内容，包括设计图纸、技术规范书、答疑、招标文件、现行规范、图集、验收等全部要求 | E39: 套 | F39: 1 | G39: 2146.79 | H39: 82.57 | I39: 27.525 | J39: 110.09 | K39: 82.57 | L39: 302.75 | M39: 247.705 | N39: =SUM(G39:M39) -> 3000
A40: 25 | B40: 030503004005 | C40: DDC控制箱DDC-8#-RF-01 | D40: 1.名称:DDC控制箱DDC-8#-RF-01 2.技术参数:1）根据点表定制，内含DDC控制器 ，支持Bacnet通讯协议；通讯转换网关；2）内置外部线路接线端子排、独立电源接线端子排、导轨、变压器；控制点不少于UI:15 DI:39 AO:3 DO:19；通讯转换网关支持多路485通讯。 3.其它:满足完成此项工作所需要的全部工作内容，包括设计图纸、技术规范书、答疑、招标文件、现行规范、图集、验收等全部要求 | E40: 套 | F40: 1 | G40: 2862.385 | H40: 110.09 | I40: 36.695 | J40: 146.79 | K40: 110.09 | L40: 403.67 | M40: 330.275 | N40: =SUM(G40:M40) -> 3999.995
A41: 本页小计 | N41: =SUM(N39:N40) -> 6999.995
A42: 26 | B42: 030503004006 | C42: DDC一体化箱DDC-12#-B1-01 | D42: 1.名称:DDC一体化箱DDC-12#-B1-01 2.技术参数:1）根据点表定制，内含DDC控制器 ，支持Bacnet通讯协议；通讯转换网关； 2）内置外部线路接线端子排、独立电源接线端子排、导轨、变压器；控制点不少于UI:5 DI:39 AO:3 DO:10；通讯转换网关支持多路485通讯。 3.其它:满足完成此项工作所需要的全部工作内容，包括设计图纸、技术规范书、答疑、招标文件、现行规范、图集、验收等全部要求 | E42: 套 | F42: 1 | G42: 3220.185 | H42: 123.855 | I42: 41.285 | J42: 165.14 | K42: 123.855 | L42: 454.13 | M42: 371.56 | N42: =SUM(G42:M42) -> 4500.01
A43: 27 | B43: 030503004007 | C43: DDC一体化箱DDC-12#-B1-02 | D43: 1.名称:DDC一体化箱DDC-12#-B1-02 2.技术参数:1）根据点表定制，内含DDC控制器 ，支持Bacnet通讯协议；通讯转换网关； 2）内置外部线路接线端子排、独立电源接线端子排、导轨、变压器；控制点不少于UI:5 DI:56 AO:3 DO:2；通讯转换网关支持多路485通讯。 3.其它:满足完成此项工作所需要的全部工作内容，包括设计图纸、技术规范书、答疑、招标文件、现行规范、图集、验收等全部要求 | E43: 套 | F43: 1 | G43: 3220.185 | H43: 123.855 | I43: 41.285 | J43: 165.14 | K43: 123.855 | L43: 454.13 | M43: 371.56 | N43: =SUM(G43:M43) -> 4500.01
A44: 本页小计 | N44: =SUM(N42:N43) -> 9000.02
A45: 28 | B45: 030503004008 | C45: DDC一体化箱DDC-12#-B1-03 | D45: 1.名称:DDC一体化箱DDC-12#-B1-03 2.技术参数:1）根据点表定制，内含DDC控制器 ，支持Bacnet通讯协议；通讯转换网关； 2）内置外部线路接线端子排、独立电源接线端子排、导轨、变压器；控制点不少于UI:10 DI:16 AO:4 DO:4；通讯转换网关支持多路485通讯。 3.其它:满足完成此项工作所需要的全部工作内容，包括设计图纸、技术规范书、答疑、招标文件、现行规范、图集、验收等全部要求 | E45: 套 | F45: 1 | G45: 2504.585 | H45: 96.33 | I45: 32.11 | J45: 128.44 | K45: 96.33 | L45: 353.21 | M45: 288.99 | N45: =SUM(G45:M45) -> 3499.995
A46: 29 | B46: 030503004009 | C46: DDC一体化箱DDC-12#-B1-04 | D46: 1.名称:DDC一体化箱DDC-12#-B1-04 2.技术参数:1）根据点表定制，内含DDC控制器 ，支持Bacnet通讯协议；通讯转换网关； 2）内置外部线路接线端子排、独立电源接线端子排、导轨、变压器；控制点不少于UI:5 DI:8 AO:0 DO:4；通讯转换网关支持多路485通讯。 3.其它:满足完成此项工作所需要的全部工作内容，包括设计图纸、技术规范书、答疑、招标文件、现行规范、图集、验收等全部要求 | E46: 套 | F46: 1 | G46: 2146.79 | H46: 82.57 | I46: 27.525 | J46: 110.09 | K46: 82.57 | L46: 302.75 | M46: 247.705 | N46: =SUM(G46:M46) -> 3000
A47: 本页小计 | N47: =SUM(N45:N46) -> 6499.995
A48: 30 | B48: 030503004010 | C48: DDC一体化箱DDC-15#-1F-03 | D48: 1.名称:DDC一体化箱DDC-15#-1F-03 2.技术参数:1）根据点表定制，内含通讯转换网关； 2）内置外部线路接线端子排、独立电源接线端子排、导轨、变压器；通讯转换网关支持多路485通讯。 3.其它:满足完成此项工作所需要的全部工作内容，包括设计图纸、技术规范书、答疑、招标文件、现行规范、图集、验收等全部要求 | E48: 套 | F48: 1 | G48: 1045.87 | H48: 275.23 | I48: 137.615 | J48: 770.64 | K48: 220.185 | L48: 302.75 | M48: 247.705 | N48: =SUM(G48:M48) -> 2999.995
A49: 31 | B49: 030503004011 | C49: DDC一体化箱DDC-15#-1F-04 | D49: 1.名称:DDC一体化箱DDC-15#-1F-04 2.技术参数:1）根据点表定制，内含通讯转换网关； 2）内置外部线路接线端子排、独立电源接线端子排、导轨、变压器；通讯转换网关支持多路485通讯。 3.其它:满足完成此项工作所需要的全部工作内容，包括设计图纸、技术规范书、答疑、招标文件、现行规范、图集、验收等全部要求 | E49: 套 | F49: 1 | G49: 1045.87 | H49: 275.23 | I49: 137.615 | J49: 770.64 | K49: 220.185 | L49: 302.75 | M49: 247.705 | N49: =SUM(G49:M49) -> 2999.995
A50: 本页小计 | N50: =SUM(N48:N49) -> 5999.99
A51: 32 | B51: 030503004012 | C51: DDC一体化箱DDC-15#-2F-03 | D51: 1.名称:DDC一体化箱DDC-15#-2F-03 2.技术参数:1）根据点表定制，内含通讯转换网关； 2）内置外部线路接线端子排、独立电源接线端子排、导轨、变压器；通讯转换网关支持多路485通讯。 3.其它:满足完成此项工作所需要的全部工作内容，包括设计图纸、技术规范书、答疑、招标文件、现行规范、图集、验收等全部要求 | E51: 套 | F51: 1 | G51: 1045.87 | H51: 275.23 | I51: 137.615 | J51: 770.64 | K51: 220.185 | L51: 302.75 | M51: 247.705 | N51: =SUM(G51:M51) -> 2999.995
A52: 33 | B52: 030503004013 | C52: DDC一体化箱DDC-15#-2F-04 | D52: 1.名称:DDC一体化箱DDC-15#-2F-04 2.技术参数:1）根据点表定制，内含通讯转换网关； 2）内置外部线路接线端子排、独立电源接线端子排、导轨、变压器；通讯转换网关支持多路485通讯。 3.其它:满足完成此项工作所需要的全部工作内容，包括设计图纸、技术规范书、答疑、招标文件、现行规范、图集、验收等全部要求 | E52: 套 | F52: 1 | G52: 1045.87 | H52: 275.23 | I52: 137.615 | J52: 770.64 | K52: 220.185 | L52: 302.75 | M52: 247.705 | N52: =SUM(G52:M52) -> 2999.995
A53: 本页小计 | N53: =SUM(N51:N52) -> 5999.99
A54: 34 | B54: 030503004014 | C54: DDC一体化箱DDC-15#-RF-02 | D54: 1.名称:DDC一体化箱DDC-15#-RF-02 2.技术参数:1）根据点表定制，内含通讯转换网关； 2）内置外部线路接线端子排、独立电源接线端子排、导轨、变压器；UI:8 DI:39 AO:0 DO:20；通讯转换网关支持多路485通讯。 3.其它:满足完成此项工作所需要的全部工作内容，包括设计图纸、技术规范书、答疑、招标文件、现行规范、图集、验收等全部要求 | E54: 套 | F54: 1 | G54: 1568.805 | H54: 412.845 | I54: 206.42 | J54: 1155.965 | K54: 330.275 | L54: 454.13 | M54: 371.56 | N54: =SUM(G54:M54) -> 4500
A55: 35 | B55: 030503006018 | C55: 压差开关 | D55: 1.名称:压差开关 2.规格:测量范围 40~400Pa，寿命100万次 开关容量 1.5A,(0.4A)/250Vac，保护等级IP54。 3.其它:满足完成此项工作所需要的全部工作内容，包括设计图纸、技术规范书、答疑、招标文件、现行规范、图集、验收等全部要求 | E55: 支 | F55: 4 | G55: 314.86 | H55: 12.11 | I55: 4.04 | J55: 16.15 | K55: 12.11 | L55: 44.4 | M55: 36.33 | N55: =SUM(G55:M55) -> 440
A56: 36 | B56: 030503006019 | C56: 风管温度传感器 | D56: 1.名称:风管温度传感器 2.规格:风道温度一体式传感器NTC20K -10 -+110℃，保护等级为IP54 3.其它:满足完成此项工作所需要的全部工作内容，包括设计图纸、技术规范书、答疑、招标文件、现行规范、图集、验收等全部要求 | E56: 支 | F56: 4 | G56: 1001.83 | H56: 38.53 | I56: 12.84 | J56: 51.38 | K56: 38.53 | L56: 141.28 | M56: 115.6 | N56: =SUM(G56:M56) -> 1399.99
A57: 本页小计 | N57: =SUM(N54:N56) -> 6339.99
A58: 37 | B58: 030503006020 | C58: 风管湿度传感器 | D58: 1.名称:风管湿度传感器 2.规格:湿度量程：0~100%RH； 精度：±3%RH； 输出信号：4~20mA或0~10VDC； 供电电源：DC24V； 防护等级IP65； 探管材质：不锈钢 3.其它:满足完成此项工作所需要的全部工作内容，包括设计图纸、技术规范书、答疑、招标文件、现行规范、图集、验收等全部要求。 | E58: 支 | F58: 4 | G58: 1431.19 | H58: 55.05 | I58: 18.35 | J58: 73.39 | K58: 55.05 | L58: 201.83 | M58: 165.14 | N58: =SUM(G58:M58) -> 2000
A59: 38 | B59: 030503007001 | C59: 风阀执行器（调节型） | D59: 1.名称:风阀执行器（调节型） 2.技术参数:连续调节型风门执行器； 扭矩：10Nm； 供电电源：24VAC/DC 3.其它:满足完成此项工作所需要的全部工作内容，包括设计图纸、技术规范书、答疑、招标文件、现行规范、图集、验收等全部要求 | E59: 个 | F59: 4 | G59: 1288.07 | H59: 49.54 | I59: 16.51 | J59: 66.06 | K59: 49.54 | L59: 181.65 | M59: 148.62 | N59: =SUM(G59:M59) -> 1799.99
A60: 39 | B60: 030503007002 | C60: 电动两通阀 | D60: 1.名称:电动两通阀 2.技术参数:24VDC，4~20mA，0~10Bar，±0.3%， 带减压管及球阀 3.其它:满足完成此项工作所需要的全部工作内容，包括设计图纸、技术规范书、答疑、招标文件、现行规范、图集、验收等全部要求。 | E60: 个 | F60: 13 | G60: 2862.39 | H60: 238.53 | I60: 95.41 | J60: 715.6 | K60: 333.94 | L60: 524.77 | M60: 429.36 | N60: =SUM(G60:M60) -> 5200
A61: 本页小计 | N61: =SUM(N58:N60) -> 8999.99
A62: 40 | B62: 030601001001 | C62: 室外温湿度 | D62: 1.名称:室外温湿度 2.规格:0-10V， 量程范围：温度范围≥-40~60℃，≤3%湿度精度，≤0.3℃温度精度，最大10KPa 3.其它:满足完成此项工作所需要的全部工作内容，包括设计图纸、技术规范书、答疑、招标文件、现行规范、图集、验收等全部要求。 | E62: 支 | F62: 2 | G62: 330.28 | H62: 27.52 | I62: 11.01 | J62: 82.57 | K62: 38.53 | L62: 60.55 | M62: 49.54 | N62: =SUM(G62:M62) -> 600
A63: 41 | B63: 030601004001 | C63: 水流开关 | D63: 1.名称:水流开关 2.规格:输出信号：SPDT,10A/250VAC； 最大允许压力：1.6Mpa； 含安装套管及靶片。 3.其它:满足完成此项工作所需要的全部工作内容，包括设计图纸、技术规范书、答疑、招标文件、现行规范、图集、验收等全部要求。 | E63: 台 | F63: 9 | G63: 470.64 | H63: 123.85 | I63: 61.93 | J63: 346.79 | K63: 99.08 | L63: 136.24 | M63: 111.47 | N63: =SUM(G63:M63) -> 1350
A64: 42 | B64: 030601001002 | C64: 水管温度 | D64: 1.名称:水管温度 2.规格:24VDC，4~20mA，4"探针 不锈钢套筒 3.其它:满足完成此项工作所需要的全部工作内容，包括设计图纸、技术规范书、答疑、招标文件、现行规范、图集、验收等全部要求。 | E64: 支 | F64: 4 | G64: 660.55 | H64: 55.05 | I64: 22.02 | J64: 165.14 | K64: 77.06 | L64: 121.1 | M64: 99.08 | N64: =SUM(G64:M64) -> 1200
A65: 43 | B65: 030503006021 | C65: 氢气传感器 | D65: 1.名称:氢气传感器 2.规格:风道温度一体式传感器NTC20K -10 -+110℃，保护等级为IP54 3.其它:满足完成此项工作所需要的全部工作内容，包括设计图纸、技术规范书、答疑、招标文件、现行规范、图集、验收等全部要求 | E65: 支 | F65: 26 | G65: 11163.3 | H65: 429.36 | I65: 143.12 | J65: 572.48 | K65: 429.36 | L65: 1574.31 | M65: 1288.07 | N65: =SUM(G65:M65) -> 15600
A66: 本页小计 | N66: =SUM(N62:N65) -> 18750
A67: 44 | B67: 030503006022 | C67: 液位开关 | D67: 1.名称:液位开关 2.规格:液位开关触点不低于电压250V/5A，自带电缆不小于5m 3.其它:满足完成此项工作所需要的全部工作内容，包括设计图纸、技术规范书、答疑、招标文件、现行规范、图集、验收等全部要求 | E67: 支 | F67: 32 | G67: 1946.42 | H67: 74.86 | I67: 24.95 | J67: 99.82 | K67: 74.86 | L67: 274.5 | M67: 224.59 | N67: =SUM(G67:M67) -> 2720
A68: 45 | B68: 030503006023 | C68: 液位计 | D68: 1.名称:液位计 2.其它:满足完成此项工作所需要的全部工作内容，包括设计图纸、技术规范书、答疑、招标文件、现行规范、图集、验收等全部要求 | E68: 支 | F68: 3 | G68: 1816.51 | H68: 151.38 | I68: 60.55 | J68: 454.13 | K68: 211.93 | L68: 333.03 | M68: 272.48 | N68: =SUM(G68:M68) -> 3300.01
A69: 46 | B69: 030503006024 | C69: 水管压力传感器 | D69: 1.名称:水管压力传感器 2.规格:24VDC，4~20mA，0~16Bar，±0.3% 带减压管及球阀 3.其它:满足完成此项工作所需要的全部工作内容，包括设计图纸、技术规范书、答疑、招标文件、现行规范、图集、验收等全部要求。 | E69: 支 | F69: 12 | G69: 3434.86 | H69: 132.11 | I69: 44.04 | J69: 176.15 | K69: 132.11 | L69: 484.4 | M69: 396.33 | N69: =SUM(G69:M69) -> 4800
A70: 47 | B70: 030503006025 | C70: 水管压差传感器 | D70: 1.名称:水管压差传感器 2.规格:24VDC，4~20mA，0~10Bar，±0.3%， 带减压管及球阀 3.其它:满足完成此项工作所需要的全部工作内容，包括设计图纸、技术规范书、答疑、招标文件、现行规范、图集、验收等全部要求。 | E70: 支 | F70: 2 | G70: 1717.43 | H70: 66.06 | I70: 22.02 | J70: 88.07 | K70: 66.06 | L70: 242.2 | M70: 198.17 | N70: =SUM(G70:M70) -> 2400.01
A71: 本页小计 | N71: =SUM(N67:N70) -> 13220.02
A72: 48 | B72: 030503005001 | C72: 全自动加药设备接口 | D72: 1.名称:全自动加药设备接口 2.技术参数:需设备厂家提供硬件接口和开放标准协议 3.其它:满足完成此项工作所需要的全部工作内容，包括设计图纸、技术规范书、答疑、招标文件、现行规范、图集、验收等全部要求。 | E72: 项 | F72: 1 | G72: 1266.06 | H72: 105.5 | I72: 42.2 | J72: 316.51 | K72: 147.71 | L72: 232.11 | M72: 189.91 | N72: =SUM(G72:M72) -> 2300
A73: 49 | B73: 030503005002 | C73: 自动补水排气定压机组接口 | D73: 1.名称:自动补水排气定压机组接口 2.技术参数:需设备厂家提供硬件接口和开放标准协议 3.其它:满足完成此项工作所需要的全部工作内容，包括设计图纸、技术规范书、答疑、招标文件、现行规范、图集、验收等全部要求。 | E73: 项 | F73: 1 | G73: 1266.06 | H73: 105.5 | I73: 42.2 | J73: 316.51 | K73: 147.71 | L73: 232.11 | M73: 189.91 | N73: =SUM(G73:M73) -> 2300
A74: 50 | B74: 030503005003 | C74: 电梯接口 | D74: 1.名称:电梯接口 2.技术参数:需设备厂家提供硬件接口和开放标准协议 3.其它:满足完成此项工作所需要的全部工作内容，包括设计图纸、技术规范书、答疑、招标文件、现行规范、图集、验收等全部要求。 | E74: 项 | F74: 1 | G74: 1266.06 | H74: 105.5 | I74: 42.2 | J74: 316.51 | K74: 147.71 | L74: 232.11 | M74: 189.91 | N74: =SUM(G74:M74) -> 2300
A75: 51 | B75: 030503005004 | C75: 风冷热泵机组接口 | D75: 1.名称:风冷热泵机组接口 2.技术参数:需设备厂家提供硬件接口和开放标准协议 3.其它:满足完成此项工作所需要的全部工作内容，包括设计图纸、技术规范书、答疑、招标文件、现行规范、图集、验收等全部要求。 | E75: 套 | F75: 1 | G75: 1266.06 | H75: 105.5 | I75: 42.2 | J75: 316.51 | K75: 147.71 | L75: 232.11 | M75: 189.91 | N75: =SUM(G75:M75) -> 2300
A76: 本页小计 | N76: =SUM(N72:N75) -> 9200
A77: 52 | B77: 030503005005 | C77: 空调新风处理机组接口 | D77: 1.名称:空调新风处理机组接口 2.技术参数:需设备厂家提供硬件接口和开放标准协议 3.其它:满足完成此项工作所需要的全部工作内容，包括设计图纸、技术规范书、答疑、招标文件、现行规范、图集、验收等全部要求。 | E77: 项 | F77: 1 | G77: 1645.87 | H77: 63.3 | I77: 21.1 | J77: 84.4 | K77: 63.3 | L77: 232.11 | M77: 189.91 | N77: =SUM(G77:M77) -> 2299.99
A78: 53 | B78: 030503005006 | C78: 风机盘管接口 | D78: 1.名称:风机盘管接口 2.技术参数:需设备厂家提供硬件接口和开放标准协议 3.其它:满足完成此项工作所需要的全部工作内容，包括设计图纸、技术规范书、答疑、招标文件、现行规范、图集、验收等全部要求。 | E78: 项 | F78: 1 | G78: 1645.87 | H78: 63.3 | I78: 21.1 | J78: 84.4 | K78: 63.3 | L78: 232.11 | M78: 189.91 | N78: =SUM(G78:M78) -> 2299.99
A79: 54 | B79: 030503005007 | C79: 水质监测仪给排水接口 | D79: 1.名称:水质监测仪给排水接口 2.技术参数:需设备厂家提供硬件接口和开放标准协议 3.其它:满足完成此项工作所需要的全部工作内容，包括设计图纸、技术规范书、答疑、招标文件、现行规范、图集、验收等全部要求。 | E79: 项 | F79: 1 | G79: 1266.06 | H79: 105.5 | I79: 42.2 | J79: 316.51 | K79: 147.71 | L79: 232.11 | M79: 189.91 | N79: =SUM(G79:M79) -> 2300
A80: 本页小计 | N80: =SUM(N77:N79) -> 6899.98
A81: 55 | B81: 03B038 | C81: 系统综合及集成 | D81: 1.清单未列项、图纸中未表示或技术规格书未做要求，但为了实现本系统各项功能必须增加的配套及辅助的材料、设备的所有工作内容及费用； 2.施工深化设计增加的实现本系统设计功能必要的配套及辅助的材料、设备所需的所有工作内容及费用； 3.实现设计功能所做的满足图纸、技术规格书要求的各项综合与集成，包括不限于各项检测、试验、调试、软件开发、联动等所有工作内容及费用 | E81: 项 | F81: 1 | G81: 1394.5 | H81: 366.97 | I81: 183.49 | J81: 1027.52 | K81: 293.58 | L81: 403.67 | M81: 330.28 | N81: =SUM(G81:M81) -> 4000.01
A82: 56 | B82: 03B039 | C82: 平台对接 | D82: 1.平台对接 2.其它:满足完成此项工作所需要的全部工作内容，包括设计图纸、技术规范书、答疑、招标文件、现行规范、图集、验收等全部要求 | E82: 项 | F82: 1 | G82: 2752.29 | H82: 229.36 | I82: 91.74 | J82: 688.07 | K82: 321.1 | L82: 504.59 | M82: 412.84 | N82: =SUM(G82:M82) -> 4999.99
A83: 57 | B83: 030411001072 | C83: 配管 | D83: 1.名称:镀锌钢管 2.材质:SC20 3.敷设方式:综合考虑 4.其他:满足完成此项工作所需要的全部工作内容，满足设计图纸、技术规范书、答疑、招标文件、现行规范、图集、验收等全部要求 | E83: m | F83: 95.2 | G83: 149.35 | H83: 39.3 | I83: 19.65 | J83: 110.05 | K83: 31.44 | L83: 43.23 | M83: 35.37 | N83: =SUM(G83:M83) -> 428.39
A84: 58 | B84: 030411001073 | C84: 配管 | D84: 1.名称：镀锌钢管 2.材质:JDG20 3.敷设方式:综合考虑 4.其他:满足完成此项工作所需要的全部工作内容，满足设计图纸、技术规范书、答疑、招标文件、现行规范、图集、验收等全部要求 | E84: m | F84: 242.2 | G84: 379.97 | H84: 99.99 | I84: 50 | J84: 279.97 | K84: 79.99 | L84: 109.99 | M84: 89.99 | N84: =SUM(G84:M84) -> 1089.9
A85: 本页小计 | N85: =SUM(N81:N84) -> 10518.29
A86: 59 | B86: 030411001074 | C86: 配管 | D86: 1.名称:紧定式镀锌钢导管 2.材质:JDG25 3.敷设方式:综合考虑 4.其他:满足完成此项工作所需要的全部工作内容，满足设计图纸、技术规范书、答疑、招标文件、现行规范、图集、验收等全部要求 | E86: m | F86: 10.1 | G86: 17.61 | H86: 4.63 | I86: 2.32 | J86: 12.97 | K86: 3.71 | L86: 5.1 | M86: 4.17 | N86: =SUM(G86:M86) -> 50.51
A87: 60 | B87: 030413001037 | C87: 铁构件 | D87: 1.名称:管道支架制作安装 2.材质:热镀锌 3.安装高度:综合考虑 4.满足完成此项工作所需要的全部工作内容，满足设计图纸、技术规范书、答疑、招标文件、现行规范、图集、验收等全部要求 | E87: kg | F87: 62.1 | G87: 103.92 | H87: 27.35 | I87: 13.67 | J87: 76.57 | K87: 21.88 | L87: 30.08 | M87: 24.61 | N87: =SUM(G87:M87) -> 298.08
A88: 61 | B88: 030411004071 | C88: 配线 | D88: 1.名称:配线 2.规格:WDZ-RYY3*1.5 3.敷设方式:管内穿线 4.满足完成此项工作所需要的全部工作内容，包括设计图纸、技术规范书、答疑、招标文件、现行规范、图集、验收等全部要求 | E88: m | F88: 36.2 | G88: 75.72 | H88: 19.93 | I88: 9.96 | J88: 55.79 | K88: 15.94 | L88: 21.92 | M88: 17.93 | N88: =SUM(G88:M88) -> 217.19
A89: 62 | B89: 030411004072 | C89: 配线 | D89: 1.名称:配线 2.规格:WDZ-RYY8*1.0 3.敷设方式:管内穿线 4.满足完成此项工作所需要的全部工作内容，包括设计图纸、技术规范书、答疑、招标文件、现行规范、图集、验收等全部要求 | E89: m | F89: 10.14 | G89: 28.28 | H89: 7.44 | I89: 3.72 | J89: 20.84 | K89: 5.95 | L89: 8.19 | M89: 6.7 | N89: =SUM(G89:M89) -> 81.12
A90: 本页小计 | N90: =SUM(N86:N89) -> 646.9
A91: 63 | B91: 030411004073 | C91: 配线 | D91: 1.名称:配线 2.规格:WDZ-RYY8*1.0 3.敷设方式:线槽配线 4.满足完成此项工作所需要的全部工作内容，包括设计图纸、技术规范书、答疑、招标文件、现行规范、图集、验收等全部要求 | E91: m | F91: 22.29 | G91: 62.17 | H91: 16.36 | I91: 8.18 | J91: 45.81 | K91: 13.09 | L91: 18 | M91: 14.72 | N91: =SUM(G91:M91) -> 178.33
A92: 64 | B92: 030411004074 | C92: 配线 | D92: 1.名称:线缆 2.规格:WDZ-RYYSP-2x1.0 3.敷设方式:管内穿线 4.满足完成此项工作所需要的全部工作内容，包括设计图纸、技术规范书、答疑、招标文件、现行规范、图集、验收等全部要求 | E92: m | F92: 191.55 | G92: 400.67 | H92: 105.44 | I92: 52.72 | J92: 295.23 | K92: 84.35 | L92: 115.98 | M92: 94.9 | N92: =SUM(G92:M92) -> 1149.29
A93: 65 | B93: 030411004075 | C93: 配线 | D93: 1.名称:配线 2.规格:WDZ-RYY8*1.0 3.敷设方式:线槽配线 4.满足完成此项工作所需要的全部工作内容，包括设计图纸、技术规范书、答疑、招标文件、现行规范、图集、验收等全部要求 | E93: m | F93: 875.7 | G93: 2442.32 | H93: 642.72 | I93: 321.36 | J93: 1799.6 | K93: 514.17 | L93: 706.99 | M93: 578.44 | N93: =SUM(G93:M93) -> 7005.6
A94: 66 | B94: 030502005018 | C94: 双绞线缆 | D94: 1.名称：六类网线 2.规格： Cat.6 UTP 3.敷设方式：桥架敷设 4.其它:满足完成此项工作所需要的全部工作内容，包括设计图纸、技术规范书、答疑、招标文件、现行规范、图集、验收等全部要求 | E94: m | F94: 1183.4 | G94: 1237.68 | H94: 325.71 | I94: 162.85 | J94: 911.98 | K94: 260.57 | L94: 358.28 | M94: 293.14 | N94: =SUM(G94:M94) -> 3550.21
A95: 本页小计 | N95: =SUM(N91:N94) -> 11883.43
A96: 67 | B96: 030502005019 | C96: 双绞线缆 | D96: 1.名称：六类网线 2.规格： Cat.6 UTP 3.敷设方式：管内敷设 4.其它:满足完成此项工作所需要的全部工作内容，包括设计图纸、技术规范书、答疑、招标文件、现行规范、图集、验收等全部要求 | E96: m | F96: 117.4 | G96: 122.79 | H96: 32.31 | I96: 16.16 | J96: 90.47 | K96: 25.85 | L96: 35.54 | M96: 29.08 | N96: =SUM(G96:M96) -> 352.2
A97: 68 | B97: 030411001075 | C97: 配管 | D97: 1.名称:配管 2.材质:金属软管DN20 3.敷设方式:明敷 4.其他:满足完成此项工作所需要的全部工作内容，满足设计图纸、技术规范书、答疑、招标文件、现行规范、图集、验收等全部要求 | E97: m | F97: 140 | G97: 146.42 | H97: 38.53 | I97: 19.27 | J97: 107.89 | K97: 30.83 | L97: 42.39 | M97: 34.68 | N97: =SUM(G97:M97) -> 420.01
A98: 69 | B98: 030502019006 | C98: 双绞线缆测试 | D98: 1.双绞线缆测试 2.满足完成此项工作所需要的全部工作内容，包括设计图纸、技术规范书、答疑、招标文件、现行规范、图集、验收等全部要求 | E98: 链路 | F98: 31 | G98: 86.46 | H98: 22.75 | I98: 11.38 | J98: 63.71 | K98: 18.2 | L98: 25.03 | M98: 20.48 | N98: =SUM(G98:M98) -> 248.01
A99: 70 | B99: 030503010005 | C99: 建筑设备自控化系统试运行 | D99: 1.系统调试及试运行 2.满足完成此项工作所需要的全部工作内容，包括设计图纸、技术规范书、答疑、招标文件、现行规范、图集、验收等全部要求 | E99: 系统 | F99: 1 | G99: 1045.87 | H99: 275.23 | I99: 137.61 | J99: 770.64 | K99: 220.18 | L99: 302.75 | M99: 247.71 | N99: =SUM(G99:M99) -> 2999.99
A100: 71 | B100: 030411001076 | C100: 配管 | D100: 1.名称:紧定式镀锌钢导管 2.材质:JDG20 3.敷设方式:综合考虑 4.其他:满足完成此项工作所需要的全部工作内容，满足设计图纸、技术规范书、答疑、招标文件、现行规范、图集、验收等全部要求 | E100: m | F100: 1224.84 | G100: 1921.54 | H100: 505.67 | I100: 252.83 | J100: 1415.87 | K100: 404.53 | L100: 556.23 | M100: 455.1 | N100: =SUM(G100:M100) -> 5511.77
...

Sheet 8#、15#非管区多媒体系统
A1: 分部分项工程和单价措施项目清单与计价表
A2: 分部分项工程和单价措施项目清单与计价表
A3: 序号 | B3: 项目编码 | C3: 项目名称 | D3: 项目特征描述 | E3: 计量单位 | F3: 工程量 | G3: 金额（元）
G4: 主材/设备费 | H4: 辅材 | I4: 机械措施 | J4: 人工 | K4: 管理费 | L4: 利润 | M4: 税金 | N4: 总价
A5: 1 | B5: 030506007003 | C5: LED小间距显示屏屏 | D5: 1.名称：LED小间距显示屏 2.规格：P0.9,尺寸8720*2980mm，SMD模组封装，含成套视频拼接处理器、配电柜和支架 3.其它:满足完成此项工作所需要的全部工作内容，满足设计图纸、技术规范书、答疑、招标文件、现行规范、图集、验收等全部要求 | E5: m2 | F5: 25.99 | G5: 119773.37 | H5: 4606.665 | I5: 1535.555 | J5: 6142.227 | K5: 4606.665 | L5: 16891.119 | M5: 13820.002 | N5: =SUM(G5:M5) -> 167375.6
A6: 2 | B6: 030506001001 | C6: 有源可调指向性音柱 | D6: 1.名称:有源可调指向性音柱 2.规格:驱动单元：不少于8个，低频单元尺寸不小于3英寸； 每个驱动单元拥有独立通道的功率放大器与DSP处理通道； 水平覆盖角度：不低于120°； 音束垂直覆盖角度：数字可调； 支持多波束覆盖，波束不少于2个； 最大声压级：不小于130dB； 可选多种音频输入：具备Dante接入； 含有源可调指向性音柱配套安装架。 3.其它:满足完成此项工作所需要的全部工作内容，包括设计图纸、技术规范书、答疑、招标文件、现行规范、图集、验收等全部要求 | E6: 台 | F6: 2 | G6: 5103.856 | H6: 1343.12 | I6: 671.56 | J6: 3760.736 | K6: 1074.496 | L6: 1477.432 | M6: 1208.808 | N6: =SUM(G6:M6) -> 14640.008
A7: 本页小计 | N7: =SUM(N5:N6) -> 182015.61
A8: 3 | B8: 030506001002 | C8: 超低音扬声器 | D8: 1.名称:超低音扬声器 2.规格:18"超低音扬声器 最大声压级≥130dB； 驱动单元不小于1个18英寸低频单元 频率响应不劣于35Hz-180Hz； 功率不小于600W； 3.其它:满足完成此项工作所需要的全部工作内容，包括设计图纸、技术规范书、答疑、招标文件、现行规范、图集、验收等全部要求 | E8: 台 | F8: 2 | G8: 3241.104 | H8: 270.088 | I8: 108.04 | J8: 810.272 | K8: 378.128 | L8: 594.2 | M8: 486.168 | N8: =SUM(G8:M8) -> 5888
A9: 4 | B9: 030506001003 | C9: 流动返听扬声器 | D9: 1.名称:流动返听扬声器 2.规格:12"返听扬声器 最大声压级≥129dB； 驱动单元不小于1个12英寸低频单元和1个高频单元; 频率响应不劣于75Hz-20KHz； 覆盖角度不小于60° ； 功率不小于300W。 3.其它:满足完成此项工作所需要的全部工作内容，包括设计图纸、技术规范书、答疑、招标文件、现行规范、图集、验收等全部要求 | E9: 台 | F9: 2 | G9: 1726.242 | H9: 143.85 | I9: 57.54 | J9: 431.557 | K9: 201.397 | L9: 316.477 | M9: 258.937 | N9: =SUM(G9:M9) -> 3136
A10: 本页小计 | N10: =SUM(N8:N9) -> 9024
A11: 5 | B11: 030506001004 | C11: 吸顶扬声器 | D11: 1.名称:吸顶扬声器 2.规格:最大声压级≥110dB； 驱动单元不小于1个6.5英寸低频单元和1个高频单元; 频率响应不劣于60Hz-20KHz (+/-3dB)； 覆盖角度不小于100° 支持70V/100V定压定阻可调； 功率不劣于30W。 3.其它:满足完成此项工作所需要的全部工作内容，包括设计图纸、技术规范书、答疑、招标文件、现行规范、图集、验收等全部要求 | E11: 台 | F11: 8 | G11: 2015.12 | H11: 167.928 | I11: 67.168 | J11: 503.776 | K11: 235.096 | L11: 369.44 | M11: 302.264 | N11: =SUM(G11:M11) -> 3660.792
A12: 6 | B12: 030506001005 | C12: 功率放大器（超低） | D12: 1.名称:功率放大器（超低） 2.技术参数:2通道D类功率放大器 频率响应：20Hz-20KHz（±1dB）； 内置扬声器调节所需DSP，包括延时、均衡器（升余弦、自定义FIR、参量IIR：峰值、高/低搁架）、全通、带通、带阻、高/低通、分频、限幅等模块； 功率满足扬声器1.5倍余量。 3.其它:满足完成此项工作所需要的全部工作内容，满足设计图纸、技术规范书、答疑、招标文件、现行规范、图集、验收等全部要求 | E12: 台 | F12: 1 | G12: 3077.634 | H12: 118.37 | I12: 39.459 | J12: 157.829 | K12: 118.37 | L12: 434.028 | M12: 355.11 | N12: =SUM(G12:M12) -> 4300.8
A13: 本页小计 | N13: =SUM(N11:N12) -> 7961.592
A14: 7 | B14: 030506001006 | C14: 功率放大器（返听） | D14: 1.名称:功率放大器（返听） 2.技术参数:2通道D类功率放大器 频率响应：20Hz-20KHz（±1dB）； 内置扬声器调节所需DSP，包括延时、均衡器（升余弦、自定义FIR、参量IIR：峰值、高/低搁架）、全通、带通、带阻、高/低通、分频、限幅等模块； 功率满足扬声器1.5倍余量。 3.其它:满足完成此项工作所需要的全部工作内容，满足设计图纸、技术规范书、答疑、招标文件、现行规范、图集、验收等全部要求 | E14: 台 | F14: 1 | G14: 2518.9 | H14: 96.88 | I14: 32.29 | J14: 129.17 | K14: 96.88 | L14: 355.23 | M14: 290.64 | N14: =SUM(G14:M14) -> 3519.99
A15: 8 | B15: 030506001007 | C15: 功率放大器（吸顶） | D15: 1.名称:功率放大器（吸顶） 2.技术参数:4通道D类功率放大器 频率响应：20Hz-20KHz（±1dB）； 内置扬声器调节所需DSP，包括延时、均衡器（升余弦、自定义FIR、参量IIR：峰值、高/低搁架）、全通、带通、带阻、高/低通、分频、限幅等模块； 功率满足扬声器1.5倍余量。 3.其它:满足完成此项工作所需要的全部工作内容，满足设计图纸、技术规范书、答疑、招标文件、现行规范、图集、验收等全部要求 | E15: 台 | F15: 1 | G15: 3142.9 | H15: 120.88 | I15: 40.29 | J15: 161.17 | K15: 120.88 | L15: 443.23 | M15: 362.64 | N15: =SUM(G15:M15) -> 4391.99
A16: 本页小计 | N16: =SUM(N14:N15) -> 7911.98
A17: 9 | B17: 030506001008 | C17: 数字音频处理器（DANTE) | D17: 1.名称:数字音频处理器（DANTE) 2.技术参数:通道数量：≥12个通道话筒/线路输入，≥8个通道线路输出； 控制端口：支持≥8个GPIO通道和1个通用串口RS232； 网络端口：≥2个千兆网口，≥32路Dante传输； AEC通道≥4路； 3.其它:满足完成此项工作所需要的全部工作内容，满足设计图纸、技术规范书、答疑、招标文件、现行规范、图集、验收等全部要求 | E17: 台 | F17: 2 | G17: 6011.01 | H17: 231.19 | I17: 77.06 | J17: 308.26 | K17: 231.19 | L17: 847.71 | M17: 693.58 | N17: =SUM(G17:M17) -> 8400
A18: 10 | B18: 030506001009 | C18: 数字调音台（含DANTE卡） | D18: 1.名称:数字调音台（含DANTE卡） 2.技术参数:不少于48路全处理输入； 不少于24个马达推子； 不少于24路输入通道； 不少于16路输出通道； 不少于1个触摸屏； 采样率≥48kHz； 内置Dante卡，Dante网络传输协议支持64路双向音频传输，通过CAT5控制 ，千兆网络端口 3.其它:满足完成此项工作所需要的全部工作内容，满足设计图纸、技术规范书、答疑、招标文件、现行规范、图集、验收等全部要求 | E18: 台 | F18: 1 | G18: 12550.46 | H18: 1045.87 | I18: 418.35 | J18: 3137.61 | K18: 1464.22 | L18: 2300.92 | M18: 1882.57 | N18: =SUM(G18:M18) -> 22800
A19: 本页小计 | N19: =SUM(N17:N18) -> 31200
A20: 11 | B20: 030503004015 | C20: 音频接口箱 | D20: 1.名称:音频接口箱 2.技术参数:不少于16个输入； 不少于8个输出； 不少于2个网络端口用于外接其它控制设备； 3.其它:满足完成此项工作所需要的全部工作内容，满足设计图纸、技术规范书、答疑、招标文件、现行规范、图集、验收等全部要求 | E20: 台 | F20: 1 | G20: 3514.13 | H20: 292.84 | I20: 117.14 | J20: 878.53 | K20: 409.98 | L20: 644.26 | M20: 527.12 | N20: =SUM(G20:M20) -> 6384
A21: 12 | B21: 030506001010 | C21: 有源监听扬声器 | D21: 1.名称:有源监听扬声器 2.规格:驱动单元：1个不小于5.25英寸低音驱动单元，不小于1个1英寸高音驱动单元； 频率响应：不劣于45-20kHz； 指向性角度(@1000Hz)：180°H x180°V 最大声压级（1m）：不小于101dB； 3.其它:满足完成此项工作所需要的全部工作内容，包括设计图纸、技术规范书、答疑、招标文件、现行规范、图集、验收等全部要求 | E21: 台 | F21: 2 | G21: 3153.03 | H21: 262.75 | I21: 105.1 | J21: 788.26 | K21: 367.85 | L21: 578.06 | M21: 472.95 | N21: =SUM(G21:M21) -> 5728
A22: 本页小计 | N22: =SUM(N20:N21) -> 12112
A23: 13 | B23: 030506001011 | C23: 无线手持话筒 | D23: 1.名称:无线手持话筒 2.技术参数:具备频率备份功能，支持跳频到备用频率 工作带宽：≥60MHz 配置单指向动圈手持音头 发射功率：≥30mW 电池：支持AA电池和充电底座 同无线话筒接收机品牌，配套使用即可 3.其它:满足完成此项工作所需要的全部工作内容，满足设计图纸、技术规范书、答疑、招标文件、现行规范、图集、验收等全部要求 | E23: 台 | F23: 4 | G23: 2289.91 | H23: 88.07 | I23: 29.36 | J23: 117.43 | K23: 88.07 | L23: 322.94 | M23: 264.22 | N23: =SUM(G23:M23) -> 3200
A24: 14 | B24: 030506001012 | C24: 无线领夹话筒 | D24: 1.名称:无线领夹话筒 2.技术参数:具备频率备份功能，支持跳频到备用频率 工作带宽：≥60MHz 配置单指向微型领夹话筒 发射功率：≥30mW 电池：支持AA电池和充电底座 同无线话筒接收机品牌，配套使用即可 3.其它:满足完成此项工作所需要的全部工作内容，满足设计图纸、技术规范书、答疑、招标文件、现行规范、图集、验收等全部要求 | E24: 台 | F24: 2 | G24: 1007.56 | H24: 38.75 | I24: 12.92 | J24: 51.67 | K24: 38.75 | L24: 142.09 | M24: 116.26 | N24: =SUM(G24:M24) -> 1408
A25: 本页小计 | N25: =SUM(N23:N24) -> 4608
A26: 15 | B26: 030506001013 | C26: 无线话筒接收机 | D26: 1.名称:无线话筒接收机 2.技术参数:具备频率备份功能，支持跳频到备用频率 工作带宽：≥60MHz 支持自动扫频及设置SQ值 支持软件远程监控 3.其它:满足完成此项工作所需要的全部工作内容，满足设计图纸、技术规范书、答疑、招标文件、现行规范、图集、验收等全部要求 | E26: 台 | F26: 6 | G26: 5152.29 | H26: 198.17 | I26: 66.06 | J26: 264.22 | K26: 198.17 | L26: 726.61 | M26: 594.5 | N26: =SUM(G26:M26) -> 7200.02
A27: 16 | B27: 031102001001 | C27: 无线话筒全向天线 | D27: 1.名称:无线话筒全向天线 2.技术参数:工作频段：不劣于470-900MHz 增益：不少于3挡可调，最大不小于12dB 3.其它:满足完成此项工作所需要的全部工作内容，满足设计图纸、技术规范书、答疑、招标文件、现行规范、图集、验收等全部要求 | E27: 副 | F27: 2 | G27: 2404.4 | H27: 92.48 | I27: 30.83 | J27: 123.3 | K27: 92.48 | L27: 339.08 | M27: 277.43 | N27: =SUM(G27:M27) -> 3360
A28: 17 | B28: 030505013003 | C28: 天线分配器 | D28: 1.名称:天线分配器 2.技术参数:工作频段：不劣于470-900MHz 接口：输入≥2，输出≥8 3.其它:满足完成此项工作所需要的全部工作内容，满足设计图纸、技术规范书、答疑、招标文件、现行规范、图集、验收等全部要求 | E28: 个 | F28: 2 | G28: 1211.01 | H28: 100.92 | I28: 40.37 | J28: 302.75 | K28: 141.28 | L28: 222.02 | M28: 181.65 | N28: =SUM(G28:M28) -> 2200
A29: 本页小计 | N29: =SUM(N26:N28) -> 12760.02
A30: 18 | B30: 030506001014 | C30: 汇报席鹅颈话筒（含底座） | D30: 1.名称:汇报席鹅颈话筒（含底座） 2.技术参数:指向特性：超指向性 频率响应：不劣于 80-18000Hz 开路灵敏度：≥-31dB 最大输入声压级：≥126dB SPL， 1 kHz 于 1% T.H.D. 含带开关底座 3.其它:满足完成此项工作所需要的全部工作内容，满足设计图纸、技术规范书、答疑、招标文件、现行规范、图集、验收等全部要求 | E30: 台 | F30: 1 | G30: 504.5 | H30: 19.4 | I30: 6.47 | J30: 25.87 | K30: 19.4 | L30: 71.15 | M30: 58.21 | N30: =SUM(G30:M30) -> 705
A31: 19 | B31: 030506001015 | C31: 数字会议系统主机 | D31: 1.名称:数字会议系统主机 2.技术参数:每台主机可连接不少于100个有线手拉手单元，有线手拉手链接方式。 内置反馈处理器等组件，可实时监测并处理系统中的啸叫点。 3.其它:满足完成此项工作所需要的全部工作内容，满足设计图纸、技术规范书、答疑、招标文件、现行规范、图集、验收等全部要求 | E31: 台 | F31: 1 | G31: 3518.445 | H31: 135.324 | I31: 45.108 | J31: 180.432 | K31: 135.324 | L31: 496.188 | M31: 405.972 | N31: =SUM(G31:M31) -> 4916.793
A32: 本页小计 | N32: =SUM(N30:N31) -> 5621.793
A33: 20 | B33: 030506001016 | C33: 有线会议发言单元 | D33: 1.名称:有线会议发言单元 2.技术参数:每个话筒均可独立调节增益控制 手拉手链接方式 指向特性：超心形指向性 频率响应：不劣于 30-20000Hz 开通灵敏度：≥-31dB(28.2mV) 以 1V 于 1 Pa 最高输入音量：≥125dB spl， 1 kHz 于 1% T.H.D. 3.其它:满足完成此项工作所需要的全部工作内容，满足设计图纸、技术规范书、答疑、招标文件、现行规范、图集、验收等全部要求 | E33: 台 | F33: 5 | G33: 2244.109 | H33: 86.31 | I33: 28.77 | J33: 115.08 | K33: 86.31 | L33: 316.477 | M33: 258.937 | N33: =SUM(G33:M33) -> 3135.993
A34: 21 | B34: 030506007004 | C34: LED显示屏 | D34: 1.名称：LED显示屏 2.规格：像素间距：1.5mm LED显示屏，彩色，3.6m宽2.7m高，比例4:3，刷新频率：≥3840Hz，最大对比度：≥ 12000:1，显示单元平整 屏幕亮度：≥600nit 安装方式：SMD封装技术含成套配电柜和支架、视频拼接处理器 水平视角：≥160°，垂直视角：≥160°，平均无故障时间：≥100,000 小时，LED屏幕表面采用电喷技术,无塑胶类结构件，显示屏对比度高，具备防蓝光功能。 3.其它:满足完成此项工作所需要的全部工作内容，满足设计图纸、技术规范书、答疑、招标文件、现行规范、图集、验收等全部要求 | E34: m2 | F34: 9.72 | G34: 29213.506 | H34: 1123.598 | I34: 374.535 | J34: 1498.126 | K34: 1123.598 | L34: 4119.85 | M34: 3370.787 | N34: =SUM(G34:M34) -> 40824
A35: 本页小计 | N35: =SUM(N33:N34) -> 43959.993
A36: 22 | B36: 030506007005 | C36: 接收系统 | D36: 1.名称:接收系统 2.技术参数:包含图像发送端、接收端、控制电脑以及信号线缆，投标人依据所投产品技术特点包干考虑。 3.其它:满足完成此项工作所需要的全部工作内容，满足设计图纸、技术规范书、答疑、招标文件、现行规范、图集、验收等全部要求 | E36: 台 | F36: 1 | G36: 1981.65 | H36: 165.14 | I36: 66.06 | J36: 495.41 | K36: 231.19 | L36: 363.3 | M36: 297.25 | N36: =SUM(G36:M36) -> 3600
A37: 23 | B37: 080904002002 | C37: 控制电脑 | D37: 1.名称:控制电脑 2.规格:不低于i5 16G 2T 256G 2G独显 含23.8寸显示器，配置鼠标键盘。 3.其它:满足完成此项工作所需要的全部工作内容，包括设计图纸、技术规范书、答疑、招标文件、现行规范、图集、验收等全部要求 | E37: 台 | F37: 1 | G37: 3721.1 | H37: 143.12 | I37: 47.71 | J37: 190.83 | K37: 143.12 | L37: 524.77 | M37: 429.36 | N37: =SUM(G37:M37) -> 5200.01
A38: 24 | B38: 030506007006 | C38: 98寸显示器 | D38: 1.名称:98寸显示器 2.不小于98英寸 分辨率不小于3840*2160 HDMI接口不少于2个，USB接口不少于2个，RJ45接口不少于1个； 3.含显示屏壁挂安装架 4.其它:满足完成此项工作所需要的全部工作内容，满足设计图纸、技术规范书、答疑、招标文件、现行规范、图集、验收等全部要求 | E38: 台 | F38: 2 | G38: 12165.14 | H38: 467.89 | I38: 155.96 | J38: 623.85 | K38: 467.89 | L38: 1715.6 | M38: 1403.67 | N38: =SUM(G38:M38) -> 17000
A39: 本页小计 | N39: =SUM(N36:N38) -> 25800.01
A40: 25 | B40: 030506007007 | C40: 98寸协作一体机 | D40: 1.名称:98寸协作一体机 2.98英寸触控一体机 内置OPS电脑，支持Window/安卓系统 物理分辨率不小于3840*2160 中心亮度(含表面玻璃) ≥400 cd/m2 红外触摸屏 支持20点同时触控，支持10笔书写 内置不低于4000万像素摄像头，阵列麦克风 支持无线投屏功能 3.含显示屏壁挂安装架 4.其它:满足完成此项工作所需要的全部工作内容，满足设计图纸、技术规范书、答疑、招标文件、现行规范、图集、验收等全部要求 | E40: 台 | F40: 1 | G40: 16888.072 | H40: 649.544 | I40: 216.512 | J40: 866.056 | K40: 649.544 | L40: 2381.648 | M40: 1948.624 | N40: =SUM(G40:M40) -> 23600
A41: 26 | B41: 030506007008 | C41: 控制室监视器 | D41: 1.名称:控制室监视器 2.屏幕尺寸不小于27英寸 屏幕比例：16:9，面板：IPS技术； 接口：具备DP或HDM接口 3.安装方式:显示屏采用固定安装；需根据现场情况厂家深化调整； 4.其它:满足完成此项工作所需要的全部工作内容，满足设计图纸、技术规范书、答疑、招标文件、现行规范、图集、验收等全部要求 | E41: 台 | F41: 2 | G41: 4007.34 | H41: 154.13 | I41: 51.38 | J41: 205.5 | K41: 154.13 | L41: 565.14 | M41: 462.39 | N41: =SUM(G41:M41) -> 5600.01
A42: 本页小计 | N42: =SUM(N40:N41) -> 29200.01
A43: 27 | B43: 030506007009 | C43: 无线投屏主机 | D43: 1.名称:无线投屏主机 2.可直接通过无线方式将PC电脑上文件投放到显示设备上； 最高可传输图像分辨率不低于1080P； 可播放流媒体 3.其它:满足完成此项工作所需要的全部工作内容，满足设计图纸、技术规范书、答疑、招标文件、现行规范、图集、验收等全部要求 | E43: 台 | F43: 1 | G43: 858.72 | H43: 33.03 | I43: 11.01 | J43: 44.04 | K43: 33.03 | L43: 121.1 | M43: 99.08 | N43: =SUM(G43:M43) -> 1200.01
A44: 本页小计 | N44: =N43 -> 1200.01
A45: 28 | B45: 030506007010 | C45: 视频分布式编码器 | D45: 1.名称:视频分布式编码器 2.采用分布式架构，浅压缩编解码技术，支持通过标准网络交换机实现音视频以及控制信号的传输和交换； 支持视频环出接口，环出画面与原画质一致； 支持 3840x2160@60Hz视频输入、支持3840x2160@60Hz视频环出；支持分辨率包括：1920x1080@60i; 1920x1080@50i，并向下兼容。 支持不少于1路3.5mm音频输入； 支持不少于1路RJ45网口；1路万兆SFP光口； 支持信号满帧采集，画面无卡顿、不丢帧； 支持信号无缝切换，画面切换时间不大于16ms。 支持故障告警提示，当节点出现故障的时，后台可发出告警提示。 3.其它:满足完成此项工作所需要的全部工作内容，满足设计图纸、技术规范书、答疑、招标文件、现行规范、图集、验收等全部要求 | E45: 台 | F45: 16 | G45: 33890.64 | H45: 1303.488 | I45: 434.496 | J45: 1737.984 | K45: 1303.488 | L45: 4779.448 | M45: 3910.456 | N45: =SUM(G45:M45) -> 47360
A46: 本页小计 | N46: =N45 -> 47360
A47: 29 | B47: 030506007011 | C47: 视频分布式解码器 | D47: 1.名称:视频分布式解码器 2.采用分布式架构，浅压缩编解码技术，支持通过标准网络交换机实现音视频以及控制信号的传输和交换； 支持视频环出接口，环出画面与原画质一致； 支持 3840x2160@60Hz视频输入、支持3840x2160@60Hz视频环出；支持分辨率包括：1920x1080@60i; 1920x1080@50i，并向下兼容。 支持不少于1路3.5mm音频输入； 支持不少于1路RJ45网口；1路万兆SFP光口； 支持信号满帧采集，画面无卡顿、不丢帧； 支持信号无缝切换，画面切换时间不大于16ms。 支持故障告警提示，当节点出现故障的时，后台可发出告警提示。 3.其它:满足完成此项工作所需要的全部工作内容，满足设计图纸、技术规范书、答疑、招标文件、现行规范、图集、验收等全部要求 | E47: 台 | F47: 20 | G47: 42363.3 | H47: 1629.36 | I47: 543.12 | J47: 2172.48 | K47: 1629.36 | L47: 5974.31 | M47: 4888.07 | N47: =SUM(G47:M47) -> 59200
A48: 本页小计 | N48: =N47 -> 59200
A49: 30 | B49: 030506001017 | C49: 分布式控制主机（8#楼会议共用） | D49: 1.名称:分布式控制主机（8#楼会议共用） 2.支持对分布式系统进行整体配置管理及控制，客户端软件界面及操作方式可根据用户需求定制； 支持本地信号、远程信号、多媒体文件等全媒体信号上屏或切换信号。 支持对所有输入信号以及大屏显示画面进行实时预监。 支持设置用户权限级别。 支持编解码器布局模式设置。 3.其它:满足完成此项工作所需要的全部工作内容，满足设计图纸、技术规范书、答疑、招标文件、现行规范、图集、验收等全部要求 | E49: 台 | F49: 1 | G49: 13418.864 | H49: 516.112 | I49: 172.04 | J49: 688.144 | K49: 516.112 | L49: 1892.4 | M49: 1548.328 | N49: =SUM(G49:M49) -> 18752
A50: 31 | B50: 030501012007 | C50: 视频分布式交换机 | D50: 1.名称：视频分布式交换机 2.48个10/100/1000Base-T以太网端口 , 4个万兆SFP+ 可插拔双电源.支持交流或直流供电,默认配置-个500W AC电源或650W DC电源 支持PoE+ 交换容量: 336Gbps/3 024Tbps 包转发率: 132Mpps 支持组播功能 3.其它:满足完成此项工作所需要的全部工作内容，包括设计图纸、技术规范书、答疑、招标文件、现行规范、图集、验收等全部要求 | E50: 台 | F50: 1 | G50: 2747.89 | H50: 105.69 | I50: 35.23 | J50: 140.92 | K50: 105.69 | L50: 387.52 | M50: 317.06 | N50: =SUM(G50:M50) -> 3840
A51: 本页小计 | N51: =SUM(N49:N50) -> 22592
A52: 32 | B52: 030501012008 | C52: 核心交换机 | D52: 1.名称:核心交换机 2.技术参数:不少于24SFP，2个2端口40GE QSFP+光接口板卡，配置双电源、双风扇。 交换容量不低于：2.56Tbps，包转率不低于：1080Mpps。满配光模块。 组播功能支持支持 PIM-DM、PIM-SM、PIM-SSM、组播静态路由；支持组播策略；IPV4组播表项≥16K。 支持2层组播转发条数不小于3000。 支持3层组播转发条数不小于3000。 3.其它:满足完成此项工作所需要的全部工作内容，包括设计图纸、技术规范书、答疑、招标文件、现行规范、图集、验收等全部要求 | E52: 台 | F52: 1 | G52: 5009.17 | H52: 192.66 | I52: 64.22 | J52: 256.88 | K52: 192.66 | L52: 706.42 | M52: 577.98 | N52: =SUM(G52:M52) -> 6999.99
A53: 本页小计 | N53: =N52 -> 6999.99
A54: 33 | B54: 030506001018 | C54: 视频会议主机 | D54: 1.名称:视频会议主机 2.分体式设备，嵌入式系统。 支持ITU-T H.323 和SIP协议同时在线，实现多媒体音视频通讯。 符合ITU H.265、H.264 HP、H.264 BP等标准；音频编码要求支持ITU-T G.711、G.722、G.722.1C、G.729A、AAC-LD、Opus等标准协议，音频质量要求能够达到≥20KHz立体声效果。图像格式具有4K30fps、1080P60fps、1080P30fps、720P60 fps、720P30fps等格式。 具备不少于3个高清视频输入接口，不少于3个高清视频输出接口；支持在三个显示设备上分别输出远端图像、本端图像、双流。 3.其它:满足完成此项工作所需要的全部工作内容，满足设计图纸、技术规范书、答疑、招标文件、现行规范、图集、验收等全部要求 | E54: 台 | F54: 1 | G54: 7556.7 | H54: 290.64 | I54: 96.88 | J54: 387.52 | K54: 290.64 | L54: 1065.69 | M54: 871.93 | N54: =SUM(G54:M54) -> 10560
A55: 本页小计 | N55: =N54 -> 10560
A56: 34 | B56: 030507008015 | C56: 高清摄像机（全景） | D56: 1.名称:高清摄像机（全景） 2.成像元器件不小于1/2.5英寸 CMOS或MOS，传感器有效像素不低于 840万像素。 最大广角（水平视角）≥70度 。 视频输出支持：2160/29.97P并兼容1080/59.94P、1080/50P 。 光学变焦不小于20倍，4K模式下不小于28倍变焦。 支持HDMI或USB 或3G-SDI视频输出接口。 摄像机支持RS422和IP控制方式。 3.其它:满足完成此项工作所需要的全部工作内容，满足设计图纸、技术规范书、答疑、招标文件、现行规范、图集、验收等全部要求 | E56: 台 | F56: 2 | G56: 6297.25 | H56: 242.2 | I56: 80.73 | J56: 322.94 | K56: 242.2 | L56: 888.07 | M56: 726.61 | N56: =SUM(G56:M56) -> 8800
A57: 本页小计 | N57: =N56 -> 8800
A58: 35 | B58: 030507008016 | C58: 高清摄像机（特写） | D58: 1.名称:高清摄像机（特写） 2.成像元器件不小于1/2.5英寸CMOS或MOS，传感器有效像素不低于 840万像素 ,水平分辨率：≥1500TV线。 最大广角（水平视角）≥70度。 视频输出支持2160/29.97p、2160/25p并兼容1080/59.94p、1080/50p。 4K支持不小于28倍变焦、1080P支持不小于36倍光学变焦，最高支持80倍变焦。 支持3G-SDI、HDMI同时输出不同格式视频信号。 具有自动追踪功能，可自动保持人物居中，并自动变焦，自动追踪功能应为本机硬件支持功能，不依赖外部软件即可实现，并支持控制器或第三方控制设备远程开启和关闭。 支持RS422和IP控制接口，并可同时控制使用。 3.其它:满足完成此项工作所需要的全部工作内容，满足设计图纸、技术规范书、答疑、招标文件、现行规范、图集、验收等全部要求 | E58: 台 | F58: 2 | G58: 6297.25 | H58: 242.2 | I58: 80.73 | J58: 322.94 | K58: 242.2 | L58: 888.07 | M58: 726.61 | N58: =SUM(G58:M58) -> 8800
A59: 36 | B59: 030507008017 | C59: 摄像机安装架 | D59: 1.名称:摄像机安装架 2.安装方式:壁装支架 3.其它:满足完成此项工作所需要的全部工作内容，包括设计图纸、技术规范书、答疑、招标文件、现行规范、图集、验收等全部要求 | E59: 台 | F59: 4 | G59: 125.5 | H59: 33.03 | I59: 16.51 | J59: 92.48 | K59: 26.42 | L59: 36.33 | M59: 29.72 | N59: =SUM(G59:M59) -> 359.99
A60: 本页小计 | N60: =SUM(N58:N59) -> 9159.99
A61: 37 | B61: 030507013003 | C61: 摄像机控制键盘 | D61: 1.名称:摄像机控制键盘 2.技术参数:控制接口支持 RS232\422\IP，支持VISCA协议 摄像机控制数量：不低于112台 控制器数量支持不少于5台。 控制摇杆支持变焦控制，并具有增益和光圈调节旋钮。 3.其它:满足完成此项工作所需要的全部工作内容，包括设计图纸、技术规范书、答疑、招标文件、现行规范、图集、验收等全部要求 | E61: 台 | F61: 1 | G61: 2289.91 | H61: 88.07 | I61: 29.36 | J61: 117.43 | K61: 88.07 | L61: 322.94 | M61: 264.22 | N61: =SUM(G61:M61) -> 3200
A62: 本页小计 | N62: =N61 -> 3200
A63: 38 | B63: 030501003001 | C63: 录播一体机 | D63: 1.名称:录播一体机 2.具备LED液晶面板，可以显示控制状态，支持前面板一键操作，支持录制的开启、暂停、停止，通过按钮操作查看及设置参数，具备视频录制、视频点播和下载等功能； 视频编码：H.264HP，网络支持DHCP和静态IP两种选择；音频编码：AAC。支持2160P60Hz、1080P60Hz信号的接入，支持选择768kbps/1Mbps/2Mbps/4mbps录制编码速率； 视频接口：≥3路DVI-I输入接口，≥3路SDI输入接口，≥2路HDMI输出接口；其中四路视频输入可SDI、DVI二选一； 支持接入中控系统；支持不少于30个并发用户的直播和点播。 2.其它:满足完成此项工作所需要的全部工作内容，满足设计图纸、技术规范书、答疑、招标文件、现行规范、图集、验收等全部要求 | E63: 台 | F63: 1 | G63: 5202.672 | H63: 200.104 | I63: 66.704 | J63: 266.8 | K63: 200.104 | L63: 733.712 | M63: 600.312 | N63: =SUM(G63:M63) -> 7270.408
A64: 本页小计 | N64: =N63 -> 7270.408
A65: 39 | B65: 030506001019 | C65: 中央控制主机 | D65: 1.名称:中央控制主机 2.技术参数:中控主机不少于2路RS-232/422/485接口、6路RS232接口 8 路红外/单向RS-232接口 8路数字I/O接口 8路弱电继电器接口； 内置不少于2个以太网接口，支持IPv6并可内置网络防火墙 3.其它:满足完成此项工作所需要的全部工作内容，满足设计图纸、技术规范书、答疑、招标文件、现行规范、图集、验收等全部要求 | E65: 台 | F65: 1 | G65: 4488.22 | H65: 172.62 | I65: 57.54 | J65: 230.17 | K65: 172.62 | L65: 632.95 | M65: 517.87 | N65: =SUM(G65:M65) -> 6271.99
A66: 40 | B66: 030501017004 | C66: 调试和编程 | D66: 1.名称:调试和编程 2.技术参数:根据现场设备及环境定制化软件编程 3.其它:满足完成此项工作所需要的全部工作内容，满足设计图纸、技术规范书、答疑、招标文件、现行规范、图集、验收等全部要求 | E66: 套 | F66: 1 | G66: 334.68 | H66: 88.07 | I66: 44.04 | J66: 246.61 | K66: 70.46 | L66: 96.88 | M66: 79.27 | N66: =SUM(G66:M66) -> 960.01
A67: 41 | B67: 030501002007 | C67: 有线墙面触控屏 | D67: 1.名称:有线墙面触控屏 2.可视区域不低于10英寸； 分辨率不低于1280x800; 不少于1个USB2.0接口，RJ-45以以太网口； 支持POE供电。 3.其它:满足完成此项工作所需要的全部工作内容，满足设计图纸、技术规范书、答疑、招标文件、现行规范、图集、验收等全部要求 | E67: 台 | F67: 2 | G67: 5415.63 | H67: 208.29 | I67: 69.43 | J67: 277.72 | K67: 208.29 | L67: 763.74 | M67: 624.88 | N67: =SUM(G67:M67) -> 7567.98
A68: 本页小计 | N68: =SUM(N65:N67) -> 14799.98
A69: 42 | B69: 030501002008 | C69: 无线触摸屏 | D69: 1.名称:无线触摸屏 2.规格:不小于10英寸； 内存不小于32G； 3.其它:满足完成此项工作所需要的全部工作内容，满足设计图纸、技术规范书、答疑、招标文件、现行规范、图集、验收等全部要求 | E69: 台 | F69: 1 | G69: 1981.65 | H69: 165.14 | I69: 66.06 | J69: 495.41 | K69: 231.19 | L69: 363.3 | M69: 297.25 | N69: =SUM(G69:M69) -> 3600
A70: 43 | B70: 030501009006 | C70: 无线AP | D70: 1.名称:无线AP 2.技术参数:最高传输速率：3000Mbps 频率范围：双频（2.4GHz，5GHz） 网络接口：1个10M/100M/1GE 电口 天线类型：内置智能天线 3.其它:满足完成此项工作所需要的全部工作内容，满足设计图纸、技术规范书、答疑、招标文件、现行规范、图集、验收等全部要求 | E70: 台 | F70: 2 | G70: 757.43 | H70: 63.12 | I70: 25.25 | J70: 189.36 | K70: 88.37 | L70: 138.86 | M70: 113.61 | N70: =SUM(G70:M70) -> 1376
A71: 44 | B71: 030506001020 | C71: AC控制器（8#楼会议共用） | D71: 1.名称:AC控制器（8#楼会议共用） 2.技术参数:不少于8口无线AP控制器 3.其它:满足完成此项工作所需要的全部工作内容，满足设计图纸、技术规范书、答疑、招标文件、现行规范、图集、验收等全部要求 | E71: 台 | F71: 1 | G71: 2003.67 | H71: 77.06 | I71: 25.69 | J71: 102.75 | K71: 77.06 | L71: 282.57 | M71: 231.19 | N71: =SUM(G71:M71) -> 2799.99
A72: 45 | B72: 030501012009 | C72: 音频/控制交换机 | D72: 1.名称:音频/控制交换机 2.技术参数:不少于24口千兆POE交换机 3.其它:满足完成此项工作所需要的全部工作内容，包括设计图纸、技术规范书、答疑、招标文件、现行规范、图集、验收等全部要求 | E72: 台 | F72: 1 | G72: 1717.43 | H72: 66.06 | I72: 22.02 | J72: 88.07 | K72: 66.06 | L72: 242.2 | M72: 198.17 | N72: =SUM(G72:M72) -> 2400.01
A73: 本页小计 | N73: =SUM(N69:N72) -> 10176
A74: 46 | B74: 030404023001 | C74: 强电继电器 | D74: 1.名称：强电继电器 2.技术参数:控制方式：RS232/RS485/干触点或手动； 额定功率：提供250VAC/15A的常开/常闭触。 3.其它:满足完成此项工作所需要的全部工作内容，包括设计图纸、技术规范书、答疑、招标文件、现行规范、图集、验收等全部要求 | E74: 台 | F74: 1 | G74: 1056.88 | H74: 88.07 | I74: 35.23 | J74: 264.22 | K74: 123.3 | L74: 193.76 | M74: 158.53 | N74: =SUM(G74:M74) -> 1919.99
A75: 47 | B75: 030502001013 | C75: 设备机柜 | D75: 1.名称:设备机柜 2.技术参数:设备机柜，尺寸不小于宽600mmx深600mmx高2000mm 3.安装方式:落地安装 4.其它:满足完成此项工作所需要的全部工作内容，包括设计图纸、技术规范书、答疑、招标文件、现行规范、图集、验收等全部要求 | E75: 台 | F75: 2 | G75: 2576.15 | H75: 99.08 | I75: 33.03 | J75: 132.11 | K75: 99.08 | L75: 363.3 | M75: 297.25 | N75: =SUM(G75:M75) -> 3600
A76: 48 | B76: 030506001021 | C76: 电源时序器 | D76: 1.名称:电源时序器 2.技术参数:8路时序设备电源； 输入电流不低于30A，输出电流:10A； 支持RS232/RS485/网络控制接口。 3.其它:满足完成此项工作所需要的全部工作内容，满足设计图纸、技术规范书、答疑、招标文件、现行规范、图集、验收等全部要求 | E76: 台 | F76: 1 | G76: 465.14 | H76: 17.89 | I76: 5.96 | J76: 23.85 | K76: 17.89 | L76: 65.6 | M76: 53.67 | N76: =SUM(G76:M76) -> 650
A77: 本页小计 | N77: =SUM(N74:N76) -> 6169.99
A78: 49 | B78: 030404035022 | C78: 多媒体插座 | D78: 1.名称：多媒体插座 2.规格：包含音频、视频、网络、电源接口 3.其它:满足完成此项工作所需要的全部工作内容，满足设计图纸、技术规范书、答疑、招标文件、现行规范、图集、验收等全部要求 | E78: 个 | F78: 6 | G78: 1202.2 | H78: 46.24 | I78: 15.41 | J78: 61.65 | K78: 46.24 | L78: 169.54 | M78: 138.72 | N78: =SUM(G78:M78) -> 1680
A79: 50 | B79: 030506001022 | C79: 主扩声柱形扬声器 | D79: 1.名称:主扩声柱形扬声器 2.规格:最大声压级不小于128dB SPL； 驱动单元不少于12个，单元尺寸不小于3英寸； 频率响应不劣于100Hz-20KHz（±3dB）； 覆盖角度不低于100°Hx20°V； 包含支架 3.其它:满足完成此项工作所需要的全部工作内容，包括设计图纸、技术规范书、答疑、招标文件、现行规范、图集、验收等全部要求 | E79: 台 | F79: 4 | G79: 4964.4 | H79: 1306.42 | I79: 653.21 | J79: 3657.98 | K79: 1045.14 | L79: 1437.06 | M79: 1175.78 | N79: =SUM(G79:M79) -> 14239.99
A80: 本页小计 | N80: =SUM(N78:N79) -> 15919.99
A81: 51 | B81: 030506001023 | C81: 功率放大器（主扩） | D81: 1.名称:功率放大器（主扩） 2.技术参数:2通道D类功率放大器 频率响应：20Hz-20KHz（±1dB）； 内置扬声器调节所需DSP，包括延时、均衡器（升余弦、自定义FIR、参量IIR：峰值、高/低搁架）、全通、带通、带阻、高/低通、分频、限幅等模块； 功率满足扬声器1.5倍余量。 3.其它:满足完成此项工作所需要的全部工作内容，满足设计图纸、技术规范书、答疑、招标文件、现行规范、图集、验收等全部要求 | E81: 台 | F81: 2 | G81: 5713.32 | H81: 219.74 | I81: 73.25 | J81: 292.99 | K81: 219.74 | L81: 805.72 | M81: 659.23 | N81: =SUM(G81:M81) -> 7983.99
A82: 52 | B82: 030506001024 | C82: 数字音频处理器（DANTE) | D82: 1.名称:数字音频处理器（DANTE) 2.技术参数:通道数量：通道数量：≥12个通道话筒/线路输入，≥8个通道线路输出； 控制端口：支持≥8个GPIO通道和1个通用串口RS232； 网络端口：≥2个千兆网口，≥32路Dante传输； AEC通道≥4路； 3.其它:满足完成此项工作所需要的全部工作内容，满足设计图纸、技术规范书、答疑、招标文件、现行规范、图集、验收等全部要求 | E82: 台 | F82: 1 | G82: 3005.5 | H82: 115.6 | I82: 38.53 | J82: 154.13 | K82: 115.6 | L82: 423.85 | M82: 346.79 | N82: =SUM(G82:M82) -> 4200
A83: 本页小计 | N83: =SUM(N81:N82) -> 12183.99
A84: 53 | B84: 030506001025 | C84: 数字会议系统主机 | D84: 1.名称:数字会议系统主机 2.技术参数:每台主机可连接不少于100个有线手拉手单元，有线手拉手链接方式。 内置反馈处理器等组件，可实时监测并处理系统中的啸叫点。 3.其它:满足完成此项工作所需要的全部工作内容，满足设计图纸、技术规范书、答疑、招标文件、现行规范、图集、验收等全部要求 | E84: 台 | F84: 1 | G84: 5026.35 | H84: 193.32 | I84: 64.44 | J84: 257.76 | K84: 193.32 | L84: 708.84 | M84: 579.96 | N84: =SUM(G84:M84) -> 7023.99
A85: 54 | B85: 030506001026 | C85: 有线会议发言单元 | D85: 1.名称:有线会议发言单元 2.技术参数:每个话筒均可独立调节增益控制 手拉手链接方式 指向特性：超心形指向性 频率响应：不劣于 30-20000Hz 开通灵敏度：≥-31dB(28.2mV) 以 1V 于 1 Pa 最高输入音量：≥125dB spl， 1 kHz 于 1% T.H.D. 3.其它:满足完成此项工作所需要的全部工作内容，满足设计图纸、技术规范书、答疑、招标文件、现行规范、图集、验收等全部要求 | E85: 台 | F85: 16 | G85: 10258.79 | H85: 394.57 | I85: 131.52 | J85: 526.09 | K85: 394.57 | L85: 1446.75 | M85: 1183.71 | N85: =SUM(G85:M85) -> 14336
A86: 本页小计 | N86: =SUM(N84:N85) -> 21359.99
A87: 55 | B87: 030506001027 | C87: 电子桌牌 | D87: 1.名称:电子桌牌 2.技术参数:屏幕不小于7.5寸三色电子墨水屏； 分辨率不低于800*480 支持通过电脑上传EXCEL名单,通过蓝牙将信息推送到屏幕； 支持显示参会人员名字、职务，单位、会议主题等信息； 支持手机蓝牙/NFC传图功能； 3.其它:满足完成此项工作所需要的全部工作内容，满足设计图纸、技术规范书、答疑、招标文件、现行规范、图集、验收等全部要求 | E87: 台 | F87: 16 | G87: 13739.45 | H87: 528.44 | I87: 176.15 | J87: 704.59 | K87: 528.44 | L87: 1937.61 | M87: 1585.32 | N87: =SUM(G87:M87) -> 19200
A88: 56 | B88: 030506007012 | C88: 98寸显示屏 | D88: 1.名称:98寸显示屏 2.技术参数：小于98英寸 分辨率不小于3840*2160 HDMI接口不少于2个，USB接口不少于2个，RJ45接口不少于1个； 含显示屏壁挂安装架 3.其它:满足完成此项工作所需要的全部工作内容，满足设计图纸、技术规范书、答疑、招标文件、现行规范、图集、验收等全部要求 | E88: 台 | F88: 1 | G88: 2963.3 | H88: 779.82 | I88: 389.91 | J88: 2183.49 | K88: 623.85 | L88: 857.8 | M88: 701.83 | N88: =SUM(G88:M88) -> 8500
A89: 本页小计 | N89: =SUM(N87:N88) -> 27700
A90: 57 | B90: 030506007013 | C90: 86寸显示屏 | D90: 1.名称:86寸显示屏 2.技术参数：显示尺寸不小于85英寸 分辨率不小于3840*2160 HDMI接口不少于2个，USB接口不少于2个，RJ45接口不少于1个； 含显示屏壁挂安装架 3.其它:满足完成此项工作所需要的全部工作内容，满足设计图纸、技术规范书、答疑、招标文件、现行规范、图集、验收等全部要求 | E90: 台 | F90: 2 | G90: 4532.11 | H90: 1192.66 | I90: 596.33 | J90: 3339.45 | K90: 954.13 | L90: 1311.93 | M90: 1073.39 | N90: =SUM(G90:M90) -> 13000
A91: 58 | B91: 030506007014 | C91: 65寸协作一体机 | D91: 1.名称:65寸协作一体机 2.技术参数：65英寸触控一体机 内置OPS电脑，支持Window/安卓系统 物理分辨率不小于3840*2160 中心亮度(含表面玻璃) ≥400 cd/m2 红外触摸屏 支持20点同时触控，支持10笔书写 内置不低于4000万像素摄像头，阵列麦克风 支持无线投屏功能 含一体机流动安装架 3.其它:满足完成此项工作所需要的全部工作内容，满足设计图纸、技术规范书、答疑、招标文件、现行规范、图集、验收等全部要求 | E91: 台 | F91: 1 | G91: 6583.49 | H91: 253.21 | I91: 84.4 | J91: 337.61 | K91: 253.21 | L91: 928.44 | M91: 759.63 | N91: =SUM(G91:M91) -> 9199.99
A92: 本页小计 | N92: =SUM(N90:N91) -> 22199.99
A93: 59 | B93: 030506007015 | C93: 无线投屏主机 | D93: 1.名称:无线投屏主机 2.可直接通过无线方式将PC电脑上文件投放到显示设备上； 最高可传输图像分辨率不低于1080P； 可播放流媒体 3.其它:满足完成此项工作所需要的全部工作内容，满足设计图纸、技术规范书、答疑、招标文件、现行规范、图集、验收等全部要求 | E93: 台 | F93: 1 | G93: 858.72 | H93: 33.03 | I93: 11.01 | J93: 44.04 | K93: 33.03 | L93: 121.1 | M93: 99.08 | N93: =SUM(G93:M93) -> 1200.01
A94: 本页小计 | N94: =N93 -> 1200.01
A95: 60 | B95: 030506007016 | C95: 视频分布式编码器 | D95: 1.名称:视频分布式编码器 2.采用分布式架构，浅压缩编解码技术，支持通过标准网络交换机实现音视频以及控制信号的传输和交换； 支持视频环出接口，环出画面与原画质一致； 支持 3840x2160@60Hz视频输入、支持3840x2160@60Hz视频环出；支持分辨率包括：1920x1080@60i; 1920x1080@50i，并向下兼容。 支持不少于1路3.5mm音频输入； 支持不少于1路RJ45网口；1路万兆SFP光口； 支持信号满帧采集，画面无卡顿、不丢帧； 支持信号无缝切换，画面切换时间不大于16ms。 支持故障告警提示，当节点出现故障的时，后台可发出告警提示。 3.其它:满足完成此项工作所需要的全部工作内容，满足设计图纸、技术规范书、答疑、招标文件、现行规范、图集、验收等全部要求 | E95: 台 | F95: 8 | G95: 16945.32 | H95: 651.744 | I95: 217.248 | J95: 868.992 | K95: 651.744 | L95: 2389.724 | M95: 1955.228 | N95: =SUM(G95:M95) -> 23680
A96: 本页小计 | N96: =N95 -> 23680
A97: 61 | B97: 030506007017 | C97: 视频分布式解码器 | D97: 1.名称:视频分布式解码器 2.采用分布式架构，浅压缩编解码技术，支持通过标准网络交换机实现音视频以及控制信号的传输和交换； 支持视频环出接口，环出画面与原画质一致； 支持 3840x2160@60Hz视频输入、支持3840x2160@60Hz视频环出；支持分辨率包括：1920x1080@60i; 1920x1080@50i，并向下兼容。 支持不少于1路3.5mm音频输入； 支持不少于1路RJ45网口；1路万兆SFP光口； 支持信号满帧采集，画面无卡顿、不丢帧； 支持信号无缝切换，画面切换时间不大于16ms。 支持故障告警提示，当节点出现故障的时，后台可发出告警提示。 3.其它:满足完成此项工作所需要的全部工作内容，满足设计图纸、技术规范书、答疑、招标文件、现行规范、图集、验收等全部要求 | E97: 台 | F97: 10 | G97: 21181.65 | H97: 814.68 | I97: 271.56 | J97: 1086.24 | K97: 814.68 | L97: 2987.155 | M97: 2444.035 | N97: =SUM(G97:M97) -> 29600
A98: 本页小计 | N98: =N97 -> 29600
A99: 62 | B99: 030501012010 | C99: 视频分布式交换机 | D99: 1.名称：视频分布式交换机 2.48个10/100/1000Base-T以太网端口 , 4个万兆SFP+ 可插拔双电源.支持交流或直流供电,默认配置-个500W AC电源或650W DC电源 支持PoE+ 交换容量: 336Gbps/3 024Tbps 包转发率: 132Mpps 支持组播功能 3.其它:满足完成此项工作所需要的全部工作内容，包括设计图纸、技术规范书、答疑、招标文件、现行规范、图集、验收等全部要求 | E99: 台 | F99: 1 | G99: 2747.89 | H99: 105.69 | I99: 35.23 | J99: 140.92 | K99: 105.69 | L99: 387.52 | M99: 317.06 | N99: =SUM(G99:M99) -> 3840
A100: 本页小计 | N100: =N99 -> 3840
...

Sheet 8#、15#非管区信息发布系统
A1: 分部分项工程和单价措施项目清单与计价表
A2: 分部分项工程和单价措施项目清单与计价表
A3: 序号 | B3: 项目编码 | C3: 项目名称 | D3: 项目特征描述 | E3: 计量单位 | F3: 工程量 | G3: 金额（元）
G4: 主材/设备费 | H4: 辅材 | I4: 机械措施 | J4: 人工 | K4: 管理费 | L4: 利润 | M4: 税金 | N4: 总价
A5: 1 | B5: 030501002024 | C5: 信息发布一体机 | D5: 1.名称：信息发布一体机（采用43寸液晶屏，画面比例 16﹕9分辨率 1920×1080） 2.含一套HDMI高清线,电源线,高清数字播放器 3.安装方式：底高1.5m壁挂或嵌墙安装，含设备支架 4.其它:满足完成此项工作所需要的全部工作内容，包括设计图纸、技术规范书、答疑、招标文件、现行规范、图集、验收等全部要求 | E5: 台 | F5: 42 | G5: 58907.891 | H5: 2265.69 | I5: 755.23 | J5: 3020.92 | K5: 2265.69 | L5: 8307.523 | M5: 6797.063 | N5: =SUM(G5:M5) -> 82320.007
A6: 2 | B6: 030505011001 | C6: 编码器安装、调试 | D6: 1.名称：编码器 2.其它:满足完成此项工作所需要的全部工作内容，包括设计图纸、技术规范书、答疑、招标文件、现行规范、图集、验收等全部要求 | E6: 台 | F6: 1 | G6: 104.59 | H6: 27.52 | I6: 13.76 | J6: 77.06 | K6: 22.02 | L6: 30.28 | M6: 24.77 | N6: =SUM(G6:M6) -> 300
A7: 3 | B7: 030506001121 | C7: 高清数字播放器 | D7: 1.名称：高清数字播放器 2.含配套连接线、电源线 3.安装方式：屏后安装 4.其它:满足完成此项工作所需要的全部工作内容，包括设计图纸、技术规范书、答疑、招标文件、现行规范、图集、验收等全部要求 | E7: 台 | F7: 2 | G7: 313.76 | H7: 82.57 | I7: 41.28 | J7: 231.19 | K7: 66.06 | L7: 90.83 | M7: 74.31 | N7: =SUM(G7:M7) -> 900
A8: 本页小计 | N8: =SUM(N5:N7) -> 83520.007
A9: 4 | B9: 030501013013 | C9: 系统管理服务器 | D9: 1.名称：系统管理服务器（含鼠标键盘、显示器、软件等） 2.技术参数：处理器：≥2颗Intel 至强 4510处理器，单颗核数≥12核， ≥2.40 GHz或以上；内存：≥128G；操作系统： 支持Microsoft Windows Server 2019、 RedHat Enterprise Linux 、 SUSE Linux Enterprise Server、 CentOS、 Ubuntu、 Vmware EXSI；内置SAS硬盘，RAID5，配备4x3TB热插拔硬盘，10000rpm以上；2个千兆以太网口；冗余电源、风扇，可以365天24小时运行；1块单口8Gb HBA卡。 3.其它:满足完成此项工作所需要的全部工作内容，包括设计图纸、技术规范书、答疑、招标文件、现行规范、图集、验收等全部要求 | E9: 台 | F9: 1 | G9: 8300.92 | H9: 319.264 | I9: 106.424 | J9: 425.688 | K9: 319.264 | L9: 1170.64 | M9: 957.8 | N9: =SUM(G9:M9) -> 11600
A10: 5 | B10: 030501013014 | C10: 信息发布系统工作站 | D10: 1.名称：信息发布系统工作站 2.含播放控制器授权许可,系统管理软件 3.其它:满足完成此项工作所需要的全部工作内容，包括设计图纸、技术规范书、答疑、招标文件、现行规范、图集、验收等全部要求 | E10: 台 | F10: 2 | G10: 5152.29 | H10: 198.17 | I10: 66.06 | J10: 264.22 | K10: 198.17 | L10: 726.61 | M10: 594.5 | N10: =SUM(G10:M10) -> 7200.02
A11: 6 | B11: 030502003007 | C11: 多路输出接口箱 | D11: 1.名称:多路输出接口箱 2.其它:满足完成此项工作所需要的全部工作内容，包括设计图纸、技术规范书、答疑、招标文件、现行规范、图集、验收等全部要求 | E11: 个 | F11: 1 | G11: 1321.1 | H11: 110.09 | I11: 44.04 | J11: 330.28 | K11: 154.13 | L11: 242.2 | M11: 198.17 | N11: =SUM(G11:M11) -> 2400.01
A12: 本页小计 | N12: =SUM(N9:N11) -> 21200.03
A13: 7 | B13: 030501012029 | C13: 24口接入交换机 | D13: 1.名称:24口接入交换机 2.其它:满足完成此项工作所需要的全部工作内容，包括设计图纸、技术规范书、答疑、招标文件、现行规范、图集、验收等全部要求 | E13: 台 | F13: 2 | G13: 3434.86 | H13: 132.11 | I13: 44.04 | J13: 176.15 | K13: 132.11 | L13: 484.4 | M13: 396.33 | N13: =SUM(G13:M13) -> 4800
A14: 8 | B14: 030506007061 | C14: LED小间距显示屏 | D14: 1.名称：LED小间距显示屏 2.规格：P1.5,尺寸12650/10210mm*4680mm，SMD模组封装，含成套视频拼接处理器、配电柜和支架 3.其它:满足完成此项工作所需要的全部工作内容，满足设计图纸、技术规范书、答疑、招标文件、现行规范、图集、验收等全部要求 | E14: m2 | F14: 40.55 | G14: 134640.88 | H14: 5178.496 | I14: 1726.168 | J14: 6904.664 | K14: 5178.496 | L14: 18987.816 | M14: 15535.488 | N14: =SUM(G14:M14) -> 188152.01
A15: 9 | B15: 030506007062 | C15: LED小间距显示屏 | D15: 1.名称：LED小间距显示屏 2.规格：P1.5,尺寸10700mm*3500mm，SMD模组封装，含成套视频拼接处理器、配电柜和支架 3.其它:满足完成此项工作所需要的全部工作内容，满足设计图纸、技术规范书、答疑、招标文件、现行规范、图集、验收等全部要求 | E15: m2 | F15: 37.45 | G15: 124347.74 | H15: 4782.608 | I15: 1594.2 | J15: 6376.808 | K15: 4782.608 | L15: 17536.224 | M15: 14347.816 | N15: =SUM(G15:M15) -> 173768.01
A16: 本页小计 | N16: =SUM(N13:N15) -> 366720.02
A17: 10 | B17: 03B051 | C17: 系统综合及集成 | D17: 1.清单未列项、图纸中未表示或技术规格书未做要求，但为了实现本系统各项功能必须增加的配套及辅助的材料、设备的所有工作内容及费用； 2.施工深化设计增加的实现本系统设计功能必要的配套及辅助的材料、设备所需的所有工作内容及费用； 3.实现设计功能所做的满足图纸、技术规格书要求的各项综合与集成，包括不限于各项检测、试验、调试、软件开发、联动等所有工作内容及费用 | E17: 项 | F17: 1 | G17: 1045.87 | H17: 275.23 | I17: 137.61 | J17: 770.64 | K17: 220.18 | L17: 302.75 | M17: 247.71 | N17: =SUM(G17:M17) -> 2999.99
A18: 11 | B18: 03B052 | C18: 平台对接 | D18: 1.平台对接 2.其它:满足完成此项工作所需要的全部工作内容，包括设计图纸、技术规范书、答疑、招标文件、现行规范、图集、验收等全部要求 | E18: 项 | F18: 1 | G18: 1100.92 | H18: 91.74 | I18: 36.7 | J18: 275.23 | K18: 128.44 | L18: 201.83 | M18: 165.14 | N18: =SUM(G18:M18) -> 2000
A19: 12 | B19: 03B053 | C19: 软件开发 | D19: 1.信息发布软件 2.其它:满足完成此项工作所需要的全部工作内容，包括设计图纸、技术规范书、答疑、招标文件、现行规范、图集、验收等全部要求 | E19: 项 | F19: 1 | G19: 5724.77 | H19: 220.18 | I19: 73.39 | J19: 293.58 | K19: 220.18 | L19: 807.34 | M19: 660.55 | N19: =SUM(G19:M19) -> 7999.99
A20: 13 | B20: 030411001092 | C20: 配管 | D20: 1.名称：紧定式镀锌钢导管 2.规格：JDG20 3.敷设方式：暗配 4.其它:满足完成此项工作所需要的全部工作内容，包括设计图纸、技术规范书、答疑、招标文件、现行规范、图集、验收等全部要求 | E20: m | F20: 11.6 | G20: 18.2 | H20: 4.79 | I20: 2.39 | J20: 13.41 | K20: 3.83 | L20: 5.27 | M20: 4.31 | N20: =SUM(G20:M20) -> 52.2
A21: 本页小计 | N21: =SUM(N17:N20) -> 13052.18
A22: 14 | B22: 030411001093 | C22: 配管 | D22: 1.名称：紧定式镀锌钢导管 2.规格：JDG20 3.敷设方式：明配 4.其它:满足完成此项工作所需要的全部工作内容，包括设计图纸、技术规范书、答疑、招标文件、现行规范、图集、验收等全部要求 | E22: m | F22: 13.3 | G22: 20.87 | H22: 5.49 | I22: 2.75 | J22: 15.37 | K22: 4.39 | L22: 6.04 | M22: 4.94 | N22: =SUM(G22:M22) -> 59.85
A23: 15 | B23: 030413001043 | C23: 管道支架/综合支架 | D23: 1.名称:管道支架制作安装 2.材质:热镀锌 3.安装高度:综合考虑 4.满足完成此项工作所需要的全部工作内容，满足设计图纸、技术规范书、答疑、招标文件、现行规范、图集、验收等全部要求 | E23: kg | F23: 2.38 | G23: 3.98 | H23: 1.05 | I23: 0.52 | J23: 2.93 | K23: 0.84 | L23: 1.15 | M23: 0.94 | N23: =SUM(G23:M23) -> 11.41
A24: 16 | B24: 030413002027 | C24: 凿（压)槽 | D24: 1.名称:管线剔槽及恢复 2.满足完成此项工作所需要的全部工作内容，满足设计图纸、答疑、招标文件、现行规范、图集、验收等全部要求 | E24: m | F24: 11.6 | G24: 191.56 | H24: 15.96 | I24: 6.39 | J24: 47.89 | K24: 22.35 | L24: 35.12 | M24: 28.73 | N24: =SUM(G24:M24) -> 348
A25: 17 | B25: 030502005030 | C25: 双绞线缆 | D25: 1.名称：六类网线 2.规格： Cat.6 UTP 3.敷设方式：桥架敷设 4.其它:满足完成此项工作所需要的全部工作内容，包括设计图纸、技术规范书、答疑、招标文件、现行规范、图集、验收等全部要求 | E25: m | F25: 335.7 | G25: 351.1 | H25: 92.39 | I25: 46.2 | J25: 258.7 | K25: 73.92 | L25: 101.63 | M25: 83.16 | N25: =SUM(G25:M25) -> 1007.1
A26: 18 | B26: 030502005031 | C26: 双绞线缆 | D26: 1.名称：六类网线 2.规格： Cat.6 UTP 3.敷设方式：管内敷设 4.其它:满足完成此项工作所需要的全部工作内容，包括设计图纸、技术规范书、答疑、招标文件、现行规范、图集、验收等全部要求 | E26: m | F26: 24.8 | G26: 25.94 | H26: 6.83 | I26: 3.41 | J26: 19.11 | K26: 5.46 | L26: 7.51 | M26: 6.14 | N26: =SUM(G26:M26) -> 74.4
A27: 本页小计 | N27: =SUM(N22:N26) -> 1500.76
A28: 19 | B28: 030502012020 | C28: 信息发布点位 | D28: 1.名称：信息发布点位 2.其它:满足完成此项工作所需要的全部工作内容，包括设计图纸、技术规范书、答疑、招标文件、现行规范、图集、验收等全部要求 | E28: 个 | F28: 4 | G28: 108.77 | H28: 4.18 | I28: 1.39 | J28: 5.58 | K28: 4.18 | L28: 15.34 | M28: 12.55 | N28: =SUM(G28:M28) -> 151.99
A29: 20 | B29: 030502012021 | C29: 信息发布点位底盒 | D29: 1.名称：信息发布点位底盒 2.结构：混凝土墙内 3.其它:满足完成此项工作所需要的全部工作内容，包括设计图纸、技术规范书、答疑、招标文件、现行规范、图集、验收等全部要求 | E29: 个 | F29: 4 | G29: 28.62 | H29: 1.1 | I29: 0.37 | J29: 1.47 | K29: 1.1 | L29: 4.04 | M29: 3.3 | N29: =SUM(G29:M29) -> 40
A30: 21 | B30: 030502019013 | C30: 双绞线缆测试 | D30: 1.名称：信息发布点调试 2.其它:满足完成此项工作所需要的全部工作内容，包括设计图纸、技术规范书、答疑、招标文件、现行规范、图集、验收等全部要求 | E30: 链路 | F30: 4 | G30: 11.16 | H30: 2.94 | I30: 1.47 | J30: 8.22 | K30: 2.35 | L30: 3.23 | M30: 2.64 | N30: =SUM(G30:M30) -> 32.01
A31: 22 | B31: 030411001094 | C31: 配管 | D31: 1.名称：紧定式镀锌钢导管 2.规格：JDG20 3.敷设方式：暗配 4.其它:满足完成此项工作所需要的全部工作内容，包括设计图纸、技术规范书、答疑、招标文件、现行规范、图集、验收等全部要求 | E31: m | F31: 30 | G31: 47.06 | H31: 12.39 | I31: 6.19 | J31: 34.68 | K31: 9.91 | L31: 13.62 | M31: 11.15 | N31: =SUM(G31:M31) -> 135
A32: 23 | B32: 030411001095 | C32: 配管 | D32: 1.名称：紧定式镀锌钢导管 2.规格：JDG20 3.敷设方式：明配 4.其它:满足完成此项工作所需要的全部工作内容，包括设计图纸、技术规范书、答疑、招标文件、现行规范、图集、验收等全部要求 | E32: m | F32: 165.81 | G32: 260.12 | H32: 68.45 | I32: 34.23 | J32: 191.67 | K32: 54.76 | L32: 75.3 | M32: 61.61 | N32: =SUM(G32:M32) -> 746.14
A33: 本页小计 | N33: =SUM(N28:N32) -> 1105.14
A34: 24 | B34: 030413001044 | C34: 管道支架/综合支架 | D34: 1.名称:管道支架制作安装 2.材质:热镀锌 3.安装高度:综合考虑 4.满足完成此项工作所需要的全部工作内容，满足设计图纸、技术规范书、答疑、招标文件、现行规范、图集、验收等全部要求 | E34: kg | F34: 49.74 | G34: 83.23 | H34: 21.9 | I34: 10.95 | J34: 61.33 | K34: 17.52 | L34: 24.09 | M34: 19.71 | N34: =SUM(G34:M34) -> 238.73
A35: 25 | B35: 030413002028 | C35: 凿（压)槽 | D35: 1.名称:管线剔槽及恢复 2.满足完成此项工作所需要的全部工作内容，满足设计图纸、答疑、招标文件、现行规范、图集、验收等全部要求 | E35: m | F35: 30 | G35: 495.41 | H35: 41.28 | I35: 16.51 | J35: 123.85 | K35: 57.8 | L35: 90.83 | M35: 74.31 | N35: =SUM(G35:M35) -> 899.99
A36: 26 | B36: 030502005032 | C36: 双绞线缆 | D36: 1.名称：六类网线 2.规格： Cat.6 UTP 3.敷设方式：桥架敷设 4.其它:满足完成此项工作所需要的全部工作内容，包括设计图纸、技术规范书、答疑、招标文件、现行规范、图集、验收等全部要求 | E36: m | F36: 1359.25 | G36: 1421.6 | H36: 374.11 | I36: 187.05 | J36: 1047.5 | K36: 299.28 | L36: 411.52 | M36: 336.69 | N36: =SUM(G36:M36) -> 4077.75
A37: 27 | B37: 030502005033 | C37: 双绞线缆 | D37: 1.名称：六类网线 2.规格： Cat.6 UTP 3.敷设方式：管内敷设 4.其它:满足完成此项工作所需要的全部工作内容，包括设计图纸、技术规范书、答疑、招标文件、现行规范、图集、验收等全部要求 | E37: m | F37: 277.34 | G37: 290.06 | H37: 76.33 | I37: 38.17 | J37: 213.73 | K37: 61.07 | L37: 83.97 | M37: 68.7 | N37: =SUM(G37:M37) -> 832.03
A38: 28 | B38: 030502012022 | C38: 信息发布点位 | D38: 1.名称：信息发布点位 2.其它:满足完成此项工作所需要的全部工作内容，包括设计图纸、技术规范书、答疑、招标文件、现行规范、图集、验收等全部要求 | E38: 个 | F38: 29 | G38: 788.59 | H38: 30.33 | I38: 10.11 | J38: 40.44 | K38: 30.33 | L38: 111.21 | M38: 90.99 | N38: =SUM(G38:M38) -> 1102
A39: 本页小计 | N39: =SUM(N34:N38) -> 7150.5
A40: 29 | B40: 030502012023 | C40: 信息发布点位底盒 | D40: 1.名称：信息发布点位底盒 2.结构：混凝土墙内 3.其它:满足完成此项工作所需要的全部工作内容，包括设计图纸、技术规范书、答疑、招标文件、现行规范、图集、验收等全部要求 | E40: 个 | F40: 29 | G40: 207.52 | H40: 7.98 | I40: 2.66 | J40: 10.64 | K40: 7.98 | L40: 29.27 | M40: 23.94 | N40: =SUM(G40:M40) -> 289.99
A41: 30 | B41: 030502019014 | C41: 双绞线缆测试 | D41: 1.名称：信息发布点调试 2.其它:满足完成此项工作所需要的全部工作内容，包括设计图纸、技术规范书、答疑、招标文件、现行规范、图集、验收等全部要求 | E41: 链路 | F41: 29 | G41: 80.88 | H41: 21.28 | I41: 10.64 | J41: 59.6 | K41: 17.03 | L41: 23.41 | M41: 19.16 | N41: =SUM(G41:M41) -> 232
A42: 31 | B42: 031301017030 | C42: 脚手架搭拆 | D42: 1.综合考虑项目脚手架搭拆或其他替代措施项目 2.场内外材料搬运 3.拆除脚手架后材料的堆放 4.满足完成此项工作所需要的全部工作内容，满足设计图纸、答疑、招标文件、现行规范、图集、验收等全部要求 | E42: 项 | F42: 1 | G42: 174.31 | H42: 45.87 | I42: 22.94 | J42: 128.44 | K42: 36.7 | L42: 50.46 | M42: 41.28 | N42: =SUM(G42:M42) -> 500
A43: 32 | B43: 03B054 | C43: 超高费 | E43: 项 | F43: 1 | G43: 275.23 | H43: 22.94 | I43: 9.17 | J43: 68.81 | K43: 32.11 | L43: 50.46 | M43: 41.28 | N43: =SUM(G43:M43) -> 500
A44: 本页小计 | N44: =SUM(N40:N43) -> 1521.99
A45: 合 计 | N45: =N8+N12+N16+N21+N27+N33+N39+N44 -> 495770.62

Sheet 8#楼ECC非管区灯光控制工程
A1: 分部分项工程和单价措施项目清单与计价表
A2: 分部分项工程和单价措施项目清单与计价表
A3: 序号 | B3: 项目编码 | C3: 项目名称 | D3: 项目特征描述 | E3: 计量单位 | F3: 工程量 | G3: 金额（元）
G4: 主材/设备费 | H4: 辅材 | I4: 机械措施 | J4: 人工 | K4: 管理费 | L4: 利润 | M4: 税金 | N4: 总价
A5: 1 | B5: 030501013001 | C5: 中心控制计算机 | D5: 1.名称:中心控制计算机 2.参数：配置 i5处理器 32G内存 1TB硬盘 3.其它:满足完成此项工作所需要的全部工作内容，包括设计图纸、技术规范书、答疑、招标文件、现行规范、图集、验收等全部要求 | E5: 台 | F5: 1 | G5: 2618.34 | H5: 100.71 | I5: 33.57 | J5: 134.27 | K5: 100.71 | L5: 369.25 | M5: 302.12 | N5: =SUM(G5:M5) -> 3658.97
A6: 2 | B6: 030501013002 | C6: 灯光控制系统服务器 | D6: 1.名称：灯光控制系统服务器 2.技术参数：处理器：≥2颗Intel 至强 4510处理器，单颗核数≥12核， ≥2.40 GHz或以上；内存：≥128G；操作系统： 支持Microsoft Windows Server 2019、 RedHat Enterprise Linux 、 SUSE Linux Enterprise Server、 CentOS、 Ubuntu、 Vmware EXSI；内置SAS硬盘，RAID5，配备4x3TB热插拔硬盘，10000rpm以上；2个千兆以太网口；冗余电源、风扇，可以365天24小时运行；1块单口8Gb HBA卡。 3.其它:满足完成此项工作所需要的全部工作内容，包括设计图纸、技术规范书、答疑、招标文件、现行规范、图集、验收等全部要求 | E6: 台 | F6: 1 | G6: 6557.82 | H6: 252.22 | I6: 84.07 | J6: 336.3 | K6: 252.22 | L6: 924.82 | M6: 756.67 | N6: =SUM(G6:M6) -> 9164.12
A7: 3 | B7: 030501017001 | C7: 灯光控制系统软件 | D7: 1.名称:灯光控制系统软件 2.规格:OPC 3.其它:满足完成此项工作所需要的全部工作内容，包括设计图纸、技术规范书、答疑、招标文件、现行规范、图集、验收等全部要求 | E7: 套 | F7: 1 | G7: 1022.36 | H7: 85.2 | I7: 34.08 | J7: 255.59 | K7: 119.28 | L7: 187.43 | M7: 153.35 | N7: =SUM(G7:M7) -> 1857.29
A8: 本页小计 | N8: =SUM(N5:N7) -> 14680.38
A9: 4 | B9: 031101007001 | C9: 不间断电源设备 | D9: 1.名称:不间断电源设备 2.参数：3kVA，包含电池柜/架、散力架、连接线、电池配电箱 3.其它:满足完成此项工作所需要的全部工作内容，包括设计图纸、技术规范书、答疑、招标文件、现行规范、图集、验收等全部要求 | E9: 套 | F9: 1 | G9: 4568.04 | H9: 175.69 | I9: 58.56 | J9: 234.26 | K9: 175.69 | L9: 644.21 | M9: 527.08 | N9: =SUM(G9:M9) -> 6383.53
A10: 5 | B10: 030501002001 | C10: 打印机 | D10: 1.名称:打印机 2.其它:满足完成此项工作所需要的全部工作内容，包括设计图纸、技术规范书、答疑、招标文件、现行规范、图集、验收等全部要求 | E10: 台 | F10: 1 | G10: 1320.71 | H10: 50.8 | I10: 16.93 | J10: 67.73 | K10: 50.8 | L10: 186.25 | M10: 152.39 | N10: =SUM(G10:M10) -> 1845.61
A11: 6 | B11: 030502001001 | C11: 机柜、机架 | D11: 1.名称:19寸机柜 2.尺寸：600*600*2000 3.其它:满足完成此项工作所需要的全部工作内容，包括设计图纸、技术规范书、答疑、招标文件、现行规范、图集、验收等全部要求 | E11: 台 | F11: 1 | G11: 1602.08 | H11: 61.62 | I11: 20.54 | J11: 82.16 | K11: 61.62 | L11: 225.93 | M11: 184.86 | N11: =SUM(G11:M11) -> 2238.81
A12: 7 | B12: 030404019003 | C12: IP主交换器 | D12: 1.名称:IP主交换器 2.型号:ISM/S 5.1 3.其它:满足完成此项工作所需要的全部工作内容，包括设计图纸、技术规范书、答疑、招标文件、现行规范、图集、验收等全部要求 | E12: 个 | F12: 1 | G12: 3197.17 | H12: 266.43 | I12: 106.57 | J12: 799.29 | K12: 373 | L12: 586.15 | M12: 479.58 | N12: =SUM(G12:M12) -> 5808.19
A13: 8 | B13: 031101055001 | C13: 光电转换器 | D13: 1.名称:光电转换器 2.型号:LL/S 1.1 3.其它:满足完成此项工作所需要的全部工作内容，包括设计图纸、技术规范书、答疑、招标文件、现行规范、图集、验收等全部要求 | E13: 个 | F13: 1 | G13: 389.83 | H13: 32.49 | I13: 12.99 | J13: 97.46 | K13: 45.48 | L13: 71.47 | M13: 58.48 | N13: =SUM(G13:M13) -> 708.2
A14: 本页小计 | N14: =SUM(N9:N13) -> 16984.34
A15: 9 | B15: 030501009001 | C15: IP路由器 | D15: 1.名称:IP路由器 2.型号:IPR/S 2.1 3.其它:满足完成此项工作所需要的全部工作内容，包括设计图纸、技术规范书、答疑、招标文件、现行规范、图集、验收等全部要求 | E15: 台 | F15: 6 | G15: 4007.71 | H15: 154.14 | I15: 51.38 | J15: 205.52 | K15: 154.14 | L15: 565.19 | M15: 462.43 | N15: =SUM(G15:M15) -> 5600.51
A16: 10 | B16: 031101001001 | C16: 电源供应器 | D16: 1.名称:电源供应器 2.型号:SV/S 30.640.5 3.其它:满足完成此项工作所需要的全部工作内容，包括设计图纸、技术规范书、答疑、招标文件、现行规范、图集、验收等全部要求 | E16: 台 | F16: 1 | G16: 933.51 | H16: 35.9 | I16: 11.97 | J16: 47.87 | K16: 35.9 | L16: 131.65 | M16: 107.71 | N16: =SUM(G16:M16) -> 1304.51
A17: 11 | B17: 030505013001 | C17: 线路耦合器 | D17: 1.名称:线路耦合器 2.型号:LK/S 4.2 3.其它:满足完成此项工作所需要的全部工作内容，包括设计图纸、技术规范书、答疑、招标文件、现行规范、图集、验收等全部要求 | E17: 个 | F17: 6 | G17: 2259.25 | H17: 188.27 | I17: 75.31 | J17: 564.81 | K17: 263.58 | L17: 414.2 | M17: 338.89 | N17: =SUM(G17:M17) -> 4104.31
A18: 12 | B18: 030506004001 | C18: 故障信号监视模块 | D18: 1.名称:故障信号监视模块 2.型号:SMB/S 1.1 3.其它:满足完成此项工作所需要的全部工作内容，包括设计图纸、技术规范书、答疑、招标文件、现行规范、图集、验收等全部要求 | E18: 台 | F18: 1 | G18: 499.16 | H18: 19.2 | I18: 6.4 | J18: 25.6 | K18: 19.2 | L18: 70.39 | M18: 57.6 | N18: =SUM(G18:M18) -> 697.55
A19: 13 | B19: 030409010001 | C19: 浪涌保护器 | D19: 1.名称:浪涌保护器 2.规格:US/E 1 3.其它:满足完成此项工作所需要的全部工作内容，包括设计图纸、技术规范书、答疑、招标文件、现行规范、图集、验收等全部要求 | E19: 个 | F19: 1 | G19: 396.06 | H19: 33.01 | I19: 13.2 | J19: 99.02 | K19: 46.21 | L19: 72.61 | M19: 59.41 | N19: =SUM(G19:M19) -> 719.52
A20: 本页小计 | N20: =SUM(N15:N19) -> 12426.4
A21: 14 | B21: 030404022001 | C21: 控制器 | D21: 1.名称:定时控制器 2.型号:FW/S 8.2.1 3.其它:满足完成此项工作所需要的全部工作内容，包括设计图纸、技术规范书、答疑、招标文件、现行规范、图集、验收等全部要求 | E21: 台 | F21: 1 | G21: 662.89 | H21: 25.5 | I21: 8.5 | J21: 33.99 | K21: 25.5 | L21: 93.48 | M21: 76.49 | N21: =SUM(G21:M21) -> 926.35
A22: 15 | B22: 030404019004 | C22: 系统监视单元 | D22: 1.名称:系统监视单元 2.型号:EUB/S 1.1 3.其它:满足完成此项工作所需要的全部工作内容，包括设计图纸、技术规范书、答疑、招标文件、现行规范、图集、验收等全部要求 | E22: 个 | F22: 1 | G22: 596.69 | H22: 49.72 | I22: 19.89 | J22: 149.17 | K22: 69.61 | L22: 109.39 | M22: 89.5 | N22: =SUM(G22:M22) -> 1083.97
A23: 16 | B23: 030404022002 | C23: 12路16A开关驱动器 | D23: 1.名称:12路16A开关驱动器 2.型号:SA/S 12.16.2.1 3.其它:满足完成此项工作所需要的全部工作内容，包括设计图纸、技术规范书、答疑、招标文件、现行规范、图集、验收等全部要求 | E23: 台 | F23: 6 | G23: 1055.23 | H23: 40.59 | I23: 13.53 | J23: 54.11 | K23: 40.59 | L23: 148.81 | M23: 121.76 | N23: =SUM(G23:M23) -> 1474.62
A24: 17 | B24: 030404022003 | C24: 8路16A开关驱动器 | D24: 1.名称:8路16A开关驱动器 2.型号:SA/S 8.16.2.1 3.其它:满足完成此项工作所需要的全部工作内容，包括设计图纸、技术规范书、答疑、招标文件、现行规范、图集、验收等全部要求 | E24: 台 | F24: 40 | G24: 13990.48 | H24: 538.1 | I24: 179.37 | J24: 717.46 | K24: 538.1 | L24: 1973.02 | M24: 1614.29 | N24: =SUM(G24:M24) -> 19550.82
A25: 18 | B25: 030502012001 | C25: 智能面板 | D25: 1.名称:智能面板 2.型号:6320/50 3.其它:满足完成此项工作所需要的全部工作内容，包括设计图纸、技术规范书、答疑、招标文件、现行规范、图集、验收等全部要求 | E25: 个 | F25: 30 | G25: 3984.23 | H25: 153.24 | I25: 51.08 | J25: 204.32 | K25: 153.24 | L25: 561.88 | M25: 459.72 | N25: =SUM(G25:M25) -> 5567.71
A26: 本页小计 | N26: =SUM(N21:N25) -> 28603.47
A27: 19 | B27: 030501002002 | C27: 彩色触摸屏 | D27: 1.名称：彩色触摸屏 2.型号：6316/100C-102 3.其它:满足完成此项工作所需要的全部工作内容，包括设计图纸、技术规范书、答疑、招标文件、现行规范、图集、验收等全部要求 | E27: 台 | F27: 1 | G27: 547.87 | H27: 45.66 | I27: 18.26 | J27: 136.97 | K27: 63.92 | L27: 100.44 | M27: 82.18 | N27: =SUM(G27:M27) -> 995.3
A28: 20 | B28: 03B012 | C28: 系统综合及集成 | D28: 1.清单未列项、图纸中未表示或技术规格书未做要求，但为了实现本系统各项功能必须增加的配套及辅助的材料、设备的所有工作内容及费用； 2.施工深化设计增加的实现本系统设计功能必要的配套及辅助的材料、设备所需的所有工作内容及费用； 3.实现设计功能所做的满足图纸、技术规格书要求的各项综合与集成，包括不限于各项检测、试验、调试、软件开发、联动等所有工作内容及费用 | E28: 项 | F28: 1 | G28: 697.25 | H28: 183.49 | I28: 91.74 | J28: 513.76 | K28: 146.79 | L28: 201.83 | M28: 165.14 | N28: =SUM(G28:M28) -> 2000
A29: 21 | B29: 030411001020 | C29: 配管 | D29: 1.名称：镀锌钢管 2.规格：SC20 3.敷设方式：暗配 4.安装高度：综合考虑 5.其它:满足完成此项工作所需要的全部工作内容，包括设计图纸、技术规范书、答疑、招标文件、现行规范、图集、验收等全部要求 | E29: m | F29: 80 | G29: 703.66 | H29: 185.17 | I29: 92.59 | J29: 518.49 | K29: 148.14 | L29: 203.69 | M29: 166.66 | N29: =SUM(G29:M29) -> 2018.4
A30: 本页小计 | N30: =SUM(N27:N29) -> 5013.7
A31: 22 | B31: 030411001021 | C31: 配管 | D31: 1.名称：镀锌钢管 2.规格：SC25 3.敷设方式：明配 4.安装高度：综合考虑 5.其它:满足完成此项工作所需要的全部工作内容，包括设计图纸、技术规范书、答疑、招标文件、现行规范、图集、验收等全部要求 | E31: m | F31: 38.4 | G31: 375.24 | H31: 98.75 | I31: 49.37 | J31: 276.49 | K31: 79 | L31: 108.62 | M31: 88.87 | N31: =SUM(G31:M31) -> 1076.34
A32: 23 | B32: 030413001008 | C32: 管道支架/综合支架 | D32: 1.名称:管道支架制作安装 2.材质:热镀锌 3.安装高度:综合考虑 4.满足完成此项工作所需要的全部工作内容，满足设计图纸、技术规范书、答疑、招标文件、现行规范、图集、验收等全部要求 | E32: kg | F32: 14.29 | G32: 66.46 | H32: 17.49 | I32: 8.74 | J32: 48.97 | K32: 13.99 | L32: 19.24 | M32: 15.74 | N32: =SUM(G32:M32) -> 190.63
A33: 24 | B33: 030413002006 | C33: 凿（压)槽 | D33: 1.名称:管线剔槽及恢复 2.满足完成此项工作所需要的全部工作内容，满足设计图纸、答疑、招标文件、现行规范、图集、验收等全部要求 | E33: m | F33: 11.6 | G33: 49.81 | H33: 4.15 | I33: 1.66 | J33: 12.45 | K33: 5.81 | L33: 9.13 | M33: 7.47 | N33: =SUM(G33:M33) -> 90.48
A34: 25 | B34: 030502005005 | C34: 双绞线缆 | D34: 1.名称：六类网线 2.规格： Cat.6 UTP 3.敷设方式：桥架敷设 4.其它:满足完成此项工作所需要的全部工作内容，包括设计图纸、技术规范书、答疑、招标文件、现行规范、图集、验收等全部要求 | E34: m | F34: 200 | G34: 373.72 | H34: 98.35 | I34: 49.17 | J34: 275.38 | K34: 78.68 | L34: 108.18 | M34: 88.51 | N34: =SUM(G34:M34) -> 1071.99
A35: 26 | B35: 030502007005 | C35: 光缆 | D35: 1.名称：4芯多模光纤 2.敷设方式：桥架敷设 3.其它:满足完成此项工作所需要的全部工作内容，包括设计图纸、技术规范书、答疑、招标文件、现行规范、图集、验收等全部要求 | E35: m | F35: 100 | G35: 570.33 | H35: 21.94 | I35: 7.31 | J35: 29.25 | K35: 21.94 | L35: 80.43 | M35: 65.81 | N35: =SUM(G35:M35) -> 797.01
A36: 本页小计 | N36: =SUM(N31:N35) -> 3226.45
A37: 27 | B37: 030411004013 | C37: 配线 | D37: 1.名称：智能照明控制系统总线 2.型号：J-Y(ST)YH-2x2x1.0 3.敷设方式：管内穿线 4.其它:满足完成此项工作所需要的全部工作内容，包括设计图纸、技术规范书、答疑、招标文件、现行规范、图集、验收等全部要求 | E37: m | F37: 118.4 | G37: 210.1 | H37: 55.29 | I37: 27.64 | J37: 154.81 | K37: 44.23 | L37: 60.82 | M37: 49.76 | N37: =SUM(G37:M37) -> 602.65
A38: 28 | B38: 030411004014 | C38: 配线 | D38: 1.名称：智能照明控制系统总线 2.型号：J-Y(ST)YH-2x2x1.0 3.敷设方式：桥架敷设 4.其它:满足完成此项工作所需要的全部工作内容，包括设计图纸、技术规范书、答疑、招标文件、现行规范、图集、验收等全部要求 | E38: m | F38: 3201 | G38: 5680.16 | H38: 1494.78 | I38: 747.39 | J38: 4185.38 | K38: 1195.82 | L38: 1644.26 | M38: 1345.3 | N38: =SUM(G38:M38) -> 16293.09
A39: 29 | B39: 031301017012 | C39: 脚手架搭拆 | D39: 1.脚手架费 2.按项包干 3.其它:满足完成此项工作所需要的全部工作内容，包括设计图纸、技术规范书、答疑、招标文件、现行规范、图集、验收等全部要求 | E39: 项 | F39: 1 | G39: 150.66 | H39: 39.65 | I39: 19.82 | J39: 111.02 | K39: 31.72 | L39: 43.61 | M39: 35.68 | N39: =SUM(G39:M39) -> 432.16
A40: 30 | B40: 03B013 | C40: 超高费 | E40: 项 | F40: 1 | G40: 1121.52 | H40: 93.46 | I40: 37.38 | J40: 280.38 | K40: 130.84 | L40: 205.61 | M40: 168.23 | N40: =SUM(G40:M40) -> 2037.42
A41: 本页小计 | N41: =SUM(N37:N40) -> 19365.32
A42: 合 计 | N42: =N8+N14+N20+N26+N30+N36+N41 -> 100300.06

Sheet 8#楼ECC非管区电动窗帘控制工程
A1: 分部分项工程和单价措施项目清单与计价表
A2: 分部分项工程和单价措施项目清单与计价表
A3: 序号 | B3: 项目编码 | C3: 项目名称 | D3: 项目特征描述 | E3: 计量单位 | F3: 工程量 | G3: 金额（元）
